{
  "type": "Feature",
  "properties": {
    "gn:admin1_code":"69",
    "gn:asciiname":"Pustosel'ye",
    "gn:country_code":"RU",
    "gn:dem":232,
    "gn:feature_class":"P",
    "gn:feature_code":"PPL",
    "gn:name":"Pustosel\u2019ye",
    "gn:population":0,
    "gn:timezone":"Europe/Moscow",
    "iso:country":"RU",
    "name:rus_x_preferred":[
        "\u041f\u0443\u0441\u0442\u043e\u0441\u0435\u043b\u044c\u0435"
    ],
    "name:und_x_variant":[
        "Pustosel\u2019ye",
        "\u041f\u0443\u0441\u0442\u043e\u0441\u0435\u043b\u044c\u0435"
    ],
    "wof:name":"Pustosel'ye",
    "wof:placetype":"locality"
},
  "geometry": {"coordinates":[31.44428,54.48433000000001],"type":"Point"}
}