{
  "type": "Feature",
  "properties": {
    "gn:admin1_code":"73",
    "gn:asciiname":"Mugezle-Yelga",
    "gn:country_code":"RU",
    "gn:dem":225,
    "gn:feature_class":"P",
    "gn:feature_code":"PPL",
    "gn:name":"Mugezle-Yelga",
    "gn:population":0,
    "gn:timezone":"Europe/Moscow",
    "iso:country":"RU",
    "name:rus_x_preferred":[
        "\u041c\u0443\u0433\u0435\u0437\u043b\u0435-\u0415\u043b\u0433\u0430"
    ],
    "name:und_x_variant":[
        "\u041c\u0443\u0433\u0435\u0437\u043b\u0435-\u0415\u043b\u0433\u0430"
    ],
    "wof:name":"Mugezle-Yelga",
    "wof:placetype":"locality"
},
  "geometry": {"coordinates":[52.429,55.0466],"type":"Point"}
}