{
  "type": "Feature",
  "properties": {
    "gn:admin1_code":"56",
    "gn:asciiname":"Privol'ye",
    "gn:country_code":"RU",
    "gn:dem":225,
    "gn:feature_class":"P",
    "gn:feature_code":"PPL",
    "gn:name":"Privol\u2019ye",
    "gn:population":0,
    "gn:timezone":"Europe/Moscow",
    "iso:country":"RU",
    "name:rus_x_preferred":[
        "\u041f\u0440\u0438\u0432\u043e\u043b\u044c\u0435"
    ],
    "name:und_x_variant":[
        "Privol\u2019ye"
    ],
    "wof:name":"Privol'ye",
    "wof:placetype":"locality"
},
  "geometry": {"coordinates":[35.988,52.6619],"type":"Point"}
}