{
  "type": "Feature",
  "properties": {
    "gn:admin1_code":"13",
    "gn:asciiname":"Put' Kommunizma",
    "gn:country_code":"RU",
    "gn:dem":492,
    "gn:feature_class":"P",
    "gn:feature_code":"PPL",
    "gn:name":"Put\u2019 Kommunizma",
    "gn:population":0,
    "gn:timezone":"Asia/Yekaterinburg",
    "iso:country":"RU",
    "name:rus_x_preferred":[
        "\u041f\u0443\u0442\u044c \u041a\u043e\u043c\u043c\u0443\u043d\u0438\u0437\u043c\u0430"
    ],
    "name:und_x_variant":[
        "Put\u2019 Kommunizma"
    ],
    "wof:name":"Put' Kommunizma",
    "wof:placetype":"locality"
},
  "geometry": {"coordinates":[58.2992,54.6117],"type":"Point"}
}