{
  "type": "Feature",
  "properties": {
    "gn:admin1_code":"33",
    "gn:asciiname":"Tolstikovy",
    "gn:country_code":"RU",
    "gn:dem":150,
    "gn:feature_class":"P",
    "gn:feature_code":"PPL",
    "gn:name":"Tolstikovy",
    "gn:population":0,
    "gn:timezone":"Europe/Kirov",
    "iso:country":"RU",
    "name:rus_x_preferred":[
        "\u0422\u043e\u043b\u0441\u0442\u0438\u043a\u043e\u0432\u044b"
    ],
    "wof:name":"Tolstikovy",
    "wof:placetype":"locality"
},
  "geometry": {"coordinates":[49.12352,58.35461],"type":"Point"}
}