{
  "type": "Feature",
  "properties": {
    "gn:admin1_code":"52",
    "gn:asciiname":"Yelkino",
    "gn:country_code":"RU",
    "gn:dem":145,
    "gn:feature_class":"P",
    "gn:feature_code":"PPL",
    "gn:name":"Y\u00eblkino",
    "gn:population":0,
    "gn:timezone":"Europe/Moscow",
    "iso:country":"RU",
    "name:eng_x_preferred":[
        "Y\u00eblkino"
    ],
    "name:nor_x_preferred":[
        "Jelkino"
    ],
    "name:rus_x_preferred":[
        "\u0415\u043b\u043a\u0438\u043d\u043e"
    ],
    "name:rus_x_variant":[
        "\u0401\u043b\u043a\u0438\u043d\u043e"
    ],
    "wof:name":"Yelkino",
    "wof:placetype":"locality"
},
  "geometry": {"coordinates":[36.02582,58.6555],"type":"Point"}
}