{
  "type": "Feature",
  "properties": {
    "gn:admin1_code":"56",
    "gn:asciiname":"Kalinov",
    "gn:country_code":"RU",
    "gn:dem":215,
    "gn:feature_class":"P",
    "gn:feature_code":"PPL",
    "gn:name":"Kalinov",
    "gn:population":0,
    "gn:timezone":"Europe/Moscow",
    "iso:country":"RU",
    "name:bul_x_preferred":[
        "\u041a\u0430\u043b\u0438\u043d\u043e\u0432"
    ],
    "name:ceb_x_preferred":[
        "Kalinov"
    ],
    "name:ces_x_preferred":[
        "Kalinov"
    ],
    "name:hye_x_preferred":[
        "\u053f\u0561\u056c\u056b\u0576\u0578\u057e"
    ],
    "name:rus_x_preferred":[
        "\u041a\u0430\u043b\u0438\u043d\u043e\u0432"
    ],
    "name:slk_x_preferred":[
        "Kalinov"
    ],
    "name:srp_x_preferred":[
        "\u041a\u0430\u043b\u0438\u043d\u043e\u0432"
    ],
    "name:swe_x_preferred":[
        "Kalinov"
    ],
    "wof:name":"Kalinov",
    "wof:placetype":"locality"
},
  "geometry": {"coordinates":[35.53361,52.7214],"type":"Point"}
}