{
  "type": "Feature",
  "properties": {
    "gn:admin1_code":"47",
    "gn:admin2_code":"579462",
    "gn:asciiname":"Sobolikha",
    "gn:country_code":"RU",
    "gn:dem":138,
    "gn:feature_class":"P",
    "gn:feature_code":"PPL",
    "gn:name":"Sobolikha",
    "gn:population":240,
    "gn:timezone":"Europe/Moscow",
    "iso:country":"RU",
    "name:rus_x_preferred":[
        "\u0421\u043e\u0431\u043e\u043b\u0438\u0445\u0430"
    ],
    "wof:name":"Sobolikha",
    "wof:placetype":"locality",
    "wof:population":240
},
  "geometry": {"coordinates":[38.04167,55.72833000000001],"type":"Point"}
}