{
  "type": "Feature",
  "properties": {
    "gn:admin1_code":"8",
    "gn:asciiname":"Yuzimyanovo",
    "gn:country_code":"RU",
    "gn:dem":201,
    "gn:feature_class":"P",
    "gn:feature_code":"PPL",
    "gn:name":"Yuzimyanovo",
    "gn:population":0,
    "gn:timezone":"Asia/Yekaterinburg",
    "iso:country":"RU",
    "name:rus_x_preferred":[
        "\u042e\u0437\u0438\u043c\u044f\u043d\u043e\u0432\u043e"
    ],
    "name:und_x_variant":[
        "\u042e\u0437\u0438\u043c\u044f\u043d\u043e\u0432\u043e",
        "Yus-Imenevo"
    ],
    "wof:name":"Yuzimyanovo",
    "wof:placetype":"locality"
},
  "geometry": {"coordinates":[56.594,54.1502],"type":"Point"}
}