{
  "type": "Feature",
  "properties": {
    "gn:admin1_code":"20",
    "gn:asciiname":"Borisovo",
    "gn:country_code":"RU",
    "gn:dem":230,
    "gn:feature_class":"P",
    "gn:feature_code":"PPL",
    "gn:name":"Borisovo",
    "gn:population":0,
    "gn:timezone":"Asia/Irkutsk",
    "iso:country":"RU",
    "name:eng_x_preferred":[
        "Borisovo"
    ],
    "name:nor_x_preferred":[
        "Borisovo"
    ],
    "name:rus_x_preferred":[
        "\u0411\u043e\u0440\u0438\u0441\u043e\u0432\u043e"
    ],
    "wof:name":"Borisovo",
    "wof:placetype":"locality"
},
  "geometry": {"coordinates":[98.2967,56.1636],"type":"Point"}
}