{
  "type": "Feature",
  "properties": {
    "gn:admin1_code":"21",
    "gn:asciiname":"Klochkovo",
    "gn:country_code":"RU",
    "gn:dem":95,
    "gn:feature_class":"P",
    "gn:feature_code":"PPL",
    "gn:name":"Klochkovo",
    "gn:population":0,
    "gn:timezone":"Europe/Moscow",
    "iso:country":"RU",
    "name:eng_x_preferred":[
        "Klochkovo"
    ],
    "name:nor_x_preferred":[
        "Klotsjkovo"
    ],
    "name:rus_x_preferred":[
        "\u041a\u043b\u043e\u0447\u043a\u043e\u0432\u043e"
    ],
    "name:und_x_variant":[
        "Klotkovo"
    ],
    "wof:name":"Klochkovo",
    "wof:placetype":"locality"
},
  "geometry": {"coordinates":[41.52131,56.71633000000001],"type":"Point"}
}