{
  "type": "Feature",
  "properties": {
    "gn:admin1_code":"29",
    "gn:asciiname":"Uspenka",
    "gn:country_code":"RU",
    "gn:dem":179,
    "gn:feature_class":"P",
    "gn:feature_code":"PPL",
    "gn:name":"Uspenka",
    "gn:population":0,
    "gn:timezone":"Asia/Novokuznetsk",
    "iso:country":"RU",
    "name:ceb_x_preferred":[
        "Uspenka"
    ],
    "name:crh_x_preferred":[
        "Uspenka"
    ],
    "name:deu_x_preferred":[
        "Uspenka"
    ],
    "name:hye_x_preferred":[
        "\u0548\u0582\u057d\u057a\u0565\u0576\u056f\u0561"
    ],
    "name:ron_x_preferred":[
        "Uspenka"
    ],
    "name:rus_x_preferred":[
        "\u0423\u0441\u043f\u0435\u043d\u043a\u0430"
    ],
    "name:spa_x_preferred":[
        "Uspenka"
    ],
    "name:ukr_x_preferred":[
        "\u0423\u0441\u043f\u0435\u043d\u043a\u0430"
    ],
    "name:zho_x_preferred":[
        "\u70cf\u65af\u7247\u5361"
    ],
    "wof:name":"Uspenka",
    "wof:placetype":"locality"
},
  "geometry": {"coordinates":[86.59896999999999,56.26122],"type":"Point"}
}