{
  "type": "Feature",
  "properties": {
    "gn:admin1_code":"28",
    "gn:asciiname":"Murdo Sel'ga",
    "gn:country_code":"RU",
    "gn:dem":95,
    "gn:feature_class":"P",
    "gn:feature_code":"PPL",
    "gn:name":"Murdo Sel\u2019ga",
    "gn:population":0,
    "gn:timezone":"Europe/Moscow",
    "iso:country":"RU",
    "name:fin_x_preferred":[
        "Murtoselk\u00e4"
    ],
    "name:rus_x_preferred":[
        "\u041c\u0443\u0440\u0434\u043e \u0421\u0435\u043b\u044c\u0433\u0430"
    ],
    "name:und_x_variant":[
        "Murdo Sel\u2019ga",
        "\u041c\u0443\u0440\u0434\u043e \u0421\u0435\u043b\u044c\u0433\u0430"
    ],
    "wof:name":"Murdo Sel'ga",
    "wof:placetype":"locality"
},
  "geometry": {"coordinates":[32.21294,61.75509],"type":"Point"}
}