{
  "type": "Feature",
  "properties": {
    "gn:admin1_code":"92",
    "gn:asciiname":"Primorskiy",
    "gn:country_code":"RU",
    "gn:dem":7,
    "gn:feature_class":"P",
    "gn:feature_code":"PPL",
    "gn:name":"Primorskiy",
    "gn:population":0,
    "gn:timezone":"Asia/Kamchatka",
    "iso:country":"RU",
    "name:rus_x_preferred":[
        "\u041f\u0440\u0438\u043c\u043e\u0440\u0441\u043a\u0438\u0439"
    ],
    "name:und_x_variant":[
        "\u041f\u0440\u0438\u043c\u043e\u0440\u0441\u043a\u0438\u0439"
    ],
    "wof:name":"Primorskiy",
    "wof:placetype":"locality"
},
  "geometry": {"coordinates":[158.43181000000001,52.90087],"type":"Point"}
}