{
  "type": "Feature",
  "properties": {
    "gn:admin1_code":"77",
    "gn:asciiname":"Konokovo",
    "gn:country_code":"RU",
    "gn:dem":258,
    "gn:feature_class":"P",
    "gn:feature_code":"PPL",
    "gn:name":"Konokovo",
    "gn:population":0,
    "gn:timezone":"Europe/Moscow",
    "iso:country":"RU",
    "name:rus_x_preferred":[
        "\u041a\u043e\u043d\u043e\u043a\u043e\u0432\u043e"
    ],
    "wof:name":"Konokovo",
    "wof:placetype":"locality"
},
  "geometry": {"coordinates":[33.99625,57.2125],"type":"Point"}
}