{
  "type": "Feature",
  "properties": {
    "gn:admin1_code":"10",
    "gn:asciiname":"Uprusy",
    "gn:country_code":"RU",
    "gn:dem":189,
    "gn:feature_class":"P",
    "gn:feature_code":"PPL",
    "gn:name":"Uprusy",
    "gn:population":0,
    "gn:timezone":"Europe/Moscow",
    "iso:country":"RU",
    "name:rus_x_preferred":[
        "\u0423\u043f\u0440\u0443\u0441\u044b"
    ],
    "name:und_x_variant":[
        "Uprussy",
        "Uprusy"
    ],
    "wof:name":"Uprusy",
    "wof:placetype":"locality"
},
  "geometry": {"coordinates":[33.5902,53.3703],"type":"Point"}
}