{
  "type": "Feature",
  "properties": {
    "gn:admin1_code":"88",
    "gn:asciiname":"Nikifertsevo",
    "gn:country_code":"RU",
    "gn:dem":120,
    "gn:feature_class":"P",
    "gn:feature_code":"PPL",
    "gn:name":"Nikifertsevo",
    "gn:population":0,
    "gn:timezone":"Europe/Moscow",
    "iso:country":"RU",
    "name:rus_x_preferred":[
        "\u041d\u0438\u043a\u0438\u0444\u0435\u0440\u0446\u0435\u0432\u043e"
    ],
    "wof:name":"Nikifertsevo",
    "wof:placetype":"locality"
},
  "geometry": {"coordinates":[39.20828,57.36433],"type":"Point"}
}