{
  "type": "Feature",
  "properties": {
    "gn:admin1_code":"93",
    "gn:asciiname":"Alako",
    "gn:country_code":"RU",
    "gn:dem":708,
    "gn:feature_class":"P",
    "gn:feature_code":"PPL",
    "gn:name":"Alako",
    "gn:population":0,
    "gn:timezone":"Asia/Chita",
    "iso:country":"RU",
    "name:eng_x_preferred":[
        "Alako"
    ],
    "name:rus_x_preferred":[
        "\u0410\u043b\u0430\u043a\u043e\u0439"
    ],
    "name:rus_x_variant":[
        "\u0410\u043b\u0430\u043a\u043e"
    ],
    "wof:name":"Alako",
    "wof:placetype":"locality"
},
  "geometry": {"coordinates":[116.06667,50.96667],"type":"Point"}
}