{
  "type": "Feature",
  "properties": {
    "gn:admin1_code":"11",
    "gn:asciiname":"Khokhorzon",
    "gn:country_code":"RU",
    "gn:dem":1788,
    "gn:feature_class":"P",
    "gn:feature_code":"PPL",
    "gn:name":"Khokhorzon",
    "gn:population":0,
    "gn:timezone":"Asia/Irkutsk",
    "iso:country":"RU",
    "name:eng_x_preferred":[
        "Khokhorzon"
    ],
    "name:nor_x_preferred":[
        "Khokhorzon"
    ],
    "name:rus_x_preferred":[
        "\u0425\u043e\u0445\u043e\u0440\u0437\u043e\u043d"
    ],
    "name:und_x_variant":[
        "\u0425\u043e\u0445\u043e\u0440\u0437\u043e\u043d",
        "Khokhorzon"
    ],
    "wof:name":"Khokhorzon",
    "wof:placetype":"locality"
},
  "geometry": {"coordinates":[100.93333,51.63333],"type":"Point"}
}