{
  "type": "Feature",
  "properties": {
    "gn:admin1_code":"20",
    "gn:asciiname":"Alymovka",
    "gn:country_code":"RU",
    "gn:dem":246,
    "gn:feature_class":"P",
    "gn:feature_code":"PPL",
    "gn:name":"Alymovka",
    "gn:population":0,
    "gn:timezone":"Asia/Irkutsk",
    "iso:country":"RU",
    "name:eng_x_preferred":[
        "Alymovka"
    ],
    "name:nor_x_preferred":[
        "Alymovka"
    ],
    "name:rus_x_preferred":[
        "\u0410\u043b\u044b\u043c\u043e\u0432\u043a\u0430"
    ],
    "wof:name":"Alymovka",
    "wof:placetype":"locality"
},
  "geometry": {"coordinates":[108.57138999999999,57.96111],"type":"Point"}
}