{
  "type": "Feature",
  "properties": {
    "gn:admin1_code":"83",
    "gn:asciiname":"Mezhakovo",
    "gn:country_code":"RU",
    "gn:dem":184,
    "gn:feature_class":"P",
    "gn:feature_code":"PPL",
    "gn:name":"Mezhakovo",
    "gn:population":0,
    "gn:timezone":"Europe/Moscow",
    "iso:country":"RU",
    "name:rus_x_preferred":[
        "\u041c\u0435\u0436\u0430\u043a\u043e\u0432\u043e"
    ],
    "wof:name":"Mezhakovo",
    "wof:placetype":"locality"
},
  "geometry": {"coordinates":[39.07702000000001,56.41652],"type":"Point"}
}