{
  "type": "Feature",
  "properties": {
    "gn:admin1_code":"38",
    "gn:asciiname":"Kovalenko",
    "gn:country_code":"RU",
    "gn:dem":19,
    "gn:feature_class":"P",
    "gn:feature_code":"PPL",
    "gn:name":"Kovalenko",
    "gn:population":0,
    "gn:timezone":"Europe/Moscow",
    "iso:country":"RU",
    "name:fra_x_preferred":[
        "Kovalenko"
    ],
    "name:rus_x_preferred":[
        "\u041a\u043e\u0432\u0430\u043b\u0435\u043d\u043a\u043e"
    ],
    "name:slv_x_preferred":[
        "Kovalenko"
    ],
    "name:und_x_variant":[
        "\u041a\u043e\u0432\u0430\u043b\u0435\u043d\u043a\u043e"
    ],
    "wof:name":"Kovalenko",
    "wof:placetype":"locality"
},
  "geometry": {"coordinates":[38.75374,44.93986],"type":"Point"}
}