{
  "type": "Feature",
  "properties": {
    "gn:admin1_code":"52",
    "gn:asciiname":"Kurakovo",
    "gn:country_code":"RU",
    "gn:dem":163,
    "gn:feature_class":"P",
    "gn:feature_code":"PPL",
    "gn:name":"Kurakovo",
    "gn:population":0,
    "gn:timezone":"Europe/Moscow",
    "iso:country":"RU",
    "name:rus_x_preferred":[
        "\u041a\u0443\u0440\u0430\u043a\u043e\u0432\u043e"
    ],
    "name:und_x_variant":[
        "\u041a\u0443\u0440\u0430\u043a\u043e\u0432\u043e"
    ],
    "wof:name":"Kurakovo",
    "wof:placetype":"locality"
},
  "geometry": {"coordinates":[34.06944,58.43632],"type":"Point"}
}