{
  "type": "Feature",
  "properties": {
    "gn:admin1_code":"17.0",
    "gn:asciiname":"Terek",
    "gn:country_code":"RU",
    "gn:dem":-15,
    "gn:feature_class":"P",
    "gn:feature_code":"PPL",
    "gn:name":"Terek",
    "gn:population":0,
    "gn:timezone":"Europe/Moscow",
    "iso:country":"RU",
    "name:rus_x_preferred":[
        "\u0422\u0435\u0440\u0435\u043a"
    ],
    "wof:name":"Terek",
    "wof:placetype":"locality"
},
  "geometry": {"coordinates":[46.98265,43.72971],"type":"Point"}
}