{
  "type": "Feature",
  "properties": {
    "gn:admin1_code":"21",
    "gn:asciiname":"Ovintsy",
    "gn:country_code":"RU",
    "gn:dem":123,
    "gn:feature_class":"P",
    "gn:feature_code":"PPL",
    "gn:name":"Ovintsy",
    "gn:population":0,
    "gn:timezone":"Europe/Moscow",
    "iso:country":"RU",
    "name:rus_x_preferred":[
        "\u041e\u0432\u0438\u043d\u0446\u044b"
    ],
    "wof:name":"Ovintsy",
    "wof:placetype":"locality"
},
  "geometry": {"coordinates":[41.98655,57.05158],"type":"Point"}
}