{
  "type": "Feature",
  "properties": {
    "gn:admin1_code":"29",
    "gn:asciiname":"Nekrosovka",
    "gn:country_code":"RU",
    "gn:dem":243,
    "gn:feature_class":"P",
    "gn:feature_code":"PPL",
    "gn:name":"Nekrosovka",
    "gn:population":0,
    "gn:timezone":"Asia/Novokuznetsk",
    "iso:country":"RU",
    "name:rus_x_preferred":[
        "\u041d\u0435\u043a\u0440\u043e\u0441\u043e\u0432\u043a\u0430"
    ],
    "wof:name":"Nekrosovka",
    "wof:placetype":"locality"
},
  "geometry": {"coordinates":[89.01971999999998,56.06889],"type":"Point"}
}