{
  "type": "Feature",
  "properties": {
    "gn:admin1_code":"88",
    "gn:asciiname":"Yusovo",
    "gn:country_code":"RU",
    "gn:dem":118,
    "gn:feature_class":"P",
    "gn:feature_code":"PPL",
    "gn:name":"Yusovo",
    "gn:population":0,
    "gn:timezone":"Europe/Moscow",
    "iso:country":"RU",
    "name:rus_x_preferred":[
        "\u042e\u0441\u043e\u0432\u043e"
    ],
    "name:und_x_variant":[
        "\u042e\u0441\u043e\u0432\u043e"
    ],
    "wof:name":"Yusovo",
    "wof:placetype":"locality"
},
  "geometry": {"coordinates":[38.3824,57.6402],"type":"Point"}
}