{
  "type": "Feature",
  "properties": {
    "gn:admin1_code":"28",
    "gn:asciiname":"Nyrki",
    "gn:country_code":"RU",
    "gn:dem":126,
    "gn:feature_class":"P",
    "gn:feature_code":"PPL",
    "gn:name":"Nyrki",
    "gn:population":0,
    "gn:timezone":"Europe/Moscow",
    "iso:country":"RU",
    "name:fin_x_preferred":[
        "Nirkki"
    ],
    "name:rus_x_preferred":[
        "\u041d\u044b\u0440\u043a\u0438"
    ],
    "wof:name":"Nyrki",
    "wof:placetype":"locality"
},
  "geometry": {"coordinates":[34.45,61.41667],"type":"Point"}
}