{
  "type": "Feature",
  "properties": {
    "gn:admin1_code":"60",
    "gn:asciiname":"Oshestki",
    "gn:country_code":"RU",
    "gn:dem":117,
    "gn:feature_class":"P",
    "gn:feature_code":"PPL",
    "gn:name":"Oshestki",
    "gn:population":0,
    "gn:timezone":"Europe/Moscow",
    "iso:country":"RU",
    "name:rus_x_preferred":[
        "\u041e\u0448\u0435\u0441\u0442\u043a\u0438"
    ],
    "wof:name":"Oshestki",
    "wof:placetype":"locality"
},
  "geometry": {"coordinates":[28.83455,56.58541],"type":"Point"}
}