{
  "type": "Feature",
  "properties": {
    "gn:admin1_code":"77.0",
    "gn:asciiname":"Gnezdtsy",
    "gn:country_code":"RU",
    "gn:dem":147,
    "gn:feature_class":"P",
    "gn:feature_code":"PPL",
    "gn:name":"Gnezdtsy",
    "gn:population":0,
    "gn:timezone":"Europe/Moscow",
    "iso:country":"RU",
    "name:eng_x_preferred":[
        "Gnezdtsy"
    ],
    "name:nor_x_preferred":[
        "Gnezdtsy"
    ],
    "name:rus_x_preferred":[
        "\u0413\u043d\u0435\u0437\u0434\u0446\u044b"
    ],
    "name:und_x_variant":[
        "Gnestsy"
    ],
    "wof:name":"Gnezdtsy",
    "wof:placetype":"locality"
},
  "geometry": {"coordinates":[35.50817,57.02517],"type":"Point"}
}