{
  "type": "Feature",
  "properties": {
    "gn:admin1_code":"51.0",
    "gn:asciiname":"Rodionikha",
    "gn:country_code":"RU",
    "gn:dem":128,
    "gn:feature_class":"P",
    "gn:feature_code":"PPL",
    "gn:name":"Rodionikha",
    "gn:population":0,
    "gn:timezone":"Europe/Moscow",
    "iso:country":"RU",
    "name:rus_x_preferred":[
        "\u0420\u043e\u0434\u0438\u043e\u043d\u0438\u0445\u0430"
    ],
    "wof:name":"Rodionikha",
    "wof:placetype":"locality"
},
  "geometry": {"coordinates":[44.37767,56.87649],"type":"Point"}
}