{
  "type": "Feature",
  "properties": {
    "gn:admin1_code":"63",
    "gn:asciiname":"Sergelyakh",
    "gn:country_code":"RU",
    "gn:dem":103,
    "gn:feature_class":"P",
    "gn:feature_code":"PPL",
    "gn:name":"Sergelyakh",
    "gn:population":0,
    "gn:timezone":"Asia/Yakutsk",
    "iso:country":"RU",
    "name:rus_x_preferred":[
        "\u0421\u0435\u0440\u0433\u0435\u043b\u044f\u0445"
    ],
    "name:und_x_variant":[
        "Sergeleyekh",
        "Sergeleekh",
        "Sergelyakh",
        "\u0421\u0435\u0440\u0433\u0435\u043b\u044f\u0445"
    ],
    "wof:name":"Sergelyakh",
    "wof:placetype":"locality"
},
  "geometry": {"coordinates":[129.65461000000002,61.97989000000001],"type":"Point"}
}