{
  "type": "Feature",
  "properties": {
    "gn:admin1_code":"38",
    "gn:asciiname":"Rad'ki",
    "gn:country_code":"RU",
    "gn:dem":8,
    "gn:feature_class":"P",
    "gn:feature_code":"PPL",
    "gn:name":"Rad\u2019ki",
    "gn:population":0,
    "gn:timezone":"Europe/Moscow",
    "iso:country":"RU",
    "name:rus_x_preferred":[
        "\u0420\u0430\u0434\u044c\u043a\u0438"
    ],
    "name:und_x_variant":[
        "Rad\u2019ki",
        "\u0420\u0430\u0434\u044c\u043a\u0438"
    ],
    "wof:name":"Rad'ki",
    "wof:placetype":"locality"
},
  "geometry": {"coordinates":[39.13167,46.11028],"type":"Point"}
}