{
  "type": "Feature",
  "properties": {
    "gn:admin1_code":"37",
    "gn:asciiname":"Sentsovo",
    "gn:country_code":"RU",
    "gn:dem":126,
    "gn:feature_class":"P",
    "gn:feature_code":"PPL",
    "gn:name":"Sentsovo",
    "gn:population":0,
    "gn:timezone":"Europe/Moscow",
    "iso:country":"RU",
    "name:rus_x_preferred":[
        "\u0421\u0435\u043d\u0446\u043e\u0432\u043e"
    ],
    "name:und_x_variant":[
        "Sintsovo",
        "Sentsovo"
    ],
    "wof:name":"Sentsovo",
    "wof:placetype":"locality"
},
  "geometry": {"coordinates":[41.12209,57.91111],"type":"Point"}
}