{
  "type": "Feature",
  "properties": {
    "gn:admin1_code":"41",
    "gn:asciiname":"Krasavchik",
    "gn:country_code":"RU",
    "gn:dem":187,
    "gn:feature_class":"P",
    "gn:feature_code":"PPL",
    "gn:name":"Krasavchik",
    "gn:population":0,
    "gn:timezone":"Europe/Moscow",
    "iso:country":"RU",
    "name:rus_x_preferred":[
        "\u041a\u0440\u0430\u0441\u0430\u0432\u0447\u0438\u043a"
    ],
    "wof:name":"Krasavchik",
    "wof:placetype":"locality"
},
  "geometry": {"coordinates":[35.7311,52.2175],"type":"Point"}
}