{
  "type": "Feature",
  "properties": {
    "gn:admin1_code":"81",
    "gn:asciiname":"Sukharevka",
    "gn:country_code":"RU",
    "gn:dem":139,
    "gn:feature_class":"P",
    "gn:feature_code":"PPL",
    "gn:name":"Sukharevka",
    "gn:population":0,
    "gn:timezone":"Europe/Ulyanovsk",
    "iso:country":"RU",
    "name:rus_x_preferred":[
        "\u0421\u0443\u0445\u0430\u0440\u0435\u0432\u043a\u0430"
    ],
    "name:und_x_variant":[
        "\u0421\u0443\u0445\u0430\u0440\u0435\u0432\u043a\u0430"
    ],
    "wof:name":"Sukharevka",
    "wof:placetype":"locality"
},
  "geometry": {"coordinates":[47.77072,53.96712],"type":"Point"}
}