{
  "type": "Feature",
  "properties": {
    "gn:admin1_code":"17.0",
    "gn:asciiname":"Dzhinabi",
    "gn:country_code":"RU",
    "gn:dem":592,
    "gn:feature_class":"P",
    "gn:feature_code":"PPL",
    "gn:name":"Dzhinabi",
    "gn:population":0,
    "gn:timezone":"Europe/Moscow",
    "iso:country":"RU",
    "name:rus_x_preferred":[
        "\u0414\u0436\u0438\u043d\u0430\u0431\u0438"
    ],
    "wof:name":"Dzhinabi",
    "wof:placetype":"locality"
},
  "geometry": {"coordinates":[47.86167,42.07395],"type":"Point"}
}