{
  "type": "Feature",
  "properties": {
    "gn:admin1_code":"90",
    "gn:asciiname":"Oni",
    "gn:country_code":"RU",
    "gn:dem":117,
    "gn:feature_class":"P",
    "gn:feature_code":"PPL",
    "gn:name":"Oni",
    "gn:population":0,
    "gn:timezone":"Asia/Yekaterinburg",
    "iso:country":"RU",
    "name:eng_x_preferred":[
        "Oni"
    ],
    "name:nor_x_preferred":[
        "Oni"
    ],
    "name:rus_x_preferred":[
        "\u041e\u043d\u0438"
    ],
    "name:und_x_variant":[
        "\u041e\u043d\u0438"
    ],
    "wof:name":"Oni",
    "wof:placetype":"locality"
},
  "geometry": {"coordinates":[55.73398,59.01129],"type":"Point"}
}