{
  "type": "Feature",
  "properties": {
    "gn:admin1_code":"90",
    "gn:asciiname":"Oni",
    "gn:country_code":"RU",
    "gn:dem":117,
    "gn:feature_class":"P",
    "gn:feature_code":"PPL",
    "gn:name":"Oni",
    "gn:population":0,
    "gn:timezone":"Asia/Yekaterinburg",
    "iso:country":"RU",
    "name:ara_x_preferred":[
        "\u0623\u0648\u0646\u064a"
    ],
    "name:aze_x_preferred":[
        "Oni"
    ],
    "name:bel_x_preferred":[
        "\u041e\u043d\u0456"
    ],
    "name:cat_x_preferred":[
        "Oni"
    ],
    "name:deu_x_preferred":[
        "Oni"
    ],
    "name:eng_x_preferred":[
        "Oni"
    ],
    "name:epo_x_preferred":[
        "Onio"
    ],
    "name:fas_x_preferred":[
        "\u0627\u0646\u06cc"
    ],
    "name:fin_x_preferred":[
        "Oni"
    ],
    "name:fra_x_preferred":[
        "Oni"
    ],
    "name:hun_x_preferred":[
        "Oni"
    ],
    "name:ind_x_preferred":[
        "Oni"
    ],
    "name:ita_x_preferred":[
        "Oni"
    ],
    "name:jav_x_preferred":[
        "Oni"
    ],
    "name:kat_x_preferred":[
        "\u10dd\u10dc\u10d8"
    ],
    "name:kor_x_preferred":[
        "\uc624\ub2c8"
    ],
    "name:nld_x_preferred":[
        "Oni"
    ],
    "name:nor_x_preferred":[
        "Oni"
    ],
    "name:pol_x_preferred":[
        "Oni"
    ],
    "name:por_x_preferred":[
        "Oni"
    ],
    "name:ron_x_preferred":[
        "Oni"
    ],
    "name:rus_x_preferred":[
        "\u041e\u043d\u0438"
    ],
    "name:spa_x_preferred":[
        "Oni"
    ],
    "name:swe_x_preferred":[
        "Oni"
    ],
    "name:tha_x_preferred":[
        "\u0e42\u0e2d\u0e30\u0e19\u0e34"
    ],
    "name:tur_x_preferred":[
        "Oni"
    ],
    "name:ukr_x_preferred":[
        "\u041e\u043d\u0456"
    ],
    "name:vie_x_preferred":[
        "Oni"
    ],
    "name:zho_x_preferred":[
        "\u9b3c"
    ],
    "wof:name":"Oni",
    "wof:placetype":"locality"
},
  "geometry": {"coordinates":[55.73398,59.01129],"type":"Point"}
}