{
  "type": "Feature",
  "properties": {
    "gn:admin1_code":"54",
    "gn:asciiname":"Bol'shaya Roshcha",
    "gn:country_code":"RU",
    "gn:dem":114,
    "gn:feature_class":"P",
    "gn:feature_code":"PPL",
    "gn:name":"Bol\u2019shaya Roshcha",
    "gn:population":0,
    "gn:timezone":"Asia/Omsk",
    "iso:country":"RU",
    "name:rus_x_preferred":[
        "\u0411\u043e\u043b\u044c\u0448\u0430\u044f \u0420\u043e\u0449\u0430"
    ],
    "name:und_x_variant":[
        "Bol\u2019shaya Roshcha",
        "\u0411\u043e\u043b\u044c\u0448\u0430\u044f \u0420\u043e\u0449\u0430"
    ],
    "wof:name":"Bol'shaya Roshcha",
    "wof:placetype":"locality"
},
  "geometry": {"coordinates":[72.5489,54.7946],"type":"Point"}
}