{
  "type": "Feature",
  "properties": {
    "gn:admin1_code":"90",
    "gn:asciiname":"Panteleyevka",
    "gn:country_code":"RU",
    "gn:dem":166,
    "gn:feature_class":"P",
    "gn:feature_code":"PPL",
    "gn:name":"Panteleyevka",
    "gn:population":0,
    "gn:timezone":"Asia/Yekaterinburg",
    "iso:country":"RU",
    "name:eng_x_preferred":[
        "Panteleyevka"
    ],
    "name:nor_x_preferred":[
        "Pantelejevka"
    ],
    "name:rus_x_preferred":[
        "\u041f\u0430\u043d\u0442\u0435\u043b\u0435\u0435\u0432\u043a\u0430"
    ],
    "wof:name":"Panteleyevka",
    "wof:placetype":"locality"
},
  "geometry": {"coordinates":[54.8706,56.6084],"type":"Point"}
}