{
  "type": "Feature",
  "properties": {
    "gn:admin1_code":"55",
    "gn:asciiname":"Krasnoarmeyskiy",
    "gn:country_code":"RU",
    "gn:dem":298,
    "gn:feature_class":"P",
    "gn:feature_code":"PPL",
    "gn:name":"Krasnoarmeyskiy",
    "gn:population":0,
    "gn:timezone":"Asia/Yekaterinburg",
    "iso:country":"RU",
    "name:eng_x_preferred":[
        "Krasnoarmeyskiy"
    ],
    "name:nor_x_preferred":[
        "Krasnoarmejskij"
    ],
    "name:rus_x_preferred":[
        "\u041a\u0440\u0430\u0441\u043d\u043e\u0430\u0440\u043c\u0435\u0439\u0441\u043a\u0438\u0439"
    ],
    "name:und_x_variant":[
        "Imeni Rozy Lyuksemburg",
        "Krasnoarmeyskaya",
        "\u041a\u0440\u0430\u0441\u043d\u043e\u0430\u0440\u043c\u0435\u0439\u0441\u043a\u0438\u0439",
        "Krasnoarmeyskiy"
    ],
    "wof:name":"Krasnoarmeyskiy",
    "wof:placetype":"locality"
},
  "geometry": {"coordinates":[59.069,51.9965],"type":"Point"}
}