{
  "type": "Feature",
  "properties": {
    "gn:admin1_code":"51",
    "gn:asciiname":"Polyanskoye",
    "gn:country_code":"RU",
    "gn:dem":140,
    "gn:feature_class":"P",
    "gn:feature_code":"PPL",
    "gn:name":"Polyanskoye",
    "gn:population":0,
    "gn:timezone":"Europe/Moscow",
    "iso:country":"RU",
    "name:rus_x_preferred":[
        "\u041f\u043e\u043b\u044f\u043d\u0441\u043a\u043e\u0435"
    ],
    "wof:name":"Polyanskoye",
    "wof:placetype":"locality"
},
  "geometry": {"coordinates":[43.41508,55.92418000000001],"type":"Point"}
}