{
  "type": "Feature",
  "properties": {
    "gn:admin1_code":"60",
    "gn:asciiname":"Lebeshovo",
    "gn:country_code":"RU",
    "gn:dem":93,
    "gn:feature_class":"P",
    "gn:feature_code":"PPL",
    "gn:name":"Lebeshovo",
    "gn:population":0,
    "gn:timezone":"Europe/Moscow",
    "iso:country":"RU",
    "name:rus_x_preferred":[
        "\u041b\u0435\u0431\u0435\u0448\u043e\u0432\u043e"
    ],
    "wof:name":"Lebeshovo",
    "wof:placetype":"locality"
},
  "geometry": {"coordinates":[30.4725,57.3251],"type":"Point"}
}