{
  "type": "Feature",
  "properties": {
    "gn:admin1_code":"20",
    "gn:asciiname":"Chikan",
    "gn:country_code":"RU",
    "gn:dem":448,
    "gn:feature_class":"P",
    "gn:feature_code":"PPL",
    "gn:name":"Chikan",
    "gn:population":0,
    "gn:timezone":"Asia/Irkutsk",
    "iso:country":"RU",
    "name:ceb_x_preferred":[
        "Chikan"
    ],
    "name:deu_x_preferred":[
        "Chikan"
    ],
    "name:eng_x_preferred":[
        "Chikan"
    ],
    "name:fra_x_preferred":[
        "Chikan"
    ],
    "name:nor_x_preferred":[
        "Tsjikan"
    ],
    "name:rus_x_preferred":[
        "\u0427\u0438\u043a\u0430\u043d"
    ],
    "name:spa_x_preferred":[
        "Chikan"
    ],
    "name:und_x_variant":[
        "\u0427\u0438\u043a\u0430\u043d",
        "Chikan"
    ],
    "wof:name":"Chikan",
    "wof:placetype":"locality"
},
  "geometry": {"coordinates":[105.65944,54.90416999999999],"type":"Point"}
}