{
  "type": "Feature",
  "properties": {
    "gn:admin1_code":"85",
    "gn:asciiname":"Podol'naya",
    "gn:country_code":"RU",
    "gn:dem":141,
    "gn:feature_class":"P",
    "gn:feature_code":"PPL",
    "gn:name":"Podol\u2019naya",
    "gn:population":0,
    "gn:timezone":"Europe/Moscow",
    "iso:country":"RU",
    "name:rus_x_preferred":[
        "\u041f\u043e\u0434\u043e\u043b\u044c\u043d\u0430\u044f"
    ],
    "name:und_x_variant":[
        "Podol\u2019naya"
    ],
    "wof:name":"Podol'naya",
    "wof:placetype":"locality"
},
  "geometry": {"coordinates":[40.50024000000001,59.48534],"type":"Point"}
}