{
  "type": "Feature",
  "properties": {
    "gn:admin1_code":"57",
    "gn:asciiname":"Kryukovka",
    "gn:country_code":"RU",
    "gn:dem":169,
    "gn:feature_class":"P",
    "gn:feature_code":"PPL",
    "gn:name":"Kryukovka",
    "gn:population":0,
    "gn:timezone":"Europe/Moscow",
    "iso:country":"RU",
    "name:rus_x_preferred":[
        "\u041a\u0440\u044e\u043a\u043e\u0432\u043a\u0430"
    ],
    "name:und_x_variant":[
        "\u041a\u0440\u044e\u043a\u043e\u0432\u043a\u0430"
    ],
    "wof:name":"Kryukovka",
    "wof:placetype":"locality"
},
  "geometry": {"coordinates":[43.47802,52.47275],"type":"Point"}
}