{
  "type": "Feature",
  "properties": {
    "gn:admin1_code":"69.0",
    "gn:asciiname":"Bol'shaya Lipnya",
    "gn:country_code":"RU",
    "gn:dem":217,
    "gn:feature_class":"P",
    "gn:feature_code":"PPL",
    "gn:name":"Bol\u2019shaya Lipnya",
    "gn:population":0,
    "gn:timezone":"Europe/Moscow",
    "iso:country":"RU",
    "name:rus_x_preferred":[
        "\u0411\u043e\u043b\u044c\u0448\u0430\u044f \u041b\u0438\u043f\u043d\u044f"
    ],
    "name:und_x_variant":[
        "Lipnya",
        "Bol\u2019shaya Lipnya"
    ],
    "wof:name":"Bol'shaya Lipnya",
    "wof:placetype":"locality"
},
  "geometry": {"coordinates":[33.153,54.48165],"type":"Point"}
}