{
  "type": "Feature",
  "properties": {
    "gn:admin1_code":"64",
    "gn:asciiname":"Vasil'yevo",
    "gn:cc2":"RU",
    "gn:country_code":"RU",
    "gn:dem":3,
    "gn:feature_class":"P",
    "gn:feature_code":"PPL",
    "gn:name":"Vasil'yevo",
    "gn:population":0,
    "gn:timezone":"Asia/Sakhalin",
    "iso:country":"RU",
    "name:und_x_variant":[
        "Futagami-gyoj\u014d",
        "Futagami",
        "Futakami"
    ],
    "wof:name":"Vasil'yevo",
    "wof:placetype":"locality"
},
  "geometry": {"coordinates":[155.41666999999995,50.01667],"type":"Point"}
}