{
  "type": "Feature",
  "properties": {
    "gn:admin1_code":"71",
    "gn:asciiname":"Petrovskaya",
    "gn:country_code":"RU",
    "gn:dem":92,
    "gn:feature_class":"P",
    "gn:feature_code":"PPL",
    "gn:name":"Petrovskaya",
    "gn:population":0,
    "gn:timezone":"Asia/Yekaterinburg",
    "iso:country":"RU",
    "name:eng_x_preferred":[
        "Petrovskaya"
    ],
    "name:nor_x_preferred":[
        "Petrovskaja"
    ],
    "name:rus_x_preferred":[
        "\u041f\u0435\u0442\u0440\u043e\u0432\u0441\u043a\u0430\u044f"
    ],
    "name:und_x_variant":[
        "Petrovskiy",
        "Petrovsk",
        "\u041f\u0435\u0442\u0440\u043e\u0432\u0441\u043a\u0430\u044f",
        "Petrovskaya"
    ],
    "wof:name":"Petrovskaya",
    "wof:placetype":"locality"
},
  "geometry": {"coordinates":[64.64875000000001,58.18431999999999],"type":"Point"}
}