{
  "type": "Feature",
  "properties": {
    "gn:admin1_code":"17.0",
    "gn:asciiname":"Kulif",
    "gn:country_code":"RU",
    "gn:dem":1009,
    "gn:feature_class":"P",
    "gn:feature_code":"PPL",
    "gn:name":"Kulif",
    "gn:population":0,
    "gn:timezone":"Europe/Moscow",
    "iso:country":"RU",
    "name:rus_x_preferred":[
        "\u041a\u0443\u043b\u0438\u0444"
    ],
    "wof:name":"Kulif",
    "wof:placetype":"locality"
},
  "geometry": {"coordinates":[47.88391,41.95955],"type":"Point"}
}