{
  "type": "Feature",
  "properties": {
    "gn:admin1_code":"4",
    "gn:asciiname":"Muravey",
    "gn:country_code":"RU",
    "gn:dem":249,
    "gn:feature_class":"P",
    "gn:feature_code":"PPL",
    "gn:name":"Muravey",
    "gn:population":0,
    "gn:timezone":"Asia/Barnaul",
    "iso:country":"RU",
    "name:eng_x_preferred":[
        "Muravey"
    ],
    "name:nor_x_preferred":[
        "Muravej"
    ],
    "name:rus_x_preferred":[
        "\u041c\u0443\u0440\u0430\u0432\u0435\u0439"
    ],
    "name:und_x_variant":[
        "Krasnyy Muravey"
    ],
    "wof:name":"Muravey",
    "wof:placetype":"locality"
},
  "geometry": {"coordinates":[84.72694,53.89471999999999],"type":"Point"}
}