{
  "type": "Feature",
  "properties": {
    "gn:admin1_code":"41",
    "gn:asciiname":"Starostinka",
    "gn:country_code":"RU",
    "gn:dem":164,
    "gn:feature_class":"P",
    "gn:feature_code":"PPL",
    "gn:name":"Starostinka",
    "gn:population":0,
    "gn:timezone":"Europe/Moscow",
    "iso:country":"RU",
    "name:rus_x_preferred":[
        "\u0421\u0442\u0430\u0440\u043e\u0441\u0442\u0438\u043d\u043a\u0430"
    ],
    "wof:name":"Starostinka",
    "wof:placetype":"locality"
},
  "geometry": {"coordinates":[34.9503,51.529],"type":"Point"}
}