{
  "type": "Feature",
  "properties": {
    "gn:admin1_code":"51",
    "gn:asciiname":"Ishutino",
    "gn:country_code":"RU",
    "gn:dem":139,
    "gn:feature_class":"P",
    "gn:feature_code":"PPL",
    "gn:name":"Ishutino",
    "gn:population":0,
    "gn:timezone":"Europe/Moscow",
    "iso:country":"RU",
    "name:rus_x_preferred":[
        "\u0418\u0448\u0443\u0442\u0438\u043d\u043e"
    ],
    "wof:name":"Ishutino",
    "wof:placetype":"locality"
},
  "geometry": {"coordinates":[42.81399999999999,55.9316],"type":"Point"}
}