{
  "type": "Feature",
  "properties": {
    "gn:admin1_code":"9.0",
    "gn:asciiname":"Repenka",
    "gn:country_code":"RU",
    "gn:dem":118,
    "gn:feature_class":"P",
    "gn:feature_code":"PPL",
    "gn:name":"Repenka",
    "gn:population":0,
    "gn:timezone":"Europe/Moscow",
    "iso:country":"RU",
    "name:rus_x_preferred":[
        "\u0420\u0435\u043f\u0435\u043d\u043a\u0430"
    ],
    "wof:name":"Repenka",
    "wof:placetype":"locality"
},
  "geometry": {"coordinates":[38.3845,50.7183],"type":"Point"}
}