{
  "type": "Feature",
  "properties": {
    "gn:admin1_code":"88.0",
    "gn:asciiname":"Kostikhino",
    "gn:country_code":"RU",
    "gn:dem":128,
    "gn:feature_class":"P",
    "gn:feature_code":"PPL",
    "gn:name":"Kostikhino",
    "gn:population":0,
    "gn:timezone":"Europe/Moscow",
    "iso:country":"RU",
    "name:rus_x_preferred":[
        "\u041a\u043e\u0441\u0442\u0438\u0445\u0438\u043d\u043e"
    ],
    "wof:name":"Kostikhino",
    "wof:placetype":"locality"
},
  "geometry": {"coordinates":[40.87027,58.39412],"type":"Point"}
}