{
  "type": "Feature",
  "properties": {
    "gn:admin1_code":"45.0",
    "gn:asciiname":"Russkiy Noledur",
    "gn:country_code":"RU",
    "gn:dem":122,
    "gn:feature_class":"P",
    "gn:feature_code":"PPL",
    "gn:name":"Russkiy Noledur",
    "gn:population":0,
    "gn:timezone":"Europe/Moscow",
    "iso:country":"RU",
    "name:rus_x_preferred":[
        "\u0420\u0443\u0441\u0441\u043a\u0438\u0439 \u041d\u043e\u043b\u0435\u0434\u0443\u0440"
    ],
    "wof:name":"Russkiy Noledur",
    "wof:placetype":"locality"
},
  "geometry": {"coordinates":[49.61058,56.75126],"type":"Point"}
}