{
  "type": "Feature",
  "properties": {
    "gn:admin1_code":"77",
    "gn:asciiname":"Babaikha",
    "gn:country_code":"RU",
    "gn:dem":140,
    "gn:feature_class":"P",
    "gn:feature_code":"PPL",
    "gn:name":"Babaikha",
    "gn:population":0,
    "gn:timezone":"Europe/Moscow",
    "iso:country":"RU",
    "name:rus_x_preferred":[
        "\u0411\u0430\u0431\u0430\u0438\u0445\u0430"
    ],
    "name:und_x_variant":[
        "\u0411\u0430\u0431\u0430\u0438\u0445\u0430"
    ],
    "wof:name":"Babaikha",
    "wof:placetype":"locality"
},
  "geometry": {"coordinates":[36.4149,57.2212],"type":"Point"}
}