{
  "type": "Feature",
  "properties": {
    "gn:admin1_code":"8",
    "gn:asciiname":"Gumbetovo",
    "gn:country_code":"RU",
    "gn:dem":237,
    "gn:feature_class":"P",
    "gn:feature_code":"PPL",
    "gn:name":"Gumbetovo",
    "gn:population":0,
    "gn:timezone":"Asia/Yekaterinburg",
    "iso:country":"RU",
    "name:rus_x_preferred":[
        "\u0413\u0443\u043c\u0431\u0435\u0442\u043e\u0432\u043e"
    ],
    "name:und_x_variant":[
        "Gumbet",
        "Gumbetovo"
    ],
    "wof:name":"Gumbetovo",
    "wof:placetype":"locality"
},
  "geometry": {"coordinates":[55.3917,53.1924],"type":"Point"}
}