{
  "type": "Feature",
  "properties": {
    "gn:admin1_code":"93",
    "gn:asciiname":"Alenguy",
    "gn:country_code":"RU",
    "gn:dem":851,
    "gn:feature_class":"P",
    "gn:feature_code":"PPL",
    "gn:name":"Alenguy",
    "gn:population":0,
    "gn:timezone":"Asia/Chita",
    "iso:country":"RU",
    "name:nor_x_preferred":[
        "Alenguj"
    ],
    "name:rus_x_preferred":[
        "\u0410\u043b\u0435\u043d\u0433\u0443\u0439"
    ],
    "wof:name":"Alenguy",
    "wof:placetype":"locality"
},
  "geometry": {"coordinates":[117.33126,51.26476],"type":"Point"}
}