{
  "type": "Feature",
  "properties": {
    "gn:admin1_code":"20",
    "gn:asciiname":"Protasova",
    "gn:country_code":"RU",
    "gn:dem":566,
    "gn:feature_class":"P",
    "gn:feature_code":"PPL",
    "gn:name":"Protasova",
    "gn:population":0,
    "gn:timezone":"Asia/Irkutsk",
    "iso:country":"RU",
    "name:rus_x_preferred":[
        "\u041f\u0440\u043e\u0442\u0430\u0441\u043e\u0432\u0430"
    ],
    "name:und_x_variant":[
        "Zimnik Protasova",
        "Protasova"
    ],
    "wof:name":"Protasova",
    "wof:placetype":"locality"
},
  "geometry": {"coordinates":[102.9555,53.0043],"type":"Point"}
}