{
  "type": "Feature",
  "properties": {
    "gn:admin1_code":"42",
    "gn:asciiname":"Uglovo",
    "gn:country_code":"RU",
    "gn:dem":46,
    "gn:feature_class":"P",
    "gn:feature_code":"PPL",
    "gn:name":"Uglovo",
    "gn:population":0,
    "gn:timezone":"Europe/Moscow",
    "iso:country":"RU",
    "name:fin_x_preferred":[
        "K\u00e4hy"
    ],
    "name:rus_x_preferred":[
        "\u0423\u0433\u043b\u043e\u0432\u043e"
    ],
    "wof:name":"Uglovo",
    "wof:placetype":"locality"
},
  "geometry": {"coordinates":[30.732,60.06779],"type":"Point"}
}