{
  "type": "Feature",
  "properties": {
    "gn:admin1_code":"62",
    "gn:asciiname":"Rzhavskiye Vyselki",
    "gn:cc2":"RU",
    "gn:country_code":"RU",
    "gn:dem":144,
    "gn:feature_class":"P",
    "gn:feature_code":"PPL",
    "gn:name":"Rzhavskiye Vyselki",
    "gn:population":0,
    "gn:timezone":"Europe/Moscow",
    "iso:country":"RU",
    "name:rus_x_preferred":[
        "\u0420\u0436\u0430\u0432\u0441\u043a\u0438\u0435 \u0412\u044b\u0441\u0435\u043b\u043a\u0438"
    ],
    "name:und_x_variant":[
        "Rzhovskiye Vyselki",
        "Rzhavskiye Vyselki"
    ],
    "wof:name":"Rzhavskiye Vyselki",
    "wof:placetype":"locality"
},
  "geometry": {"coordinates":[39.75611,54.11306],"type":"Point"}
}