{
  "type": "Feature",
  "properties": {
    "gn:admin1_code":"76",
    "gn:asciiname":"Poselok Michurina",
    "gn:country_code":"RU",
    "gn:dem":232,
    "gn:feature_class":"P",
    "gn:feature_code":"PPL",
    "gn:name":"Pos\u00eblok Michurina",
    "gn:population":0,
    "gn:timezone":"Europe/Moscow",
    "iso:country":"RU",
    "name:rus_x_preferred":[
        "\u041f\u043e\u0441\u0451\u043b\u043e\u043a \u041c\u0438\u0447\u0443\u0440\u0438\u043d\u0430"
    ],
    "name:und_x_variant":[
        "Pos\u00eblok Michurina",
        "\u041f\u043e\u0441\u0451\u043b\u043e\u043a \u041c\u0438\u0447\u0443\u0440\u0438\u043d\u0430",
        "Pos\u00eblok Imeni Michurina"
    ],
    "wof:name":"Poselok Michurina",
    "wof:placetype":"locality"
},
  "geometry": {"coordinates":[38.015,53.1745],"type":"Point"}
}