{
  "type": "Feature",
  "properties": {
    "gn:admin1_code":"20.0",
    "gn:asciiname":"Kherbuy",
    "gn:country_code":"RU",
    "gn:dem":391,
    "gn:feature_class":"P",
    "gn:feature_code":"PPL",
    "gn:name":"Kherbuy",
    "gn:population":0,
    "gn:timezone":"Asia/Irkutsk",
    "iso:country":"RU",
    "name:rus_x_preferred":[
        "\u0425\u0435\u0440\u0431\u0443\u0439"
    ],
    "wof:name":"Kherbuy",
    "wof:placetype":"locality"
},
  "geometry": {"coordinates":[103.68600000000001,53.5441],"type":"Point"}
}