{
  "type": "Feature",
  "properties": {
    "gn:admin1_code":"53",
    "gn:asciiname":"Lyashkino",
    "gn:cc2":"RU",
    "gn:country_code":"RU",
    "gn:dem":123,
    "gn:feature_class":"P",
    "gn:feature_code":"PPL",
    "gn:name":"Lyashkino",
    "gn:population":0,
    "gn:timezone":"Asia/Novosibirsk",
    "iso:country":"RU",
    "name:rus_x_preferred":[
        "\u041b\u044f\u0448\u043a\u0438\u043d\u043e"
    ],
    "name:und_x_variant":[
        "Lyashkina",
        "Lyashkino"
    ],
    "wof:name":"Lyashkino",
    "wof:placetype":"locality"
},
  "geometry": {"coordinates":[78.43333,55.73333],"type":"Point"}
}