{
  "type": "Feature",
  "properties": {
    "gn:admin1_code":"76",
    "gn:asciiname":"Gryzlovo Pervoye",
    "gn:country_code":"RU",
    "gn:dem":204,
    "gn:feature_class":"P",
    "gn:feature_code":"PPL",
    "gn:name":"Gryzlovo Pervoye",
    "gn:population":0,
    "gn:timezone":"Europe/Moscow",
    "iso:country":"RU",
    "name:rus_x_preferred":[
        "\u0413\u0440\u044b\u0437\u043b\u043e\u0432\u043e \u041f\u0435\u0440\u0432\u043e\u0435"
    ],
    "name:und_x_variant":[
        "\u0413\u0440\u044b\u0437\u043b\u043e\u0432\u043e \u041f\u0435\u0440\u0432\u043e\u0435"
    ],
    "wof:name":"Gryzlovo Pervoye",
    "wof:placetype":"locality"
},
  "geometry": {"coordinates":[38.01667,54.25],"type":"Point"}
}