{
  "type": "Feature",
  "properties": {
    "gn:admin1_code":"37.0",
    "gn:asciiname":"Krasnyye Pozhni",
    "gn:country_code":"RU",
    "gn:dem":104,
    "gn:feature_class":"P",
    "gn:feature_code":"PPL",
    "gn:name":"Krasnyye Pozhni",
    "gn:population":0,
    "gn:timezone":"Europe/Moscow",
    "iso:country":"RU",
    "name:rus_x_preferred":[
        "\u041a\u0440\u0430\u0441\u043d\u044b\u0435 \u041f\u043e\u0436\u043d\u0438"
    ],
    "name:und_x_variant":[
        "\u041a\u0440\u0430\u0441\u043d\u044b\u0435 \u041f\u043e\u0436\u043d\u0438"
    ],
    "wof:name":"Krasnyye Pozhni",
    "wof:placetype":"locality"
},
  "geometry": {"coordinates":[41.22716,57.48342],"type":"Point"}
}