{
  "type": "Feature",
  "properties": {
    "gn:admin1_code":"10",
    "gn:asciiname":"Platovyy Dub",
    "gn:country_code":"RU",
    "gn:dem":184,
    "gn:feature_class":"P",
    "gn:feature_code":"PPL",
    "gn:name":"Platovyy Dub",
    "gn:population":0,
    "gn:timezone":"Europe/Moscow",
    "iso:country":"RU",
    "name:rus_x_preferred":[
        "\u041f\u043b\u0430\u0442\u043e\u0432\u044b\u0439 \u0414\u0443\u0431"
    ],
    "wof:name":"Platovyy Dub",
    "wof:placetype":"locality"
},
  "geometry": {"coordinates":[33.92095,53.10491999999999],"type":"Point"}
}