{
  "type": "Feature",
  "properties": {
    "gn:admin1_code":"69",
    "gn:asciiname":"Ustinovka",
    "gn:country_code":"RU",
    "gn:dem":204,
    "gn:feature_class":"P",
    "gn:feature_code":"PPL",
    "gn:name":"Ustinovka",
    "gn:population":0,
    "gn:timezone":"Europe/Moscow",
    "iso:country":"RU",
    "name:rus_x_preferred":[
        "\u0423\u0441\u0442\u0438\u043d\u043e\u0432\u043a\u0430"
    ],
    "wof:name":"Ustinovka",
    "wof:placetype":"locality"
},
  "geometry": {"coordinates":[32.24237,55.03356],"type":"Point"}
}