{
  "type": "Feature",
  "properties": {
    "gn:admin1_code":"88",
    "gn:asciiname":"Latka",
    "gn:country_code":"RU",
    "gn:dem":133,
    "gn:feature_class":"P",
    "gn:feature_code":"PPL",
    "gn:name":"Latka",
    "gn:population":0,
    "gn:timezone":"Europe/Moscow",
    "iso:country":"RU",
    "name:eng_x_preferred":[
        "Latka"
    ],
    "name:nor_x_preferred":[
        "Latka"
    ],
    "name:rus_x_preferred":[
        "\u041b\u0430\u0442\u043a\u0430"
    ],
    "wof:name":"Latka",
    "wof:placetype":"locality"
},
  "geometry": {"coordinates":[39.04467,57.42829],"type":"Point"}
}