{
  "type": "Feature",
  "properties": {
    "gn:admin1_code":"47",
    "gn:asciiname":"Mogil'tsy",
    "gn:country_code":"RU",
    "gn:dem":160,
    "gn:feature_class":"P",
    "gn:feature_code":"PPL",
    "gn:name":"Mogil\u2019tsy",
    "gn:population":0,
    "gn:timezone":"Europe/Moscow",
    "iso:country":"RU",
    "name:nor_x_preferred":[
        "Mogiltsy"
    ],
    "name:rus_x_preferred":[
        "\u041c\u043e\u0433\u0438\u043b\u044c\u0446\u044b"
    ],
    "name:und_x_variant":[
        "Mogil\u2019tsy"
    ],
    "wof:name":"Mogil'tsy",
    "wof:placetype":"locality"
},
  "geometry": {"coordinates":[35.57078,56.32645],"type":"Point"}
}