{
  "type": "Feature",
  "properties": {
    "gn:admin1_code":"71",
    "gn:asciiname":"Aramashevo",
    "gn:country_code":"RU",
    "gn:dem":158,
    "gn:feature_class":"P",
    "gn:feature_code":"PPL",
    "gn:name":"Aramashevo",
    "gn:population":0,
    "gn:timezone":"Asia/Yekaterinburg",
    "iso:country":"RU",
    "name:eng_x_preferred":[
        "Aramashevo"
    ],
    "name:nor_x_preferred":[
        "Aramasjevo"
    ],
    "name:rus_x_preferred":[
        "\u0410\u0440\u0430\u043c\u0430\u0448\u0435\u0432\u043e"
    ],
    "name:und_x_variant":[
        "Armashev"
    ],
    "wof:name":"Aramashevo",
    "wof:placetype":"locality"
},
  "geometry": {"coordinates":[61.72941,57.6079],"type":"Point"}
}