{
  "type": "Feature",
  "properties": {
    "gn:admin1_code":"91",
    "gn:asciiname":"Il'inka",
    "gn:country_code":"RU",
    "gn:dem":253,
    "gn:feature_class":"P",
    "gn:feature_code":"PPL",
    "gn:name":"Il\u2019inka",
    "gn:population":0,
    "gn:timezone":"Asia/Krasnoyarsk",
    "iso:country":"RU",
    "name:eng_x_preferred":[
        "Il'inka"
    ],
    "name:nor_x_preferred":[
        "Ilinka"
    ],
    "name:rus_x_preferred":[
        "\u0418\u043b\u044c\u0438\u043d\u043a\u0430"
    ],
    "name:und_x_variant":[
        "Pen\u2019ki",
        "Il\u2019inskoye",
        "Il\u2019inka"
    ],
    "wof:name":"Il'inka",
    "wof:placetype":"locality"
},
  "geometry": {"coordinates":[90.54194,55.88583000000001],"type":"Point"}
}