{
  "type": "Feature",
  "properties": {
    "gn:admin1_code":"10",
    "gn:asciiname":"Krasnyy Ugol",
    "gn:country_code":"RU",
    "gn:dem":180,
    "gn:feature_class":"P",
    "gn:feature_code":"PPL",
    "gn:name":"Krasnyy Ugol",
    "gn:population":0,
    "gn:timezone":"Europe/Moscow",
    "iso:country":"RU",
    "name:rus_x_preferred":[
        "\u041a\u0440\u0430\u0441\u043d\u044b\u0439 \u0423\u0433\u043e\u043b"
    ],
    "wof:name":"Krasnyy Ugol",
    "wof:placetype":"locality"
},
  "geometry": {"coordinates":[33.885,53.51167],"type":"Point"}
}