{
  "type": "Feature",
  "properties": {
    "gn:admin1_code":"37",
    "gn:asciiname":"Tentyukovo",
    "gn:country_code":"RU",
    "gn:dem":190,
    "gn:feature_class":"P",
    "gn:feature_code":"PPL",
    "gn:name":"Tentyukovo",
    "gn:population":0,
    "gn:timezone":"Europe/Moscow",
    "iso:country":"RU",
    "name:rus_x_preferred":[
        "\u0422\u0435\u043d\u0442\u044e\u043a\u043e\u0432\u043e"
    ],
    "wof:name":"Tentyukovo",
    "wof:placetype":"locality"
},
  "geometry": {"coordinates":[42.4707,58.4577],"type":"Point"}
}