{
  "type": "Feature",
  "properties": {
    "gn:admin1_code":"53",
    "gn:asciiname":"Kirovo",
    "gn:country_code":"RU",
    "gn:dem":148,
    "gn:feature_class":"P",
    "gn:feature_code":"PPL",
    "gn:name":"Kirovo",
    "gn:population":0,
    "gn:timezone":"Asia/Novosibirsk",
    "iso:country":"RU",
    "name:bel_x_preferred":[
        "\u041a\u0456\u0440\u0430\u0432\u0430"
    ],
    "name:ceb_x_preferred":[
        "Kirovo"
    ],
    "name:che_x_preferred":[
        "\u041a\u0438\u0440\u043e\u0432\u043e"
    ],
    "name:hye_x_preferred":[
        "\u053f\u056b\u0580\u0578\u057e\u0578"
    ],
    "name:kaz_x_preferred":[
        "\u041a\u0438\u0440\u043e\u0432\u043e"
    ],
    "name:lav_x_preferred":[
        "Kirovo"
    ],
    "name:oss_x_preferred":[
        "\u041a\u0438\u0440\u043e\u0432\u043e"
    ],
    "name:rus_x_preferred":[
        "\u041a\u0438\u0440\u043e\u0432\u043e"
    ],
    "name:ukr_x_preferred":[
        "\u041a\u0456\u0440\u043e\u0432\u043e"
    ],
    "name:und_x_variant":[
        "Imeni Kirova",
        "Kirovo",
        "\u041a\u0438\u0440\u043e\u0432\u043e"
    ],
    "wof:name":"Kirovo",
    "wof:placetype":"locality"
},
  "geometry": {"coordinates":[83.0945,54.813],"type":"Point"}
}