{
  "type": "Feature",
  "properties": {
    "gn:admin1_code":"21",
    "gn:asciiname":"Trubkino",
    "gn:country_code":"RU",
    "gn:dem":136,
    "gn:feature_class":"P",
    "gn:feature_code":"PPL",
    "gn:name":"Trubkino",
    "gn:population":0,
    "gn:timezone":"Europe/Moscow",
    "iso:country":"RU",
    "name:rus_x_preferred":[
        "\u0422\u0440\u0443\u0431\u043a\u0438\u043d\u043e"
    ],
    "wof:name":"Trubkino",
    "wof:placetype":"locality"
},
  "geometry": {"coordinates":[40.10248,56.94923000000001],"type":"Point"}
}