{
  "type": "Feature",
  "properties": {
    "gn:admin1_code":"8",
    "gn:asciiname":"Urmantau",
    "gn:country_code":"RU",
    "gn:dem":256,
    "gn:feature_class":"P",
    "gn:feature_code":"PPL",
    "gn:name":"Urmantau",
    "gn:population":0,
    "gn:timezone":"Asia/Yekaterinburg",
    "iso:country":"RU",
    "name:eng_x_preferred":[
        "Urmantau"
    ],
    "name:nor_x_preferred":[
        "Urmantau"
    ],
    "name:rus_x_preferred":[
        "\u0423\u0440\u043c\u0430\u043d\u0442\u0430\u0443"
    ],
    "wof:name":"Urmantau",
    "wof:placetype":"locality"
},
  "geometry": {"coordinates":[57.70932,55.47567],"type":"Point"}
}