{
  "type": "Feature",
  "properties": {
    "gn:admin1_code":"41",
    "gn:asciiname":"Vyshniye Dereven'ki",
    "gn:country_code":"RU",
    "gn:dem":161,
    "gn:feature_class":"P",
    "gn:feature_code":"PPL",
    "gn:name":"Vyshniye Dereven\u2019ki",
    "gn:population":0,
    "gn:timezone":"Europe/Moscow",
    "iso:country":"RU",
    "name:eng_x_preferred":[
        "Vyshniye Dereven'ki"
    ],
    "name:nor_x_preferred":[
        "Vysjnije-Derevenki"
    ],
    "name:rus_x_preferred":[
        "\u0412\u044b\u0448\u043d\u0438\u0435-\u0414\u0435\u0440\u0435\u0432\u0435\u043d\u044c\u043a\u0438"
    ],
    "name:rus_x_variant":[
        "\u0412\u044b\u0448\u043d\u0438\u0435 \u0414\u0435\u0440\u0435\u0432\u0435\u043d\u044c\u043a\u0438"
    ],
    "name:und_x_variant":[
        "Vyshniye Dereven\u2019ki"
    ],
    "wof:name":"Vyshniye Dereven'ki",
    "wof:placetype":"locality"
},
  "geometry": {"coordinates":[35.2963,51.5552],"type":"Point"}
}