{
  "type": "Feature",
  "properties": {
    "gn:admin1_code":"78",
    "gn:asciiname":"Usovo",
    "gn:country_code":"RU",
    "gn:dem":136,
    "gn:feature_class":"P",
    "gn:feature_code":"PPL",
    "gn:name":"Usovo",
    "gn:population":0,
    "gn:timezone":"Asia/Yekaterinburg",
    "iso:country":"RU",
    "name:eng_x_preferred":[
        "Usovo"
    ],
    "name:nor_x_preferred":[
        "Usovo"
    ],
    "name:rus_x_preferred":[
        "\u0423\u0441\u043e\u0432\u043e"
    ],
    "name:und_x_variant":[
        "Usovskoye",
        "Usovo"
    ],
    "wof:name":"Usovo",
    "wof:placetype":"locality"
},
  "geometry": {"coordinates":[69.90828,55.44843],"type":"Point"}
}