{
  "type": "Feature",
  "properties": {
    "gn:admin1_code":"80.0",
    "gn:asciiname":"Sedoylud",
    "gn:country_code":"RU",
    "gn:dem":175,
    "gn:feature_class":"P",
    "gn:feature_code":"PPL",
    "gn:name":"Sedoylud",
    "gn:population":0,
    "gn:timezone":"Europe/Samara",
    "iso:country":"RU",
    "name:rus_x_preferred":[
        "\u0421\u0435\u0434\u043e\u0439\u043b\u0443\u0434"
    ],
    "wof:name":"Sedoylud",
    "wof:placetype":"locality"
},
  "geometry": {"coordinates":[53.3999,57.549],"type":"Point"}
}