{
  "type": "Feature",
  "properties": {
    "gn:admin1_code":"90",
    "gn:asciiname":"Rodniki",
    "gn:country_code":"RU",
    "gn:dem":276,
    "gn:feature_class":"P",
    "gn:feature_code":"PPL",
    "gn:name":"Rodniki",
    "gn:population":0,
    "gn:timezone":"Asia/Yekaterinburg",
    "iso:country":"RU",
    "name:eng_x_preferred":[
        "Rodniki"
    ],
    "name:nor_x_preferred":[
        "Rodniki"
    ],
    "name:rus_x_preferred":[
        "\u0420\u043e\u0434\u043d\u0438\u043a\u0438"
    ],
    "name:sco_x_preferred":[
        "Rodniki"
    ],
    "name:und_x_variant":[
        "\u0420\u043e\u0434\u043d\u0438\u043a\u0438",
        "Rodniki"
    ],
    "wof:name":"Rodniki",
    "wof:placetype":"locality"
},
  "geometry": {"coordinates":[56.7573,58.4831],"type":"Point"}
}