{
  "type": "Feature",
  "properties": {
    "gn:admin1_code":"90.0",
    "gn:asciiname":"Staroye Tyapugino",
    "gn:country_code":"RU",
    "gn:dem":152,
    "gn:feature_class":"P",
    "gn:feature_code":"PPL",
    "gn:name":"Staroye Tyapugino",
    "gn:population":0,
    "gn:timezone":"Asia/Yekaterinburg",
    "iso:country":"RU",
    "name:rus_x_preferred":[
        "\u0421\u0442\u0430\u0440\u043e\u0435 \u0422\u044f\u043f\u0443\u0433\u0438\u043d\u043e"
    ],
    "wof:name":"Staroye Tyapugino",
    "wof:placetype":"locality"
},
  "geometry": {"coordinates":[55.7359,58.794],"type":"Point"}
}