{
  "type": "Feature",
  "properties": {
    "gn:admin1_code":"16",
    "gn:asciiname":"Ishmurzino-Surinsk",
    "gn:country_code":"RU",
    "gn:dem":104,
    "gn:feature_class":"P",
    "gn:feature_code":"PPL",
    "gn:name":"Ishmurzino-Surinsk",
    "gn:population":0,
    "gn:timezone":"Europe/Moscow",
    "iso:country":"RU",
    "name:rus_x_preferred":[
        "\u0418\u0448\u043c\u0443\u0440\u0437\u0438\u043d\u043e-\u0421\u0443\u0440\u0438\u043d\u0441\u043a"
    ],
    "name:und_x_variant":[
        "Irmurzino-Surinsk",
        "Ishmurzino-Surinsk",
        "\u0418\u0448\u043c\u0443\u0440\u0437\u0438\u043d\u043e-\u0421\u0443\u0440\u0438\u043d\u0441\u043a"
    ],
    "wof:name":"Ishmurzino-Surinsk",
    "wof:placetype":"locality"
},
  "geometry": {"coordinates":[47.8974,55.05646],"type":"Point"}
}