{
  "type": "Feature",
  "properties": {
    "gn:admin1_code":"80",
    "gn:asciiname":"Mozhvay",
    "gn:country_code":"RU",
    "gn:dem":136,
    "gn:feature_class":"P",
    "gn:feature_code":"PPL",
    "gn:name":"Mozhvay",
    "gn:population":0,
    "gn:timezone":"Europe/Samara",
    "iso:country":"RU",
    "name:rus_x_preferred":[
        "\u041c\u043e\u0436\u0432\u0430\u0439"
    ],
    "wof:name":"Mozhvay",
    "wof:placetype":"locality"
},
  "geometry": {"coordinates":[52.90311,56.82631],"type":"Point"}
}