{
  "type": "Feature",
  "properties": {
    "gn:admin1_code":"72.0",
    "gn:asciiname":"Al'fa",
    "gn:country_code":"RU",
    "gn:dem":125,
    "gn:feature_class":"P",
    "gn:feature_code":"PPL",
    "gn:name":"Al\u2019fa",
    "gn:population":0,
    "gn:timezone":"Europe/Moscow",
    "iso:country":"RU",
    "name:nor_x_preferred":[
        "Alfa"
    ],
    "name:rus_x_preferred":[
        "\u0410\u043b\u044c\u0444\u0430"
    ],
    "name:rus_x_variant":[
        "Al\u2019fa"
    ],
    "name:und_x_variant":[
        "Al\u2019fa"
    ],
    "wof:name":"Al'fa",
    "wof:placetype":"locality"
},
  "geometry": {"coordinates":[40.5347,52.4539],"type":"Point"}
}