{
  "type": "Feature",
  "properties": {
    "gn:admin1_code":"4",
    "gn:asciiname":"Pobedim",
    "gn:country_code":"RU",
    "gn:dem":208,
    "gn:feature_class":"P",
    "gn:feature_code":"PPL",
    "gn:name":"Pobedim",
    "gn:population":0,
    "gn:timezone":"Asia/Barnaul",
    "iso:country":"RU",
    "name:cat_x_preferred":[
        "Pobedim"
    ],
    "name:ces_x_preferred":[
        "Pobedim"
    ],
    "name:deu_x_preferred":[
        "Pobedim"
    ],
    "name:epo_x_preferred":[
        "Pobedim"
    ],
    "name:eus_x_preferred":[
        "Pobedim"
    ],
    "name:fra_x_preferred":[
        "Pobedim"
    ],
    "name:hun_x_preferred":[
        "Pobed\u00e9ny"
    ],
    "name:ita_x_preferred":[
        "Pobedim"
    ],
    "name:msa_x_preferred":[
        "Pobedim"
    ],
    "name:nld_x_preferred":[
        "Pobedim"
    ],
    "name:pol_x_preferred":[
        "Pobedim"
    ],
    "name:ron_x_preferred":[
        "Pobedim"
    ],
    "name:rus_x_preferred":[
        "\u041f\u043e\u0431\u0435\u0434\u0438\u043c"
    ],
    "name:slk_x_preferred":[
        "Pobedim"
    ],
    "name:spa_x_preferred":[
        "Pobedim"
    ],
    "name:srp_x_preferred":[
        "\u041f\u043e\u0431\u0435\u0434\u0438\u043c"
    ],
    "name:war_x_preferred":[
        "Pobedim"
    ],
    "wof:name":"Pobedim",
    "wof:placetype":"locality"
},
  "geometry": {"coordinates":[82.8094,52.6425],"type":"Point"}
}