{
  "type": "Feature",
  "properties": {
    "gn:admin1_code":"52",
    "gn:asciiname":"Spasskaya Polist'",
    "gn:country_code":"RU",
    "gn:dem":34,
    "gn:feature_class":"P",
    "gn:feature_code":"PPL",
    "gn:name":"Spasskaya Polist\u2019",
    "gn:population":0,
    "gn:timezone":"Europe/Moscow",
    "iso:country":"RU",
    "name:eng_x_preferred":[
        "Spasskaya Polist"
    ],
    "name:nor_x_preferred":[
        "Spasskaja-Polist"
    ],
    "name:rus_x_preferred":[
        "\u0421\u043f\u0430\u0441\u0441\u043a\u0430\u044f-\u041f\u043e\u043b\u0438\u0441\u0442\u044c"
    ],
    "name:rus_x_variant":[
        "\u0421\u043f\u0430\u0441\u0441\u043a\u0430\u044f \u041f\u043e\u043b\u0438\u0441\u0442\u044c"
    ],
    "name:und_x_variant":[
        "Spasskaya Polist\u2019"
    ],
    "wof:name":"Spasskaya Polist'",
    "wof:placetype":"locality"
},
  "geometry": {"coordinates":[31.51667,58.93333000000001],"type":"Point"}
}