{
  "type": "Feature",
  "properties": {
    "gn:admin1_code":"9.0",
    "gn:asciiname":"Bezgodovka",
    "gn:country_code":"RU",
    "gn:dem":92,
    "gn:feature_class":"P",
    "gn:feature_code":"PPL",
    "gn:name":"Bezgodovka",
    "gn:population":0,
    "gn:timezone":"Europe/Moscow",
    "iso:country":"RU",
    "name:nor_x_preferred":[
        "Bezgodovka"
    ],
    "name:rus_x_preferred":[
        "\u0411\u0435\u0437\u0433\u043e\u0434\u043e\u0432\u043a\u0430"
    ],
    "wof:name":"Bezgodovka",
    "wof:placetype":"locality"
},
  "geometry": {"coordinates":[38.2338,50.2679],"type":"Point"}
}