{
  "type": "Feature",
  "properties": {
    "gn:admin1_code":"80.0",
    "gn:asciiname":"Fedoski",
    "gn:country_code":"RU",
    "gn:dem":187,
    "gn:feature_class":"P",
    "gn:feature_code":"PPL",
    "gn:name":"Fedoski",
    "gn:population":0,
    "gn:timezone":"Europe/Samara",
    "iso:country":"RU",
    "name:rus_x_preferred":[
        "\u0424\u0435\u0434\u043e\u0441\u043a\u0438"
    ],
    "name:und_x_variant":[
        "\u0424\u0435\u0434\u043e\u0441\u043a\u0438"
    ],
    "wof:name":"Fedoski",
    "wof:placetype":"locality"
},
  "geometry": {"coordinates":[53.43333000000001,56.73333],"type":"Point"}
}