{
  "type": "Feature",
  "properties": {
    "gn:admin1_code":"77",
    "gn:asciiname":"Yur'yevskoye",
    "gn:country_code":"RU",
    "gn:dem":134,
    "gn:feature_class":"P",
    "gn:feature_code":"PPL",
    "gn:name":"Yur\u2019yevskoye",
    "gn:population":0,
    "gn:timezone":"Europe/Moscow",
    "iso:country":"RU",
    "name:rus_x_preferred":[
        "\u042e\u0440\u044c\u0435\u0432\u0441\u043a\u043e\u0435"
    ],
    "name:und_x_variant":[
        "Yur\u2019yevskoye",
        "\u042e\u0440\u044c\u0435\u0432\u0441\u043a\u043e\u0435"
    ],
    "wof:name":"Yur'yevskoye",
    "wof:placetype":"locality"
},
  "geometry": {"coordinates":[36.5668,57.6751],"type":"Point"}
}