{
  "type": "Feature",
  "properties": {
    "gn:admin1_code":"6",
    "gn:asciiname":"Zadovaya",
    "gn:country_code":"RU",
    "gn:dem":69,
    "gn:feature_class":"P",
    "gn:feature_code":"PPL",
    "gn:name":"Zadovaya",
    "gn:population":0,
    "gn:timezone":"Europe/Moscow",
    "iso:country":"RU",
    "name:eng_x_preferred":[
        "Zadovaya"
    ],
    "name:nor_x_preferred":[
        "Zadovaja"
    ],
    "name:rus_x_preferred":[
        "\u0417\u0430\u0434\u043e\u0432\u0430\u044f"
    ],
    "wof:name":"Zadovaya",
    "wof:placetype":"locality"
},
  "geometry": {"coordinates":[47.31728,61.36691],"type":"Point"}
}