{
  "type": "Feature",
  "properties": {
    "gn:admin1_code":"23",
    "gn:asciiname":"Sadovoye",
    "gn:country_code":"RU",
    "gn:dem":87,
    "gn:feature_class":"P",
    "gn:feature_code":"PPL",
    "gn:name":"Sadovoye",
    "gn:population":0,
    "gn:timezone":"Europe/Kaliningrad",
    "iso:country":"RU",
    "name:rus_x_preferred":[
        "\u0421\u0430\u0434\u043e\u0432\u043e\u0435"
    ],
    "name:und_x_variant":[
        "Baletkhen",
        "Sadovoe",
        "Ballethen",
        "Sadovoye"
    ],
    "wof:name":"Sadovoye",
    "wof:placetype":"locality"
},
  "geometry": {"coordinates":[21.9236,54.47725],"type":"Point"}
}