{
  "type": "Feature",
  "properties": {
    "gn:admin1_code":"77",
    "gn:asciiname":"Nemkovo",
    "gn:country_code":"RU",
    "gn:dem":261,
    "gn:feature_class":"P",
    "gn:feature_code":"PPL",
    "gn:name":"Nemkovo",
    "gn:population":0,
    "gn:timezone":"Europe/Moscow",
    "iso:country":"RU",
    "name:rus_x_preferred":[
        "\u041d\u0435\u043c\u043a\u043e\u0432\u043e"
    ],
    "name:und_x_variant":[
        "\u041d\u0435\u043c\u043a\u043e\u0432\u043e"
    ],
    "wof:name":"Nemkovo",
    "wof:placetype":"locality"
},
  "geometry": {"coordinates":[31.64141,56.91437],"type":"Point"}
}