{
  "type": "Feature",
  "properties": {
    "gn:country":"RU",
    "gn:fcode":"PPL",
    "gn:pop":0,
    "iso:country":"RU",
    "name:eng_x_preferred":[
        "Sogratl'"
    ],
    "name:nor_x_preferred":[
        "Sogratl"
    ],
    "name:rus_x_preferred":[
        "\u0421\u043e\u0433\u0440\u0430\u0442\u043b\u044c"
    ],
    "name:unk_x_variant":[
        "\u0421\u043e\u0433\u0440\u0430\u0442\u043b\u044c"
    ],
    "qs:name":"Sogratl'",
    "qs:name_adm0":"Russia",
    "qs:name_adm1":"Dagestan Republic",
    "qs:photos_9r":0,
    "qs:photos_sr":0,
    "qs:placetype":"Town",
    "qs:pop_sr":"0",
    "wof:name":"Sogratl'",
    "wof:placetype":"locality",
    "wof:population":0
},
  "geometry": {"coordinates":[46.99106,42.28127],"type":"Point"}
}