{
  "type": "Feature",
  "properties": {
    "gn:admin1_code":"85.0",
    "gn:asciiname":"Dushnevo",
    "gn:country_code":"RU",
    "gn:dem":131,
    "gn:feature_class":"P",
    "gn:feature_code":"PPL",
    "gn:name":"Dushn\u00ebvo",
    "gn:population":0,
    "gn:timezone":"Europe/Moscow",
    "iso:country":"RU",
    "name:rus_x_preferred":[
        "\u0414\u0443\u0448\u043d\u0451\u0432\u043e"
    ],
    "name:und_x_variant":[
        "Dushn\u00ebvo"
    ],
    "wof:name":"Dushnevo",
    "wof:placetype":"locality"
},
  "geometry": {"coordinates":[43.99254000000001,59.46961999999999],"type":"Point"}
}