{
  "type": "Feature",
  "properties": {
    "gn:admin1_code":"83",
    "gn:asciiname":"Sel'tsovy-Dereven'ki",
    "gn:country_code":"RU",
    "gn:dem":76,
    "gn:feature_class":"P",
    "gn:feature_code":"PPL",
    "gn:name":"Sel\u2019tsovy-Dereven\u2019ki",
    "gn:population":0,
    "gn:timezone":"Europe/Moscow",
    "iso:country":"RU",
    "name:nor_x_preferred":[
        "Seltsovy-Derevenki"
    ],
    "name:rus_x_preferred":[
        "\u0421\u0435\u043b\u044c\u0446\u043e\u0432\u044b-\u0414\u0435\u0440\u0435\u0432\u0435\u043d\u044c\u043a\u0438"
    ],
    "name:und_x_variant":[
        "Sel\u2019tsovy-Dereven\u2019ki"
    ],
    "wof:name":"Sel'tsovy-Dereven'ki",
    "wof:placetype":"locality"
},
  "geometry": {"coordinates":[42.14352,56.28214000000001],"type":"Point"}
}