{
  "type": "Feature",
  "properties": {
    "gn:admin1_code":"8",
    "gn:asciiname":"Tupchanovo Pervoye",
    "gn:country_code":"RU",
    "gn:dem":244,
    "gn:feature_class":"P",
    "gn:feature_code":"PPL",
    "gn:name":"Tupchanovo Pervoye",
    "gn:population":0,
    "gn:timezone":"Asia/Yekaterinburg",
    "iso:country":"RU",
    "name:und_x_variant":[
        "Tupchanovo",
        "Tupchanovo Pervoye"
    ],
    "wof:name":"Tupchanovo Pervoye",
    "wof:placetype":"locality"
},
  "geometry": {"coordinates":[56.745,52.65935],"type":"Point"}
}