{
  "type": "Feature",
  "properties": {
    "gn:admin1_code":"43",
    "gn:asciiname":"Zheltyye Dvoriki",
    "gn:country_code":"RU",
    "gn:dem":209,
    "gn:feature_class":"P",
    "gn:feature_code":"PPL",
    "gn:name":"Zh\u00ebltyye Dvoriki",
    "gn:population":0,
    "gn:timezone":"Europe/Moscow",
    "iso:country":"RU",
    "name:rus_x_preferred":[
        "\u0416\u0451\u043b\u0442\u044b\u0435 \u0414\u0432\u043e\u0440\u0438\u043a\u0438"
    ],
    "name:und_x_variant":[
        "Zh\u00ebltyye Dvoriki",
        "\u0416\u0451\u043b\u0442\u044b\u0435 \u0414\u0432\u043e\u0440\u0438\u043a\u0438"
    ],
    "wof:name":"Zheltyye Dvoriki",
    "wof:placetype":"locality"
},
  "geometry": {"coordinates":[38.7629,52.4866],"type":"Point"}
}