{
  "type": "Feature",
  "properties": {
    "gn:admin1_code":"77.0",
    "gn:asciiname":"Bol'shaya Zheleznitsa",
    "gn:country_code":"RU",
    "gn:dem":183,
    "gn:feature_class":"P",
    "gn:feature_code":"PPL",
    "gn:name":"Bol\u2019shaya Zheleznitsa",
    "gn:population":0,
    "gn:timezone":"Europe/Moscow",
    "iso:country":"RU",
    "name:rus_x_preferred":[
        "\u0411\u043e\u043b\u044c\u0448\u0430\u044f \u0416\u0435\u043b\u0435\u0437\u043d\u0438\u0446\u0430"
    ],
    "name:und_x_variant":[
        "Bol\u2019shaya Zheleznitsa"
    ],
    "wof:name":"Bol'shaya Zheleznitsa",
    "wof:placetype":"locality"
},
  "geometry": {"coordinates":[31.87428,55.89779],"type":"Point"}
}