{
  "type": "Feature",
  "properties": {
    "gn:admin1_code":"47",
    "gn:asciiname":"Goloven'ka",
    "gn:country_code":"RU",
    "gn:dem":195,
    "gn:feature_class":"P",
    "gn:feature_code":"PPL",
    "gn:name":"Goloven\u2019ka",
    "gn:population":0,
    "gn:timezone":"Europe/Moscow",
    "iso:country":"RU",
    "name:rus_x_preferred":[
        "\u0413\u043e\u043b\u043e\u0432\u0435\u043d\u044c\u043a\u0430"
    ],
    "name:und_x_variant":[
        "Goloven\u2019ki",
        "Goloven\u2019kino",
        "Goloven\u2019ka",
        "\u0413\u043e\u043b\u043e\u0432\u0435\u043d\u044c\u043a\u0430"
    ],
    "wof:name":"Goloven'ka",
    "wof:placetype":"locality"
},
  "geometry": {"coordinates":[36.69191,55.47291],"type":"Point"}
}