{
  "type": "Feature",
  "properties": {
    "gn:admin1_code":"60",
    "gn:asciiname":"Nochevo",
    "gn:country_code":"RU",
    "gn:dem":108,
    "gn:feature_class":"P",
    "gn:feature_code":"PPL",
    "gn:name":"Nochevo",
    "gn:population":0,
    "gn:timezone":"Europe/Moscow",
    "iso:country":"RU",
    "name:eng_x_preferred":[
        "Nochevo"
    ],
    "name:nor_x_preferred":[
        "Notsjevo"
    ],
    "name:rus_x_preferred":[
        "\u041d\u043e\u0447\u0435\u0432\u043e"
    ],
    "wof:name":"Nochevo",
    "wof:placetype":"locality"
},
  "geometry": {"coordinates":[28.23768,56.80533000000001],"type":"Point"}
}