{
  "type": "Feature",
  "properties": {
    "gn:admin1_code":"67.0",
    "gn:asciiname":"Alent'yevka",
    "gn:country_code":"RU",
    "gn:dem":217,
    "gn:feature_class":"P",
    "gn:feature_code":"PPL",
    "gn:name":"Alent\u2019yevka",
    "gn:population":0,
    "gn:timezone":"Europe/Saratov",
    "iso:country":"RU",
    "name:nor_x_preferred":[
        "Alentjevka"
    ],
    "name:rus_x_preferred":[
        "\u0410\u043b\u0435\u043d\u0442\u044c\u0435\u0432\u043a\u0430"
    ],
    "name:und_x_variant":[
        "Alent\u2019yevka"
    ],
    "wof:name":"Alent'yevka",
    "wof:placetype":"locality"
},
  "geometry": {"coordinates":[46.39641,52.58303000000001],"type":"Point"}
}