{
  "type": "Feature",
  "properties": {
    "gn:admin1_code":"21.0",
    "gn:asciiname":"Ozerkovo",
    "gn:country_code":"RU",
    "gn:dem":105,
    "gn:feature_class":"P",
    "gn:feature_code":"PPL",
    "gn:name":"Ozerkovo",
    "gn:population":0,
    "gn:timezone":"Europe/Moscow",
    "iso:country":"RU",
    "name:rus_x_preferred":[
        "\u041e\u0437\u0435\u0440\u043a\u043e\u0432\u043e"
    ],
    "wof:name":"Ozerkovo",
    "wof:placetype":"locality"
},
  "geometry": {"coordinates":[41.41128,56.94518000000001],"type":"Point"}
}