{
  "type": "Feature",
  "properties": {
    "gn:admin1_code":"45",
    "gn:asciiname":"Rim",
    "gn:country_code":"RU",
    "gn:dem":121,
    "gn:feature_class":"P",
    "gn:feature_code":"PPL",
    "gn:name":"Rim",
    "gn:population":0,
    "gn:timezone":"Europe/Moscow",
    "iso:country":"RU",
    "name:ara_x_preferred":[
        "\u0631\u064a\u0645"
    ],
    "name:bel_x_preferred":[
        "\u0420\u044b\u043c"
    ],
    "name:bos_x_preferred":[
        "Rim"
    ],
    "name:ceb_x_preferred":[
        "Rim"
    ],
    "name:hrv_x_preferred":[
        "Rim"
    ],
    "name:hun_x_preferred":[
        "Rim"
    ],
    "name:hye_x_preferred":[
        "\u0540\u057c\u0578\u0574"
    ],
    "name:mhr_x_preferred":[
        "\u0420\u0438\u043c"
    ],
    "name:rus_x_preferred":[
        "\u0420\u0438\u043c"
    ],
    "name:slk_x_preferred":[
        "R\u00edm"
    ],
    "name:slv_x_preferred":[
        "Rim"
    ],
    "name:srp_x_preferred":[
        "\u0420\u0438\u043c"
    ],
    "name:swe_x_preferred":[
        "Rim"
    ],
    "name:ukr_x_preferred":[
        "\u0420\u0438\u043c"
    ],
    "name:uzb_x_preferred":[
        "Rim"
    ],
    "wof:name":"Rim",
    "wof:placetype":"locality"
},
  "geometry": {"coordinates":[47.98333,56.58333],"type":"Point"}
}