{
  "type": "Feature",
  "properties": {
    "gn:admin1_code":"47",
    "gn:asciiname":"Ivonino",
    "gn:country_code":"RU",
    "gn:dem":195,
    "gn:feature_class":"P",
    "gn:feature_code":"PPL",
    "gn:name":"Ivonino",
    "gn:population":0,
    "gn:timezone":"Europe/Moscow",
    "iso:country":"RU",
    "name:rus_x_preferred":[
        "\u0418\u0432\u043e\u043d\u0438\u043d\u043e"
    ],
    "wof:name":"Ivonino",
    "wof:placetype":"locality"
},
  "geometry": {"coordinates":[36.81173,55.62181999999999],"type":"Point"}
}