{
  "type": "Feature",
  "properties": {
    "gn:admin1_code":"34",
    "gn:asciiname":"Sizyabsk",
    "gn:country_code":"RU",
    "gn:dem":36,
    "gn:feature_class":"P",
    "gn:feature_code":"PPL",
    "gn:name":"Sizyabsk",
    "gn:population":0,
    "gn:timezone":"Europe/Moscow",
    "iso:country":"RU",
    "name:eng_x_preferred":[
        "Sizyabsk"
    ],
    "name:nor_x_preferred":[
        "Siziabsk"
    ],
    "name:rus_x_preferred":[
        "\u0421\u0438\u0437\u044f\u0431\u0441\u043a"
    ],
    "name:und_x_variant":[
        "Sizyabok",
        "Sizyabskoye"
    ],
    "wof:name":"Sizyabsk",
    "wof:placetype":"locality"
},
  "geometry": {"coordinates":[53.8591,65.06201],"type":"Point"}
}