{
  "type": "Feature",
  "properties": {
    "gn:admin1_code":"8",
    "gn:asciiname":"Keushte",
    "gn:country_code":"RU",
    "gn:dem":625,
    "gn:feature_class":"P",
    "gn:feature_code":"PPL",
    "gn:name":"Keushte",
    "gn:population":0,
    "gn:timezone":"Asia/Yekaterinburg",
    "iso:country":"RU",
    "name:rus_x_preferred":[
        "\u041a\u0435\u0443\u0448\u0442\u0435"
    ],
    "wof:name":"Keushte",
    "wof:placetype":"locality"
},
  "geometry": {"coordinates":[57.98333,52.95],"type":"Point"}
}