{
  "type": "Feature",
  "properties": {
    "gn:admin1_code":"16",
    "gn:asciiname":"Syatrakasy",
    "gn:country_code":"RU",
    "gn:dem":153,
    "gn:feature_class":"P",
    "gn:feature_code":"PPL",
    "gn:name":"Syatrakasy",
    "gn:population":0,
    "gn:timezone":"Europe/Moscow",
    "iso:country":"RU",
    "name:rus_x_preferred":[
        "\u0421\u044f\u0442\u0440\u0430\u043a\u0430\u0441\u044b"
    ],
    "wof:name":"Syatrakasy",
    "wof:placetype":"locality"
},
  "geometry": {"coordinates":[46.5304,55.9332],"type":"Point"}
}