{
  "type": "Feature",
  "properties": {
    "gn:admin1_code":"61",
    "gn:asciiname":"Kovyl'nyy",
    "gn:country_code":"RU",
    "gn:dem":173,
    "gn:feature_class":"P",
    "gn:feature_code":"PPL",
    "gn:name":"Kovyl\u2019nyy",
    "gn:population":0,
    "gn:timezone":"Europe/Moscow",
    "iso:country":"RU",
    "name:rus_x_preferred":[
        "\u041a\u043e\u0432\u044b\u043b\u044c\u043d\u044b\u0439"
    ],
    "name:und_x_variant":[
        "Kovyl\u2019nyy",
        "\u041a\u043e\u0432\u044b\u043b\u044c\u043d\u044b\u0439"
    ],
    "wof:name":"Kovyl'nyy",
    "wof:placetype":"locality"
},
  "geometry": {"coordinates":[40.79833,49.47083],"type":"Point"}
}