{
  "type": "Feature",
  "properties": {
    "gn:admin1_code":"47.0",
    "gn:asciiname":"Kirillovka",
    "gn:country_code":"RU",
    "gn:dem":127,
    "gn:feature_class":"P",
    "gn:feature_code":"PPL",
    "gn:name":"Kirillovka",
    "gn:population":0,
    "gn:timezone":"Europe/Moscow",
    "iso:country":"RU",
    "name:che_x_preferred":[
        "\u041a\u0438\u0440\u0438\u043b\u043b\u043e\u0432\u043a\u0430"
    ],
    "name:rus_x_preferred":[
        "\u041a\u0438\u0440\u0438\u043b\u043b\u043e\u0432\u043a\u0430"
    ],
    "wof:name":"Kirillovka",
    "wof:placetype":"locality"
},
  "geometry": {"coordinates":[37.95917,55.64694],"type":"Point"}
}