{
  "type": "Feature",
  "properties": {
    "gn:admin1_code":"28.0",
    "gn:asciiname":"Ledma",
    "gn:country_code":"RU",
    "gn:dem":139,
    "gn:feature_class":"P",
    "gn:feature_code":"PPL",
    "gn:name":"Ledma",
    "gn:population":0,
    "gn:timezone":"Europe/Moscow",
    "iso:country":"RU",
    "name:fin_x_preferred":[
        "Lietma"
    ],
    "wof:name":"Ledma",
    "wof:placetype":"locality"
},
  "geometry": {"coordinates":[31.89022000000001,64.31626],"type":"Point"}
}