{
  "type": "Feature",
  "properties": {
    "gn:admin1_code":"63",
    "gn:asciiname":"Oyun-Kyuyel'",
    "gn:country_code":"RU",
    "gn:dem":160,
    "gn:feature_class":"P",
    "gn:feature_code":"PPL",
    "gn:name":"Oyun-Kyuy\u00ebl\u2019",
    "gn:population":0,
    "gn:timezone":"Asia/Yakutsk",
    "iso:country":"RU",
    "name:rus_x_preferred":[
        "\u041e\u044e\u043d-\u041a\u044e\u0451\u043b\u044c"
    ],
    "name:und_x_variant":[
        "Oyun-Kyuy\u00ebl\u2019"
    ],
    "wof:name":"Oyun-Kyuyel'",
    "wof:placetype":"locality"
},
  "geometry": {"coordinates":[134.51667,62.08333],"type":"Point"}
}