{
  "type": "Feature",
  "properties": {
    "gn:admin1_code":"61.0",
    "gn:asciiname":"Gerasimov",
    "gn:country_code":"RU",
    "gn:dem":160,
    "gn:feature_class":"P",
    "gn:feature_code":"PPL",
    "gn:name":"Gerasimov",
    "gn:population":0,
    "gn:timezone":"Europe/Moscow",
    "iso:country":"RU",
    "name:rus_x_preferred":[
        "\u0413\u0435\u0440\u0430\u0441\u0438\u043c\u043e\u0432"
    ],
    "name:ukr_x_preferred":[
        "\u0413\u0435\u0440\u0430\u0441\u0438\u043c\u043e\u0432"
    ],
    "name:und_x_variant":[
        "\u0413\u0435\u0440\u0430\u0441\u0438\u043c\u043e\u0432"
    ],
    "wof:name":"Gerasimov",
    "wof:placetype":"locality"
},
  "geometry": {"coordinates":[40.09139,49.08635],"type":"Point"}
}