{
  "type": "Feature",
  "properties": {
    "gn:admin1_code":"52",
    "gn:asciiname":"Khotynya",
    "gn:country_code":"RU",
    "gn:dem":53,
    "gn:feature_class":"P",
    "gn:feature_code":"PPL",
    "gn:name":"Khotynya",
    "gn:population":0,
    "gn:timezone":"Europe/Moscow",
    "iso:country":"RU",
    "name:rus_x_preferred":[
        "\u0425\u043e\u0442\u044b\u043d\u044f"
    ],
    "name:und_x_variant":[
        "\u0425\u043e\u0442\u044b\u043d\u044f"
    ],
    "wof:name":"Khotynya",
    "wof:placetype":"locality"
},
  "geometry": {"coordinates":[30.17217,58.39066999999999],"type":"Point"}
}