{
  "type": "Feature",
  "properties": {
    "iso:country":"RU",
    "name:bul_x_preferred":[
        "\u041e\u0441\u0442\u0430\u043d\u043a\u0438\u043d\u0441\u043a\u0438 \u0440\u0430\u0439\u043e\u043d"
    ],
    "name:ceb_x_preferred":[
        "Ostankinskiy"
    ],
    "name:deu_x_preferred":[
        "Moskau-Ostankino"
    ],
    "name:eng_x_preferred":[
        "Ostankinsky District"
    ],
    "name:epo_x_preferred":[
        "Ostankino"
    ],
    "name:fin_x_preferred":[
        "Ostankino"
    ],
    "name:fra_x_preferred":[
        "Ostankinski"
    ],
    "name:ita_x_preferred":[
        "Ostankinskij"
    ],
    "name:nld_x_preferred":[
        "Ostankinsky District"
    ],
    "name:por_x_preferred":[
        "Ostankinsky"
    ],
    "name:rus_x_preferred":[
        "\u041e\u0441\u0442\u0430\u043d\u043a\u0438\u043d\u0441\u043a\u0438\u0439 \u0440\u0430\u0439\u043e\u043d"
    ],
    "name:sco_x_preferred":[
        "Ostankinsky Destrict"
    ],
    "name:ukr_x_preferred":[
        "\u041e\u0441\u0442\u0430\u043d\u043a\u0456\u043d\u0441\u044c\u043a\u0438\u0439"
    ],
    "name:zho_x_preferred":[
        "\u5967\u65af\u5766\u91d1\u8afe\u5340"
    ],
    "qs:name":"Ostankinsky",
    "qs:name_adm0":"Russia",
    "qs:name_adm1":"Moscow Federal City",
    "qs:photos":3,
    "qs:photos_1k":1,
    "qs:photos_9k":1,
    "qs:photos_9r":1,
    "qs:photos_all":3,
    "qs:photos_sr":1,
    "qs:placetype":"Suburb",
    "qs:pop_sr":"0",
    "wd:wordcount":272,
    "wof:name":"Ostankinsky",
    "wof:placetype":"neighbourhood"
},
  "geometry": {"coordinates":[37.616356,55.754071],"type":"Point"}
}