{
  "type": "Feature",
  "properties": {
    "gn:admin1_code":"45.0",
    "gn:asciiname":"Opalikha",
    "gn:country_code":"RU",
    "gn:dem":168,
    "gn:feature_class":"P",
    "gn:feature_code":"PPL",
    "gn:name":"Opalikha",
    "gn:population":0,
    "gn:timezone":"Europe/Moscow",
    "iso:country":"RU",
    "name:rus_x_preferred":[
        "\u041e\u043f\u0430\u043b\u0438\u0445\u0430"
    ],
    "wof:name":"Opalikha",
    "wof:placetype":"locality"
},
  "geometry": {"coordinates":[48.81417,56.74583000000001],"type":"Point"}
}