{
  "type": "Feature",
  "properties": {
    "gn:admin1_code":"53",
    "gn:asciiname":"Sarybalyk",
    "gn:country_code":"RU",
    "gn:dem":109,
    "gn:feature_class":"P",
    "gn:feature_code":"PPL",
    "gn:name":"Sarybalyk",
    "gn:population":0,
    "gn:timezone":"Asia/Novosibirsk",
    "iso:country":"RU",
    "name:eng_x_preferred":[
        "Sarybalyk"
    ],
    "name:nor_x_preferred":[
        "Sarybalyk"
    ],
    "name:rus_x_preferred":[
        "\u0421\u0430\u0440\u044b\u0431\u0430\u043b\u044b\u043a"
    ],
    "name:und_x_variant":[
        "Sarba",
        "Sarbalyk"
    ],
    "wof:name":"Sarybalyk",
    "wof:placetype":"locality"
},
  "geometry": {"coordinates":[76.6541,55.26286999999999],"type":"Point"}
}