{
  "type": "Feature",
  "properties": {
    "gn:admin1_code":"52",
    "gn:asciiname":"Kornovitsy",
    "gn:country_code":"RU",
    "gn:dem":76,
    "gn:feature_class":"P",
    "gn:feature_code":"PPL",
    "gn:name":"Kornovitsy",
    "gn:population":0,
    "gn:timezone":"Europe/Moscow",
    "iso:country":"RU",
    "name:rus_x_preferred":[
        "\u041a\u043e\u0440\u043d\u043e\u0432\u0438\u0446\u044b"
    ],
    "name:und_x_variant":[
        "\u041a\u043e\u0440\u043d\u043e\u0432\u0438\u0446\u044b"
    ],
    "wof:name":"Kornovitsy",
    "wof:placetype":"locality"
},
  "geometry": {"coordinates":[30.43333,58.58333],"type":"Point"}
}