{
  "type": "Feature",
  "properties": {
    "gn:admin1_code":"77",
    "gn:asciiname":"Nishevitsy",
    "gn:country_code":"RU",
    "gn:dem":215,
    "gn:feature_class":"P",
    "gn:feature_code":"PPL",
    "gn:name":"Nishevitsy",
    "gn:population":0,
    "gn:timezone":"Europe/Moscow",
    "iso:country":"RU",
    "name:rus_x_preferred":[
        "\u041d\u0438\u0448\u0435\u0432\u0438\u0446\u044b"
    ],
    "name:und_x_variant":[
        "Pishchevitsy",
        "Nishevitsy"
    ],
    "wof:name":"Nishevitsy",
    "wof:placetype":"locality"
},
  "geometry": {"coordinates":[31.4875,56.56308000000001],"type":"Point"}
}