{
  "type": "Feature",
  "properties": {
    "gn:admin1_code":"45",
    "gn:asciiname":"Durmagashevo",
    "gn:country_code":"RU",
    "gn:dem":100,
    "gn:feature_class":"P",
    "gn:feature_code":"PPL",
    "gn:name":"Durmagashevo",
    "gn:population":0,
    "gn:timezone":"Europe/Moscow",
    "iso:country":"RU",
    "name:rus_x_preferred":[
        "\u0414\u0443\u0440\u043c\u0430\u0433\u0430\u0448\u0435\u0432\u043e"
    ],
    "wof:name":"Durmagashevo",
    "wof:placetype":"locality"
},
  "geometry": {"coordinates":[49.2087,57.2994],"type":"Point"}
}