{
  "type": "Feature",
  "properties": {
    "gn:admin1_code":"21",
    "gn:asciiname":"Imeni Vos'mogo Fevralya",
    "gn:country_code":"RU",
    "gn:dem":84,
    "gn:feature_class":"P",
    "gn:feature_code":"PPL",
    "gn:name":"Imeni Vos\u2019mogo Fevralya",
    "gn:population":0,
    "gn:timezone":"Europe/Moscow",
    "iso:country":"RU",
    "name:rus_x_preferred":[
        "\u0418\u043c\u0435\u043d\u0438 \u0412\u043e\u0441\u044c\u043c\u043e\u0433\u043e \u0424\u0435\u0432\u0440\u0430\u043b\u044f"
    ],
    "name:und_x_variant":[
        "Imeni Vos\u2019mogo Fevralya"
    ],
    "wof:name":"Imeni Vos'mogo Fevralya",
    "wof:placetype":"locality"
},
  "geometry": {"coordinates":[41.93039,56.51826],"type":"Point"}
}