{
  "type": "Feature",
  "properties": {
    "gn:admin1_code":"69.0",
    "gn:asciiname":"Bol'shaya Vergova",
    "gn:country_code":"RU",
    "gn:dem":200,
    "gn:feature_class":"P",
    "gn:feature_code":"PPL",
    "gn:name":"Bol\u2019shaya Vergova",
    "gn:population":0,
    "gn:timezone":"Europe/Moscow",
    "iso:country":"RU",
    "name:rus_x_preferred":[
        "\u0411\u043e\u043b\u044c\u0448\u0430\u044f \u0412\u0435\u0440\u0433\u043e\u0432\u0430"
    ],
    "name:und_x_variant":[
        "Bol\u2019shaya Veregova",
        "Bol\u2019shaya Vergova",
        "\u0411\u043e\u043b\u044c\u0448\u0430\u044f \u0412\u0435\u0440\u0433\u043e\u0432\u0430"
    ],
    "wof:name":"Bol'shaya Vergova",
    "wof:placetype":"locality"
},
  "geometry": {"coordinates":[33.77848,54.74359000000001],"type":"Point"}
}