{
  "type": "Feature",
  "properties": {
    "gn:admin1_code":"28",
    "gn:asciiname":"Kaskesruchey",
    "gn:cc2":"RU",
    "gn:country_code":"RU",
    "gn:dem":23,
    "gn:feature_class":"P",
    "gn:feature_code":"PPL",
    "gn:name":"Kaskesruchey",
    "gn:population":0,
    "gn:timezone":"Europe/Moscow",
    "iso:country":"RU",
    "name:fin_x_preferred":[
        "Kaskesoja"
    ],
    "name:rus_x_preferred":[
        "\u041a\u0430\u0441\u043a\u0435\u0441\u0440\u0443\u0447\u0435\u0439"
    ],
    "name:und_x_variant":[
        "Kaskez-Ruchey",
        "Kaskesruchey",
        "\u041a\u0430\u0441\u043a\u0435\u0441\u0440\u0443\u0447\u0435\u0439"
    ],
    "name:vep_x_preferred":[
        "Kaskez"
    ],
    "wof:name":"Kaskesruchey",
    "wof:placetype":"locality"
},
  "geometry": {"coordinates":[35.5945,61.2068],"type":"Point"}
}