{
  "type": "Feature",
  "properties": {
    "gn:admin1_code":"52",
    "gn:asciiname":"Zelema",
    "gn:country_code":"RU",
    "gn:dem":84,
    "gn:feature_class":"P",
    "gn:feature_code":"PPL",
    "gn:name":"Zelema",
    "gn:population":0,
    "gn:timezone":"Europe/Moscow",
    "iso:country":"RU",
    "name:rus_x_preferred":[
        "\u0417\u0435\u043b\u0435\u043c\u0430"
    ],
    "name:und_x_variant":[
        "Zyulema",
        "Zelemo",
        "Zelema",
        "\u0417\u0435\u043b\u0435\u043c\u0430"
    ],
    "wof:name":"Zelema",
    "wof:placetype":"locality"
},
  "geometry": {"coordinates":[30.89451,57.62143],"type":"Point"}
}