{
  "type": "Feature",
  "properties": {
    "gn:admin1_code":"47",
    "gn:asciiname":"Serednikovo",
    "gn:country_code":"RU",
    "gn:dem":141,
    "gn:feature_class":"P",
    "gn:feature_code":"PPL",
    "gn:name":"Serednikovo",
    "gn:population":0,
    "gn:timezone":"Europe/Moscow",
    "iso:country":"RU",
    "name:eng_x_preferred":[
        "Serednikovo"
    ],
    "name:nor_x_preferred":[
        "Serednikovo"
    ],
    "name:rus_x_preferred":[
        "\u0421\u0435\u0440\u0435\u0434\u043d\u0438\u043a\u043e\u0432\u043e"
    ],
    "name:und_x_variant":[
        "Serednikova"
    ],
    "wof:name":"Serednikovo",
    "wof:placetype":"locality"
},
  "geometry": {"coordinates":[39.6577,55.25487],"type":"Point"}
}