{
  "type": "Feature",
  "properties": {
    "gn:admin1_code":"72",
    "gn:asciiname":"Olenevo",
    "gn:country_code":"RU",
    "gn:dem":135,
    "gn:feature_class":"P",
    "gn:feature_code":"PPL",
    "gn:name":"Olenevo",
    "gn:population":0,
    "gn:timezone":"Europe/Moscow",
    "iso:country":"RU",
    "name:rus_x_preferred":[
        "\u041e\u043b\u0435\u043d\u0435\u0432\u043e"
    ],
    "wof:name":"Olenevo",
    "wof:placetype":"locality"
},
  "geometry": {"coordinates":[41.14556,52.55416999999999],"type":"Point"}
}