{
  "type": "Feature",
  "properties": {
    "gn:admin1_code":"37",
    "gn:asciiname":"Golovino",
    "gn:country_code":"RU",
    "gn:dem":125,
    "gn:feature_class":"P",
    "gn:feature_code":"PPL",
    "gn:name":"Golovino",
    "gn:population":0,
    "gn:timezone":"Europe/Moscow",
    "iso:country":"RU",
    "name:eng_x_preferred":[
        "Golovino"
    ],
    "name:fas_x_preferred":[
        "\u06af\u0648\u0644\u0648\u0648\u06cc\u0646\u0648"
    ],
    "name:nor_x_preferred":[
        "Golovino"
    ],
    "name:rus_x_preferred":[
        "\u0413\u043e\u043b\u043e\u0432\u0438\u043d\u043e"
    ],
    "name:und_x_variant":[
        "\u0413\u043e\u043b\u043e\u0432\u0438\u043d\u043e",
        "Golovino"
    ],
    "wof:name":"Golovino",
    "wof:placetype":"locality"
},
  "geometry": {"coordinates":[45.69217,58.62644],"type":"Point"}
}