{
  "type": "Feature",
  "properties": {
    "gn:admin1_code":"20",
    "gn:asciiname":"Kukunur",
    "gn:country_code":"RU",
    "gn:dem":527,
    "gn:feature_class":"P",
    "gn:feature_code":"PPL",
    "gn:name":"Kukunur",
    "gn:population":0,
    "gn:timezone":"Asia/Irkutsk",
    "iso:country":"RU",
    "name:eng_x_preferred":[
        "Kukunur"
    ],
    "name:nor_x_preferred":[
        "Kukunur"
    ],
    "name:rus_x_preferred":[
        "\u041a\u0443\u043a\u0443\u043d\u0443\u0440"
    ],
    "name:und_x_variant":[
        "Kukhunur"
    ],
    "wof:name":"Kukunur",
    "wof:placetype":"locality"
},
  "geometry": {"coordinates":[102.51278000000001,53.1875],"type":"Point"}
}