{
  "type": "Feature",
  "properties": {
    "gn:admin1_code":"84.0",
    "gn:asciiname":"Astakhovskiy",
    "gn:country_code":"RU",
    "gn:dem":120,
    "gn:feature_class":"P",
    "gn:feature_code":"PPL",
    "gn:name":"Astakhovskiy",
    "gn:population":0,
    "gn:timezone":"Europe/Volgograd",
    "iso:country":"RU",
    "name:nor_x_preferred":[
        "Astakhovskij"
    ],
    "name:rus_x_preferred":[
        "\u0410\u0441\u0442\u0430\u0445\u043e\u0432\u0441\u043a\u0438\u0439"
    ],
    "name:und_x_variant":[
        "Astakhov",
        "Astakhovskiy"
    ],
    "wof:name":"Astakhovskiy",
    "wof:placetype":"locality"
},
  "geometry": {"coordinates":[41.6021,50.9222],"type":"Point"}
}