{
  "type": "Feature",
  "properties": {
    "gn:admin1_code":"42.0",
    "gn:asciiname":"Yaskelevo",
    "gn:country_code":"RU",
    "gn:dem":146,
    "gn:feature_class":"P",
    "gn:feature_code":"PPL",
    "gn:name":"Yaskelevo",
    "gn:population":0,
    "gn:timezone":"Europe/Moscow",
    "iso:country":"RU",
    "name:fin_x_preferred":[
        "H\u00e4ysk\u00e4l\u00e4"
    ],
    "wof:name":"Yaskelevo",
    "wof:placetype":"locality"
},
  "geometry": {"coordinates":[29.76577,59.51982],"type":"Point"}
}