{
  "type": "Feature",
  "properties": {
    "gn:admin1_code":"90",
    "gn:asciiname":"Shishi",
    "gn:country_code":"RU",
    "gn:dem":247,
    "gn:feature_class":"P",
    "gn:feature_code":"PPL",
    "gn:name":"Shishi",
    "gn:population":0,
    "gn:timezone":"Asia/Yekaterinburg",
    "iso:country":"RU",
    "name:rus_x_preferred":[
        "\u0428\u0438\u0448\u0438"
    ],
    "name:und_x_variant":[
        "\u0428\u0438\u0448\u0438"
    ],
    "wof:name":"Shishi",
    "wof:placetype":"locality"
},
  "geometry": {"coordinates":[58.0118,57.70676],"type":"Point"}
}