{
  "type": "Feature",
  "properties": {
    "gn:admin1_code":"77",
    "gn:asciiname":"Spas Mit'kovo",
    "gn:country_code":"RU",
    "gn:dem":185,
    "gn:feature_class":"P",
    "gn:feature_code":"PPL",
    "gn:name":"Spas Mit\u2019kovo",
    "gn:population":0,
    "gn:timezone":"Europe/Moscow",
    "iso:country":"RU",
    "name:rus_x_preferred":[
        "\u0421\u043f\u0430\u0441 \u041c\u0438\u0442\u044c\u043a\u043e\u0432\u043e"
    ],
    "name:und_x_variant":[
        "Spasskoye",
        "Spas Mit\u2019kovo",
        "\u0421\u043f\u0430\u0441 \u041c\u0438\u0442\u044c\u043a\u043e\u0432\u043e"
    ],
    "wof:name":"Spas Mit'kovo",
    "wof:placetype":"locality"
},
  "geometry": {"coordinates":[34.15,56.31667],"type":"Point"}
}