{
  "type": "Feature",
  "properties": {
    "gn:admin1_code":"52",
    "gn:asciiname":"Vesen'ye",
    "gn:country_code":"RU",
    "gn:dem":146,
    "gn:feature_class":"P",
    "gn:feature_code":"PPL",
    "gn:name":"Vesen\u2019ye",
    "gn:population":0,
    "gn:timezone":"Europe/Moscow",
    "iso:country":"RU",
    "wof:name":"Vesen'ye",
    "wof:placetype":"locality"
},
  "geometry": {"coordinates":[33.47889,58.72528000000001],"type":"Point"}
}