{
  "type": "Feature",
  "properties": {
    "gn:admin1_code":"20",
    "gn:asciiname":"Novaya Tel'ba",
    "gn:country_code":"RU",
    "gn:dem":468,
    "gn:feature_class":"P",
    "gn:feature_code":"PPL",
    "gn:name":"Novaya Tel\u2019ba",
    "gn:population":0,
    "gn:timezone":"Asia/Irkutsk",
    "iso:country":"RU",
    "name:rus_x_preferred":[
        "\u041d\u043e\u0432\u0430\u044f \u0422\u0435\u043b\u044c\u0431\u0430"
    ],
    "name:und_x_variant":[
        "Novaya Tel\u2019ba",
        "\u041d\u043e\u0432\u0430\u044f \u0422\u0435\u043b\u044c\u0431\u0430"
    ],
    "wof:name":"Novaya Tel'ba",
    "wof:placetype":"locality"
},
  "geometry": {"coordinates":[101.9919,54.78055],"type":"Point"}
}