{
  "type": "Feature",
  "properties": {
    "gn:admin1_code":"40",
    "gn:asciiname":"Frunze",
    "gn:cc2":"RU",
    "gn:country_code":"RU",
    "gn:dem":150,
    "gn:feature_class":"P",
    "gn:feature_code":"PPL",
    "gn:name":"Frunze",
    "gn:population":0,
    "gn:timezone":"Asia/Yekaterinburg",
    "iso:country":"RU",
    "name:eng_x_preferred":[
        "Frunze"
    ],
    "name:nor_x_preferred":[
        "Frunze"
    ],
    "name:rus_x_preferred":[
        "\u0424\u0440\u0443\u043d\u0437\u0435"
    ],
    "name:und_x_variant":[
        "Imeni Frunze",
        "\u0424\u0440\u0443\u043d\u0437\u0435",
        "Frunze"
    ],
    "wof:name":"Frunze",
    "wof:placetype":"locality"
},
  "geometry": {"coordinates":[63.2875,55.78111],"type":"Point"}
}