{
  "type": "Feature",
  "properties": {
    "gn:admin1_code":"60",
    "gn:asciiname":"Ustinovo",
    "gn:country_code":"RU",
    "gn:dem":197,
    "gn:feature_class":"P",
    "gn:feature_code":"PPL",
    "gn:name":"Ustinovo",
    "gn:population":0,
    "gn:timezone":"Europe/Moscow",
    "iso:country":"RU",
    "name:rus_x_preferred":[
        "\u0423\u0441\u0442\u0438\u043d\u043e\u0432\u043e"
    ],
    "name:und_x_variant":[
        "\u0423\u0441\u0442\u0438\u043d\u043e\u0432\u043e"
    ],
    "wof:name":"Ustinovo",
    "wof:placetype":"locality"
},
  "geometry": {"coordinates":[29.7354,56.22600000000001],"type":"Point"}
}