{
  "type": "Feature",
  "properties": {
    "gn:admin1_code":"69",
    "gn:asciiname":"Starosel'ye",
    "gn:country_code":"RU",
    "gn:dem":177,
    "gn:feature_class":"P",
    "gn:feature_code":"PPL",
    "gn:name":"Starosel\u2019ye",
    "gn:population":0,
    "gn:timezone":"Europe/Moscow",
    "iso:country":"RU",
    "name:rus_x_preferred":[
        "\u0421\u0442\u0430\u0440\u043e\u0441\u0435\u043b\u044c\u0435"
    ],
    "name:und_x_variant":[
        "Starosel\u2019ye",
        "\u0421\u0442\u0430\u0440\u043e\u0441\u0435\u043b\u044c\u0435"
    ],
    "wof:name":"Starosel'ye",
    "wof:placetype":"locality"
},
  "geometry": {"coordinates":[32.76667,53.68306],"type":"Point"}
}