{
  "type": "Feature",
  "properties": {
    "gn:admin1_code":"4.0",
    "gn:asciiname":"Chistaya Griva",
    "gn:country_code":"RU",
    "gn:dem":334,
    "gn:feature_class":"P",
    "gn:feature_code":"PPL",
    "gn:name":"Chistaya Griva",
    "gn:population":60,
    "gn:timezone":"Asia/Barnaul",
    "iso:country":"RU",
    "name:rus_x_preferred":[
        "\u0427\u0438\u0441\u0442\u0430\u044f \u0413\u0440\u0438\u0432\u0430"
    ],
    "wof:name":"Chistaya Griva",
    "wof:placetype":"locality",
    "wof:population":60
},
  "geometry": {"coordinates":[86.4627,53.191],"type":"Point"}
}