{
  "type": "Feature",
  "properties": {
    "gn:admin1_code":"85",
    "gn:asciiname":"Rameshki",
    "gn:country_code":"RU",
    "gn:dem":208,
    "gn:feature_class":"P",
    "gn:feature_code":"PPL",
    "gn:name":"Rameshki",
    "gn:population":0,
    "gn:timezone":"Europe/Moscow",
    "iso:country":"RU",
    "name:eng_x_preferred":[
        "Rameshki"
    ],
    "name:nor_x_preferred":[
        "Ramesjki"
    ],
    "name:rus_x_preferred":[
        "\u0420\u0430\u043c\u0435\u0448\u043a\u0438"
    ],
    "name:und_x_variant":[
        "\u0420\u0430\u043c\u0435\u0448\u043a\u0438",
        "Rameshki"
    ],
    "wof:name":"Rameshki",
    "wof:placetype":"locality"
},
  "geometry": {"coordinates":[45.32129000000001,59.45175],"type":"Point"}
}