{
  "type": "Feature",
  "properties": {
    "gn:admin1_code":"3",
    "gn:asciiname":"Krasnosel'sk",
    "gn:country_code":"RU",
    "gn:dem":463,
    "gn:feature_class":"P",
    "gn:feature_code":"PPL",
    "gn:name":"Krasnosel\u2019sk",
    "gn:population":0,
    "gn:timezone":"Asia/Omsk",
    "iso:country":"RU",
    "name:eng_x_preferred":[
        "Krasnosel'sk"
    ],
    "name:nor_x_preferred":[
        "Krasnoselsk"
    ],
    "name:rus_x_preferred":[
        "\u041a\u0440\u0430\u0441\u043d\u043e\u0441\u0435\u043b\u044c\u0441\u043a"
    ],
    "name:und_x_variant":[
        "Krasnosel\u2019sk"
    ],
    "wof:name":"Krasnosel'sk",
    "wof:placetype":"locality"
},
  "geometry": {"coordinates":[86.79222,51.80611],"type":"Point"}
}