{
  "type": "Feature",
  "properties": {
    "gn:admin1_code":"60",
    "gn:asciiname":"Kolkishkino",
    "gn:country_code":"RU",
    "gn:dem":264,
    "gn:feature_class":"P",
    "gn:feature_code":"PPL",
    "gn:name":"Kolkishkino",
    "gn:population":0,
    "gn:timezone":"Europe/Moscow",
    "iso:country":"RU",
    "name:rus_x_preferred":[
        "\u041a\u043e\u043b\u043a\u0438\u0448\u043a\u0438\u043d\u043e"
    ],
    "name:und_x_variant":[
        "\u041a\u043e\u043b\u043a\u0438\u0448\u043a\u0438\u043d\u043e"
    ],
    "wof:name":"Kolkishkino",
    "wof:placetype":"locality"
},
  "geometry": {"coordinates":[29.3233,56.8614],"type":"Point"}
}