{
  "type": "Feature",
  "properties": {
    "gn:admin1_code":"76",
    "gn:asciiname":"Tishinovo",
    "gn:country_code":"RU",
    "gn:dem":220,
    "gn:feature_class":"P",
    "gn:feature_code":"PPL",
    "gn:name":"Tishinovo",
    "gn:population":0,
    "gn:timezone":"Europe/Moscow",
    "iso:country":"RU",
    "name:rus_x_preferred":[
        "\u0422\u0438\u0448\u0438\u043d\u043e\u0432\u043e"
    ],
    "name:und_x_variant":[
        "Tishinki",
        "Tishinovo"
    ],
    "wof:name":"Tishinovo",
    "wof:placetype":"locality"
},
  "geometry": {"coordinates":[38.54492,53.46335],"type":"Point"}
}