{
  "type": "Feature",
  "properties": {
    "gn:admin1_code":"16",
    "gn:asciiname":"Vurmankas-Churino",
    "gn:country_code":"RU",
    "gn:dem":148,
    "gn:feature_class":"P",
    "gn:feature_code":"PPL",
    "gn:name":"Vurmankas-Churino",
    "gn:population":0,
    "gn:timezone":"Europe/Moscow",
    "iso:country":"RU",
    "name:rus_x_preferred":[
        "\u0412\u0443\u0440\u043c\u0430\u043d\u043a\u0430\u0441-\u0427\u0443\u0440\u0438\u043d\u043e"
    ],
    "name:und_x_variant":[
        "Vurman-Kas",
        "Vurmankas-Churino"
    ],
    "wof:name":"Vurmankas-Churino",
    "wof:placetype":"locality"
},
  "geometry": {"coordinates":[47.2728,55.66938],"type":"Point"}
}