{
  "type": "Feature",
  "properties": {
    "gn:admin1_code":"34",
    "gn:asciiname":"Yarpiyag",
    "gn:country_code":"RU",
    "gn:dem":55,
    "gn:feature_class":"P",
    "gn:feature_code":"PPL",
    "gn:name":"Yarpiyag",
    "gn:population":0,
    "gn:timezone":"Europe/Moscow",
    "iso:country":"RU",
    "name:eng_x_preferred":[
        "Yarpiyag"
    ],
    "name:nor_x_preferred":[
        "Jarpijag"
    ],
    "name:rus_x_preferred":[
        "\u042f\u0440\u043f\u0438\u044f\u0433"
    ],
    "name:und_x_variant":[
        "Yarpiyakh",
        "Yarpiyak",
        "Yarpi-Yaga"
    ],
    "wof:name":"Yarpiyag",
    "wof:placetype":"locality"
},
  "geometry": {"coordinates":[62.01127,66.52129000000001],"type":"Point"}
}