{
  "type": "Feature",
  "properties": {
    "gn:admin1_code":"60",
    "gn:asciiname":"Maksimikha",
    "gn:country_code":"RU",
    "gn:dem":203,
    "gn:feature_class":"P",
    "gn:feature_code":"PPL",
    "gn:name":"Maksimikha",
    "gn:population":0,
    "gn:timezone":"Europe/Moscow",
    "iso:country":"RU",
    "name:rus_x_preferred":[
        "\u041c\u0430\u043a\u0441\u0438\u043c\u0438\u0445\u0430"
    ],
    "name:und_x_variant":[
        "\u041c\u0430\u043a\u0441\u0438\u043c\u0438\u0445\u0430"
    ],
    "wof:name":"Maksimikha",
    "wof:placetype":"locality"
},
  "geometry": {"coordinates":[29.9215,56.728],"type":"Point"}
}