{
  "type": "Feature",
  "properties": {
    "gn:admin1_code":"90",
    "gn:asciiname":"Tashka",
    "gn:country_code":"RU",
    "gn:dem":152,
    "gn:feature_class":"P",
    "gn:feature_code":"PPL",
    "gn:name":"Tashka",
    "gn:population":0,
    "gn:timezone":"Asia/Yekaterinburg",
    "iso:country":"RU",
    "name:eng_x_preferred":[
        "Tashka"
    ],
    "name:nor_x_preferred":[
        "Tasjka"
    ],
    "name:rus_x_preferred":[
        "\u0422\u0430\u0448\u043a\u0430"
    ],
    "name:und_x_variant":[
        "Gashka",
        "Tashka"
    ],
    "wof:name":"Tashka",
    "wof:placetype":"locality"
},
  "geometry": {"coordinates":[54.362,59.4909],"type":"Point"}
}