{
  "type": "Feature",
  "properties": {
    "gn:admin1_code":"31",
    "gn:asciiname":"Malyy Anzas",
    "gn:country_code":"RU",
    "gn:dem":660,
    "gn:feature_class":"P",
    "gn:feature_code":"PPL",
    "gn:name":"Malyy Anzas",
    "gn:population":0,
    "gn:timezone":"Asia/Krasnoyarsk",
    "iso:country":"RU",
    "name:eng_x_preferred":[
        "Malyy Anzas"
    ],
    "name:nor_x_preferred":[
        "Mal.Anzas"
    ],
    "name:rus_x_preferred":[
        "\u041c\u0430\u043b.\u0410\u043d\u0437\u0430\u0441"
    ],
    "name:rus_x_variant":[
        "\u041c\u0430\u043b\u044b\u0439 \u0410\u043d\u0437\u0430\u0441"
    ],
    "wof:name":"Malyy Anzas",
    "wof:placetype":"locality"
},
  "geometry": {"coordinates":[89.81222,52.40361],"type":"Point"}
}