{
  "type": "Feature",
  "properties": {
    "gn:admin1_code":"43",
    "gn:asciiname":"Borovskoye",
    "gn:country_code":"RU",
    "gn:dem":134,
    "gn:feature_class":"P",
    "gn:feature_code":"PPL",
    "gn:name":"Borovskoye",
    "gn:population":0,
    "gn:timezone":"Europe/Moscow",
    "iso:country":"RU",
    "name:rus_x_preferred":[
        "\u0411\u043e\u0440\u043e\u0432\u0441\u043a\u043e\u0435"
    ],
    "wof:name":"Borovskoye",
    "wof:placetype":"locality"
},
  "geometry": {"coordinates":[40.3554,52.1626],"type":"Point"}
}