{
  "type": "Feature",
  "properties": {
    "gn:admin1_code":"88.0",
    "gn:asciiname":"Borisovskoye",
    "gn:country_code":"RU",
    "gn:dem":99,
    "gn:feature_class":"P",
    "gn:feature_code":"PPL",
    "gn:name":"Borisovskoye",
    "gn:population":0,
    "gn:timezone":"Europe/Moscow",
    "iso:country":"RU",
    "name:rus_x_preferred":[
        "\u0411\u043e\u0440\u0438\u0441\u043e\u0432\u0441\u043a\u043e\u0435"
    ],
    "wof:name":"Borisovskoye",
    "wof:placetype":"locality"
},
  "geometry": {"coordinates":[39.49985,57.1815],"type":"Point"}
}