{
  "type": "Feature",
  "properties": {
    "gn:admin1_code":"11",
    "gn:asciiname":"Leonovka",
    "gn:country_code":"RU",
    "gn:dem":715,
    "gn:feature_class":"P",
    "gn:feature_code":"PPL",
    "gn:name":"Leonovka",
    "gn:population":0,
    "gn:timezone":"Asia/Irkutsk",
    "iso:country":"RU",
    "name:eng_x_preferred":[
        "Leonovka"
    ],
    "name:nor_x_preferred":[
        "Leonovka"
    ],
    "name:rus_x_preferred":[
        "\u041b\u0435\u043e\u043d\u043e\u0432\u043a\u0430"
    ],
    "wof:name":"Leonovka",
    "wof:placetype":"locality"
},
  "geometry": {"coordinates":[109.73976999999999,51.75105],"type":"Point"}
}