{
  "type": "Feature",
  "properties": {
    "gn:admin1_code":"90.0",
    "gn:asciiname":"Chirkovo",
    "gn:country_code":"RU",
    "gn:dem":185,
    "gn:feature_class":"P",
    "gn:feature_code":"PPL",
    "gn:name":"Chirkovo",
    "gn:population":0,
    "gn:timezone":"Asia/Yekaterinburg",
    "iso:country":"RU",
    "name:che_x_preferred":[
        "\u0427\u0438\u0440\u043a\u043e\u0432\u043e"
    ],
    "name:eng_x_preferred":[
        "Chirkovo"
    ],
    "name:nor_x_preferred":[
        "Tsjirkovo"
    ],
    "name:rus_x_preferred":[
        "\u0427\u0438\u0440\u043a\u043e\u0432\u043e"
    ],
    "name:und_x_variant":[
        "Chirkova",
        "Chirkovo",
        "\u0427\u0438\u0440\u043a\u043e\u0432\u043e"
    ],
    "wof:name":"Chirkovo",
    "wof:placetype":"locality"
},
  "geometry": {"coordinates":[54.986,59.8636],"type":"Point"}
}