{
  "type": "Feature",
  "properties": {
    "gn:country":"RU",
    "gn:fcode":"PPL",
    "gn:pop":0,
    "iso:country":"RU",
    "name:rus_x_preferred":[
        "\u0422\u0443\u0440\u043c\u0430\u0441\u043e\u0432\u043e"
    ],
    "qs:name":"Turmasovo",
    "qs:name_adm0":"Russia",
    "qs:name_adm1":"Tambov Oblast",
    "qs:photos_9r":0,
    "qs:photos_sr":0,
    "qs:placetype":"Town",
    "qs:pop_sr":"0",
    "wof:name":"Turmasovo",
    "wof:placetype":"locality",
    "wof:population":0
},
  "geometry": {"coordinates":[40.5496,52.9441],"type":"Point"}
}