{
  "type": "Feature",
  "properties": {
    "gn:admin1_code":"10",
    "gn:asciiname":"Sluchovsk",
    "gn:country_code":"RU",
    "gn:dem":147,
    "gn:feature_class":"P",
    "gn:feature_code":"PPL",
    "gn:name":"Sluchovsk",
    "gn:population":0,
    "gn:timezone":"Europe/Moscow",
    "iso:country":"RU",
    "name:rus_x_preferred":[
        "\u0421\u043b\u0443\u0447\u043e\u0432\u0441\u043a"
    ],
    "name:und_x_variant":[
        "\u0421\u043b\u0443\u0447\u043e\u0432\u0441\u043a",
        "Sluchevsk"
    ],
    "wof:name":"Sluchovsk",
    "wof:placetype":"locality"
},
  "geometry": {"coordinates":[33.29933,52.36912],"type":"Point"}
}