{
  "type": "Feature",
  "properties": {
    "gn:admin1_code":"53",
    "gn:asciiname":"Belolebyazhiy",
    "gn:country_code":"RU",
    "gn:dem":120,
    "gn:feature_class":"P",
    "gn:feature_code":"PPL",
    "gn:name":"Belolebyazhiy",
    "gn:population":0,
    "gn:timezone":"Asia/Novosibirsk",
    "iso:country":"RU",
    "name:nor_x_preferred":[
        "Belolebjazjij"
    ],
    "name:rus_x_preferred":[
        "\u0411\u0435\u043b\u043e\u043b\u0435\u0431\u044f\u0436\u0438\u0439"
    ],
    "wof:name":"Belolebyazhiy",
    "wof:placetype":"locality"
},
  "geometry": {"coordinates":[79.29073000000002,54.98034000000001],"type":"Point"}
}