{
  "type": "Feature",
  "properties": {
    "gn:admin1_code":"45.0",
    "gn:asciiname":"Shuashnur",
    "gn:country_code":"RU",
    "gn:dem":107,
    "gn:feature_class":"P",
    "gn:feature_code":"PPL",
    "gn:name":"Shuashnur",
    "gn:population":0,
    "gn:timezone":"Europe/Moscow",
    "iso:country":"RU",
    "name:rus_x_preferred":[
        "\u0428\u0443\u0430\u0448\u043d\u0443\u0440"
    ],
    "wof:name":"Shuashnur",
    "wof:placetype":"locality"
},
  "geometry": {"coordinates":[48.10778,56.74861],"type":"Point"}
}