{
  "type": "Feature",
  "properties": {
    "gn:admin1_code":"77",
    "gn:asciiname":"Studenik",
    "gn:country_code":"RU",
    "gn:dem":171,
    "gn:feature_class":"P",
    "gn:feature_code":"PPL",
    "gn:name":"Studenik",
    "gn:population":0,
    "gn:timezone":"Europe/Moscow",
    "iso:country":"RU",
    "name:rus_x_preferred":[
        "\u0421\u0442\u0443\u0434\u0435\u043d\u0438\u043a"
    ],
    "wof:name":"Studenik",
    "wof:placetype":"locality"
},
  "geometry": {"coordinates":[35.61723,58.3704],"type":"Point"}
}