{
  "type": "Feature",
  "properties": {
    "gn:admin1_code":"85.0",
    "gn:asciiname":"Anosovo",
    "gn:country_code":"RU",
    "gn:dem":214,
    "gn:feature_class":"P",
    "gn:feature_code":"PPL",
    "gn:name":"Anosovo",
    "gn:population":0,
    "gn:timezone":"Europe/Moscow",
    "iso:country":"RU",
    "name:che_x_preferred":[
        "\u0410\u043d\u043e\u0441\u043e\u0432\u043e"
    ],
    "name:nor_x_preferred":[
        "Anosovo"
    ],
    "name:rus_x_preferred":[
        "\u0410\u043d\u043e\u0441\u043e\u0432\u043e"
    ],
    "wof:name":"Anosovo",
    "wof:placetype":"locality"
},
  "geometry": {"coordinates":[40.35448,58.62572],"type":"Point"}
}