{
  "type": "Feature",
  "properties": {
    "gn:admin1_code":"84",
    "gn:asciiname":"Sukhovskiy Vtoroy",
    "gn:country_code":"RU",
    "gn:dem":141,
    "gn:feature_class":"P",
    "gn:feature_code":"PPL",
    "gn:name":"Sukhovskiy Vtoroy",
    "gn:population":0,
    "gn:timezone":"Europe/Volgograd",
    "iso:country":"RU",
    "name:rus_x_preferred":[
        "\u0421\u0443\u0445\u043e\u0432\u0441\u043a\u0438\u0439 \u0412\u0442\u043e\u0440\u043e\u0439"
    ],
    "wof:name":"Sukhovskiy Vtoroy",
    "wof:placetype":"locality"
},
  "geometry": {"coordinates":[41.5702,50.5405],"type":"Point"}
}