{
  "type": "Feature",
  "properties": {
    "gn:admin1_code":"52.0",
    "gn:asciiname":"Bol'shaya Karavayeva",
    "gn:country_code":"RU",
    "gn:dem":82,
    "gn:feature_class":"P",
    "gn:feature_code":"PPL",
    "gn:name":"Bol\u2019shaya Karavayeva",
    "gn:population":0,
    "gn:timezone":"Europe/Moscow",
    "iso:country":"RU",
    "name:rus_x_preferred":[
        "\u0411\u043e\u043b\u044c\u0448\u0430\u044f \u041a\u0430\u0440\u0430\u0432\u0430\u0435\u0432\u0430"
    ],
    "name:und_x_variant":[
        "Bol\u2019shaya Karavayeva",
        "\u0411\u043e\u043b\u044c\u0448\u0430\u044f \u041a\u0430\u0440\u0430\u0432\u0430\u0435\u0432\u0430"
    ],
    "wof:name":"Bol'shaya Karavayeva",
    "wof:placetype":"locality"
},
  "geometry": {"coordinates":[30.96342000000001,57.05143],"type":"Point"}
}