{
  "type": "Feature",
  "properties": {
    "gn:admin1_code":"60",
    "gn:asciiname":"Izluch'ye",
    "gn:country_code":"RU",
    "gn:dem":62,
    "gn:feature_class":"P",
    "gn:feature_code":"PPL",
    "gn:name":"Izluch\u2019ye",
    "gn:population":0,
    "gn:timezone":"Europe/Moscow",
    "iso:country":"RU",
    "name:eng_x_preferred":[
        "Izluch'ye"
    ],
    "name:nor_x_preferred":[
        "Izlutsje"
    ],
    "name:rus_x_preferred":[
        "\u0418\u0437\u043b\u0443\u0447\u044c\u0435"
    ],
    "name:und_x_variant":[
        "Izluch\u2019ye"
    ],
    "wof:name":"Izluch'ye",
    "wof:placetype":"locality"
},
  "geometry": {"coordinates":[28.1098,58.89746],"type":"Point"}
}