{
  "type": "Feature",
  "properties": {
    "gn:admin1_code":"86.0",
    "gn:asciiname":"Kutepovka",
    "gn:country_code":"RU",
    "gn:dem":125,
    "gn:feature_class":"P",
    "gn:feature_code":"PPL",
    "gn:name":"Kutepovka",
    "gn:population":0,
    "gn:timezone":"Europe/Moscow",
    "iso:country":"RU",
    "name:rus_x_preferred":[
        "\u041a\u0443\u0442\u0435\u043f\u043e\u0432\u043a\u0430"
    ],
    "wof:name":"Kutepovka",
    "wof:placetype":"locality"
},
  "geometry": {"coordinates":[40.19639,50.91028],"type":"Point"}
}