{
  "type": "Feature",
  "properties": {
    "gn:admin1_code":"21.0",
    "gn:asciiname":"Meshkovo",
    "gn:country_code":"RU",
    "gn:dem":118,
    "gn:feature_class":"P",
    "gn:feature_code":"PPL",
    "gn:name":"Meshkovo",
    "gn:population":0,
    "gn:timezone":"Europe/Moscow",
    "iso:country":"RU",
    "name:che_x_preferred":[
        "\u041c\u0435\u0448\u043a\u043e\u0432\u043e"
    ],
    "name:rus_x_preferred":[
        "\u041c\u0435\u0448\u043a\u043e\u0432\u043e"
    ],
    "name:tgk_x_preferred":[
        "\u041c\u0435\u0448\u043a\u043e\u0432\u043e"
    ],
    "name:und_x_variant":[
        "\u041c\u0435\u0448\u043a\u043e\u0432\u043e"
    ],
    "wof:name":"Meshkovo",
    "wof:placetype":"locality"
},
  "geometry": {"coordinates":[42.02399000000001,57.51266999999999],"type":"Point"}
}