{
  "type": "Feature",
  "properties": {
    "gn:admin1_code":"76",
    "gn:asciiname":"Muravlyanka",
    "gn:country_code":"RU",
    "gn:dem":155,
    "gn:feature_class":"P",
    "gn:feature_code":"PPL",
    "gn:name":"Muravlyanka",
    "gn:population":0,
    "gn:timezone":"Europe/Moscow",
    "iso:country":"RU",
    "name:eng_x_preferred":[
        "Muravlyanka"
    ],
    "name:nor_x_preferred":[
        "Muravljanka"
    ],
    "name:rus_x_preferred":[
        "\u041c\u0443\u0440\u0430\u0432\u043b\u044f\u043d\u043a\u0430"
    ],
    "name:und_x_variant":[
        "Murovlyanka",
        "Muravlyanki",
        "\u041c\u0443\u0440\u0430\u0432\u043b\u044f\u043d\u043a\u0430",
        "Muravlyanka"
    ],
    "wof:name":"Muravlyanka",
    "wof:placetype":"locality"
},
  "geometry": {"coordinates":[38.49206,53.74023],"type":"Point"}
}