{
  "type": "Feature",
  "properties": {
    "gn:admin1_code":"61.0",
    "gn:asciiname":"Avilo-Uspenka",
    "gn:country_code":"RU",
    "gn:dem":123,
    "gn:feature_class":"P",
    "gn:feature_code":"PPL",
    "gn:name":"Avilo-Uspenka",
    "gn:population":0,
    "gn:timezone":"Europe/Moscow",
    "iso:country":"RU",
    "name:eng_x_preferred":[
        "Avilo-Uspenskiy"
    ],
    "name:rus_x_preferred":[
        "\u0410\u0432\u0438\u043b\u043e-\u0423\u0441\u043f\u0435\u043d\u043a\u0430"
    ],
    "name:und_x_variant":[
        "Uspenskiy",
        "Avilo-Uspenka",
        "Uspenskaya"
    ],
    "wof:name":"Avilo-Uspenka",
    "wof:placetype":"locality"
},
  "geometry": {"coordinates":[38.67561,47.69367],"type":"Point"}
}