{
  "type": "Feature",
  "properties": {
    "gn:admin1_code":"72",
    "gn:asciiname":"Gordenino",
    "gn:country_code":"RU",
    "gn:dem":165,
    "gn:feature_class":"P",
    "gn:feature_code":"PPL",
    "gn:name":"Gordenino",
    "gn:population":0,
    "gn:timezone":"Europe/Moscow",
    "iso:country":"RU",
    "name:rus_x_preferred":[
        "\u0413\u043e\u0440\u0434\u0435\u043d\u0438\u043d\u043e"
    ],
    "name:und_x_variant":[
        "Maslovka",
        "Gordenino"
    ],
    "wof:name":"Gordenino",
    "wof:placetype":"locality"
},
  "geometry": {"coordinates":[41.13791,51.88375],"type":"Point"}
}