{
  "type": "Feature",
  "properties": {
    "gn:admin1_code":"60.0",
    "gn:asciiname":"Apalevo",
    "gn:country_code":"RU",
    "gn:dem":47,
    "gn:feature_class":"P",
    "gn:feature_code":"PPL",
    "gn:name":"Apal\u00ebvo",
    "gn:population":0,
    "gn:timezone":"Europe/Moscow",
    "iso:country":"RU",
    "name:eng_x_preferred":[
        "Apalevo"
    ],
    "name:nor_x_preferred":[
        "Apalevo"
    ],
    "name:rus_x_preferred":[
        "\u0410\u043f\u0430\u043b\u0451\u0432\u043e"
    ],
    "name:rus_x_variant":[
        "Apal\u00ebvo"
    ],
    "wof:name":"Apalevo",
    "wof:placetype":"locality"
},
  "geometry": {"coordinates":[28.30112,58.54139],"type":"Point"}
}