{
  "type": "Feature",
  "properties": {
    "gn:admin1_code":"77",
    "gn:asciiname":"Lykovo",
    "gn:country_code":"RU",
    "gn:dem":148,
    "gn:feature_class":"P",
    "gn:feature_code":"PPL",
    "gn:name":"Lykovo",
    "gn:population":0,
    "gn:timezone":"Europe/Moscow",
    "iso:country":"RU",
    "name:rus_x_preferred":[
        "\u041b\u044b\u043a\u043e\u0432\u043e"
    ],
    "name:und_x_variant":[
        "\u041b\u044b\u043a\u043e\u0432\u043e"
    ],
    "wof:name":"Lykovo",
    "wof:placetype":"locality"
},
  "geometry": {"coordinates":[36.769,57.146],"type":"Point"}
}