{
  "type": "Feature",
  "properties": {
    "gn:admin1_code":"62",
    "gn:asciiname":"Klobuchki",
    "gn:country_code":"RU",
    "gn:dem":196,
    "gn:feature_class":"P",
    "gn:feature_code":"PPL",
    "gn:name":"Klobuchki",
    "gn:population":0,
    "gn:timezone":"Europe/Moscow",
    "iso:country":"RU",
    "name:rus_x_preferred":[
        "\u041a\u043b\u043e\u0431\u0443\u0447\u043a\u0438"
    ],
    "name:und_x_variant":[
        "Klabuchki",
        "Klobuchki",
        "\u041a\u043b\u043e\u0431\u0443\u0447\u043a\u0438"
    ],
    "wof:name":"Klobuchki",
    "wof:placetype":"locality"
},
  "geometry": {"coordinates":[39.01211,53.92461],"type":"Point"}
}