{
  "type": "Feature",
  "properties": {
    "gn:admin1_code":"42.0",
    "gn:asciiname":"Kar'yer Myaglovo",
    "gn:country_code":"RU",
    "gn:dem":32,
    "gn:feature_class":"P",
    "gn:feature_code":"PPL",
    "gn:name":"Kar\u2019yer Myaglovo",
    "gn:population":0,
    "gn:timezone":"Europe/Moscow",
    "iso:country":"RU",
    "name:fin_x_preferred":[
        "M\u00e4hn\u00e4l\u00e4nlouhos"
    ],
    "name:rus_x_preferred":[
        "\u041a\u0430\u0440\u044c\u0435\u0440 \u041c\u044f\u0433\u043b\u043e\u0432\u043e"
    ],
    "name:und_x_variant":[
        "Myaglovo Kar\u2019yer",
        "Kar\u2019yer Myaglovo",
        "\u041a\u0430\u0440\u044c\u0435\u0440 \u041c\u044f\u0433\u043b\u043e\u0432\u043e"
    ],
    "wof:name":"Kar'yer Myaglovo",
    "wof:placetype":"locality"
},
  "geometry": {"coordinates":[30.67537,59.85667],"type":"Point"}
}