{
  "type": "Feature",
  "properties": {
    "gn:admin1_code":"17.0",
    "gn:asciiname":"Mulla-Ali",
    "gn:country_code":"RU",
    "gn:dem":-13,
    "gn:feature_class":"P",
    "gn:feature_code":"PPL",
    "gn:name":"Mulla-Ali",
    "gn:population":0,
    "gn:timezone":"Europe/Moscow",
    "iso:country":"RU",
    "name:rus_x_preferred":[
        "\u041c\u0443\u043b\u043b\u0430-\u0410\u043b\u0438"
    ],
    "name:und_x_variant":[
        "Muha-Ali",
        "Mulla-Ali"
    ],
    "wof:name":"Mulla-Ali",
    "wof:placetype":"locality"
},
  "geometry": {"coordinates":[46.88344,43.86792],"type":"Point"}
}