{
  "type": "Feature",
  "properties": {
    "gn:admin1_code":"47",
    "gn:asciiname":"Radiontsevo",
    "gn:country_code":"RU",
    "gn:dem":184,
    "gn:feature_class":"P",
    "gn:feature_code":"PPL",
    "gn:name":"Radiontsevo",
    "gn:population":0,
    "gn:timezone":"Europe/Moscow",
    "iso:country":"RU",
    "name:rus_x_preferred":[
        "\u0420\u0430\u0434\u0438\u043e\u043d\u0446\u0435\u0432\u043e"
    ],
    "name:und_x_variant":[
        "\u0420\u0430\u0434\u0438\u043e\u043d\u0446\u0435\u0432\u043e",
        "Rodiontsevo"
    ],
    "wof:name":"Radiontsevo",
    "wof:placetype":"locality"
},
  "geometry": {"coordinates":[36.7214,56.0942],"type":"Point"}
}