{
  "type": "Feature",
  "properties": {
    "gn:admin1_code":"90",
    "gn:asciiname":"Gryaznukha",
    "gn:country_code":"RU",
    "gn:dem":168,
    "gn:feature_class":"P",
    "gn:feature_code":"PPL",
    "gn:name":"Gryaznukha",
    "gn:population":0,
    "gn:timezone":"Asia/Yekaterinburg",
    "iso:country":"RU",
    "name:rus_x_preferred":[
        "\u0413\u0440\u044f\u0437\u043d\u0443\u0445\u0430"
    ],
    "name:und_x_variant":[
        "\u0413\u0440\u044f\u0437\u043d\u0443\u0445\u0430"
    ],
    "wof:name":"Gryaznukha",
    "wof:placetype":"locality"
},
  "geometry": {"coordinates":[57.2505,57.7954],"type":"Point"}
}