{
  "type": "Feature",
  "properties": {
    "gn:admin1_code":"70",
    "gn:asciiname":"Pravokumskiy",
    "gn:cc2":"RU",
    "gn:country_code":"RU",
    "gn:dem":148,
    "gn:feature_class":"P",
    "gn:feature_code":"PPL",
    "gn:name":"Pravokumskiy",
    "gn:population":0,
    "gn:timezone":"Europe/Moscow",
    "iso:country":"RU",
    "name:eng_x_preferred":[
        "Pravokumskiy"
    ],
    "name:nor_x_preferred":[
        "Pravokumskoje"
    ],
    "name:rus_x_preferred":[
        "\u041f\u0440\u0430\u0432\u043e\u043a\u0443\u043c\u0441\u043a\u043e\u0435"
    ],
    "name:rus_x_variant":[
        "\u041f\u0440\u0430\u0432\u043e\u043a\u0443\u043c\u0441\u043a\u0438\u0439"
    ],
    "name:und_x_variant":[
        "Prayokumskiy"
    ],
    "wof:name":"Pravokumskiy",
    "wof:placetype":"locality"
},
  "geometry": {"coordinates":[44.09444000000001,44.38111],"type":"Point"}
}