{
  "type": "Feature",
  "properties": {
    "gn:admin1_code":"4",
    "gn:asciiname":"Chaynoye",
    "gn:country_code":"RU",
    "gn:dem":551,
    "gn:feature_class":"P",
    "gn:feature_code":"PPL",
    "gn:name":"Chaynoye",
    "gn:population":0,
    "gn:timezone":"Asia/Barnaul",
    "iso:country":"RU",
    "name:eng_x_preferred":[
        "Chaynoye"
    ],
    "name:nor_x_preferred":[
        "Tsjajnoje"
    ],
    "name:rus_x_preferred":[
        "\u0427\u0430\u0439\u043d\u043e\u0435"
    ],
    "name:und_x_variant":[
        "Chaynaya"
    ],
    "wof:name":"Chaynoye",
    "wof:placetype":"locality"
},
  "geometry": {"coordinates":[83.617,51.6268],"type":"Point"}
}