{
  "type": "Feature",
  "properties": {
    "gn:country":"RU",
    "gn:fcode":"PPL",
    "gn:pop":3442,
    "iso:country":"RU",
    "name:eng_x_preferred":[
        "Gagatli"
    ],
    "name:nor_x_preferred":[
        "Gagatli"
    ],
    "name:rus_x_preferred":[
        "\u0413\u0430\u0433\u0430\u0442\u043b\u0438"
    ],
    "name:unk_x_variant":[
        "Gogatl\u2019"
    ],
    "qs:name":"Gagatli",
    "qs:photos_9r":0,
    "qs:photos_sr":0,
    "qs:pop_sr":"4",
    "wof:name":"Gagatli",
    "wof:placetype":"locality",
    "wof:population":3442
},
  "geometry": {"coordinates":[46.29162,42.8013],"type":"Point"}
}