{
  "type": "Feature",
  "properties": {
    "gn:admin1_code":"53",
    "gn:asciiname":"Taylenok",
    "gn:cc2":"RU",
    "gn:country_code":"RU",
    "gn:dem":327,
    "gn:feature_class":"P",
    "gn:feature_code":"PPL",
    "gn:name":"Tayl\u00ebnok",
    "gn:population":0,
    "gn:timezone":"Asia/Novosibirsk",
    "iso:country":"RU",
    "name:und_x_variant":[
        "Tayly",
        "Tayl\u00ebnok"
    ],
    "wof:name":"Taylenok",
    "wof:placetype":"locality"
},
  "geometry": {"coordinates":[84.65000000000001,54.56667],"type":"Point"}
}