{
  "type": "Feature",
  "properties": {
    "gn:admin1_code":"69",
    "gn:asciiname":"Utekhovo Vtoroye",
    "gn:country_code":"RU",
    "gn:dem":197,
    "gn:feature_class":"P",
    "gn:feature_code":"PPL",
    "gn:name":"Utekhovo Vtoroye",
    "gn:population":0,
    "gn:timezone":"Europe/Moscow",
    "iso:country":"RU",
    "name:eng_x_preferred":[
        "Utekhovo Vtoroye"
    ],
    "name:nor_x_preferred":[
        "Utekhovo"
    ],
    "name:rus_x_preferred":[
        "\u0423\u0442\u0435\u0445\u043e\u0432\u043e"
    ],
    "name:und_x_variant":[
        "Utekhovo",
        "Utekhovo Vtoroye"
    ],
    "wof:name":"Utekhovo Vtoroye",
    "wof:placetype":"locality"
},
  "geometry": {"coordinates":[33.04118,54.10381999999999],"type":"Point"}
}