{
  "type": "Feature",
  "properties": {
    "gn:admin1_code":"84.0",
    "gn:asciiname":"Avramovskiy",
    "gn:country_code":"RU",
    "gn:dem":111,
    "gn:feature_class":"P",
    "gn:feature_code":"PPL",
    "gn:name":"Avramovskiy",
    "gn:population":0,
    "gn:timezone":"Europe/Volgograd",
    "iso:country":"RU",
    "name:nor_x_preferred":[
        "Avramovskij"
    ],
    "name:rus_x_preferred":[
        "\u0410\u0432\u0440\u0430\u043c\u043e\u0432\u0441\u043a\u0438\u0439"
    ],
    "wof:name":"Avramovskiy",
    "wof:placetype":"locality"
},
  "geometry": {"coordinates":[41.6079,50.3961],"type":"Point"}
}