{
  "type": "Feature",
  "properties": {
    "gn:admin1_code":"15",
    "gn:asciiname":"Tumannaya Stantsiya",
    "gn:country_code":"RU",
    "gn:dem":71,
    "gn:feature_class":"P",
    "gn:feature_code":"PPL",
    "gn:name":"Tumannaya Stantsiya",
    "gn:population":0,
    "gn:timezone":"Asia/Anadyr",
    "iso:country":"RU",
    "wof:name":"Tumannaya Stantsiya",
    "wof:placetype":"locality"
},
  "geometry": {"coordinates":[170.55090000000001,70.12236999999999],"type":"Point"}
}