{
  "type": "Feature",
  "properties": {
    "gn:admin1_code":"8",
    "gn:asciiname":"Kartkisyak",
    "gn:country_code":"RU",
    "gn:dem":173,
    "gn:feature_class":"P",
    "gn:feature_code":"PPL",
    "gn:name":"Kartkisyak",
    "gn:population":0,
    "gn:timezone":"Asia/Yekaterinburg",
    "iso:country":"RU",
    "name:eng_x_preferred":[
        "Kartkisyak"
    ],
    "name:nor_x_preferred":[
        "Kartkisiak"
    ],
    "name:rus_x_preferred":[
        "\u041a\u0430\u0440\u0442\u043a\u0438\u0441\u044f\u043a"
    ],
    "name:und_x_variant":[
        "\u041a\u0430\u0440\u0442\u043a\u0438\u0441\u044f\u043a",
        "Kartkisyak"
    ],
    "wof:name":"Kartkisyak",
    "wof:placetype":"locality"
},
  "geometry": {"coordinates":[56.58922,55.9433],"type":"Point"}
}