{
  "type": "Feature",
  "properties": {
    "gn:admin1_code":"8",
    "gn:asciiname":"Kartkisyak",
    "gn:country_code":"RU",
    "gn:dem":173,
    "gn:feature_class":"P",
    "gn:feature_code":"PPL",
    "gn:name":"Kartkisyak",
    "gn:population":0,
    "gn:timezone":"Asia/Yekaterinburg",
    "iso:country":"RU",
    "name:aze_x_preferred":[
        "Kartki\u00e7\u0259k"
    ],
    "name:bak_x_preferred":[
        "\u04a0\u0430\u0440\u0442\u043a\u0438\u04ab\u04d9\u043a"
    ],
    "name:che_x_preferred":[
        "\u041a\u0430\u0440\u0442\u043a\u0438\u0441\u044f\u043a"
    ],
    "name:eng_x_preferred":[
        "Kartkisyak"
    ],
    "name:hye_x_preferred":[
        "\u053f\u0561\u0580\u057f\u056f\u056b\u057d\u0575\u0561\u056f"
    ],
    "name:kat_x_preferred":[
        "\u10d9\u10d0\u10e0\u10e2\u10d9\u10d8\u10e1\u10d8\u10d0\u10d9\u10d8"
    ],
    "name:kaz_x_preferred":[
        "\u041a\u0430\u0440\u0442\u043a\u0438\u0441\u044f\u043a"
    ],
    "name:kir_x_preferred":[
        "\u041a\u0430\u0440\u0442\u043a\u0438\u0441\u044f\u043a"
    ],
    "name:nor_x_preferred":[
        "Kartkisiak"
    ],
    "name:rus_x_preferred":[
        "\u041a\u0430\u0440\u0442\u043a\u0438\u0441\u044f\u043a"
    ],
    "name:tat_x_preferred":[
        "\u041a\u0430\u0440\u0442\u043a\u0438\u0441\u04d9\u043a"
    ],
    "wof:name":"Kartkisyak",
    "wof:placetype":"locality"
},
  "geometry": {"coordinates":[56.58922,55.9433],"type":"Point"}
}