{
  "type": "Feature",
  "properties": {
    "gn:admin1_code":"84",
    "gn:asciiname":"Shchepkin",
    "gn:country_code":"RU",
    "gn:dem":68,
    "gn:feature_class":"P",
    "gn:feature_code":"PPL",
    "gn:name":"Shchepkin",
    "gn:population":0,
    "gn:timezone":"Europe/Volgograd",
    "iso:country":"RU",
    "name:rus_x_preferred":[
        "\u0429\u0435\u043f\u043a\u0438\u043d"
    ],
    "wof:name":"Shchepkin",
    "wof:placetype":"locality"
},
  "geometry": {"coordinates":[44.9711,49.72838],"type":"Point"}
}