{
  "type": "Feature",
  "properties": {
    "gn:admin1_code":"6",
    "gn:asciiname":"Konetsbor",
    "gn:country_code":"RU",
    "gn:dem":7,
    "gn:feature_class":"P",
    "gn:feature_code":"PPL",
    "gn:name":"Konetsbor",
    "gn:population":0,
    "gn:timezone":"Europe/Moscow",
    "iso:country":"RU",
    "name:rus_x_preferred":[
        "\u041a\u043e\u043d\u0435\u0446\u0431\u043e\u0440"
    ],
    "wof:name":"Konetsbor",
    "wof:placetype":"locality"
},
  "geometry": {"coordinates":[39.75,64.48333000000001],"type":"Point"}
}