{
  "type": "Feature",
  "properties": {
    "gn:admin1_code":"86",
    "gn:asciiname":"Khmelevoye",
    "gn:country_code":"RU",
    "gn:dem":153,
    "gn:feature_class":"P",
    "gn:feature_code":"PPL",
    "gn:name":"Khmelevoye",
    "gn:population":0,
    "gn:timezone":"Europe/Moscow",
    "iso:country":"RU",
    "name:rus_x_preferred":[
        "\u0425\u043c\u0435\u043b\u0435\u0432\u043e\u0435"
    ],
    "wof:name":"Khmelevoye",
    "wof:placetype":"locality"
},
  "geometry": {"coordinates":[38.9495,51.8498],"type":"Point"}
}