{
  "type": "Feature",
  "properties": {
    "gn:admin1_code":"10",
    "gn:asciiname":"Skachok",
    "gn:country_code":"RU",
    "gn:dem":129,
    "gn:feature_class":"P",
    "gn:feature_code":"PPL",
    "gn:name":"Skachok",
    "gn:population":0,
    "gn:timezone":"Europe/Moscow",
    "iso:country":"RU",
    "name:rus_x_preferred":[
        "\u0421\u043a\u0430\u0447\u043e\u043a"
    ],
    "name:und_x_variant":[
        "\u0421\u043a\u0430\u0447\u043e\u043a"
    ],
    "wof:name":"Skachok",
    "wof:placetype":"locality"
},
  "geometry": {"coordinates":[32.31728,52.14047],"type":"Point"}
}