{
  "type": "Feature",
  "properties": {
    "gn:admin1_code":"29",
    "gn:asciiname":"Krokhalevka",
    "gn:cc2":"RU",
    "gn:country_code":"RU",
    "gn:dem":233,
    "gn:feature_class":"P",
    "gn:feature_code":"PPL",
    "gn:name":"Krokhalevka",
    "gn:population":0,
    "gn:timezone":"Asia/Novokuznetsk",
    "iso:country":"RU",
    "name:rus_x_preferred":[
        "\u041a\u0440\u043e\u0445\u0430\u043b\u0435\u0432\u043a\u0430"
    ],
    "name:und_x_variant":[
        "Krokhalevskiy",
        "Krokhalevka",
        "\u041a\u0440\u043e\u0445\u0430\u043b\u0435\u0432\u043a\u0430"
    ],
    "wof:name":"Krokhalevka",
    "wof:placetype":"locality"
},
  "geometry": {"coordinates":[86.21666999999999,55.56667],"type":"Point"}
}