{
  "type": "Feature",
  "properties": {
    "gn:admin1_code":"49",
    "gn:asciiname":"Koproyva",
    "gn:country_code":"RU",
    "gn:dem":275,
    "gn:feature_class":"P",
    "gn:feature_code":"PPL",
    "gn:name":"Koproyva",
    "gn:population":0,
    "gn:timezone":"Europe/Moscow",
    "iso:country":"RU",
    "name:fin_x_preferred":[
        "Koproiva"
    ],
    "name:rus_x_preferred":[
        "\u041a\u043e\u043f\u0440\u043e\u0439\u0432\u0430"
    ],
    "wof:name":"Koproyva",
    "wof:placetype":"locality"
},
  "geometry": {"coordinates":[31.04427,66.96783000000001],"type":"Point"}
}