{
  "type": "Feature",
  "properties": {
    "gn:admin1_code":"71",
    "gn:asciiname":"Puksinka",
    "gn:country_code":"RU",
    "gn:dem":69,
    "gn:feature_class":"P",
    "gn:feature_code":"PPL",
    "gn:name":"Puksinka",
    "gn:population":0,
    "gn:timezone":"Asia/Yekaterinburg",
    "iso:country":"RU",
    "name:eng_x_preferred":[
        "Puksinka"
    ],
    "name:nor_x_preferred":[
        "Puksinka"
    ],
    "name:rus_x_preferred":[
        "\u041f\u0443\u043a\u0441\u0438\u043d\u043a\u0430"
    ],
    "wof:name":"Puksinka",
    "wof:placetype":"locality"
},
  "geometry": {"coordinates":[62.94657,59.71657],"type":"Point"}
}