{
  "type": "Feature",
  "properties": {
    "gn:admin1_code":"85",
    "gn:asciiname":"Poselok Siuch",
    "gn:country_code":"RU",
    "gn:dem":125,
    "gn:feature_class":"P",
    "gn:feature_code":"PPL",
    "gn:name":"Pos\u00eblok Siuch",
    "gn:population":0,
    "gn:timezone":"Europe/Moscow",
    "iso:country":"RU",
    "name:rus_x_preferred":[
        "\u041f\u043e\u0441\u0451\u043b\u043e\u043a \u0421\u0438\u0443\u0447"
    ],
    "name:und_x_variant":[
        "Pos\u00eblok Siuch",
        "\u041f\u043e\u0441\u0451\u043b\u043e\u043a \u0421\u0438\u0443\u0447"
    ],
    "wof:name":"Poselok Siuch",
    "wof:placetype":"locality"
},
  "geometry": {"coordinates":[36.4263,59.2852],"type":"Point"}
}