{
  "type": "Feature",
  "properties": {
    "gn:admin1_code":"23",
    "gn:asciiname":"Dubravino",
    "gn:country_code":"RU",
    "gn:dem":25,
    "gn:feature_class":"P",
    "gn:feature_code":"PPL",
    "gn:name":"Dubravino",
    "gn:population":0,
    "gn:timezone":"Europe/Kaliningrad",
    "iso:country":"RU",
    "name:rus_x_preferred":[
        "\u0414\u0443\u0431\u0440\u0430\u0432\u0438\u043d\u043e"
    ],
    "name:und_x_variant":[
        "\u0414\u0443\u0431\u0440\u0430\u0432\u0438\u043d\u043e"
    ],
    "wof:name":"Dubravino",
    "wof:placetype":"locality"
},
  "geometry": {"coordinates":[22.06806,54.99556],"type":"Point"}
}