{
  "type": "Feature",
  "properties": {
    "gn:admin1_code":"43",
    "gn:asciiname":"Sredneye",
    "gn:country_code":"RU",
    "gn:dem":154,
    "gn:feature_class":"P",
    "gn:feature_code":"PPL",
    "gn:name":"Sredneye",
    "gn:population":0,
    "gn:timezone":"Europe/Moscow",
    "iso:country":"RU",
    "name:eng_x_preferred":[
        "Sredneye"
    ],
    "name:nor_x_preferred":[
        "Sredneje"
    ],
    "name:rus_x_preferred":[
        "\u0421\u0440\u0435\u0434\u043d\u0435\u0435"
    ],
    "name:und_x_variant":[
        "Gagarino",
        "Knyazhaya",
        "Knyazhaya Baygora",
        "\u0421\u0440\u0435\u0434\u043d\u0435\u0435",
        "Sredneye"
    ],
    "wof:name":"Sredneye",
    "wof:placetype":"locality"
},
  "geometry": {"coordinates":[40.5555,52.2317],"type":"Point"}
}