{
  "type": "Feature",
  "properties": {
    "gn:admin1_code":"60",
    "gn:asciiname":"Timokhi",
    "gn:country_code":"RU",
    "gn:dem":91,
    "gn:feature_class":"P",
    "gn:feature_code":"PPL",
    "gn:name":"Timokhi",
    "gn:population":0,
    "gn:timezone":"Europe/Moscow",
    "iso:country":"RU",
    "name:rus_x_preferred":[
        "\u0422\u0438\u043c\u043e\u0445\u0438"
    ],
    "wof:name":"Timokhi",
    "wof:placetype":"locality"
},
  "geometry": {"coordinates":[28.43581,56.9035],"type":"Point"}
}