{
  "type": "Feature",
  "properties": {
    "gn:admin1_code":"29",
    "gn:asciiname":"Koksu",
    "gn:country_code":"RU",
    "gn:dem":490,
    "gn:feature_class":"P",
    "gn:feature_code":"PPL",
    "gn:name":"Koksu",
    "gn:population":0,
    "gn:timezone":"Asia/Novokuznetsk",
    "iso:country":"RU",
    "name:msa_x_preferred":[
        "Koksu"
    ],
    "name:rus_x_preferred":[
        "\u041a\u043e\u043a\u0441\u0443"
    ],
    "name:und_x_variant":[
        "\u041a\u043e\u043a\u0441\u0443"
    ],
    "wof:name":"Koksu",
    "wof:placetype":"locality"
},
  "geometry": {"coordinates":[88.71666999999999,53.53333000000001],"type":"Point"}
}