{
  "type": "Feature",
  "properties": {
    "gn:admin1_code":"84",
    "gn:asciiname":"Nizhnekardail'skiy",
    "gn:country_code":"RU",
    "gn:dem":98,
    "gn:feature_class":"P",
    "gn:feature_code":"PPL",
    "gn:name":"Nizhnekardail\u2019skiy",
    "gn:population":0,
    "gn:timezone":"Europe/Volgograd",
    "iso:country":"RU",
    "name:eng_x_preferred":[
        "Nizhne-Kardail'skiy"
    ],
    "name:nor_x_preferred":[
        "Nizjnekardailskij"
    ],
    "name:rus_x_preferred":[
        "\u041d\u0438\u0436\u043d\u0435\u043a\u0430\u0440\u0434\u0430\u0438\u043b\u044c\u0441\u043a\u0438\u0439"
    ],
    "name:und_x_variant":[
        "Nizhnekardail\u2019skiy"
    ],
    "wof:name":"Nizhnekardail'skiy",
    "wof:placetype":"locality"
},
  "geometry": {"coordinates":[42.7396,50.8762],"type":"Point"}
}