{
  "type": "Feature",
  "properties": {
    "gn:admin1_code":"9.0",
    "gn:asciiname":"Vtoraya Maya",
    "gn:country_code":"RU",
    "gn:dem":193,
    "gn:feature_class":"P",
    "gn:feature_code":"PPL",
    "gn:name":"Vtoraya Maya",
    "gn:population":0,
    "gn:timezone":"Europe/Moscow",
    "iso:country":"RU",
    "name:und_x_variant":[
        "May",
        "Vtoraya Maya"
    ],
    "wof:name":"Vtoraya Maya",
    "wof:placetype":"locality"
},
  "geometry": {"coordinates":[36.3466,50.48483],"type":"Point"}
}