{
  "type": "Feature",
  "properties": {
    "gn:admin1_code":"93.0",
    "gn:asciiname":"Zastep'",
    "gn:country_code":"RU",
    "gn:dem":683,
    "gn:feature_class":"P",
    "gn:feature_code":"PPL",
    "gn:name":"Zastep\u2019",
    "gn:population":0,
    "gn:timezone":"Asia/Chita",
    "iso:country":"RU",
    "name:rus_x_preferred":[
        "\u0417\u0430\u0441\u0442\u0435\u043f\u044c"
    ],
    "name:und_x_variant":[
        "Zastep\u2019"
    ],
    "wof:name":"Zastep'",
    "wof:placetype":"locality"
},
  "geometry": {"coordinates":[113.25888999999999,51.98622],"type":"Point"}
}