{
  "type": "Feature",
  "properties": {
    "gn:admin1_code":"53",
    "gn:asciiname":"Staryy Iskitim",
    "gn:country_code":"RU",
    "gn:dem":121,
    "gn:feature_class":"P",
    "gn:feature_code":"PPL",
    "gn:name":"Staryy Iskitim",
    "gn:population":0,
    "gn:timezone":"Asia/Novosibirsk",
    "iso:country":"RU",
    "name:rus_x_preferred":[
        "\u0421\u0442\u0430\u0440\u044b\u0439 \u0418\u0441\u043a\u0438\u0442\u0438\u043c"
    ],
    "name:und_x_variant":[
        "Iskitim",
        "Staryy Iskitim"
    ],
    "wof:name":"Staryy Iskitim",
    "wof:placetype":"locality"
},
  "geometry": {"coordinates":[83.4006,54.6122],"type":"Point"}
}