{
  "type": "Feature",
  "properties": {
    "gn:admin1_code":"69",
    "gn:asciiname":"Pyatern",
    "gn:country_code":"RU",
    "gn:dem":251,
    "gn:feature_class":"P",
    "gn:feature_code":"PPL",
    "gn:name":"Pyatern",
    "gn:population":0,
    "gn:timezone":"Europe/Moscow",
    "iso:country":"RU",
    "name:rus_x_preferred":[
        "\u041f\u044f\u0442\u0435\u0440\u043d"
    ],
    "name:und_x_variant":[
        "Peternikova",
        "Pyatern",
        "\u041f\u044f\u0442\u0435\u0440\u043d",
        "Pyaternikovo"
    ],
    "wof:name":"Pyatern",
    "wof:placetype":"locality"
},
  "geometry": {"coordinates":[34.03671,55.63415],"type":"Point"}
}