{
  "type": "Feature",
  "properties": {
    "gn:admin1_code":"81",
    "gn:asciiname":"Ponika",
    "gn:country_code":"RU",
    "gn:dem":215,
    "gn:feature_class":"P",
    "gn:feature_code":"PPL",
    "gn:name":"Ponika",
    "gn:population":0,
    "gn:timezone":"Europe/Ulyanovsk",
    "iso:country":"RU",
    "name:eng_x_preferred":[
        "Ponika"
    ],
    "name:nor_x_preferred":[
        "Ponika"
    ],
    "name:rus_x_preferred":[
        "\u041f\u043e\u043d\u0438\u043a\u0430"
    ],
    "name:und_x_variant":[
        "Panika",
        "\u041f\u043e\u043d\u0438\u043a\u0430",
        "Ponika"
    ],
    "wof:name":"Ponika",
    "wof:placetype":"locality"
},
  "geometry": {"coordinates":[47.15144,53.18962],"type":"Point"}
}