{
  "type": "Feature",
  "properties": {
    "gn:admin1_code":"29",
    "gn:asciiname":"Chernyshevo",
    "gn:country_code":"RU",
    "gn:dem":217,
    "gn:feature_class":"P",
    "gn:feature_code":"PPL",
    "gn:name":"Chernyshevo",
    "gn:population":0,
    "gn:timezone":"Asia/Novokuznetsk",
    "iso:country":"RU",
    "name:eng_x_preferred":[
        "Chernyshevo"
    ],
    "name:nor_x_preferred":[
        "Tsjernysjevo"
    ],
    "name:rus_x_preferred":[
        "\u0427\u0435\u0440\u043d\u044b\u0448\u0435\u0432\u043e"
    ],
    "name:und_x_variant":[
        "\u0427\u0435\u0440\u043d\u044b\u0448\u0435\u0432\u043e",
        "Chernyshevo"
    ],
    "wof:name":"Chernyshevo",
    "wof:placetype":"locality"
},
  "geometry": {"coordinates":[89.26167,55.95083],"type":"Point"}
}