{
  "type": "Feature",
  "properties": {
    "gn:admin1_code":"05",
    "gn:asciiname":"Kamennyy Klyuch",
    "gn:country_code":"RU",
    "gn:dem":270,
    "gn:feature_class":"P",
    "gn:feature_code":"PPL",
    "gn:name":"Kamennyy Klyuch",
    "gn:population":0,
    "gn:timezone":"Asia/Yakutsk",
    "iso:country":"RU",
    "name:rus_x_preferred":[
        "\u041a\u0430\u043c\u0435\u043d\u043d\u044b\u0439 \u041a\u043b\u044e\u0447"
    ],
    "wof:name":"Kamennyy Klyuch",
    "wof:placetype":"locality"
},
  "geometry": {"coordinates":[130.75,49.75],"type":"Point"}
}