{
  "type": "Feature",
  "properties": {
    "gn:admin1_code":"9.0",
    "gn:asciiname":"Berestovo",
    "gn:country_code":"RU",
    "gn:dem":100,
    "gn:feature_class":"P",
    "gn:feature_code":"PPL",
    "gn:name":"Berestovo",
    "gn:population":0,
    "gn:timezone":"Europe/Moscow",
    "iso:country":"RU",
    "name:nor_x_preferred":[
        "Berestovo"
    ],
    "name:rus_x_preferred":[
        "\u0411\u0435\u0440\u0435\u0441\u0442\u043e\u0432\u043e"
    ],
    "wof:name":"Berestovo",
    "wof:placetype":"locality"
},
  "geometry": {"coordinates":[39.09306,50.25222],"type":"Point"}
}