{
  "type": "Feature",
  "properties": {
    "gn:admin1_code":"84.0",
    "gn:asciiname":"Cherebayevo",
    "gn:country_code":"RU",
    "gn:dem":17,
    "gn:feature_class":"P",
    "gn:feature_code":"PPL",
    "gn:name":"Cherebayevo",
    "gn:population":0,
    "gn:timezone":"Europe/Volgograd",
    "iso:country":"RU",
    "name:eng_x_preferred":[
        "Cherebayevo"
    ],
    "name:nor_x_preferred":[
        "Tsjerobajevo"
    ],
    "name:rus_x_preferred":[
        "\u0427\u0435\u0440\u043e\u0431\u0430\u0435\u0432\u043e"
    ],
    "name:rus_x_variant":[
        "\u0427\u0435\u0440\u0435\u0431\u0430\u0435\u0432\u043e"
    ],
    "name:und_x_variant":[
        "Cherebava"
    ],
    "wof:name":"Cherebayevo",
    "wof:placetype":"locality"
},
  "geometry": {"coordinates":[45.91505,50.71988],"type":"Point"}
}