{
  "type": "Feature",
  "properties": {
    "gn:admin1_code":"65.0",
    "gn:asciiname":"Svetlyy Luch",
    "gn:country_code":"RU",
    "gn:dem":45,
    "gn:feature_class":"P",
    "gn:feature_code":"PPL",
    "gn:name":"Svetlyy Luch",
    "gn:population":0,
    "gn:timezone":"Europe/Samara",
    "iso:country":"RU",
    "name:rus_x_preferred":[
        "\u0421\u0432\u0435\u0442\u043b\u044b\u0439 \u041b\u0443\u0447"
    ],
    "wof:name":"Svetlyy Luch",
    "wof:placetype":"locality"
},
  "geometry": {"coordinates":[50.27353,53.69644],"type":"Point"}
}