{
  "type": "Feature",
  "properties": {
    "gn:admin1_code":"55",
    "gn:asciiname":"Sazan",
    "gn:country_code":"RU",
    "gn:dem":164,
    "gn:feature_class":"P",
    "gn:feature_code":"PPL",
    "gn:name":"Sazan",
    "gn:population":0,
    "gn:timezone":"Asia/Yekaterinburg",
    "iso:country":"RU",
    "name:eng_x_preferred":[
        "Sazan"
    ],
    "name:nor_x_preferred":[
        "Sazan"
    ],
    "name:rus_x_preferred":[
        "\u0421\u0430\u0437\u0430\u043d"
    ],
    "name:und_x_variant":[
        "Sazanskaya",
        "Sazenskaya"
    ],
    "wof:name":"Sazan",
    "wof:placetype":"locality"
},
  "geometry": {"coordinates":[56.06667,51.22068],"type":"Point"}
}