{
  "type": "Feature",
  "properties": {
    "gn:admin1_code":"21.0",
    "gn:asciiname":"Litovkino",
    "gn:country_code":"RU",
    "gn:dem":114,
    "gn:feature_class":"P",
    "gn:feature_code":"PPL",
    "gn:name":"Litovkino",
    "gn:population":0,
    "gn:timezone":"Europe/Moscow",
    "iso:country":"RU",
    "name:rus_x_preferred":[
        "\u041b\u0438\u0442\u043e\u0432\u043a\u0438\u043d\u043e"
    ],
    "name:und_x_variant":[
        "\u041b\u0438\u0442\u043e\u0432\u043a\u0438\u043d\u043e"
    ],
    "wof:name":"Litovkino",
    "wof:placetype":"locality"
},
  "geometry": {"coordinates":[42.25744,57.14791999999999],"type":"Point"}
}