{
  "type": "Feature",
  "properties": {
    "gn:admin1_code":"65.0",
    "gn:asciiname":"Batratskiye Vyselki",
    "gn:country_code":"RU",
    "gn:dem":74,
    "gn:feature_class":"P",
    "gn:feature_code":"PPL",
    "gn:name":"Batratskiye Vyselki",
    "gn:population":0,
    "gn:timezone":"Europe/Samara",
    "iso:country":"RU",
    "name:nor_x_preferred":[
        "Batratskije Vyselki"
    ],
    "name:rus_x_preferred":[
        "\u0411\u0430\u0442\u0440\u0430\u0442\u0441\u043a\u0438\u0435 \u0412\u044b\u0441\u0435\u043b\u043a\u0438"
    ],
    "wof:name":"Batratskiye Vyselki",
    "wof:placetype":"locality"
},
  "geometry": {"coordinates":[48.56361,53.17417],"type":"Point"}
}