{
  "type": "Feature",
  "properties": {
    "gn:admin1_code":"91",
    "gn:asciiname":"Mar'yasovo",
    "gn:country_code":"RU",
    "gn:dem":300,
    "gn:feature_class":"P",
    "gn:feature_code":"PPL",
    "gn:name":"Mar\u2019yasovo",
    "gn:population":0,
    "gn:timezone":"Asia/Krasnoyarsk",
    "iso:country":"RU",
    "name:eng_x_preferred":[
        "Mar'yasovo"
    ],
    "name:nor_x_preferred":[
        "Marjasovo"
    ],
    "name:rus_x_preferred":[
        "\u041c\u0430\u0440\u044c\u044f\u0441\u043e\u0432\u043e"
    ],
    "name:und_x_variant":[
        "Mar\u2019yasova",
        "Mar\u2019yasovo"
    ],
    "wof:name":"Mar'yasovo",
    "wof:placetype":"locality"
},
  "geometry": {"coordinates":[91.44861,55.3225],"type":"Point"}
}