{
  "type": "Feature",
  "properties": {
    "gn:admin1_code":"76",
    "gn:asciiname":"Krasenki",
    "gn:country_code":"RU",
    "gn:dem":227,
    "gn:feature_class":"P",
    "gn:feature_code":"PPL",
    "gn:name":"Krasenki",
    "gn:population":0,
    "gn:timezone":"Europe/Moscow",
    "iso:country":"RU",
    "name:rus_x_preferred":[
        "\u041a\u0440\u0430\u0441\u0435\u043d\u043a\u0438"
    ],
    "wof:name":"Krasenki",
    "wof:placetype":"locality"
},
  "geometry": {"coordinates":[36.78013,53.97144],"type":"Point"}
}