{
  "type": "Feature",
  "properties": {
    "gn:admin1_code":"8",
    "gn:asciiname":"Lapyshta",
    "gn:country_code":"RU",
    "gn:dem":519,
    "gn:feature_class":"P",
    "gn:feature_code":"PPL",
    "gn:name":"Lapyshta",
    "gn:population":0,
    "gn:timezone":"Asia/Yekaterinburg",
    "iso:country":"RU",
    "name:eng_x_preferred":[
        "Lapyshta"
    ],
    "name:nor_x_preferred":[
        "Lapysjta"
    ],
    "name:rus_x_preferred":[
        "\u041b\u0430\u043f\u044b\u0448\u0442\u0430"
    ],
    "wof:name":"Lapyshta",
    "wof:placetype":"locality"
},
  "geometry": {"coordinates":[57.7216,53.9871],"type":"Point"}
}