{
  "type": "Feature",
  "properties": {
    "gn:admin1_code":"23",
    "gn:asciiname":"Lugovoye",
    "gn:country_code":"RU",
    "gn:dem":15,
    "gn:feature_class":"P",
    "gn:feature_code":"PPL",
    "gn:name":"Lugovoye",
    "gn:population":0,
    "gn:timezone":"Europe/Kaliningrad",
    "iso:country":"RU",
    "name:rus_x_preferred":[
        "\u041b\u0443\u0433\u043e\u0432\u043e\u0435"
    ],
    "name:und_x_variant":[
        "Gutenfeld",
        "Lugovoye",
        "\u041b\u0443\u0433\u043e\u0432\u043e\u0435"
    ],
    "wof:name":"Lugovoye",
    "wof:placetype":"locality"
},
  "geometry": {"coordinates":[20.63492,54.65136],"type":"Point"}
}