{
  "type": "Feature",
  "properties": {
    "gn:admin1_code":"42.0",
    "gn:asciiname":"Gakkova",
    "gn:country_code":"RU",
    "gn:dem":6,
    "gn:feature_class":"P",
    "gn:feature_code":"PPL",
    "gn:name":"Gakkova",
    "gn:population":0,
    "gn:timezone":"Europe/Moscow",
    "iso:country":"RU",
    "name:fin_x_preferred":[
        "Hakaja"
    ],
    "name:rus_x_preferred":[
        "\u0413\u0430\u043a\u043a\u043e\u0432\u0430"
    ],
    "name:und_x_variant":[
        "Hakkovo",
        "Gakkovo",
        "Takkovo",
        "Gankova",
        "Gakkova"
    ],
    "wof:name":"Gakkova",
    "wof:placetype":"locality"
},
  "geometry": {"coordinates":[28.02799000000001,59.65626],"type":"Point"}
}