{
  "type": "Feature",
  "properties": {
    "gn:admin1_code":"57.0",
    "gn:asciiname":"Istambul",
    "gn:country_code":"RU",
    "gn:dem":219,
    "gn:feature_class":"P",
    "gn:feature_code":"PPL",
    "gn:name":"Istambul",
    "gn:population":0,
    "gn:timezone":"Europe/Moscow",
    "iso:country":"RU",
    "name:rus_x_preferred":[
        "\u0418\u0441\u0442\u0430\u043c\u0431\u0443\u043b"
    ],
    "wof:name":"Istambul",
    "wof:placetype":"locality"
},
  "geometry": {"coordinates":[44.8332,52.8557],"type":"Point"}
}