{
  "type": "Feature",
  "properties": {
    "gn:admin1_code":"6",
    "gn:asciiname":"Ol'seyeva",
    "gn:country_code":"RU",
    "gn:dem":156,
    "gn:feature_class":"P",
    "gn:feature_code":"PPL",
    "gn:name":"Ol\u2019seyeva",
    "gn:population":0,
    "gn:timezone":"Europe/Moscow",
    "iso:country":"RU",
    "name:rus_x_preferred":[
        "\u041e\u043b\u044c\u0441\u0435\u0435\u0432\u0430"
    ],
    "name:und_x_variant":[
        "Ol\u2019seyeva",
        "\u041e\u043b\u044c\u0441\u0435\u0435\u0432\u0430"
    ],
    "wof:name":"Ol'seyeva",
    "wof:placetype":"locality"
},
  "geometry": {"coordinates":[38.80207,61.64662],"type":"Point"}
}