{
  "type": "Feature",
  "properties": {
    "gn:admin1_code":"21",
    "gn:asciiname":"Pyal'tsevo",
    "gn:country_code":"RU",
    "gn:dem":149,
    "gn:feature_class":"P",
    "gn:feature_code":"PPL",
    "gn:name":"Pyal\u2019tsevo",
    "gn:population":0,
    "gn:timezone":"Europe/Moscow",
    "iso:country":"RU",
    "name:rus_x_preferred":[
        "\u041f\u044f\u043b\u044c\u0446\u0435\u0432\u043e"
    ],
    "name:und_x_variant":[
        "Pyal\u2019tsevo",
        "\u041f\u044f\u043b\u044c\u0446\u0435\u0432\u043e"
    ],
    "wof:name":"Pyal'tsevo",
    "wof:placetype":"locality"
},
  "geometry": {"coordinates":[41.03941,57.22438],"type":"Point"}
}