{
  "type": "Feature",
  "properties": {
    "gn:admin1_code":"77",
    "gn:asciiname":"Nogino",
    "gn:country_code":"RU",
    "gn:dem":136,
    "gn:feature_class":"P",
    "gn:feature_code":"PPL",
    "gn:name":"Nogino",
    "gn:population":0,
    "gn:timezone":"Europe/Moscow",
    "iso:country":"RU",
    "name:rus_x_preferred":[
        "\u041d\u043e\u0433\u0438\u043d\u043e"
    ],
    "name:und_x_variant":[
        "\u041d\u043e\u0433\u0438\u043d\u043e"
    ],
    "wof:name":"Nogino",
    "wof:placetype":"locality"
},
  "geometry": {"coordinates":[38.2455,57.0643],"type":"Point"}
}