{
  "type": "Feature",
  "properties": {
    "gn:admin1_code":"55",
    "gn:asciiname":"Tretiy Reshayushchiy",
    "gn:country_code":"RU",
    "gn:dem":186,
    "gn:feature_class":"P",
    "gn:feature_code":"PPL",
    "gn:name":"Tretiy Reshayushchiy",
    "gn:population":0,
    "gn:timezone":"Asia/Yekaterinburg",
    "iso:country":"RU",
    "wof:name":"Tretiy Reshayushchiy",
    "wof:placetype":"locality"
},
  "geometry": {"coordinates":[55.18333000000001,51.45],"type":"Point"}
}