{
  "type": "Feature",
  "properties": {
    "gn:admin1_code":"38",
    "gn:asciiname":"Tel'man",
    "gn:country_code":"RU",
    "gn:dem":190,
    "gn:feature_class":"P",
    "gn:feature_code":"PPL",
    "gn:name":"Tel\u2019man",
    "gn:population":0,
    "gn:timezone":"Europe/Moscow",
    "iso:country":"RU",
    "name:und_x_variant":[
        "Imeni Tel\u2019mana",
        "Tel\u2019man"
    ],
    "wof:name":"Tel'man",
    "wof:placetype":"locality"
},
  "geometry": {"coordinates":[40.84556,45.09417],"type":"Point"}
}