{
  "type": "Feature",
  "properties": {
    "gn:admin1_code":"40",
    "gn:asciiname":"Kazantseva",
    "gn:country_code":"RU",
    "gn:dem":121,
    "gn:feature_class":"P",
    "gn:feature_code":"PPL",
    "gn:name":"Kazantseva",
    "gn:population":0,
    "gn:timezone":"Asia/Yekaterinburg",
    "iso:country":"RU",
    "name:eng_x_preferred":[
        "Kazantseva"
    ],
    "name:nor_x_preferred":[
        "Kazantseva"
    ],
    "name:rus_x_preferred":[
        "\u041a\u0430\u0437\u0430\u043d\u0446\u0435\u0432\u0430"
    ],
    "name:und_x_variant":[
        "Kazantsevo",
        "\u041a\u0430\u0437\u0430\u043d\u0446\u0435\u0432\u0430",
        "Kazantseva"
    ],
    "wof:name":"Kazantseva",
    "wof:placetype":"locality"
},
  "geometry": {"coordinates":[62.5695,55.9357],"type":"Point"}
}