{
  "type": "Feature",
  "properties": {
    "gn:admin1_code":"64",
    "gn:asciiname":"Prostornaya",
    "gn:cc2":"RU",
    "gn:country_code":"RU",
    "gn:dem":14,
    "gn:feature_class":"P",
    "gn:feature_code":"PPL",
    "gn:name":"Prostornaya",
    "gn:population":0,
    "gn:timezone":"Asia/Sakhalin",
    "iso:country":"RU",
    "name:rus_x_preferred":[
        "\u041f\u0440\u043e\u0441\u0442\u043e\u0440\u043d\u0430\u044f"
    ],
    "name:und_x_variant":[
        "Minami-shokuminchi",
        "Prostornaya",
        "\u041f\u0440\u043e\u0441\u0442\u043e\u0440\u043d\u0430\u044f"
    ],
    "wof:name":"Prostornaya",
    "wof:placetype":"locality"
},
  "geometry": {"coordinates":[142.19999999999999,47.88333],"type":"Point"}
}