{
  "type": "Feature",
  "properties": {
    "gn:admin1_code":"6",
    "gn:asciiname":"Dorofeyevskaya",
    "gn:country_code":"RU",
    "gn:dem":68,
    "gn:feature_class":"P",
    "gn:feature_code":"PPL",
    "gn:name":"Dorofeyevskaya",
    "gn:population":0,
    "gn:timezone":"Europe/Moscow",
    "iso:country":"RU",
    "name:rus_x_preferred":[
        "\u0414\u043e\u0440\u043e\u0444\u0435\u0435\u0432c\u043a\u0430\u044f"
    ],
    "name:und_x_variant":[
        "\u0414\u043e\u0440\u043e\u0444\u0435\u0435\u0432c\u043a\u0430\u044f"
    ],
    "wof:name":"Dorofeyevskaya",
    "wof:placetype":"locality"
},
  "geometry": {"coordinates":[48.3692,61.8112],"type":"Point"}
}