{
  "type": "Feature",
  "properties": {
    "gn:admin1_code":"61",
    "gn:asciiname":"Izobil'nyy",
    "gn:country_code":"RU",
    "gn:dem":67,
    "gn:feature_class":"P",
    "gn:feature_code":"PPL",
    "gn:name":"Izobil\u2019nyy",
    "gn:population":0,
    "gn:timezone":"Europe/Moscow",
    "iso:country":"RU",
    "name:rus_x_preferred":[
        "\u0418\u0437\u043e\u0431\u0438\u043b\u044c\u043d\u044b\u0439"
    ],
    "name:und_x_variant":[
        "Izobil\u2019nyy"
    ],
    "wof:name":"Izobil'nyy",
    "wof:placetype":"locality"
},
  "geometry": {"coordinates":[40.55854,46.66261],"type":"Point"}
}