{
  "type": "Feature",
  "properties": {
    "gn:admin1_code":"52",
    "gn:asciiname":"Radom'ye",
    "gn:country_code":"RU",
    "gn:dem":143,
    "gn:feature_class":"P",
    "gn:feature_code":"PPL",
    "gn:name":"Radom\u2019ye",
    "gn:population":0,
    "gn:timezone":"Europe/Moscow",
    "iso:country":"RU",
    "name:rus_x_preferred":[
        "\u0420\u0430\u0434\u043e\u043c\u044c\u0435"
    ],
    "name:und_x_variant":[
        "Radom\u2019ye",
        "\u0420\u0430\u0434\u043e\u043c\u044c\u0435"
    ],
    "wof:name":"Radom'ye",
    "wof:placetype":"locality"
},
  "geometry": {"coordinates":[32.91383,58.71233],"type":"Point"}
}