{
  "type": "Feature",
  "properties": {
    "gn:admin1_code":"45.0",
    "gn:asciiname":"Bereznyaki",
    "gn:country_code":"RU",
    "gn:dem":93,
    "gn:feature_class":"P",
    "gn:feature_code":"PPL",
    "gn:name":"Bereznyaki",
    "gn:population":0,
    "gn:timezone":"Europe/Moscow",
    "iso:country":"RU",
    "name:nor_x_preferred":[
        "Berjoznjaki"
    ],
    "name:rus_x_preferred":[
        "\u0411\u0435\u0440\u0435\u0437\u043d\u044f\u043a\u0438"
    ],
    "wof:name":"Bereznyaki",
    "wof:placetype":"locality"
},
  "geometry": {"coordinates":[48.0025,56.69722],"type":"Point"}
}