{
  "type": "Feature",
  "properties": {
    "gn:admin1_code":"77.0",
    "gn:asciiname":"Dorokhovo",
    "gn:country_code":"RU",
    "gn:dem":167,
    "gn:feature_class":"P",
    "gn:feature_code":"PPL",
    "gn:name":"Dorokhovo",
    "gn:population":0,
    "gn:timezone":"Europe/Moscow",
    "iso:country":"RU",
    "name:nor_x_preferred":[
        "Dorokhovo"
    ],
    "name:rus_x_preferred":[
        "\u0414\u043e\u0440\u043e\u0445\u043e\u0432\u043e"
    ],
    "wof:name":"Dorokhovo",
    "wof:placetype":"locality"
},
  "geometry": {"coordinates":[35.07369,56.41988000000001],"type":"Point"}
}