{
  "type": "Feature",
  "properties": {
    "gn:country":"RU",
    "gn:fcode":"PPL",
    "gn:pop":16019,
    "iso:country":"RU",
    "name:ara_x_preferred":[
        "\u062c\u064a\u0631\u062f\u064a\u0641\u0643\u0627"
    ],
    "name:azb_x_preferred":[
        "\u0698\u0627\u0631\u062f\u0648\u06a9\u0627"
    ],
    "name:aze_x_preferred":[
        "Jerdyovka"
    ],
    "name:bel_x_preferred":[
        "\u0416\u044d\u0440\u0434\u0437\u0435\u045e\u043a\u0430"
    ],
    "name:bul_x_preferred":[
        "\u0416\u0435\u0440\u0434\u0435\u0432\u043a\u0430"
    ],
    "name:che_x_preferred":[
        "\u0416\u0435\u0440\u0434\u0435\u0432\u043a\u0430"
    ],
    "name:chi_x_preferred":[
        "\u70ed\u5c14\u6770\u592b\u5361"
    ],
    "name:chv_x_preferred":[
        "\u0416\u0435\u0440\u0434\u0435\u0432\u043a\u0430"
    ],
    "name:dut_x_preferred":[
        "Zjerdevka"
    ],
    "name:eng_x_preferred":[
        "Zherdevka"
    ],
    "name:epo_x_preferred":[
        "\u0134erdevka"
    ],
    "name:fre_x_preferred":[
        "Jerdevka"
    ],
    "name:ger_x_preferred":[
        "Scherdewka"
    ],
    "name:hsb_x_preferred":[
        "\u017derdewka"
    ],
    "name:ita_x_preferred":[
        "\u017derdevka"
    ],
    "name:jpn_x_preferred":[
        "\u30b8\u30a7\u30eb\u30c7\u30d5\u30ab"
    ],
    "name:ltz_x_preferred":[
        "Jerdewka"
    ],
    "name:nno_x_preferred":[
        "Zjerdevka"
    ],
    "name:nob_x_preferred":[
        "Zjerdevka"
    ],
    "name:nor_x_preferred":[
        "Zjerdevka"
    ],
    "name:per_x_preferred":[
        "\u0698\u0631\u062f\u0641\u06a9\u0627"
    ],
    "name:pol_x_preferred":[
        "\u017berdiewka"
    ],
    "name:rus_x_preferred":[
        "\u0416\u0435\u0440\u0434\u0435\u0432\u043a\u0430"
    ],
    "name:srp_x_preferred":[
        "\u0416\u0435\u0440\u0434\u0435\u0432\u043a\u0430"
    ],
    "name:tat_x_preferred":[
        "\u0416\u0435\u0440\u0434\u0435\u0432\u043a\u0430"
    ],
    "name:tgk_x_preferred":[
        "\u0416\u0435\u0440\u0434\u0435\u0432\u043a\u0430"
    ],
    "name:tgl_x_preferred":[
        "Zherdevka"
    ],
    "name:ukr_x_preferred":[
        "\u0416\u0435\u0440\u0434\u0454\u0432\u043a\u0430"
    ],
    "name:unk_x_variant":[
        "Chibisovka"
    ],
    "name:war_x_preferred":[
        "Zherdevka"
    ],
    "name:xal_x_preferred":[
        "\u0416\u0435\u0440\u0434\u0435\u0432\u043a\u0430 \u0431\u0430\u043b\u04bb\u0441\u043d"
    ],
    "qs:name":"Zherdevka",
    "qs:name_adm0":"Russia",
    "qs:name_adm1":"Tambov Oblast",
    "qs:photos_9r":0,
    "qs:photos_sr":0,
    "qs:placetype":"Town",
    "qs:pop_sr":"6",
    "wd:wordcount":50,
    "wof:name":"Zherdevka",
    "wof:placetype":"locality",
    "wof:population":16019
},
  "geometry": {"coordinates":[41.46056,51.84861],"type":"Point"}
}