{
  "type": "Feature",
  "properties": {
    "gn:admin1_code":"37",
    "gn:asciiname":"Shestidvorka",
    "gn:country_code":"RU",
    "gn:dem":122,
    "gn:feature_class":"P",
    "gn:feature_code":"PPL",
    "gn:name":"Shestidvorka",
    "gn:population":0,
    "gn:timezone":"Europe/Moscow",
    "iso:country":"RU",
    "name:rus_x_preferred":[
        "\u0428\u0435\u0441\u0442\u0438\u0434\u0432\u043e\u0440\u043a\u0430"
    ],
    "wof:name":"Shestidvorka",
    "wof:placetype":"locality"
},
  "geometry": {"coordinates":[46.5166,58.8155],"type":"Point"}
}