{
  "type": "Feature",
  "properties": {
    "gn:admin1_code":"28",
    "gn:asciiname":"Pebru",
    "gn:country_code":"RU",
    "gn:dem":14,
    "gn:feature_class":"P",
    "gn:feature_code":"PPL",
    "gn:name":"Pebru",
    "gn:population":0,
    "gn:timezone":"Europe/Moscow",
    "iso:country":"RU",
    "name:fin_x_preferred":[
        "Pebru"
    ],
    "name:rus_x_preferred":[
        "\u041f\u0435\u0431\u0440\u0443"
    ],
    "name:und_x_variant":[
        "\u041f\u0435\u0431\u0440\u0443"
    ],
    "wof:name":"Pebru",
    "wof:placetype":"locality"
},
  "geometry": {"coordinates":[31.92387,61.33255],"type":"Point"}
}