{
  "type": "Feature",
  "properties": {
    "gn:admin1_code":"37",
    "gn:asciiname":"Malaya Pas'ma",
    "gn:country_code":"RU",
    "gn:dem":173,
    "gn:feature_class":"P",
    "gn:feature_code":"PPL",
    "gn:name":"Malaya Pas\u2019ma",
    "gn:population":0,
    "gn:timezone":"Europe/Moscow",
    "iso:country":"RU",
    "name:rus_x_preferred":[
        "\u041c\u0430\u043b\u0430\u044f \u041f\u0430\u0441\u044c\u043c\u0430"
    ],
    "name:und_x_variant":[
        "Malaya Pas\u2019ma"
    ],
    "wof:name":"Malaya Pas'ma",
    "wof:placetype":"locality"
},
  "geometry": {"coordinates":[43.8452,58.663],"type":"Point"}
}