{
  "type": "Feature",
  "properties": {
    "gn:admin1_code":"77",
    "gn:asciiname":"Yermolino",
    "gn:country_code":"RU",
    "gn:dem":190,
    "gn:feature_class":"P",
    "gn:feature_code":"PPL",
    "gn:name":"Yermolino",
    "gn:population":0,
    "gn:timezone":"Europe/Moscow",
    "iso:country":"RU",
    "name:rus_x_preferred":[
        "\u0415\u0440\u043c\u043e\u043b\u0438\u043d\u043e"
    ],
    "name:und_x_variant":[
        "\u0415\u0440\u043c\u043e\u043b\u0438\u043d\u043e"
    ],
    "wof:name":"Yermolino",
    "wof:placetype":"locality"
},
  "geometry": {"coordinates":[35.0922,58.1852],"type":"Point"}
}