{
  "type": "Feature",
  "properties": {
    "gn:admin1_code":"31",
    "gn:asciiname":"Dmitriyevka",
    "gn:cc2":"RU",
    "gn:country_code":"RU",
    "gn:dem":294,
    "gn:feature_class":"P",
    "gn:feature_code":"PPL",
    "gn:name":"Dmitriyevka",
    "gn:population":0,
    "gn:timezone":"Asia/Krasnoyarsk",
    "iso:country":"RU",
    "name:eng_x_preferred":[
        "Dmitriyevka"
    ],
    "name:nor_x_preferred":[
        "Dmitrijevka"
    ],
    "name:rus_x_preferred":[
        "\u0414\u043c\u0438\u0442\u0440\u0438\u0435\u0432\u043a\u0430"
    ],
    "name:und_x_variant":[
        "Dmitrievka",
        "Dmitriyevskoye",
        "\u0414\u043c\u0438\u0442\u0440\u0438\u0435\u0432\u043a\u0430",
        "Dmitriyevka"
    ],
    "wof:name":"Dmitriyevka",
    "wof:placetype":"locality"
},
  "geometry": {"coordinates":[91.40722,53.26833000000001],"type":"Point"}
}