{
  "type": "Feature",
  "properties": {
    "gn:admin1_code":"6",
    "gn:asciiname":"Vozhgora",
    "gn:country_code":"RU",
    "gn:dem":94,
    "gn:feature_class":"P",
    "gn:feature_code":"PPL",
    "gn:name":"Vozhgora",
    "gn:population":0,
    "gn:timezone":"Europe/Moscow",
    "iso:country":"RU",
    "name:eng_x_preferred":[
        "Vozhgora"
    ],
    "name:nor_x_preferred":[
        "Vozjgora"
    ],
    "name:rus_x_preferred":[
        "\u0412\u043e\u0436\u0433\u043e\u0440\u0430"
    ],
    "name:und_x_variant":[
        "Vazhgora",
        "Vozhgory",
        "Vazhgort",
        "Vazhgory",
        "Vazhgorskoye",
        "Vozhgora"
    ],
    "wof:name":"Vozhgora",
    "wof:placetype":"locality"
},
  "geometry": {"coordinates":[48.45578,64.53579000000001],"type":"Point"}
}