{
  "type": "Feature",
  "properties": {
    "gn:admin1_code":"17.0",
    "gn:asciiname":"Kakamakhi",
    "gn:country_code":"RU",
    "gn:dem":783,
    "gn:feature_class":"P",
    "gn:feature_code":"PPL",
    "gn:name":"Kakamakhi",
    "gn:population":0,
    "gn:timezone":"Europe/Moscow",
    "iso:country":"RU",
    "name:rus_x_preferred":[
        "\u041a\u0430\u043a\u0430\u043c\u0430\u0445\u0438"
    ],
    "name:und_x_variant":[
        "Guvshan-Bash",
        "Kakamakhi",
        "\u041a\u0430\u043a\u0430\u043c\u0430\u0445\u0438"
    ],
    "wof:name":"Kakamakhi",
    "wof:placetype":"locality"
},
  "geometry": {"coordinates":[47.43554,42.63212],"type":"Point"}
}