{
  "type": "Feature",
  "properties": {
    "gn:admin1_code":"21",
    "gn:asciiname":"Starilovo",
    "gn:country_code":"RU",
    "gn:dem":108,
    "gn:feature_class":"P",
    "gn:feature_code":"PPL",
    "gn:name":"Starilovo",
    "gn:population":0,
    "gn:timezone":"Europe/Moscow",
    "iso:country":"RU",
    "name:eng_x_preferred":[
        "Starilovo"
    ],
    "name:nor_x_preferred":[
        "Starilovo"
    ],
    "name:rus_x_preferred":[
        "\u0421\u0442\u0430\u0440\u0438\u043b\u043e\u0432\u043e"
    ],
    "name:und_x_variant":[
        "Storilovo",
        "\u0421\u0442\u0430\u0440\u0438\u043b\u043e\u0432\u043e",
        "Starilovo"
    ],
    "wof:name":"Starilovo",
    "wof:placetype":"locality"
},
  "geometry": {"coordinates":[42.49587,56.75812],"type":"Point"}
}