{
  "type": "Feature",
  "properties": {
    "gn:admin1_code":"41.0",
    "gn:asciiname":"Dmitriyevskaya Koloniya",
    "gn:country_code":"RU",
    "gn:dem":180,
    "gn:feature_class":"P",
    "gn:feature_code":"PPL",
    "gn:name":"Dmitriyevskaya Koloniya",
    "gn:population":0,
    "gn:timezone":"Europe/Moscow",
    "iso:country":"RU",
    "name:rus_x_preferred":[
        "\u0414\u043c\u0438\u0442\u0440\u0438\u0435\u0432\u0441\u043a\u0430\u044f \u041a\u043e\u043b\u043e\u043d\u0438\u044f"
    ],
    "name:und_x_variant":[
        "Dmitriyevskaya Koloiya",
        "Dmitriyevskaya Koloniya"
    ],
    "wof:name":"Dmitriyevskaya Koloniya",
    "wof:placetype":"locality"
},
  "geometry": {"coordinates":[35.1369,52.038],"type":"Point"}
}