{
  "type": "Feature",
  "properties": {
    "gn:admin1_code":"85",
    "gn:asciiname":"Goryaynovo",
    "gn:country_code":"RU",
    "gn:dem":159,
    "gn:feature_class":"P",
    "gn:feature_code":"PPL",
    "gn:name":"Goryaynovo",
    "gn:population":0,
    "gn:timezone":"Europe/Moscow",
    "iso:country":"RU",
    "name:rus_x_preferred":[
        "\u0413\u043e\u0440\u044f\u0439\u043d\u043e\u0432\u043e"
    ],
    "wof:name":"Goryaynovo",
    "wof:placetype":"locality"
},
  "geometry": {"coordinates":[38.3833,59.9073],"type":"Point"}
}