{
  "type": "Feature",
  "properties": {
    "gn:admin1_code":"8",
    "gn:asciiname":"Mutayevo",
    "gn:country_code":"RU",
    "gn:dem":206,
    "gn:feature_class":"P",
    "gn:feature_code":"PPL",
    "gn:name":"Mutayevo",
    "gn:population":0,
    "gn:timezone":"Asia/Yekaterinburg",
    "iso:country":"RU",
    "name:rus_x_preferred":[
        "\u041c\u0443\u0442\u0430\u0435\u0432\u043e"
    ],
    "name:und_x_variant":[
        "Mutayeva",
        "Mutayevo"
    ],
    "wof:name":"Mutayevo",
    "wof:placetype":"locality"
},
  "geometry": {"coordinates":[56.37815,52.96188000000001],"type":"Point"}
}