{
  "type": "Feature",
  "properties": {
    "gn:admin1_code":"62",
    "gn:asciiname":"Verkhniy Ostrov",
    "gn:cc2":"RU",
    "gn:country_code":"RU",
    "gn:dem":164,
    "gn:feature_class":"P",
    "gn:feature_code":"PPL",
    "gn:name":"Verkhniy Ostrov",
    "gn:population":0,
    "gn:timezone":"Europe/Moscow",
    "iso:country":"RU",
    "name:und_x_variant":[
        "Ostrov",
        "Verkhniy Ostrov"
    ],
    "wof:name":"Verkhniy Ostrov",
    "wof:placetype":"locality"
},
  "geometry": {"coordinates":[41.34694,53.6425],"type":"Point"}
}