{
  "type": "Feature",
  "properties": {
    "gn:admin1_code":"28",
    "gn:asciiname":"Parola",
    "gn:country_code":"RU",
    "gn:dem":1,
    "gn:feature_class":"P",
    "gn:feature_code":"PPL",
    "gn:name":"Parola",
    "gn:population":0,
    "gn:timezone":"Europe/Moscow",
    "iso:country":"RU",
    "name:fin_x_preferred":[
        "Parola"
    ],
    "name:rus_x_preferred":[
        "\u041f\u0430\u0440\u043e\u043b\u0430"
    ],
    "name:und_x_variant":[
        "\u041f\u0430\u0440\u043e\u043b\u0430"
    ],
    "wof:name":"Parola",
    "wof:placetype":"locality"
},
  "geometry": {"coordinates":[30.80669,61.68572],"type":"Point"}
}