{
  "type": "Feature",
  "properties": {
    "gn:admin1_code":"60",
    "gn:asciiname":"Pavlyuchki",
    "gn:country_code":"RU",
    "gn:dem":158,
    "gn:feature_class":"P",
    "gn:feature_code":"PPL",
    "gn:name":"Pavlyuchki",
    "gn:population":0,
    "gn:timezone":"Europe/Moscow",
    "iso:country":"RU",
    "name:rus_x_preferred":[
        "\u041f\u0430\u0432\u043b\u044e\u0447\u043a\u0438"
    ],
    "wof:name":"Pavlyuchki",
    "wof:placetype":"locality"
},
  "geometry": {"coordinates":[29.8689,56.0437],"type":"Point"}
}