{
  "type": "Feature",
  "properties": {
    "gn:admin1_code":"91",
    "gn:asciiname":"Preobrazhenka",
    "gn:country_code":"RU",
    "gn:dem":221,
    "gn:feature_class":"P",
    "gn:feature_code":"PPL",
    "gn:name":"Preobrazhenka",
    "gn:population":0,
    "gn:timezone":"Asia/Krasnoyarsk",
    "iso:country":"RU",
    "name:bak_x_preferred":[
        "\u041f\u0440\u0435\u043e\u0431\u0440\u0430\u0436\u0435\u043d\u043a\u0430"
    ],
    "name:che_x_preferred":[
        "\u041f\u0440\u0435\u043e\u0431\u0440\u0430\u0436\u0435\u043d\u043a\u0430"
    ],
    "name:hye_x_preferred":[
        "\u054a\u0580\u0565\u0578\u0562\u0580\u0561\u056a\u0565\u0576\u056f\u0561"
    ],
    "name:kaz_x_preferred":[
        "\u041f\u0440\u0435\u043e\u0431\u0440\u0430\u0436\u0435\u043d\u043a\u0430"
    ],
    "name:kir_x_preferred":[
        "\u041f\u0440\u0435\u043e\u0431\u0440\u0430\u0436\u0435\u043d\u043a\u0430"
    ],
    "name:rus_x_preferred":[
        "\u041f\u0440\u0435\u043e\u0431\u0440\u0430\u0436\u0435\u043d\u043a\u0430"
    ],
    "name:tat_x_preferred":[
        "\u041f\u0440\u0435\u043e\u0431\u0440\u0430\u0436\u0435\u043d\u043a\u0430"
    ],
    "name:ukr_x_preferred":[
        "\u041f\u0440\u0435\u043e\u0431\u0440\u0430\u0436\u0435\u043d\u043a\u0430"
    ],
    "wof:name":"Preobrazhenka",
    "wof:placetype":"locality"
},
  "geometry": {"coordinates":[95.62139000000001,56.67471999999999],"type":"Point"}
}