{
  "type": "Feature",
  "properties": {
    "gn:admin1_code":"6.0",
    "gn:asciiname":"Cherevkovo",
    "gn:country_code":"RU",
    "gn:dem":48,
    "gn:feature_class":"P",
    "gn:feature_code":"PPL",
    "gn:name":"Cherevkovo",
    "gn:population":0,
    "gn:timezone":"Europe/Moscow",
    "iso:country":"RU",
    "name:eng_x_preferred":[
        "Cherevkovo"
    ],
    "name:nor_x_preferred":[
        "Tsjerevkovo"
    ],
    "name:rus_x_preferred":[
        "\u0427\u0435\u0440\u0435\u0432\u043a\u043e\u0432\u043e"
    ],
    "wof:name":"Cherevkovo",
    "wof:placetype":"locality"
},
  "geometry": {"coordinates":[45.26609000000001,61.78321],"type":"Point"}
}