{
  "type": "Feature",
  "properties": {
    "gn:admin1_code":"4",
    "gn:asciiname":"Demidovka",
    "gn:cc2":"RU",
    "gn:country_code":"RU",
    "gn:dem":220,
    "gn:feature_class":"P",
    "gn:feature_code":"PPL",
    "gn:name":"Demidovka",
    "gn:population":0,
    "gn:timezone":"Asia/Barnaul",
    "iso:country":"RU",
    "name:rus_x_preferred":[
        "\u0414\u0435\u043c\u0438\u0434\u043e\u0432\u043a\u0430"
    ],
    "name:und_x_variant":[
        "Demidovskiy",
        "Demidovka",
        "\u0414\u0435\u043c\u0438\u0434\u043e\u0432\u043a\u0430"
    ],
    "wof:name":"Demidovka",
    "wof:placetype":"locality"
},
  "geometry": {"coordinates":[79.91667,53.41667],"type":"Point"}
}