{
  "type": "Feature",
  "properties": {
    "gn:admin1_code":"93",
    "gn:asciiname":"Dayakon",
    "gn:country_code":"RU",
    "gn:dem":642,
    "gn:feature_class":"P",
    "gn:feature_code":"PPL",
    "gn:name":"Dayakon",
    "gn:population":0,
    "gn:timezone":"Asia/Chita",
    "iso:country":"RU",
    "name:eng_x_preferred":[
        "Dayakon"
    ],
    "name:nor_x_preferred":[
        "Dajakon"
    ],
    "name:rus_x_preferred":[
        "\u0414\u0430\u044f\u043a\u043e\u043d"
    ],
    "name:und_x_variant":[
        "Pos\u00eblok Dayakanskiy",
        "Dayakan"
    ],
    "wof:name":"Dayakon",
    "wof:placetype":"locality"
},
  "geometry": {"coordinates":[117.54465999999999,51.82445],"type":"Point"}
}