{
  "type": "Feature",
  "properties": {
    "gn:admin1_code":"56",
    "gn:asciiname":"Koz'ma-Dem'yanovskoye",
    "gn:country_code":"RU",
    "gn:dem":207,
    "gn:feature_class":"P",
    "gn:feature_code":"PPL",
    "gn:name":"Koz\u2019ma-Dem\u2019yanovskoye",
    "gn:population":0,
    "gn:timezone":"Europe/Moscow",
    "iso:country":"RU",
    "name:rus_x_preferred":[
        "\u041a\u043e\u0437\u044c\u043c\u0430-\u0414\u0435\u043c\u044c\u044f\u043d\u043e\u0432\u0441\u043a\u043e\u0435"
    ],
    "name:und_x_variant":[
        "Kuz\u2019modem\u2019yanskoye",
        "Koz\u2019ma-Dem\u2019yanovskoye",
        "\u041a\u043e\u0437\u044c\u043c\u0430-\u0414\u0435\u043c\u044c\u044f\u043d\u043e\u0432\u0441\u043a\u043e\u0435"
    ],
    "wof:name":"Koz'ma-Dem'yanovskoye",
    "wof:placetype":"locality"
},
  "geometry": {"coordinates":[37.62721,52.01528],"type":"Point"}
}