{
  "type": "Feature",
  "properties": {
    "gn:admin1_code":"45.0",
    "gn:asciiname":"Chashkayal",
    "gn:country_code":"RU",
    "gn:dem":238,
    "gn:feature_class":"P",
    "gn:feature_code":"PPL",
    "gn:name":"Chashkayal",
    "gn:population":0,
    "gn:timezone":"Europe/Moscow",
    "iso:country":"RU",
    "name:rus_x_preferred":[
        "\u0427\u0430\u0448\u043a\u0430\u044f\u043b"
    ],
    "name:und_x_variant":[
        "Bol\u2019shoy Chashkoyal",
        "Chashkoyal",
        "Chashkayal",
        "\u0427\u0430\u0448\u043a\u0430\u044f\u043b"
    ],
    "wof:name":"Chashkayal",
    "wof:placetype":"locality"
},
  "geometry": {"coordinates":[48.98194,56.88417],"type":"Point"}
}