{
  "type": "Feature",
  "properties": {
    "gn:admin1_code":"13",
    "gn:asciiname":"Burova",
    "gn:country_code":"RU",
    "gn:dem":409,
    "gn:feature_class":"P",
    "gn:feature_code":"PPL",
    "gn:name":"Burova",
    "gn:population":0,
    "gn:timezone":"Asia/Yekaterinburg",
    "iso:country":"RU",
    "name:rus_x_preferred":[
        "\u0411\u0443\u0440\u043e\u0432\u0430"
    ],
    "name:und_x_variant":[
        "\u0411\u0443\u0440\u043e\u0432\u0430"
    ],
    "wof:name":"Burova",
    "wof:placetype":"locality"
},
  "geometry": {"coordinates":[60.03333000000001,54.73333],"type":"Point"}
}