{
  "type": "Feature",
  "properties": {
    "gn:admin1_code":"20",
    "gn:asciiname":"Tayshetka",
    "gn:country_code":"RU",
    "gn:dem":292,
    "gn:feature_class":"P",
    "gn:feature_code":"PPL",
    "gn:name":"Tayshetka",
    "gn:population":0,
    "gn:timezone":"Asia/Irkutsk",
    "iso:country":"RU",
    "name:rus_x_preferred":[
        "\u0422\u0430\u0439\u0448\u0435\u0442\u043a\u0430"
    ],
    "wof:name":"Tayshetka",
    "wof:placetype":"locality"
},
  "geometry": {"coordinates":[97.9562,55.9611],"type":"Point"}
}