{
  "type": "Feature",
  "properties": {
    "gn:admin1_code":"78",
    "gn:asciiname":"Gerasimovka",
    "gn:country_code":"RU",
    "gn:dem":77,
    "gn:feature_class":"P",
    "gn:feature_code":"PPL",
    "gn:name":"Gerasimovka",
    "gn:population":0,
    "gn:timezone":"Asia/Yekaterinburg",
    "iso:country":"RU",
    "name:eng_x_preferred":[
        "Gerasimovka"
    ],
    "name:nor_x_preferred":[
        "Gerasimovka"
    ],
    "name:rus_x_preferred":[
        "\u0413\u0435\u0440\u0430\u0441\u0438\u043c\u043e\u0432\u043a\u0430"
    ],
    "wof:name":"Gerasimovka",
    "wof:placetype":"locality"
},
  "geometry": {"coordinates":[71.9093,58.597],"type":"Point"}
}