{
  "type": "Feature",
  "properties": {
    "gn:admin1_code":"10",
    "gn:asciiname":"Tureyka",
    "gn:country_code":"RU",
    "gn:dem":183,
    "gn:feature_class":"P",
    "gn:feature_code":"PPL",
    "gn:name":"Tureyka",
    "gn:population":0,
    "gn:timezone":"Europe/Moscow",
    "iso:country":"RU",
    "name:rus_x_preferred":[
        "\u0422\u0443\u0440\u0435\u0439\u043a\u0430"
    ],
    "wof:name":"Tureyka",
    "wof:placetype":"locality"
},
  "geometry": {"coordinates":[33.44235,53.13741],"type":"Point"}
}