{
  "type": "Feature",
  "properties": {
    "gn:admin1_code":"59",
    "gn:asciiname":"Druzhba",
    "gn:country_code":"RU",
    "gn:dem":149,
    "gn:feature_class":"P",
    "gn:feature_code":"PPL",
    "gn:name":"Druzhba",
    "gn:population":54,
    "gn:timezone":"Asia/Vladivostok",
    "iso:country":"RU",
    "name:bel_x_preferred":[
        "\u0414\u0440\u0443\u0436\u0431\u0430"
    ],
    "name:bul_x_preferred":[
        "\u0414\u0440\u0443\u0436\u0431\u0430"
    ],
    "name:ceb_x_preferred":[
        "Druzhba"
    ],
    "name:ces_x_preferred":[
        "Dru\u017eba"
    ],
    "name:deu_x_preferred":[
        "Druschba"
    ],
    "name:est_x_preferred":[
        "Dru\u017eba"
    ],
    "name:fra_x_preferred":[
        "Droujba"
    ],
    "name:hye_x_preferred":[
        "\u0534\u0580\u0578\u0582\u056a\u0562\u0561"
    ],
    "name:ita_x_preferred":[
        "Druzhba"
    ],
    "name:kaz_x_preferred":[
        "\u0414\u0440\u0443\u0436\u0431\u0430"
    ],
    "name:rus_x_preferred":[
        "\u0414\u0440\u0443\u0436\u0431\u0430"
    ],
    "name:slk_x_preferred":[
        "Dru\u017eba"
    ],
    "name:spa_x_preferred":[
        "Druzhba"
    ],
    "name:swe_x_preferred":[
        "Druzhba"
    ],
    "name:tat_x_preferred":[
        "\u0414\u0440\u0443\u0436\u0431\u0430"
    ],
    "name:ukr_x_preferred":[
        "\u0414\u0440\u0443\u0436\u0431\u0430"
    ],
    "name:und_x_variant":[
        "\u0414\u0440\u0443\u0436\u0431\u0430"
    ],
    "name:zho_x_preferred":[
        "\u5fb7\u9b6f\u65e5\u5df4"
    ],
    "wof:name":"Druzhba",
    "wof:placetype":"locality",
    "wof:population":54
},
  "geometry": {"coordinates":[131.64251999999999,44.28999],"type":"Point"}
}