{
  "type": "Feature",
  "properties": {
    "gn:admin1_code":"71",
    "gn:asciiname":"Neloba",
    "gn:country_code":"RU",
    "gn:dem":186,
    "gn:feature_class":"P",
    "gn:feature_code":"PPL",
    "gn:name":"Neloba",
    "gn:population":0,
    "gn:timezone":"Asia/Yekaterinburg",
    "iso:country":"RU",
    "name:eng_x_preferred":[
        "Neloba"
    ],
    "name:nor_x_preferred":[
        "Neloba"
    ],
    "name:rus_x_preferred":[
        "\u041d\u0435\u043b\u043e\u0431\u0430"
    ],
    "name:und_x_variant":[
        "\u041d\u0435\u043b\u043e\u0431\u0430",
        "Neloba"
    ],
    "wof:name":"Neloba",
    "wof:placetype":"locality"
},
  "geometry": {"coordinates":[60.72119,58.00718000000001],"type":"Point"}
}