{
  "type": "Feature",
  "properties": {
    "gn:admin1_code":"71.0",
    "gn:asciiname":"Korosteleva",
    "gn:country_code":"RU",
    "gn:dem":64,
    "gn:feature_class":"P",
    "gn:feature_code":"PPL",
    "gn:name":"Korostel\u00ebva",
    "gn:population":0,
    "gn:timezone":"Asia/Yekaterinburg",
    "iso:country":"RU",
    "name:rus_x_preferred":[
        "\u041a\u043e\u0440\u043e\u0441\u0442\u0435\u043b\u0451\u0432\u0430"
    ],
    "name:und_x_variant":[
        "Korostel\u00ebva"
    ],
    "wof:name":"Korosteleva",
    "wof:placetype":"locality"
},
  "geometry": {"coordinates":[63.37347,57.60222],"type":"Point"}
}