{
  "type": "Feature",
  "properties": {
    "gn:admin1_code":"69",
    "gn:asciiname":"Kozly",
    "gn:country_code":"RU",
    "gn:dem":166,
    "gn:feature_class":"P",
    "gn:feature_code":"PPL",
    "gn:name":"Kozly",
    "gn:population":0,
    "gn:timezone":"Europe/Moscow",
    "iso:country":"RU",
    "name:rus_x_preferred":[
        "\u041a\u043e\u0437\u043b\u044b"
    ],
    "name:und_x_variant":[
        "Provalennoye",
        "Kozly",
        "\u041a\u043e\u0437\u043b\u044b"
    ],
    "wof:name":"Kozly",
    "wof:placetype":"locality"
},
  "geometry": {"coordinates":[31.21831,54.67622],"type":"Point"}
}