{
  "type": "Feature",
  "properties": {
    "gn:admin1_code":"47",
    "gn:asciiname":"Novomar'inka",
    "gn:country_code":"RU",
    "gn:dem":137,
    "gn:feature_class":"P",
    "gn:feature_code":"PPL",
    "gn:name":"Novomar\u2019inka",
    "gn:population":0,
    "gn:timezone":"Europe/Moscow",
    "iso:country":"RU",
    "name:rus_x_preferred":[
        "\u041d\u043e\u0432\u043e\u043c\u0430\u0440\u044c\u0438\u043d\u043a\u0430"
    ],
    "name:und_x_variant":[
        "Novomar\u2019inka"
    ],
    "wof:name":"Novomar'inka",
    "wof:placetype":"locality"
},
  "geometry": {"coordinates":[38.38235,55.32261],"type":"Point"}
}