{
  "type": "Feature",
  "properties": {
    "gn:admin1_code":"81.0",
    "gn:asciiname":"Astradamovka",
    "gn:country_code":"RU",
    "gn:dem":106,
    "gn:feature_class":"P",
    "gn:feature_code":"PPL",
    "gn:name":"Astradamovka",
    "gn:population":0,
    "gn:timezone":"Europe/Ulyanovsk",
    "iso:country":"RU",
    "name:eng_x_preferred":[
        "Astradamovka"
    ],
    "name:nor_x_preferred":[
        "Astradamovka"
    ],
    "name:rus_x_preferred":[
        "\u0410\u0441\u0442\u0440\u0430\u0434\u0430\u043c\u043e\u0432\u043a\u0430"
    ],
    "wof:name":"Astradamovka",
    "wof:placetype":"locality"
},
  "geometry": {"coordinates":[47.1458,54.5468],"type":"Point"}
}