{
  "type": "Feature",
  "properties": {
    "gn:admin1_code":"77",
    "gn:asciiname":"Bryukhanovo",
    "gn:country_code":"RU",
    "gn:dem":267,
    "gn:feature_class":"P",
    "gn:feature_code":"PPL",
    "gn:name":"Bryukhanovo",
    "gn:population":0,
    "gn:timezone":"Europe/Moscow",
    "iso:country":"RU",
    "name:rus_x_preferred":[
        "\u0411\u0440\u044e\u0445\u0430\u043d\u043e\u0432\u043e"
    ],
    "wof:name":"Bryukhanovo",
    "wof:placetype":"locality"
},
  "geometry": {"coordinates":[33.6774,56.38983],"type":"Point"}
}