{
  "type": "Feature",
  "properties": {
    "gn:admin1_code":"70",
    "gn:asciiname":"Tumanskiy",
    "gn:country_code":"RU",
    "gn:dem":498,
    "gn:feature_class":"P",
    "gn:feature_code":"PPL",
    "gn:name":"Tumanskiy",
    "gn:population":0,
    "gn:timezone":"Europe/Moscow",
    "iso:country":"RU",
    "name:rus_x_preferred":[
        "\u0422\u0443\u043c\u0430\u043d\u0441\u043a\u0438\u0439"
    ],
    "wof:name":"Tumanskiy",
    "wof:placetype":"locality"
},
  "geometry": {"coordinates":[42.7906,44.1993],"type":"Point"}
}