{
  "type": "Feature",
  "properties": {
    "gn:admin1_code":"43",
    "gn:asciiname":"Kordyuki",
    "gn:country_code":"RU",
    "gn:dem":198,
    "gn:feature_class":"P",
    "gn:feature_code":"PPL",
    "gn:name":"Kordyuki",
    "gn:population":0,
    "gn:timezone":"Europe/Moscow",
    "iso:country":"RU",
    "name:rus_x_preferred":[
        "\u041a\u043e\u0440\u0434\u044e\u043a\u0438"
    ],
    "name:und_x_variant":[
        "\u041a\u043e\u0440\u0434\u044e\u043a\u0438"
    ],
    "wof:name":"Kordyuki",
    "wof:placetype":"locality"
},
  "geometry": {"coordinates":[39.59232,53.38139],"type":"Point"}
}