{
  "type": "Feature",
  "properties": {
    "gn:admin1_code":"16",
    "gn:asciiname":"Novoye Toyderyakovo",
    "gn:country_code":"RU",
    "gn:dem":94,
    "gn:feature_class":"P",
    "gn:feature_code":"PPL",
    "gn:name":"Novoye Toyderyakovo",
    "gn:population":0,
    "gn:timezone":"Europe/Moscow",
    "iso:country":"RU",
    "name:rus_x_preferred":[
        "\u041d\u043e\u0432\u043e\u0435 \u0422\u043e\u0439\u0434\u0435\u0440\u044f\u043a\u043e\u0432\u043e"
    ],
    "wof:name":"Novoye Toyderyakovo",
    "wof:placetype":"locality"
},
  "geometry": {"coordinates":[47.9663,55.1577],"type":"Point"}
}