{
  "type": "Feature",
  "properties": {
    "gn:admin1_code":"83",
    "gn:asciiname":"Ignat'yevo",
    "gn:country_code":"RU",
    "gn:dem":140,
    "gn:feature_class":"P",
    "gn:feature_code":"PPL",
    "gn:name":"Ignat\u2019yevo",
    "gn:population":0,
    "gn:timezone":"Europe/Moscow",
    "iso:country":"RU",
    "name:rus_x_preferred":[
        "\u0418\u0433\u043d\u0430\u0442\u044c\u0435\u0432\u043e"
    ],
    "name:und_x_variant":[
        "Ignat\u2019yevo",
        "\u0418\u0433\u043d\u0430\u0442\u044c\u0435\u0432\u043e"
    ],
    "wof:name":"Ignat'yevo",
    "wof:placetype":"locality"
},
  "geometry": {"coordinates":[41.2756,55.8401],"type":"Point"}
}