{
  "type": "Feature",
  "properties": {
    "gn:admin1_code":"80",
    "gn:asciiname":"Kur'ya",
    "gn:country_code":"RU",
    "gn:dem":168,
    "gn:feature_class":"P",
    "gn:feature_code":"PPL",
    "gn:name":"Kur\u2019ya",
    "gn:population":0,
    "gn:timezone":"Europe/Samara",
    "iso:country":"RU",
    "name:eng_x_preferred":[
        "Kur'ya"
    ],
    "name:nor_x_preferred":[
        "Kurja"
    ],
    "name:rus_x_preferred":[
        "\u041a\u0443\u0440\u044c\u044f"
    ],
    "name:und_x_variant":[
        "\u041a\u0443\u0440\u044c\u044f",
        "Kur\u2019ya"
    ],
    "wof:name":"Kur'ya",
    "wof:placetype":"locality"
},
  "geometry": {"coordinates":[52.0702,57.7097],"type":"Point"}
}