{
  "type": "Feature",
  "properties": {
    "gn:admin1_code":"63",
    "gn:asciiname":"Keptin",
    "gn:country_code":"RU",
    "gn:dem":275,
    "gn:feature_class":"P",
    "gn:feature_code":"PPL",
    "gn:name":"Keptin",
    "gn:population":0,
    "gn:timezone":"Asia/Yakutsk",
    "iso:country":"RU",
    "name:eng_x_preferred":[
        "Keptin"
    ],
    "name:nor_x_preferred":[
        "Keptin"
    ],
    "name:rus_x_preferred":[
        "\u041a\u0435\u043f\u0442\u0438\u043d"
    ],
    "name:und_x_variant":[
        "Kettin",
        "Kentin",
        "\u041a\u0435\u043f\u0442\u0438\u043d",
        "Keptin"
    ],
    "wof:name":"Keptin",
    "wof:placetype":"locality"
},
  "geometry": {"coordinates":[124.45032,62.3408],"type":"Point"}
}