{
  "type": "Feature",
  "properties": {
    "gn:admin1_code":"77",
    "gn:asciiname":"Matino",
    "gn:country_code":"RU",
    "gn:dem":143,
    "gn:feature_class":"P",
    "gn:feature_code":"PPL",
    "gn:name":"Matino",
    "gn:population":0,
    "gn:timezone":"Europe/Moscow",
    "iso:country":"RU",
    "name:ara_x_preferred":[
        "\u0645\u0627\u062a\u064a\u0646\u0648"
    ],
    "name:azb_x_preferred":[
        "\u0645\u0627\u062a\u06cc\u0646\u0648"
    ],
    "name:bel_x_preferred":[
        "\u041c\u0430\u0446\u0456\u043d\u0430"
    ],
    "name:bul_x_preferred":[
        "\u041c\u0430\u0442\u0438\u043d\u043e"
    ],
    "name:ceb_x_preferred":[
        "Matino"
    ],
    "name:deu_x_preferred":[
        "Matino"
    ],
    "name:epo_x_preferred":[
        "Matino"
    ],
    "name:eus_x_preferred":[
        "Matino"
    ],
    "name:fas_x_preferred":[
        "\u0645\u0627\u062a\u06cc\u0646\u0648"
    ],
    "name:fra_x_preferred":[
        "Matino"
    ],
    "name:hun_x_preferred":[
        "Matino"
    ],
    "name:hye_x_preferred":[
        "\u0544\u0561\u057f\u056b\u0576\u0578"
    ],
    "name:ina_x_preferred":[
        "Matino"
    ],
    "name:ita_x_preferred":[
        "Matino"
    ],
    "name:jpn_x_preferred":[
        "\u30de\u30c6\u30a3\u30fc\u30ce"
    ],
    "name:kaz_x_preferred":[
        "\u041c\u0430\u0442\u0438\u043d\u043e"
    ],
    "name:lat_x_preferred":[
        "Matinum"
    ],
    "name:lmo_x_preferred":[
        "Matino"
    ],
    "name:msa_x_preferred":[
        "Matino"
    ],
    "name:nap_x_preferred":[
        "Matino"
    ],
    "name:nld_x_preferred":[
        "Matino"
    ],
    "name:pms_x_preferred":[
        "Matino"
    ],
    "name:pol_x_preferred":[
        "Matino"
    ],
    "name:por_x_preferred":[
        "Matino"
    ],
    "name:ron_x_preferred":[
        "Matino"
    ],
    "name:rus_x_preferred":[
        "\u041c\u0430\u0442\u0438\u043d\u043e"
    ],
    "name:scn_x_preferred":[
        "Matinu"
    ],
    "name:spa_x_preferred":[
        "Matino"
    ],
    "name:srp_x_preferred":[
        "\u041c\u0430\u0442\u0438\u043d\u043e"
    ],
    "name:tgl_x_preferred":[
        "Matino"
    ],
    "name:ukr_x_preferred":[
        "\u041c\u0430\u0442\u0456\u043d\u043e"
    ],
    "name:uzb_x_preferred":[
        "Matino"
    ],
    "name:vie_x_preferred":[
        "Matino"
    ],
    "name:war_x_preferred":[
        "Matino"
    ],
    "name:zho_x_preferred":[
        "\u9a6c\u8482\u8bfa"
    ],
    "wof:name":"Matino",
    "wof:placetype":"locality"
},
  "geometry": {"coordinates":[37.1487,57.3036],"type":"Point"}
}