{
  "type": "Feature",
  "properties": {
    "gn:admin1_code":"6.0",
    "gn:asciiname":"Berezinskaya",
    "gn:country_code":"RU",
    "gn:dem":133,
    "gn:feature_class":"P",
    "gn:feature_code":"PPL",
    "gn:name":"Berezinskaya",
    "gn:population":0,
    "gn:timezone":"Europe/Moscow",
    "iso:country":"RU",
    "name:nor_x_preferred":[
        "Berezinskaja"
    ],
    "name:rus_x_preferred":[
        "\u0411\u0435\u0440\u0435\u0437\u0438\u043d\u0441\u043a\u0430\u044f"
    ],
    "wof:name":"Berezinskaya",
    "wof:placetype":"locality"
},
  "geometry": {"coordinates":[41.9843,61.1488],"type":"Point"}
}