{
  "type": "Feature",
  "properties": {
    "gn:admin1_code":"52",
    "gn:asciiname":"Tsarevo",
    "gn:country_code":"RU",
    "gn:dem":141,
    "gn:feature_class":"P",
    "gn:feature_code":"PPL",
    "gn:name":"Tsar\u00ebvo",
    "gn:population":0,
    "gn:timezone":"Europe/Moscow",
    "iso:country":"RU",
    "name:azb_x_preferred":[
        "\u062a\u0633\u0627\u0631\u0648"
    ],
    "name:bul_x_preferred":[
        "\u0426\u0430\u0440\u0435\u0432\u043e"
    ],
    "name:ces_x_preferred":[
        "Carevo"
    ],
    "name:ckb_x_preferred":[
        "\u062a\u0633\u0627\u0631\u06ce\u06a4\u06c6"
    ],
    "name:deu_x_preferred":[
        "Zarewo"
    ],
    "name:ell_x_preferred":[
        "\u0392\u03b1\u03c3\u03b9\u03bb\u03b9\u03ba\u03cc \u03a0\u03cd\u03c1\u03b3\u03bf\u03c5"
    ],
    "name:fas_x_preferred":[
        "\u062a\u0633\u0627\u0631\u0648\u0648"
    ],
    "name:fin_x_preferred":[
        "Tsarevo"
    ],
    "name:fra_x_preferred":[
        "Tsar\u00e9vo"
    ],
    "name:jpn_x_preferred":[
        "\u30c4\u30a1\u30ec\u30f4\u30a9"
    ],
    "name:kaz_x_preferred":[
        "\u0426\u0430\u0440\u0435\u0432\u043e"
    ],
    "name:oss_x_preferred":[
        "\u0426\u0430\u0440\u0435\u0432\u043e"
    ],
    "name:pol_x_preferred":[
        "Carewo"
    ],
    "name:por_x_preferred":[
        "Carevo"
    ],
    "name:ron_x_preferred":[
        "\u021aarevo"
    ],
    "name:rus_x_preferred":[
        "\u0426\u0430\u0440\u0435\u0432\u043e"
    ],
    "name:slk_x_preferred":[
        "Carevo"
    ],
    "name:spa_x_preferred":[
        "Tsarevo"
    ],
    "name:srp_x_preferred":[
        "\u0426\u0430\u0440\u0435\u0432\u043e"
    ],
    "name:swe_x_preferred":[
        "Tsarevo"
    ],
    "name:tur_x_preferred":[
        "Tsarevo"
    ],
    "name:ukr_x_preferred":[
        "\u0426\u0430\u0440\u0435\u0432\u043e"
    ],
    "name:vie_x_preferred":[
        "Tsarevo"
    ],
    "name:war_x_preferred":[
        "Tsarevo"
    ],
    "name:zho_x_preferred":[
        "\u5bdf\u96f7\u6c83"
    ],
    "wof:name":"Tsarevo",
    "wof:placetype":"locality"
},
  "geometry": {"coordinates":[34.46667,58.31667],"type":"Point"}
}