{
  "type": "Feature",
  "properties": {
    "gn:admin1_code":"52",
    "gn:asciiname":"Tsarevo",
    "gn:country_code":"RU",
    "gn:dem":141,
    "gn:feature_class":"P",
    "gn:feature_code":"PPL",
    "gn:name":"Tsar\u00ebvo",
    "gn:population":0,
    "gn:timezone":"Europe/Moscow",
    "iso:country":"RU",
    "wof:name":"Tsarevo",
    "wof:placetype":"locality"
},
  "geometry": {"coordinates":[34.46667,58.31667],"type":"Point"}
}