{
  "type": "Feature",
  "properties": {
    "gn:admin1_code":"21.0",
    "gn:asciiname":"Dudintsy",
    "gn:country_code":"RU",
    "gn:dem":134,
    "gn:feature_class":"P",
    "gn:feature_code":"PPL",
    "gn:name":"Dudintsy",
    "gn:population":0,
    "gn:timezone":"Europe/Moscow",
    "iso:country":"RU",
    "name:rus_x_preferred":[
        "\u0414\u0443\u0434\u0438\u043d\u0446\u044b"
    ],
    "wof:name":"Dudintsy",
    "wof:placetype":"locality"
},
  "geometry": {"coordinates":[41.45,57.35],"type":"Point"}
}