{
  "type": "Feature",
  "properties": {
    "gn:admin1_code":"93",
    "gn:asciiname":"Chatanga",
    "gn:country_code":"RU",
    "gn:dem":997,
    "gn:feature_class":"P",
    "gn:feature_code":"PPL",
    "gn:name":"Chatanga",
    "gn:population":0,
    "gn:timezone":"Asia/Chita",
    "iso:country":"RU",
    "name:eng_x_preferred":[
        "Chitanga"
    ],
    "name:nor_x_preferred":[
        "Tsjatanga"
    ],
    "name:rus_x_preferred":[
        "\u0427\u0430\u0442\u0430\u043d\u0433\u0430"
    ],
    "name:und_x_variant":[
        "Chitanga"
    ],
    "wof:name":"Chatanga",
    "wof:placetype":"locality"
},
  "geometry": {"coordinates":[110.7167,50.24100000000001],"type":"Point"}
}