{
  "type": "Feature",
  "properties": {
    "gn:admin1_code":"45",
    "gn:asciiname":"Fedotkino",
    "gn:country_code":"RU",
    "gn:dem":112,
    "gn:feature_class":"P",
    "gn:feature_code":"PPL",
    "gn:name":"Fedotkino",
    "gn:population":0,
    "gn:timezone":"Europe/Moscow",
    "iso:country":"RU",
    "name:rus_x_preferred":[
        "\u0424\u0435\u0434\u043e\u0442\u043a\u0438\u043d\u043e"
    ],
    "name:und_x_variant":[
        "\u0424\u0435\u0434\u043e\u0442\u043a\u0438\u043d\u043e"
    ],
    "wof:name":"Fedotkino",
    "wof:placetype":"locality"
},
  "geometry": {"coordinates":[46.2956,56.1661],"type":"Point"}
}