{
  "type": "Feature",
  "properties": {
    "gn:admin1_code":"90.0",
    "gn:asciiname":"Klyuch-Mys",
    "gn:country_code":"RU",
    "gn:dem":204,
    "gn:feature_class":"P",
    "gn:feature_code":"PPL",
    "gn:name":"Klyuch-Mys",
    "gn:population":0,
    "gn:timezone":"Asia/Yekaterinburg",
    "iso:country":"RU",
    "name:rus_x_preferred":[
        "\u041a\u043b\u044e\u0447-\u041c\u044b\u0441"
    ],
    "wof:name":"Klyuch-Mys",
    "wof:placetype":"locality"
},
  "geometry": {"coordinates":[54.1964,58.9549],"type":"Point"}
}