{
  "type": "Feature",
  "properties": {
    "gn:admin1_code":"62.0",
    "gn:asciiname":"Bugrovka",
    "gn:country_code":"RU",
    "gn:dem":200,
    "gn:feature_class":"P",
    "gn:feature_code":"PPL",
    "gn:name":"Bugrovka",
    "gn:population":0,
    "gn:timezone":"Europe/Moscow",
    "iso:country":"RU",
    "name:rus_x_preferred":[
        "\u0411\u0443\u0433\u0440\u043e\u0432\u043a\u0430"
    ],
    "wof:name":"Bugrovka",
    "wof:placetype":"locality"
},
  "geometry": {"coordinates":[39.05642,53.66839],"type":"Point"}
}