{
  "type": "Feature",
  "properties": {
    "gn:admin1_code":"73",
    "gn:asciiname":"Nizhniy Shuban",
    "gn:country_code":"RU",
    "gn:dem":96,
    "gn:feature_class":"P",
    "gn:feature_code":"PPL",
    "gn:name":"Nizhniy Shuban",
    "gn:population":0,
    "gn:timezone":"Europe/Moscow",
    "iso:country":"RU",
    "name:rus_x_preferred":[
        "\u041d\u0438\u0436\u043d\u0438\u0439 \u0428\u0443\u0431\u0430\u043d"
    ],
    "wof:name":"Nizhniy Shuban",
    "wof:placetype":"locality"
},
  "geometry": {"coordinates":[50.0721,56.3549],"type":"Point"}
}