{
  "type": "Feature",
  "properties": {
    "gn:admin1_code":"61",
    "gn:asciiname":"Zhilploshchadka",
    "gn:country_code":"RU",
    "gn:dem":116,
    "gn:feature_class":"P",
    "gn:feature_code":"PPL",
    "gn:name":"Zhilploshchadka",
    "gn:population":0,
    "gn:timezone":"Europe/Moscow",
    "iso:country":"RU",
    "wof:name":"Zhilploshchadka",
    "wof:placetype":"locality"
},
  "geometry": {"coordinates":[39.95,48.33333],"type":"Point"}
}