{
  "type": "Feature",
  "properties": {
    "gn:admin1_code":"91",
    "gn:asciiname":"Shagirislam",
    "gn:country_code":"RU",
    "gn:dem":237,
    "gn:feature_class":"P",
    "gn:feature_code":"PPL",
    "gn:name":"Shagirislam",
    "gn:population":0,
    "gn:timezone":"Asia/Krasnoyarsk",
    "iso:country":"RU",
    "name:eng_x_preferred":[
        "Shagirislam"
    ],
    "name:rus_x_preferred":[
        "\u0428\u0430\u0433\u0438\u0440\u0438\u0441\u043b\u0430\u043c"
    ],
    "name:rus_x_variant":[
        "\u0428\u0430\u0433\u0438\u0441\u043b\u0430\u043c"
    ],
    "wof:name":"Shagirislam",
    "wof:placetype":"locality"
},
  "geometry": {"coordinates":[92.33620000000001,57.5015],"type":"Point"}
}