{
  "type": "Feature",
  "properties": {
    "gn:admin1_code":"23",
    "gn:asciiname":"Konstantinovka",
    "gn:country_code":"RU",
    "gn:dem":88,
    "gn:feature_class":"P",
    "gn:feature_code":"PPL",
    "gn:name":"Konstantinovka",
    "gn:population":0,
    "gn:timezone":"Europe/Kaliningrad",
    "iso:country":"RU",
    "name:bel_x_preferred":[
        "\u041a\u0430\u043d\u0441\u0442\u0430\u043d\u0446\u0456\u043d\u0430\u045e\u043a\u0430"
    ],
    "name:ceb_x_preferred":[
        "Konstantinovka"
    ],
    "name:hun_x_preferred":[
        "Konsztantyinovka"
    ],
    "name:kaz_x_preferred":[
        "\u041a\u043e\u043d\u0441\u0442\u0430\u043d\u0442\u0438\u043d\u043e\u0432\u043a\u0430"
    ],
    "name:lav_x_preferred":[
        "Konstantinovka"
    ],
    "name:lit_x_preferred":[
        "Konstantinuvka"
    ],
    "name:pol_x_preferred":[
        "Konstantyn\u00f3wka"
    ],
    "name:rus_x_preferred":[
        "\u041a\u043e\u043d\u0441\u0442\u0430\u043d\u0442\u0438\u043d\u043e\u0432\u043a\u0430"
    ],
    "name:sco_x_preferred":[
        "Konstantinovka"
    ],
    "name:swe_x_preferred":[
        "Konstantinovka"
    ],
    "name:ukr_x_preferred":[
        "\u041a\u043e\u043d\u0441\u0442\u0430\u043d\u0442\u0438\u043d\u043e\u0432\u043a\u0430"
    ],
    "wof:name":"Konstantinovka",
    "wof:placetype":"locality"
},
  "geometry": {"coordinates":[22.06139,54.5025],"type":"Point"}
}