{
  "type": "Feature",
  "properties": {
    "gn:admin1_code":"37",
    "gn:asciiname":"Titovo",
    "gn:country_code":"RU",
    "gn:dem":195,
    "gn:feature_class":"P",
    "gn:feature_code":"PPL",
    "gn:name":"Titovo",
    "gn:population":0,
    "gn:timezone":"Europe/Moscow",
    "iso:country":"RU",
    "name:rus_x_preferred":[
        "\u0422\u0438\u0442\u043e\u0432\u043e"
    ],
    "name:und_x_variant":[
        "\u0422\u0438\u0442\u043e\u0432\u043e"
    ],
    "wof:name":"Titovo",
    "wof:placetype":"locality"
},
  "geometry": {"coordinates":[46.6357,59.0436],"type":"Point"}
}