{
  "type": "Feature",
  "properties": {
    "gn:admin1_code":"86.0",
    "gn:asciiname":"Goryushkin",
    "gn:country_code":"RU",
    "gn:dem":194,
    "gn:feature_class":"P",
    "gn:feature_code":"PPL",
    "gn:name":"Goryushkin",
    "gn:population":0,
    "gn:timezone":"Europe/Moscow",
    "iso:country":"RU",
    "name:rus_x_preferred":[
        "\u0413\u043e\u0440\u044e\u0448\u043a\u0438\u043d"
    ],
    "name:und_x_variant":[
        "\u0413\u043e\u0440\u044e\u0448\u043a\u0438\u043d"
    ],
    "wof:name":"Goryushkin",
    "wof:placetype":"locality"
},
  "geometry": {"coordinates":[41.0752,50.5668],"type":"Point"}
}