{
  "type": "Feature",
  "properties": {
    "gn:admin1_code":"7",
    "gn:asciiname":"Nikonov",
    "gn:cc2":"RU",
    "gn:country_code":"RU",
    "gn:dem":-14,
    "gn:feature_class":"P",
    "gn:feature_code":"PPL",
    "gn:name":"Nikonov",
    "gn:population":0,
    "gn:timezone":"Europe/Astrakhan",
    "iso:country":"RU",
    "name:rus_x_preferred":[
        "\u041d\u0438\u043a\u043e\u043d\u043e\u0432"
    ],
    "name:und_x_variant":[
        "Nikonova",
        "Nikonov"
    ],
    "wof:name":"Nikonov",
    "wof:placetype":"locality"
},
  "geometry": {"coordinates":[45.71667,48.51667],"type":"Point"}
}