{
  "type": "Feature",
  "properties": {
    "gn:admin1_code":"55",
    "gn:asciiname":"Koveshinka",
    "gn:country_code":"RU",
    "gn:dem":89,
    "gn:feature_class":"P",
    "gn:feature_code":"PPL",
    "gn:name":"Koveshinka",
    "gn:population":0,
    "gn:timezone":"Asia/Yekaterinburg",
    "iso:country":"RU",
    "name:rus_x_preferred":[
        "\u041a\u043e\u0432\u0435\u0448\u0438\u043d\u043a\u0430"
    ],
    "name:und_x_variant":[
        "\u041a\u043e\u0432\u0435\u0448\u0438\u043d\u043a\u0430",
        "Koveshnikovo"
    ],
    "wof:name":"Koveshinka",
    "wof:placetype":"locality"
},
  "geometry": {"coordinates":[52.4319,52.4951],"type":"Point"}
}