{
  "type": "Feature",
  "properties": {
    "gn:admin1_code":"60",
    "gn:asciiname":"Shishlovo",
    "gn:country_code":"RU",
    "gn:dem":65,
    "gn:feature_class":"P",
    "gn:feature_code":"PPL",
    "gn:name":"Shishlovo",
    "gn:population":0,
    "gn:timezone":"Europe/Moscow",
    "iso:country":"RU",
    "name:rus_x_preferred":[
        "\u0428\u0438\u0448\u043b\u043e\u0432\u043e"
    ],
    "wof:name":"Shishlovo",
    "wof:placetype":"locality"
},
  "geometry": {"coordinates":[28.8617,57.6597],"type":"Point"}
}