{
  "type": "Feature",
  "properties": {
    "gn:admin1_code":"24",
    "gn:asciiname":"Gorodovikovo",
    "gn:cc2":"RU",
    "gn:country_code":"RU",
    "gn:dem":-17,
    "gn:feature_class":"P",
    "gn:feature_code":"PPL",
    "gn:name":"Gorodovikovo",
    "gn:population":0,
    "gn:timezone":"Europe/Moscow",
    "iso:country":"RU",
    "name:rus_x_preferred":[
        "\u0413\u043e\u0440\u043e\u0434\u043e\u0432\u0438\u043a\u043e\u0432\u043e"
    ],
    "name:und_x_variant":[
        "Khuduk Antasyuk",
        "Gorodovikovo",
        "\u0413\u043e\u0440\u043e\u0434\u043e\u0432\u0438\u043a\u043e\u0432\u043e"
    ],
    "wof:name":"Gorodovikovo",
    "wof:placetype":"locality"
},
  "geometry": {"coordinates":[46.16583,45.92222],"type":"Point"}
}