{
  "type": "Feature",
  "properties": {
    "gn:admin1_code":"11",
    "gn:asciiname":"Taloye",
    "gn:country_code":"RU",
    "gn:dem":725,
    "gn:feature_class":"P",
    "gn:feature_code":"PPL",
    "gn:name":"Taloye",
    "gn:population":0,
    "gn:timezone":"Asia/Irkutsk",
    "iso:country":"RU",
    "name:eng_x_preferred":[
        "Taloye"
    ],
    "name:nor_x_preferred":[
        "Taloje"
    ],
    "name:rus_x_preferred":[
        "\u0422\u0430\u043b\u043e\u0435"
    ],
    "name:und_x_variant":[
        "Talaya"
    ],
    "wof:name":"Taloye",
    "wof:placetype":"locality"
},
  "geometry": {"coordinates":[102.47880000000001,51.82100000000001],"type":"Point"}
}