{
  "type": "Feature",
  "properties": {
    "gn:admin1_code":"59",
    "gn:asciiname":"Kuruma",
    "gn:country_code":"RU",
    "gn:dem":80,
    "gn:feature_class":"P",
    "gn:feature_code":"PPL",
    "gn:name":"Kuruma",
    "gn:population":0,
    "gn:timezone":"Asia/Vladivostok",
    "iso:country":"RU",
    "name:ceb_x_preferred":[
        "Kuruma"
    ],
    "name:deu_x_preferred":[
        "Kuruma"
    ],
    "name:rus_x_preferred":[
        "\u041a\u0443\u0440\u0443\u043c\u0430"
    ],
    "name:und_x_variant":[
        "\u041a\u0443\u0440\u0443\u043c\u0430"
    ],
    "wof:name":"Kuruma",
    "wof:placetype":"locality"
},
  "geometry": {"coordinates":[136.19999999999999,44.85],"type":"Point"}
}