{
  "type": "Feature",
  "properties": {
    "gn:admin1_code":"8",
    "gn:asciiname":"Staromusino",
    "gn:country_code":"RU",
    "gn:dem":150,
    "gn:feature_class":"P",
    "gn:feature_code":"PPL",
    "gn:name":"Staromusino",
    "gn:population":0,
    "gn:timezone":"Asia/Yekaterinburg",
    "iso:country":"RU",
    "name:eng_x_preferred":[
        "Staromusino"
    ],
    "name:nor_x_preferred":[
        "Staromusino"
    ],
    "name:rus_x_preferred":[
        "\u0421\u0442\u0430\u0440\u043e\u043c\u0443\u0441\u0438\u043d\u043e"
    ],
    "name:und_x_variant":[
        "Musina",
        "\u0421\u0442\u0430\u0440\u043e\u043c\u0443\u0441\u0438\u043d\u043e",
        "Staromusino"
    ],
    "wof:name":"Staromusino",
    "wof:placetype":"locality"
},
  "geometry": {"coordinates":[55.5107,54.38922],"type":"Point"}
}