{
  "type": "Feature",
  "properties": {
    "gn:admin1_code":"38",
    "gn:asciiname":"Veselyy",
    "gn:cc2":"RU",
    "gn:country_code":"RU",
    "gn:dem":71,
    "gn:feature_class":"P",
    "gn:feature_code":"PPL",
    "gn:name":"Ves\u00eblyy",
    "gn:population":0,
    "gn:timezone":"Europe/Moscow",
    "iso:country":"RU",
    "name:und_x_variant":[
        "Vesely",
        "Ves\u00eblyy"
    ],
    "wof:name":"Veselyy",
    "wof:placetype":"locality"
},
  "geometry": {"coordinates":[40.30361,45.26444],"type":"Point"}
}