{
  "type": "Feature",
  "properties": {
    "gn:admin1_code":"8",
    "gn:asciiname":"Novotroitskoye",
    "gn:country_code":"RU",
    "gn:dem":98,
    "gn:feature_class":"P",
    "gn:feature_code":"PPL",
    "gn:name":"Novotroitskoye",
    "gn:population":0,
    "gn:timezone":"Asia/Yekaterinburg",
    "iso:country":"RU",
    "name:rus_x_preferred":[
        "\u041d\u043e\u0432\u043e\u0442\u0440\u043e\u0438\u0446\u043a\u043e\u0435"
    ],
    "wof:name":"Novotroitskoye",
    "wof:placetype":"locality"
},
  "geometry": {"coordinates":[53.8137,55.2425],"type":"Point"}
}