{
  "type": "Feature",
  "properties": {
    "gn:admin1_code":"25",
    "gn:asciiname":"Dyaglevo",
    "gn:country_code":"RU",
    "gn:dem":189,
    "gn:feature_class":"P",
    "gn:feature_code":"PPL",
    "gn:name":"Dyaglevo",
    "gn:population":0,
    "gn:timezone":"Europe/Moscow",
    "iso:country":"RU",
    "name:rus_x_preferred":[
        "\u0414\u044f\u0433\u043b\u0435\u0432\u043e"
    ],
    "name:und_x_variant":[
        "\u0414\u044f\u0433\u043b\u0435\u0432\u043e"
    ],
    "wof:name":"Dyaglevo",
    "wof:placetype":"locality"
},
  "geometry": {"coordinates":[35.24918,53.96832],"type":"Point"}
}