{
  "type": "Feature",
  "properties": {
    "gn:admin1_code":"63",
    "gn:asciiname":"Begidzhyan",
    "gn:country_code":"RU",
    "gn:dem":56,
    "gn:feature_class":"P",
    "gn:feature_code":"PPL",
    "gn:name":"Begidzhyan",
    "gn:population":0,
    "gn:timezone":"Asia/Yakutsk",
    "iso:country":"RU",
    "name:nor_x_preferred":[
        "Begidzjan"
    ],
    "name:rus_x_preferred":[
        "\u0411\u0435\u0433\u0438\u0434\u0436\u044f\u043d"
    ],
    "name:und_x_variant":[
        "Begid\u2019een",
        "Begidzhyan"
    ],
    "wof:name":"Begidzhyan",
    "wof:placetype":"locality"
},
  "geometry": {"coordinates":[124.06667,66.56667],"type":"Point"}
}