{
  "type": "Feature",
  "properties": {
    "gn:admin1_code":"6",
    "gn:asciiname":"Gora",
    "gn:country_code":"RU",
    "gn:dem":23,
    "gn:feature_class":"P",
    "gn:feature_code":"PPL",
    "gn:name":"Gora",
    "gn:population":0,
    "gn:timezone":"Europe/Moscow",
    "iso:country":"RU",
    "name:eng_x_preferred":[
        "Gora"
    ],
    "name:nor_x_preferred":[
        "Gora"
    ],
    "name:rus_x_preferred":[
        "\u0413\u043e\u0440\u0430"
    ],
    "name:und_x_variant":[
        "\u0413\u043e\u0440\u0430",
        "Gora"
    ],
    "wof:name":"Gora",
    "wof:placetype":"locality"
},
  "geometry": {"coordinates":[41.49369,63.09529000000001],"type":"Point"}
}