{
  "type": "Feature",
  "properties": {
    "gn:admin1_code":"50",
    "gn:asciiname":"Nosovaya",
    "gn:country_code":"RU",
    "gn:dem":1,
    "gn:feature_class":"P",
    "gn:feature_code":"PPL",
    "gn:name":"Nosovaya",
    "gn:population":0,
    "gn:timezone":"Europe/Moscow",
    "iso:country":"RU",
    "name:eng_x_preferred":[
        "Nosovaya"
    ],
    "name:nor_x_preferred":[
        "Nosovaja"
    ],
    "name:rus_x_preferred":[
        "\u041d\u043e\u0441\u043e\u0432\u0430\u044f"
    ],
    "name:und_x_variant":[
        "Tonya Nosovaya",
        "Stoybishche Nosovaya"
    ],
    "wof:name":"Nosovaya",
    "wof:placetype":"locality"
},
  "geometry": {"coordinates":[54.57178,68.24994000000001],"type":"Point"}
}