{
  "type": "Feature",
  "properties": {
    "gn:admin1_code":"69",
    "gn:asciiname":"Ledishche",
    "gn:country_code":"RU",
    "gn:dem":197,
    "gn:feature_class":"P",
    "gn:feature_code":"PPL",
    "gn:name":"Ledishche",
    "gn:population":0,
    "gn:timezone":"Europe/Moscow",
    "iso:country":"RU",
    "wof:name":"Ledishche",
    "wof:placetype":"locality"
},
  "geometry": {"coordinates":[34.42194,55.63694],"type":"Point"}
}