{
  "type": "Feature",
  "properties": {
    "gn:admin1_code":"61",
    "gn:asciiname":"Verkhneyaninskiy",
    "gn:country_code":"RU",
    "gn:dem":62,
    "gn:feature_class":"P",
    "gn:feature_code":"PPL",
    "gn:name":"Verkhneyaninskiy",
    "gn:population":0,
    "gn:timezone":"Europe/Moscow",
    "iso:country":"RU",
    "name:rus_x_preferred":[
        "\u0412\u0435\u0440\u0445\u043d\u0435\u044f\u043d\u0438\u043d\u0441\u043a\u0438\u0439"
    ],
    "wof:name":"Verkhneyaninskiy",
    "wof:placetype":"locality"
},
  "geometry": {"coordinates":[41.5209,46.5917],"type":"Point"}
}