{
  "type": "Feature",
  "properties": {
    "gn:admin1_code":"47.0",
    "gn:asciiname":"Sapronovo",
    "gn:country_code":"RU",
    "gn:dem":122,
    "gn:feature_class":"P",
    "gn:feature_code":"PPL",
    "gn:name":"Sapronovo",
    "gn:population":0,
    "gn:timezone":"Europe/Moscow",
    "iso:country":"RU",
    "name:rus_x_preferred":[
        "\u0421\u0430\u043f\u0440\u043e\u043d\u043e\u0432\u043e"
    ],
    "name:und_x_variant":[
        "\u0421\u0430\u043f\u0440\u043e\u043d\u043e\u0432\u043e"
    ],
    "wof:name":"Sapronovo",
    "wof:placetype":"locality"
},
  "geometry": {"coordinates":[37.71,55.52],"type":"Point"}
}