{
  "type": "Feature",
  "properties": {
    "gn:admin1_code":"72",
    "gn:asciiname":"Novyy Svet Vtoroy",
    "gn:country_code":"RU",
    "gn:dem":166,
    "gn:feature_class":"P",
    "gn:feature_code":"PPL",
    "gn:name":"Novyy Svet Vtoroy",
    "gn:population":0,
    "gn:timezone":"Europe/Moscow",
    "iso:country":"RU",
    "name:rus_x_preferred":[
        "\u041d\u043e\u0432\u044b\u0439 \u0421\u0432\u0435\u0442 \u0412\u0442\u043e\u0440\u043e\u0439"
    ],
    "name:und_x_variant":[
        "Novy Svet Vtory",
        "Novyy Svet Vtoroy"
    ],
    "wof:name":"Novyy Svet Vtoroy",
    "wof:placetype":"locality"
},
  "geometry": {"coordinates":[41.84091,51.87013],"type":"Point"}
}