{
  "type": "Feature",
  "properties": {
    "gn:admin1_code":"8",
    "gn:asciiname":"Kiyevonikol'skiy",
    "gn:country_code":"RU",
    "gn:dem":533,
    "gn:feature_class":"P",
    "gn:feature_code":"PPL",
    "gn:name":"Kiyevonikol\u2019skiy",
    "gn:population":0,
    "gn:timezone":"Asia/Yekaterinburg",
    "iso:country":"RU",
    "name:rus_x_preferred":[
        "\u041a\u0438\u0435\u0432\u043e\u043d\u0438\u043a\u043e\u043b\u044c\u0441\u043a\u0438\u0439"
    ],
    "name:und_x_variant":[
        "Kiyevonikol\u2019skiy"
    ],
    "wof:name":"Kiyevonikol'skiy",
    "wof:placetype":"locality"
},
  "geometry": {"coordinates":[57.08333,52.48333],"type":"Point"}
}