{
  "type": "Feature",
  "properties": {
    "gn:country":"RU",
    "gn:fcode":"PPL",
    "gn:pop":4979,
    "iso:country":"RU",
    "name:nor_x_preferred":[
        "Psjekhskaja"
    ],
    "name:rus_x_preferred":[
        "\u041f\u0448\u0435\u0445\u0441\u043a\u0430\u044f"
    ],
    "name:unk_x_variant":[
        "\u041f\u0448\u0435\u0445\u0441\u043a\u0430\u044f"
    ],
    "qs:name":"Pshekhskaya",
    "qs:photos_9r":0,
    "qs:photos_sr":0,
    "qs:pop_sr":"4",
    "wof:name":"Pshekhskaya",
    "wof:placetype":"locality",
    "wof:population":4979
},
  "geometry": {"coordinates":[39.79665,44.69597],"type":"Point"}
}