{
  "type": "Feature",
  "properties": {
    "gn:admin1_code":"91",
    "gn:asciiname":"Nakhval'skoye",
    "gn:country_code":"RU",
    "gn:dem":145,
    "gn:feature_class":"P",
    "gn:feature_code":"PPL",
    "gn:name":"Nakhval\u2019skoye",
    "gn:population":0,
    "gn:timezone":"Asia/Krasnoyarsk",
    "iso:country":"RU",
    "name:eng_x_preferred":[
        "Nakhval'skoye"
    ],
    "name:nor_x_preferred":[
        "Nakhvalskoje"
    ],
    "name:rus_x_preferred":[
        "\u041d\u0430\u0445\u0432\u0430\u043b\u044c\u0441\u043a\u043e\u0435"
    ],
    "name:und_x_variant":[
        "Nakhval\u2019skoye"
    ],
    "wof:name":"Nakhval'skoye",
    "wof:placetype":"locality"
},
  "geometry": {"coordinates":[93.57250000000001,56.67333000000001],"type":"Point"}
}