{
  "type": "Feature",
  "properties": {
    "gn:admin1_code":"60",
    "gn:asciiname":"Kosovo",
    "gn:country_code":"RU",
    "gn:dem":142,
    "gn:feature_class":"P",
    "gn:feature_code":"PPL",
    "gn:name":"Kosovo",
    "gn:population":0,
    "gn:timezone":"Europe/Moscow",
    "iso:country":"RU",
    "name:rus_x_preferred":[
        "\u041a\u043e\u0441\u043e\u0432\u043e"
    ],
    "name:und_x_variant":[
        "\u041a\u043e\u0441\u043e\u0432\u043e"
    ],
    "wof:name":"Kosovo",
    "wof:placetype":"locality"
},
  "geometry": {"coordinates":[30.3174,56.0817],"type":"Point"}
}