{
  "type": "Feature",
  "properties": {
    "gn:admin1_code":"20",
    "gn:asciiname":"Malaya Topka",
    "gn:country_code":"RU",
    "gn:dem":456,
    "gn:feature_class":"P",
    "gn:feature_code":"PPL",
    "gn:name":"Malaya Topka",
    "gn:population":0,
    "gn:timezone":"Asia/Irkutsk",
    "iso:country":"RU",
    "name:rus_x_preferred":[
        "\u041c\u0430\u043b\u0430\u044f \u0422\u043e\u043f\u043a\u0430"
    ],
    "name:und_x_variant":[
        "\u041c\u0430\u043b\u0430\u044f \u0422\u043e\u043f\u043a\u0430"
    ],
    "wof:name":"Malaya Topka",
    "wof:placetype":"locality"
},
  "geometry": {"coordinates":[104.31444,52.34472],"type":"Point"}
}