{
  "type": "Feature",
  "properties": {
    "gn:admin1_code":"47",
    "gn:asciiname":"Yakimovo",
    "gn:country_code":"RU",
    "gn:dem":152,
    "gn:feature_class":"P",
    "gn:feature_code":"PPL",
    "gn:name":"Yakimovo",
    "gn:population":0,
    "gn:timezone":"Europe/Moscow",
    "iso:country":"RU",
    "name:bul_x_preferred":[
        "\u042f\u043a\u0438\u043c\u043e\u0432\u043e"
    ],
    "name:jpn_x_preferred":[
        "\u30e4\u30ad\u30e2\u30f4\u30a9"
    ],
    "name:kaz_x_preferred":[
        "\u042f\u043a\u0438\u043c\u043e\u0432\u043e"
    ],
    "name:msa_x_preferred":[
        "Yakimovo"
    ],
    "name:pol_x_preferred":[
        "Jakimowo"
    ],
    "name:ron_x_preferred":[
        "Iakimovo"
    ],
    "name:rus_x_preferred":[
        "\u042f\u043a\u0438\u043c\u043e\u0432\u043e"
    ],
    "name:tur_x_preferred":[
        "Yakimovo"
    ],
    "name:ukr_x_preferred":[
        "\u042f\u043a\u0438\u043c\u043e\u0432\u043e"
    ],
    "name:urd_x_preferred":[
        "\u06cc\u06a9\u0645\u0648\u0648\u0648"
    ],
    "name:war_x_preferred":[
        "Yakimovo"
    ],
    "name:zho_x_preferred":[
        "\u4e9e\u57fa\u83ab\u6c83"
    ],
    "wof:name":"Yakimovo",
    "wof:placetype":"locality"
},
  "geometry": {"coordinates":[38.36667,56.01667],"type":"Point"}
}