{
  "type": "Feature",
  "properties": {
    "gn:admin1_code":"10",
    "gn:asciiname":"Zhirkiny Dvory",
    "gn:country_code":"RU",
    "gn:dem":196,
    "gn:feature_class":"P",
    "gn:feature_code":"PPL",
    "gn:name":"Zhirkiny Dvory",
    "gn:population":0,
    "gn:timezone":"Europe/Moscow",
    "iso:country":"RU",
    "name:und_x_variant":[
        "Zhirkimy Dvory",
        "Zharkino",
        "Zhirkiny Dvory"
    ],
    "wof:name":"Zhirkiny Dvory",
    "wof:placetype":"locality"
},
  "geometry": {"coordinates":[34.95853,53.23466],"type":"Point"}
}