{
  "type": "Feature",
  "properties": {
    "gn:admin1_code":"84",
    "gn:asciiname":"Guli Korolevoy",
    "gn:country_code":"RU",
    "gn:dem":123,
    "gn:feature_class":"P",
    "gn:feature_code":"PPL",
    "gn:name":"Guli Korolevoy",
    "gn:population":0,
    "gn:timezone":"Europe/Volgograd",
    "iso:country":"RU",
    "name:rus_x_preferred":[
        "\u0413\u0443\u043b\u0438 \u041a\u043e\u0440\u043e\u043b\u0435\u0432\u043e\u0439"
    ],
    "wof:name":"Guli Korolevoy",
    "wof:placetype":"locality"
},
  "geometry": {"coordinates":[44.2963,48.63251],"type":"Point"}
}