{
  "type": "Feature",
  "properties": {
    "gn:admin1_code":"37",
    "gn:asciiname":"Shchipitsyno",
    "gn:country_code":"RU",
    "gn:dem":155,
    "gn:feature_class":"P",
    "gn:feature_code":"PPL",
    "gn:name":"Shchipitsyno",
    "gn:population":0,
    "gn:timezone":"Europe/Moscow",
    "iso:country":"RU",
    "name:rus_x_preferred":[
        "\u0429\u0438\u043f\u0438\u0446\u044b\u043d\u043e"
    ],
    "name:und_x_variant":[
        "\u0429\u0438\u043f\u0438\u0446\u044b\u043d\u043e"
    ],
    "wof:name":"Shchipitsyno",
    "wof:placetype":"locality"
},
  "geometry": {"coordinates":[46.7341,58.9322],"type":"Point"}
}