{
  "type": "Feature",
  "properties": {
    "gn:admin1_code":"56",
    "gn:asciiname":"Slobodka",
    "gn:country_code":"RU",
    "gn:dem":215,
    "gn:feature_class":"P",
    "gn:feature_code":"PPL",
    "gn:name":"Slobodka",
    "gn:population":0,
    "gn:timezone":"Europe/Moscow",
    "iso:country":"RU",
    "name:ceb_x_preferred":[
        "Slobodka"
    ],
    "name:lav_x_preferred":[
        "Slobodka"
    ],
    "name:rus_x_preferred":[
        "\u0421\u043b\u043e\u0431\u043e\u0434\u043a\u0430"
    ],
    "name:swe_x_preferred":[
        "Slobodka"
    ],
    "wof:name":"Slobodka",
    "wof:placetype":"locality"
},
  "geometry": {"coordinates":[35.53397000000001,53.25505],"type":"Point"}
}