{
  "type": "Feature",
  "properties": {
    "gn:admin1_code":"69",
    "gn:asciiname":"Novoye Sinyavino",
    "gn:country_code":"RU",
    "gn:dem":188,
    "gn:feature_class":"P",
    "gn:feature_code":"PPL",
    "gn:name":"Novoye Sinyavino",
    "gn:population":0,
    "gn:timezone":"Europe/Moscow",
    "iso:country":"RU",
    "name:rus_x_preferred":[
        "\u041d\u043e\u0432\u043e\u0435 \u0421\u0438\u043d\u044f\u0432\u0438\u043d\u043e"
    ],
    "name:und_x_variant":[
        "Sinyavino",
        "Novoye Sinyavino"
    ],
    "wof:name":"Novoye Sinyavino",
    "wof:placetype":"locality"
},
  "geometry": {"coordinates":[32.27353,54.78522],"type":"Point"}
}