{
  "type": "Feature",
  "properties": {
    "gn:admin1_code":"84",
    "gn:asciiname":"Podtikhov",
    "gn:country_code":"RU",
    "gn:dem":30,
    "gn:feature_class":"P",
    "gn:feature_code":"PPL",
    "gn:name":"Podtikhov",
    "gn:population":0,
    "gn:timezone":"Europe/Volgograd",
    "iso:country":"RU",
    "name:rus_x_preferred":[
        "\u041f\u043e\u0434\u0442\u0438\u0445\u043e\u0432"
    ],
    "name:und_x_variant":[
        "\u041f\u043e\u0434\u0442\u0438\u0445\u043e\u0432"
    ],
    "wof:name":"Podtikhov",
    "wof:placetype":"locality"
},
  "geometry": {"coordinates":[43.45,48.53333],"type":"Point"}
}