{
  "type": "Feature",
  "properties": {
    "gn:admin1_code":"23",
    "gn:asciiname":"Abluch'ye",
    "gn:country_code":"RU",
    "gn:dem":73,
    "gn:feature_class":"P",
    "gn:feature_code":"PPL",
    "gn:name":"Abluch\u2019ye",
    "gn:population":0,
    "gn:timezone":"Europe/Kaliningrad",
    "iso:country":"RU",
    "name:nor_x_preferred":[
        "Ablutsje"
    ],
    "name:rus_x_preferred":[
        "\u0410\u0431\u043b\u0443\u0447\u044c\u0435"
    ],
    "name:und_x_variant":[
        "Abluch\u2019ye"
    ],
    "wof:name":"Abluch'ye",
    "wof:placetype":"locality"
},
  "geometry": {"coordinates":[21.65187,54.36587],"type":"Point"}
}