{
  "type": "Feature",
  "properties": {
    "gn:admin1_code":"69",
    "gn:asciiname":"Polozovo",
    "gn:country_code":"RU",
    "gn:dem":198,
    "gn:feature_class":"P",
    "gn:feature_code":"PPL",
    "gn:name":"Polozovo",
    "gn:population":0,
    "gn:timezone":"Europe/Moscow",
    "iso:country":"RU",
    "name:che_x_preferred":[
        "\u041f\u043e\u043b\u043e\u0437\u043e\u0432\u043e"
    ],
    "name:eng_x_preferred":[
        "Polozovo"
    ],
    "name:hye_x_preferred":[
        "\u054a\u0578\u056c\u0578\u0566\u0578\u057e\u0578"
    ],
    "name:nor_x_preferred":[
        "Polozovo"
    ],
    "name:rus_x_preferred":[
        "\u041f\u043e\u043b\u043e\u0437\u043e\u0432\u043e"
    ],
    "name:und_x_variant":[
        "\u041f\u043e\u043b\u043e\u0437\u043e\u0432\u043e",
        "Polozovo"
    ],
    "wof:name":"Polozovo",
    "wof:placetype":"locality"
},
  "geometry": {"coordinates":[35.00365,55.74121],"type":"Point"}
}