{
  "type": "Feature",
  "properties": {
    "gn:admin1_code":"61",
    "gn:asciiname":"Krinichno-Lugskiy",
    "gn:country_code":"RU",
    "gn:dem":64,
    "gn:feature_class":"P",
    "gn:feature_code":"PPL",
    "gn:name":"Krinichno-Lugskiy",
    "gn:population":0,
    "gn:timezone":"Europe/Moscow",
    "iso:country":"RU",
    "name:eng_x_preferred":[
        "Krinichno-Lugskiy"
    ],
    "name:nor_x_preferred":[
        "Krinitsjno-Lugskoje"
    ],
    "name:rus_x_preferred":[
        "\u041a\u0440\u0438\u043d\u0438\u0447\u043d\u043e-\u041b\u0443\u0433\u0441\u043a\u043e\u0435"
    ],
    "name:rus_x_variant":[
        "\u041a\u0440\u0438\u043d\u0438\u0447\u043d\u043e-\u041b\u0443\u0433\u0441\u043a\u0438\u0439"
    ],
    "name:ukr_x_preferred":[
        "Krynychno-Lugs\u2019ke"
    ],
    "name:und_x_variant":[
        "Krinichno-Lugskoye"
    ],
    "wof:name":"Krinichno-Lugskiy",
    "wof:placetype":"locality"
},
  "geometry": {"coordinates":[39.21777,47.75061],"type":"Point"}
}