{
  "type": "Feature",
  "properties": {
    "gn:admin1_code":"38",
    "gn:asciiname":"Nikolayevka",
    "gn:cc2":"RU",
    "gn:country_code":"RU",
    "gn:dem":6,
    "gn:feature_class":"P",
    "gn:feature_code":"PPL",
    "gn:name":"Nikolayevka",
    "gn:population":0,
    "gn:timezone":"Europe/Moscow",
    "iso:country":"RU",
    "name:rus_x_preferred":[
        "\u041d\u0438\u043a\u043e\u043b\u0430\u0435\u0432\u043a\u0430"
    ],
    "name:und_x_variant":[
        "Nikolayevskiy",
        "Nikolayevka",
        "\u041d\u0438\u043a\u043e\u043b\u0430\u0435\u0432\u043a\u0430"
    ],
    "wof:name":"Nikolayevka",
    "wof:placetype":"locality"
},
  "geometry": {"coordinates":[38.51667,45.01667],"type":"Point"}
}