{
  "type": "Feature",
  "properties": {
    "gn:admin1_code":"23",
    "gn:asciiname":"Dubrava",
    "gn:country_code":"RU",
    "gn:dem":69,
    "gn:feature_class":"P",
    "gn:feature_code":"PPL",
    "gn:name":"Dubrava",
    "gn:population":0,
    "gn:timezone":"Europe/Kaliningrad",
    "iso:country":"RU",
    "name:eng_x_preferred":[
        "Dubrava"
    ],
    "name:nor_x_preferred":[
        "Dubrava"
    ],
    "name:rus_x_preferred":[
        "\u0414\u0443\u0431\u0440\u0430\u0432\u0430"
    ],
    "name:und_x_variant":[
        "\u0414\u0443\u0431\u0440\u0430\u0432\u0430",
        "Dubrava"
    ],
    "wof:name":"Dubrava",
    "wof:placetype":"locality"
},
  "geometry": {"coordinates":[22.18444,54.48639],"type":"Point"}
}