{
  "type": "Feature",
  "properties": {
    "gn:admin1_code":"23",
    "gn:asciiname":"Dubrava",
    "gn:country_code":"RU",
    "gn:dem":69,
    "gn:feature_class":"P",
    "gn:feature_code":"PPL",
    "gn:name":"Dubrava",
    "gn:population":0,
    "gn:timezone":"Europe/Kaliningrad",
    "iso:country":"RU",
    "name:bel_x_preferred":[
        "\u0414\u0443\u0431\u0440\u0430\u0432\u0430"
    ],
    "name:bos_x_preferred":[
        "Dubrava"
    ],
    "name:ceb_x_preferred":[
        "Dubrava"
    ],
    "name:deu_x_preferred":[
        "Dubrava"
    ],
    "name:eng_x_preferred":[
        "Dubrava"
    ],
    "name:fra_x_preferred":[
        "Dubrava"
    ],
    "name:hrv_x_preferred":[
        "Dubrava"
    ],
    "name:hun_x_preferred":[
        "Dubrava"
    ],
    "name:hye_x_preferred":[
        "\u0534\u0578\u0582\u0562\u0580\u0561\u057e\u0561"
    ],
    "name:mkd_x_preferred":[
        "\u0414\u0443\u0431\u0440\u0430\u0432\u0430"
    ],
    "name:nld_x_preferred":[
        "Dubrava"
    ],
    "name:nor_x_preferred":[
        "Dubrava"
    ],
    "name:rus_x_preferred":[
        "\u0414\u0443\u0431\u0440\u0430\u0432\u0430"
    ],
    "name:slv_x_preferred":[
        "Dubrava"
    ],
    "name:srp_x_preferred":[
        "\u0414\u0443\u0431\u0440\u0430\u0432\u0430"
    ],
    "name:swe_x_preferred":[
        "Dubrava"
    ],
    "name:ukr_x_preferred":[
        "\u0414\u0443\u0431\u0440\u0430\u0432\u0430"
    ],
    "wof:name":"Dubrava",
    "wof:placetype":"locality"
},
  "geometry": {"coordinates":[22.18444,54.48639],"type":"Point"}
}