{
  "type": "Feature",
  "properties": {
    "gn:admin1_code":"71",
    "gn:asciiname":"Kiselevka",
    "gn:country_code":"RU",
    "gn:dem":268,
    "gn:feature_class":"P",
    "gn:feature_code":"PPL",
    "gn:name":"Kisel\u00ebvka",
    "gn:population":0,
    "gn:timezone":"Asia/Yekaterinburg",
    "iso:country":"RU",
    "name:eng_x_preferred":[
        "Kisel\u00ebvka"
    ],
    "name:nor_x_preferred":[
        "Kiselevka"
    ],
    "name:rus_x_preferred":[
        "\u041a\u0438\u0441\u0435\u043b\u0435\u0432\u043a\u0430"
    ],
    "name:rus_x_variant":[
        "\u041a\u0438\u0441\u0435\u043b\u0451\u0432\u043a\u0430"
    ],
    "wof:name":"Kiselevka",
    "wof:placetype":"locality"
},
  "geometry": {"coordinates":[58.6144,56.7702],"type":"Point"}
}