{
  "type": "Feature",
  "properties": {
    "gn:admin1_code":"51",
    "gn:asciiname":"Shlyapino",
    "gn:country_code":"RU",
    "gn:dem":129,
    "gn:feature_class":"P",
    "gn:feature_code":"PPL",
    "gn:name":"Shlyapino",
    "gn:population":0,
    "gn:timezone":"Europe/Moscow",
    "iso:country":"RU",
    "name:rus_x_preferred":[
        "\u0428\u043b\u044f\u043f\u0438\u043d\u043e"
    ],
    "wof:name":"Shlyapino",
    "wof:placetype":"locality"
},
  "geometry": {"coordinates":[44.0125,57.2422],"type":"Point"}
}