{
  "type": "Feature",
  "properties": {
    "gn:admin1_code":"28",
    "gn:asciiname":"Lokh'yansel'kya",
    "gn:country_code":"RU",
    "gn:dem":121,
    "gn:feature_class":"P",
    "gn:feature_code":"PPL",
    "gn:name":"Lokh\u2019yansel\u2019kya",
    "gn:population":0,
    "gn:timezone":"Europe/Moscow",
    "iso:country":"RU",
    "name:fin_x_preferred":[
        "Lohjanselk\u00e4"
    ],
    "name:rus_x_preferred":[
        "\u041b\u043e\u0445\u044c\u044f\u043d\u0441\u0435\u043b\u044c\u043a\u044f"
    ],
    "name:und_x_variant":[
        "Lokh\u2019yansel\u2019kya",
        "\u041b\u043e\u0445\u044c\u044f\u043d\u0441\u0435\u043b\u044c\u043a\u044f"
    ],
    "wof:name":"Lokh'yansel'kya",
    "wof:placetype":"locality"
},
  "geometry": {"coordinates":[31.16907,61.97728000000001],"type":"Point"}
}