{
  "type": "Feature",
  "properties": {
    "gn:country":"RU",
    "gn:fcode":"PPL",
    "gn:pop":3102,
    "iso:country":"RU",
    "name:rus_x_preferred":[
        "\u041b\u0438\u0445\u043e\u0439"
    ],
    "name:unk_x_variant":[
        "Likhoy"
    ],
    "qs:name":"Likhoj",
    "qs:name_adm0":"Russia",
    "qs:name_adm1":"Rostov Oblast",
    "qs:photos_9r":0,
    "qs:photos_sr":0,
    "qs:placetype":"Town",
    "qs:pop_sr":"4",
    "wof:name":"Likhoj",
    "wof:placetype":"locality",
    "wof:population":3102
},
  "geometry": {"coordinates":[40.20556,48.12662],"type":"Point"}
}