{
  "type": "Feature",
  "properties": {
    "gn:admin1_code":"47.0",
    "gn:asciiname":"Frolovskoye",
    "gn:country_code":"RU",
    "gn:dem":121,
    "gn:feature_class":"P",
    "gn:feature_code":"PPL",
    "gn:name":"Frolovskoye",
    "gn:population":0,
    "gn:timezone":"Europe/Moscow",
    "iso:country":"RU",
    "name:rus_x_preferred":[
        "\u0424\u0440\u043e\u043b\u043e\u0432\u0441\u043a\u043e\u0435"
    ],
    "name:und_x_variant":[
        "Glebovo",
        "Frolovskoye",
        "\u0424\u0440\u043e\u043b\u043e\u0432\u0441\u043a\u043e\u0435"
    ],
    "wof:name":"Frolovskoye",
    "wof:placetype":"locality"
},
  "geometry": {"coordinates":[38.5191,54.76271],"type":"Point"}
}