{
  "type": "Feature",
  "properties": {
    "gn:admin1_code":"6",
    "gn:asciiname":"Grivy",
    "gn:country_code":"RU",
    "gn:dem":3,
    "gn:feature_class":"P",
    "gn:feature_code":"PPL",
    "gn:name":"Grivy",
    "gn:population":0,
    "gn:timezone":"Europe/Moscow",
    "iso:country":"RU",
    "name:rus_x_preferred":[
        "\u0413\u0440\u0438\u0432\u044b"
    ],
    "name:und_x_variant":[
        "Grivskaya",
        "Grivy"
    ],
    "wof:name":"Grivy",
    "wof:placetype":"locality"
},
  "geometry": {"coordinates":[41.0338,64.3417],"type":"Point"}
}