{
  "type": "Feature",
  "properties": {
    "gn:admin1_code":"6",
    "gn:asciiname":"Ust'-Nermanka",
    "gn:country_code":"RU",
    "gn:dem":38,
    "gn:feature_class":"P",
    "gn:feature_code":"PPL",
    "gn:name":"Ust\u2019-Nermanka",
    "gn:population":1,
    "gn:timezone":"Europe/Moscow",
    "iso:country":"RU",
    "name:rus_x_preferred":[
        "\u0423\u0441\u0442\u044c-\u041d\u0435\u0440\u043c\u0430\u043d\u043a\u0430"
    ],
    "name:und_x_variant":[
        "Ust\u2019-Nermanskaya",
        "Ust\u2019-Neromskaya",
        "Ust\u2019-Nermanka",
        "Yekaterinina"
    ],
    "wof:name":"Ust'-Nermanka",
    "wof:placetype":"locality",
    "wof:population":1
},
  "geometry": {"coordinates":[45.5292,65.1754],"type":"Point"}
}