{
  "type": "Feature",
  "properties": {
    "gn:admin1_code":"33",
    "gn:asciiname":"Zalozhena",
    "gn:country_code":"RU",
    "gn:dem":170,
    "gn:feature_class":"P",
    "gn:feature_code":"PPL",
    "gn:name":"Zalozhena",
    "gn:population":0,
    "gn:timezone":"Europe/Kirov",
    "iso:country":"RU",
    "name:rus_x_preferred":[
        "\u0417\u0430\u043b\u043e\u0436\u0435\u043d\u0430"
    ],
    "wof:name":"Zalozhena",
    "wof:placetype":"locality"
},
  "geometry": {"coordinates":[49.875,58.0499],"type":"Point"}
}