{
  "type": "Feature",
  "properties": {
    "gn:admin1_code":"6",
    "gn:asciiname":"Naumovskaya",
    "gn:country_code":"RU",
    "gn:dem":107,
    "gn:feature_class":"P",
    "gn:feature_code":"PPL",
    "gn:name":"Naumovskaya",
    "gn:population":0,
    "gn:timezone":"Europe/Moscow",
    "iso:country":"RU",
    "name:che_x_preferred":[
        "\u041d\u0430\u0443\u043c\u043e\u0432\u0441\u043a\u0438"
    ],
    "name:rus_x_preferred":[
        "\u041d\u0430\u0443\u043c\u043e\u0432\u0441\u043a\u0430\u044f"
    ],
    "wof:name":"Naumovskaya",
    "wof:placetype":"locality"
},
  "geometry": {"coordinates":[41.98333,62.36666999999999],"type":"Point"}
}