{
  "type": "Feature",
  "properties": {
    "gn:admin1_code":"85",
    "gn:asciiname":"Raduga",
    "gn:cc2":"RU",
    "gn:country_code":"RU",
    "gn:dem":130,
    "gn:feature_class":"P",
    "gn:feature_code":"PPL",
    "gn:name":"Raduga",
    "gn:population":0,
    "gn:timezone":"Europe/Moscow",
    "iso:country":"RU",
    "name:rus_x_preferred":[
        "\u0420\u0430\u0434\u0443\u0433\u0430"
    ],
    "name:und_x_variant":[
        "Durkovo",
        "Raduga",
        "\u0420\u0430\u0434\u0443\u0433\u0430"
    ],
    "wof:name":"Raduga",
    "wof:placetype":"locality"
},
  "geometry": {"coordinates":[37.91667,59.13333000000001],"type":"Point"}
}