{
  "type": "Feature",
  "properties": {
    "gn:admin1_code":"61",
    "gn:asciiname":"Kegichev",
    "gn:country_code":"RU",
    "gn:dem":24,
    "gn:feature_class":"P",
    "gn:feature_code":"PPL",
    "gn:name":"Kegich\u00ebv",
    "gn:population":0,
    "gn:timezone":"Europe/Moscow",
    "iso:country":"RU",
    "name:rus_x_preferred":[
        "\u041a\u0435\u0433\u0438\u0447\u0451\u0432"
    ],
    "name:und_x_variant":[
        "Kegich\u00ebv"
    ],
    "wof:name":"Kegichev",
    "wof:placetype":"locality"
},
  "geometry": {"coordinates":[41.61389000000001,47.23778],"type":"Point"}
}