{
  "type": "Feature",
  "properties": {
    "gn:admin1_code":"16",
    "gn:asciiname":"Toysi",
    "gn:country_code":"RU",
    "gn:dem":116,
    "gn:feature_class":"P",
    "gn:feature_code":"PPL",
    "gn:name":"Toysi",
    "gn:population":0,
    "gn:timezone":"Europe/Moscow",
    "iso:country":"RU",
    "name:rus_x_preferred":[
        "\u0422\u043e\u0439\u0441\u044b"
    ],
    "wof:name":"Toysi",
    "wof:placetype":"locality"
},
  "geometry": {"coordinates":[47.707,55.80501999999999],"type":"Point"}
}