{
  "type": "Feature",
  "properties": {
    "gn:admin1_code":"73.0",
    "gn:asciiname":"Krasnaya Zvezda",
    "gn:country_code":"RU",
    "gn:dem":185,
    "gn:feature_class":"P",
    "gn:feature_code":"PPL",
    "gn:name":"Krasnaya Zvezda",
    "gn:population":0,
    "gn:timezone":"Europe/Moscow",
    "iso:country":"RU",
    "wof:name":"Krasnaya Zvezda",
    "wof:placetype":"locality"
},
  "geometry": {"coordinates":[48.6466,54.84075],"type":"Point"}
}