{
  "type": "Feature",
  "properties": {
    "gn:admin1_code":"12.0",
    "gn:asciiname":"Tatay",
    "gn:country_code":"RU",
    "gn:dem":550,
    "gn:feature_class":"P",
    "gn:feature_code":"PPL",
    "gn:name":"Tatay",
    "gn:population":0,
    "gn:timezone":"Europe/Moscow",
    "iso:country":"RU",
    "name:che_x_preferred":[
        "Oc-Tata"
    ],
    "name:che_x_variant":[
        "Tatay-Khotar",
        "\u0422\u0430\u0442\u0430\u0439-\u041a\u0406\u043e\u0442\u0430\u0440",
        "\u041e\u0446-\u0422\u0430\u0442\u0430"
    ],
    "name:rus_x_preferred":[
        "\u0422\u0430\u0442\u0430\u0439"
    ],
    "name:und_x_variant":[
        "Ots-Tata",
        "Baytarki",
        "Tataj",
        "Tatay"
    ],
    "wof:name":"Tatay",
    "wof:placetype":"locality"
},
  "geometry": {"coordinates":[46.48532,43.03838],"type":"Point"}
}