{
  "type": "Feature",
  "properties": {
    "gn:admin1_code":"17",
    "gn:admin2_code":"Shamil'skiy Rayon",
    "gn:asciiname":"Genitsurib",
    "gn:country_code":"RU",
    "gn:dem":1752,
    "gn:feature_class":"P",
    "gn:feature_code":"PPL",
    "gn:name":"Genitsurib",
    "gn:population":0,
    "gn:timezone":"Europe/Moscow",
    "iso:country":"RU",
    "name:rus_x_preferred":[
        "\u0413\u0435\u043d\u0438\u0446\u0443\u0440\u0438\u0431"
    ],
    "name:und_x_variant":[
        "\u0413\u0435\u043d\u0438\u0446\u0443\u0440\u0438\u0431"
    ],
    "wof:name":"Genitsurib",
    "wof:placetype":"locality"
},
  "geometry": {"coordinates":[46.70379000000001,42.42423],"type":"Point"}
}