{
  "type": "Feature",
  "properties": {
    "gn:admin1_code":"8",
    "gn:asciiname":"Idyash",
    "gn:country_code":"RU",
    "gn:dem":220,
    "gn:feature_class":"P",
    "gn:feature_code":"PPL",
    "gn:name":"Idyash",
    "gn:population":0,
    "gn:timezone":"Asia/Yekaterinburg",
    "iso:country":"RU",
    "name:eng_x_preferred":[
        "Idyash"
    ],
    "name:nor_x_preferred":[
        "Idjasj"
    ],
    "name:rus_x_preferred":[
        "\u0418\u0434\u044f\u0448"
    ],
    "name:und_x_variant":[
        "Idyash-Bikberdina",
        "\u0418\u0434\u044f\u0448",
        "Idyash"
    ],
    "wof:name":"Idyash",
    "wof:placetype":"locality"
},
  "geometry": {"coordinates":[57.0012,51.7422],"type":"Point"}
}