{
  "type": "Feature",
  "properties": {
    "gn:admin1_code":"77",
    "gn:asciiname":"Fedoseyevo",
    "gn:country_code":"RU",
    "gn:dem":169,
    "gn:feature_class":"P",
    "gn:feature_code":"PPL",
    "gn:name":"Fedoseyevo",
    "gn:population":0,
    "gn:timezone":"Europe/Moscow",
    "iso:country":"RU",
    "name:rus_x_preferred":[
        "\u0424\u0435\u0434\u043e\u0441\u0435\u0435\u0432\u043e"
    ],
    "wof:name":"Fedoseyevo",
    "wof:placetype":"locality"
},
  "geometry": {"coordinates":[36.7374,58.4749],"type":"Point"}
}