{
  "type": "Feature",
  "properties": {
    "gn:admin1_code":"61.0",
    "gn:asciiname":"Donetskiy",
    "gn:country_code":"RU",
    "gn:dem":107,
    "gn:feature_class":"P",
    "gn:feature_code":"PPL",
    "gn:name":"Donetskiy",
    "gn:population":0,
    "gn:timezone":"Europe/Moscow",
    "iso:country":"RU",
    "name:rus_x_preferred":[
        "\u0414\u043e\u043d\u0435\u0446\u043a\u0438\u0439"
    ],
    "wof:name":"Donetskiy",
    "wof:placetype":"locality"
},
  "geometry": {"coordinates":[39.9838,48.7168],"type":"Point"}
}