{
  "type": "Feature",
  "properties": {
    "gn:admin1_code":"76",
    "gn:asciiname":"Romanovka",
    "gn:country_code":"RU",
    "gn:dem":208,
    "gn:feature_class":"P",
    "gn:feature_code":"PPL",
    "gn:name":"Romanovka",
    "gn:population":0,
    "gn:timezone":"Europe/Moscow",
    "iso:country":"RU",
    "name:ceb_x_preferred":[
        "Romanovka"
    ],
    "name:lav_x_preferred":[
        "Romanovka"
    ],
    "name:swe_x_preferred":[
        "Romanovka"
    ],
    "wof:name":"Romanovka",
    "wof:placetype":"locality"
},
  "geometry": {"coordinates":[37.73778,53.2917],"type":"Point"}
}