{
  "type": "Feature",
  "properties": {
    "gn:admin1_code":"85",
    "gn:asciiname":"Kizboy",
    "gn:country_code":"RU",
    "gn:dem":166,
    "gn:feature_class":"P",
    "gn:feature_code":"PPL",
    "gn:name":"Kizboy",
    "gn:population":0,
    "gn:timezone":"Europe/Moscow",
    "iso:country":"RU",
    "name:eng_x_preferred":[
        "Kizboy"
    ],
    "name:nor_x_preferred":[
        "Kizboj"
    ],
    "name:rus_x_preferred":[
        "\u041a\u0438\u0437\u0431\u043e\u0439"
    ],
    "name:und_x_variant":[
        "\u041a\u0438\u0437\u0431\u043e\u0439",
        "Kizboy"
    ],
    "wof:name":"Kizboy",
    "wof:placetype":"locality"
},
  "geometry": {"coordinates":[37.60108,59.6171],"type":"Point"}
}