{
  "type": "Feature",
  "properties": {
    "gn:admin1_code":"33.0",
    "gn:asciiname":"Zyablets",
    "gn:country_code":"RU",
    "gn:dem":131,
    "gn:feature_class":"P",
    "gn:feature_code":"PPL",
    "gn:name":"Zyablets",
    "gn:population":0,
    "gn:timezone":"Europe/Kirov",
    "iso:country":"RU",
    "name:rus_x_preferred":[
        "\u0417\u044f\u0431\u043b\u0435\u0446"
    ],
    "wof:name":"Zyablets",
    "wof:placetype":"locality"
},
  "geometry": {"coordinates":[49.54166,58.79214],"type":"Point"}
}