{
  "type": "Feature",
  "properties": {
    "gn:admin1_code":"7",
    "gn:asciiname":"Lenino",
    "gn:country_code":"RU",
    "gn:dem":-14,
    "gn:feature_class":"P",
    "gn:feature_code":"PPL",
    "gn:name":"Lenino",
    "gn:population":0,
    "gn:timezone":"Europe/Astrakhan",
    "iso:country":"RU",
    "name:eng_x_preferred":[
        "Lenino"
    ],
    "name:nor_x_preferred":[
        "Lenino"
    ],
    "name:rus_x_preferred":[
        "\u041b\u0435\u043d\u0438\u043d\u043e"
    ],
    "name:und_x_variant":[
        "\u041b\u0435\u043d\u0438\u043d\u043e",
        "Lenino"
    ],
    "wof:name":"Lenino",
    "wof:placetype":"locality"
},
  "geometry": {"coordinates":[47.33141,47.01385],"type":"Point"}
}