{
  "type": "Feature",
  "properties": {
    "gn:admin1_code":"70.0",
    "gn:asciiname":"Vinogradnyy",
    "gn:country_code":"RU",
    "gn:dem":334,
    "gn:feature_class":"P",
    "gn:feature_code":"PPL",
    "gn:name":"Vinogradnyy",
    "gn:population":0,
    "gn:timezone":"Europe/Moscow",
    "iso:country":"RU",
    "wof:name":"Vinogradnyy",
    "wof:placetype":"locality"
},
  "geometry": {"coordinates":[42.84556,44.34333],"type":"Point"}
}