{
  "type": "Feature",
  "properties": {
    "gn:admin1_code":"65",
    "gn:asciiname":"Zolotovskiy",
    "gn:country_code":"RU",
    "gn:dem":28,
    "gn:feature_class":"P",
    "gn:feature_code":"PPL",
    "gn:name":"Zolotovskiy",
    "gn:population":0,
    "gn:timezone":"Europe/Samara",
    "iso:country":"RU",
    "name:rus_x_preferred":[
        "\u0417\u043e\u043b\u043e\u0442\u043e\u0432\u0441\u043a\u0438\u0439"
    ],
    "wof:name":"Zolotovskiy",
    "wof:placetype":"locality"
},
  "geometry": {"coordinates":[48.9719,53.1298],"type":"Point"}
}