{
  "type": "Feature",
  "properties": {
    "gn:admin1_code":"47",
    "gn:asciiname":"Sen'kovo",
    "gn:country_code":"RU",
    "gn:dem":138,
    "gn:feature_class":"P",
    "gn:feature_code":"PPL",
    "gn:name":"Sen\u2019kovo",
    "gn:population":0,
    "gn:timezone":"Europe/Moscow",
    "iso:country":"RU",
    "name:rus_x_preferred":[
        "\u0421\u0435\u043d\u044c\u043a\u043e\u0432\u043e"
    ],
    "name:und_x_variant":[
        "Sen\u2019kovo",
        "\u0421\u0435\u043d\u044c\u043a\u043e\u0432\u043e"
    ],
    "wof:name":"Sen'kovo",
    "wof:placetype":"locality"
},
  "geometry": {"coordinates":[38.44819,54.84576],"type":"Point"}
}