{
  "type": "Feature",
  "properties": {
    "gn:admin1_code":"41",
    "gn:asciiname":"Vel'ye",
    "gn:country_code":"RU",
    "gn:dem":149,
    "gn:feature_class":"P",
    "gn:feature_code":"PPL",
    "gn:name":"Vel\u2019ye",
    "gn:population":0,
    "gn:timezone":"Europe/Moscow",
    "iso:country":"RU",
    "name:rus_x_preferred":[
        "\u0412\u0435\u043b\u044c\u0435"
    ],
    "name:und_x_variant":[
        "Vel\u2019ye"
    ],
    "wof:name":"Vel'ye",
    "wof:placetype":"locality"
},
  "geometry": {"coordinates":[34.9289,51.65],"type":"Point"}
}