{
  "type": "Feature",
  "properties": {
    "gn:admin1_code":"42",
    "gn:asciiname":"Shemenskiy Pogost",
    "gn:cc2":"RU",
    "gn:country_code":"RU",
    "gn:dem":111,
    "gn:feature_class":"P",
    "gn:feature_code":"PPL",
    "gn:name":"Shemenskiy Pogost",
    "gn:population":0,
    "gn:timezone":"Europe/Moscow",
    "iso:country":"RU",
    "name:rus_x_preferred":[
        "\u0428\u0435\u043c\u0435\u043d\u0441\u043a\u0438\u0439 \u041f\u043e\u0433\u043e\u0441\u0442"
    ],
    "name:und_x_variant":[
        "Pogost",
        "Shemenskiy Pogost",
        "\u0428\u0435\u043c\u0435\u043d\u0441\u043a\u0438\u0439 \u041f\u043e\u0433\u043e\u0441\u0442"
    ],
    "wof:name":"Shemenskiy Pogost",
    "wof:placetype":"locality"
},
  "geometry": {"coordinates":[34.45,60.88333000000001],"type":"Point"}
}