{
  "type": "Feature",
  "properties": {
    "gn:admin1_code":"81",
    "gn:asciiname":"Smorodino",
    "gn:country_code":"RU",
    "gn:dem":187,
    "gn:feature_class":"P",
    "gn:feature_code":"PPL",
    "gn:name":"Smorodino",
    "gn:population":0,
    "gn:timezone":"Europe/Ulyanovsk",
    "iso:country":"RU",
    "name:rus_x_preferred":[
        "\u0421\u043c\u043e\u0440\u043e\u0434\u0438\u043d\u043e"
    ],
    "wof:name":"Smorodino",
    "wof:placetype":"locality"
},
  "geometry": {"coordinates":[48.4052,53.9791],"type":"Point"}
}