{
  "type": "Feature",
  "properties": {
    "gn:admin1_code":"47",
    "gn:asciiname":"Rupasovo",
    "gn:country_code":"RU",
    "gn:dem":157,
    "gn:feature_class":"P",
    "gn:feature_code":"PPL",
    "gn:name":"Rupasovo",
    "gn:population":0,
    "gn:timezone":"Europe/Moscow",
    "iso:country":"RU",
    "name:rus_x_preferred":[
        "\u0420\u0443\u043f\u0430\u0441\u043e\u0432\u043e"
    ],
    "name:und_x_variant":[
        "\u0420\u0443\u043f\u0430\u0441\u043e\u0432\u043e"
    ],
    "wof:name":"Rupasovo",
    "wof:placetype":"locality"
},
  "geometry": {"coordinates":[37.75,55.93333000000001],"type":"Point"}
}