{
  "type": "Feature",
  "properties": {
    "gn:admin1_code":"90",
    "gn:asciiname":"Shushpanka",
    "gn:country_code":"RU",
    "gn:dem":177,
    "gn:feature_class":"P",
    "gn:feature_code":"PPL",
    "gn:name":"Shushpanka",
    "gn:population":0,
    "gn:timezone":"Asia/Yekaterinburg",
    "iso:country":"RU",
    "name:eng_x_preferred":[
        "Shushpanka"
    ],
    "name:nor_x_preferred":[
        "Sjusjpanka"
    ],
    "name:rus_x_preferred":[
        "\u0428\u0443\u0448\u043f\u0430\u043d\u043a\u0430"
    ],
    "name:und_x_variant":[
        "Glukhaya Shushpanka"
    ],
    "wof:name":"Shushpanka",
    "wof:placetype":"locality"
},
  "geometry": {"coordinates":[57.3228,58.2681],"type":"Point"}
}