{
  "type": "Feature",
  "properties": {
    "gn:admin1_code":"67.0",
    "gn:asciiname":"Solontsovo",
    "gn:country_code":"RU",
    "gn:dem":76,
    "gn:feature_class":"P",
    "gn:feature_code":"PPL",
    "gn:name":"Solontsovo",
    "gn:population":0,
    "gn:timezone":"Europe/Saratov",
    "iso:country":"RU",
    "name:und_x_variant":[
        "Zarya",
        "Solontsovo"
    ],
    "wof:name":"Solontsovo",
    "wof:placetype":"locality"
},
  "geometry": {"coordinates":[46.55928,51.2438],"type":"Point"}
}