{
  "type": "Feature",
  "properties": {
    "gn:admin1_code":"16",
    "gn:asciiname":"Tatarskiye Timyashi",
    "gn:country_code":"RU",
    "gn:dem":88,
    "gn:feature_class":"P",
    "gn:feature_code":"PPL",
    "gn:name":"Tatarskiye Timyashi",
    "gn:population":0,
    "gn:timezone":"Europe/Moscow",
    "iso:country":"RU",
    "name:rus_x_preferred":[
        "\u0422\u0430\u0442\u0430\u0440\u0441\u043a\u0438\u0435 \u0422\u0438\u043c\u044f\u0448\u0438"
    ],
    "wof:name":"Tatarskiye Timyashi",
    "wof:placetype":"locality"
},
  "geometry": {"coordinates":[47.82243,55.08193000000001],"type":"Point"}
}