{
  "type": "Feature",
  "properties": {
    "gn:admin1_code":"69",
    "gn:asciiname":"Kobylkino",
    "gn:country_code":"RU",
    "gn:dem":194,
    "gn:feature_class":"P",
    "gn:feature_code":"PPL",
    "gn:name":"Kobylkino",
    "gn:population":0,
    "gn:timezone":"Europe/Moscow",
    "iso:country":"RU",
    "name:eng_x_preferred":[
        "Kobylkino"
    ],
    "name:nor_x_preferred":[
        "Kobylkino"
    ],
    "name:rus_x_preferred":[
        "\u041a\u043e\u0431\u044b\u043b\u043a\u0438\u043d\u043e"
    ],
    "name:und_x_variant":[
        "Kobylkina",
        "Kobylkino"
    ],
    "wof:name":"Kobylkino",
    "wof:placetype":"locality"
},
  "geometry": {"coordinates":[32.02823,54.27316999999999],"type":"Point"}
}