{
  "type": "Feature",
  "properties": {
    "gn:admin1_code":"11.0",
    "gn:asciiname":"Ul'durga",
    "gn:country_code":"RU",
    "gn:dem":779,
    "gn:feature_class":"P",
    "gn:feature_code":"PPL",
    "gn:name":"Ul\u2019durga",
    "gn:population":0,
    "gn:timezone":"Asia/Irkutsk",
    "iso:country":"RU",
    "name:rus_x_preferred":[
        "\u0423\u043b\u044c\u0434\u0443\u0440\u0433\u0430"
    ],
    "name:und_x_variant":[
        "Ul\u2019durga"
    ],
    "wof:name":"Ul'durga",
    "wof:placetype":"locality"
},
  "geometry": {"coordinates":[110.539,52.22193],"type":"Point"}
}