{
  "type": "Feature",
  "properties": {
    "gn:admin1_code":"80.0",
    "gn:asciiname":"Begesh",
    "gn:country_code":"RU",
    "gn:dem":170,
    "gn:feature_class":"P",
    "gn:feature_code":"PPL",
    "gn:name":"Begesh",
    "gn:population":0,
    "gn:timezone":"Europe/Samara",
    "iso:country":"RU",
    "name:eng_x_preferred":[
        "Begesh"
    ],
    "name:nor_x_preferred":[
        "Begesj"
    ],
    "name:rus_x_preferred":[
        "\u0411\u0435\u0433\u0435\u0448"
    ],
    "wof:name":"Begesh",
    "wof:placetype":"locality"
},
  "geometry": {"coordinates":[53.23878000000001,57.12995],"type":"Point"}
}