{
  "type": "Feature",
  "properties": {
    "gn:admin1_code":"88",
    "gn:asciiname":"Sudoverf'",
    "gn:country_code":"RU",
    "gn:dem":110,
    "gn:feature_class":"P",
    "gn:feature_code":"PPL",
    "gn:name":"Sudoverf\u2019",
    "gn:population":2321,
    "gn:timezone":"Europe/Moscow",
    "iso:country":"RU",
    "name:rus_x_preferred":[
        "\u0421\u0443\u0434\u043e\u0432\u0435\u0440\u0444\u044c"
    ],
    "name:und_x_variant":[
        "Sudoverf\u2019"
    ],
    "wof:name":"Sudoverf'",
    "wof:placetype":"locality",
    "wof:population":2321
},
  "geometry": {"coordinates":[38.64175,58.11696],"type":"Point"}
}