{
  "type": "Feature",
  "properties": {
    "gn:admin1_code":"85.0",
    "gn:asciiname":"Golovinskoye",
    "gn:country_code":"RU",
    "gn:dem":172,
    "gn:feature_class":"P",
    "gn:feature_code":"PPL",
    "gn:name":"Golovinskoye",
    "gn:population":0,
    "gn:timezone":"Europe/Moscow",
    "iso:country":"RU",
    "name:rus_x_preferred":[
        "\u0413\u043e\u043b\u043e\u0432\u0438\u043d\u0441\u043a\u043e\u0435"
    ],
    "name:und_x_variant":[
        "\u0413\u043e\u043b\u043e\u0432\u0438\u043d\u0441\u043a\u043e\u0435"
    ],
    "wof:name":"Golovinskoye",
    "wof:placetype":"locality"
},
  "geometry": {"coordinates":[40.9882,58.62996],"type":"Point"}
}