{
  "type": "Feature",
  "properties": {
    "gn:admin1_code":"90",
    "gn:asciiname":"Brody",
    "gn:country_code":"RU",
    "gn:dem":194,
    "gn:feature_class":"P",
    "gn:feature_code":"PPL",
    "gn:name":"Brody",
    "gn:population":0,
    "gn:timezone":"Asia/Yekaterinburg",
    "iso:country":"RU",
    "name:rus_x_preferred":[
        "\u0411\u0440\u043e\u0434\u044b"
    ],
    "name:und_x_variant":[
        "\u0411\u0440\u043e\u0434\u044b"
    ],
    "wof:name":"Brody",
    "wof:placetype":"locality"
},
  "geometry": {"coordinates":[56.4607,57.9494],"type":"Point"}
}