{
  "type": "Feature",
  "properties": {
    "gn:admin1_code":"37",
    "gn:asciiname":"Lisitsino",
    "gn:country_code":"RU",
    "gn:dem":169,
    "gn:feature_class":"P",
    "gn:feature_code":"PPL",
    "gn:name":"Lisitsino",
    "gn:population":0,
    "gn:timezone":"Europe/Moscow",
    "iso:country":"RU",
    "name:eng_x_preferred":[
        "Lisitsino"
    ],
    "name:nor_x_preferred":[
        "Lisitsyno"
    ],
    "name:rus_x_preferred":[
        "\u041b\u0438\u0441\u0438\u0446\u044b\u043d\u043e"
    ],
    "name:rus_x_variant":[
        "\u041b\u0438\u0441\u0438\u0446\u0438\u043d\u043e"
    ],
    "name:und_x_variant":[
        "Lisitsyno",
        "Lisitsino",
        "\u041b\u0438\u0441\u0438\u0446\u0438\u043d\u043e"
    ],
    "wof:name":"Lisitsino",
    "wof:placetype":"locality"
},
  "geometry": {"coordinates":[44.54265,58.64484],"type":"Point"}
}