{
  "type": "Feature",
  "properties": {
    "gn:admin1_code":"45.0",
    "gn:asciiname":"Verkhnyaya Chucha",
    "gn:country_code":"RU",
    "gn:dem":148,
    "gn:feature_class":"P",
    "gn:feature_code":"PPL",
    "gn:name":"Verkhnyaya Chucha",
    "gn:population":0,
    "gn:timezone":"Europe/Moscow",
    "iso:country":"RU",
    "name:rus_x_preferred":[
        "\u0412\u0435\u0440\u0445\u043d\u044f\u044f \u0427\u0443\u0447\u0430"
    ],
    "wof:name":"Verkhnyaya Chucha",
    "wof:placetype":"locality"
},
  "geometry": {"coordinates":[48.70722,57.04806],"type":"Point"}
}