{
  "type": "Feature",
  "properties": {
    "gn:admin1_code":"78",
    "gn:asciiname":"Baybadulino",
    "gn:country_code":"RU",
    "gn:dem":135,
    "gn:feature_class":"P",
    "gn:feature_code":"PPL",
    "gn:name":"Baybadulino",
    "gn:population":0,
    "gn:timezone":"Asia/Yekaterinburg",
    "iso:country":"RU",
    "name:nor_x_preferred":[
        "Bajbadulino"
    ],
    "name:rus_x_preferred":[
        "\u0411\u0430\u0439\u0431\u0430\u0434\u0443\u043b\u0438\u043d\u043e"
    ],
    "wof:name":"Baybadulino",
    "wof:placetype":"locality"
},
  "geometry": {"coordinates":[67.48333000000001,56.05],"type":"Point"}
}