{
  "type": "Feature",
  "properties": {
    "gn:admin1_code":"61",
    "gn:asciiname":"Pereboynyy",
    "gn:country_code":"RU",
    "gn:dem":38,
    "gn:feature_class":"P",
    "gn:feature_code":"PPL",
    "gn:name":"Pereboynyy",
    "gn:population":0,
    "gn:timezone":"Europe/Moscow",
    "iso:country":"RU",
    "name:rus_x_preferred":[
        "\u041f\u0435\u0440\u0435\u0431\u043e\u0439\u043d\u044b\u0439"
    ],
    "name:und_x_variant":[
        "\u041f\u0435\u0440\u0435\u0431\u043e\u0439\u043d\u044b\u0439"
    ],
    "wof:name":"Pereboynyy",
    "wof:placetype":"locality"
},
  "geometry": {"coordinates":[40.53109,48.26559],"type":"Point"}
}