{
  "type": "Feature",
  "properties": {
    "gn:admin1_code":"32",
    "gn:asciiname":"Yuil'sk",
    "gn:country_code":"RU",
    "gn:dem":71,
    "gn:feature_class":"P",
    "gn:feature_code":"PPL",
    "gn:name":"Yuil\u2019sk",
    "gn:population":0,
    "gn:timezone":"Asia/Yekaterinburg",
    "iso:country":"RU",
    "name:eng_x_preferred":[
        "Yuil'sk"
    ],
    "name:nor_x_preferred":[
        "Juilsk"
    ],
    "name:rus_x_preferred":[
        "\u042e\u0438\u043b\u044c\u0441\u043a"
    ],
    "name:und_x_variant":[
        "Yuil\u2019sk"
    ],
    "wof:name":"Yuil'sk",
    "wof:placetype":"locality"
},
  "geometry": {"coordinates":[69.64404999999999,63.67794],"type":"Point"}
}