{
  "type": "Feature",
  "properties": {
    "gn:admin1_code":"16",
    "gn:asciiname":"Maloye Yangorchino",
    "gn:country_code":"RU",
    "gn:dem":165,
    "gn:feature_class":"P",
    "gn:feature_code":"PPL",
    "gn:name":"Maloye Yangorchino",
    "gn:population":0,
    "gn:timezone":"Europe/Moscow",
    "iso:country":"RU",
    "name:rus_x_preferred":[
        "\u041c\u0430\u043b\u043e\u0435 \u042f\u043d\u0433\u043e\u0440\u0447\u0438\u043d\u043e"
    ],
    "wof:name":"Maloye Yangorchino",
    "wof:placetype":"locality"
},
  "geometry": {"coordinates":[47.30323,55.90063000000001],"type":"Point"}
}