{
  "type": "Feature",
  "properties": {
    "gn:admin1_code":"71",
    "gn:asciiname":"Reft",
    "gn:country_code":"RU",
    "gn:dem":181,
    "gn:feature_class":"P",
    "gn:feature_code":"PPL",
    "gn:name":"Reft",
    "gn:population":0,
    "gn:timezone":"Asia/Yekaterinburg",
    "iso:country":"RU",
    "name:rus_x_preferred":[
        "\u0420\u0435\u0444\u0442"
    ],
    "wof:name":"Reft",
    "wof:placetype":"locality"
},
  "geometry": {"coordinates":[61.904,57.1543],"type":"Point"}
}