{
  "type": "Feature",
  "properties": {
    "gn:admin1_code":"20",
    "gn:asciiname":"Kozaki",
    "gn:country_code":"RU",
    "gn:dem":493,
    "gn:feature_class":"P",
    "gn:feature_code":"PPL",
    "gn:name":"Kozaki",
    "gn:population":0,
    "gn:timezone":"Asia/Irkutsk",
    "iso:country":"RU",
    "name:rus_x_preferred":[
        "\u041a\u043e\u0437\u0430\u043a\u0438"
    ],
    "wof:name":"Kozaki",
    "wof:placetype":"locality"
},
  "geometry": {"coordinates":[100.43333,54.15],"type":"Point"}
}