{
  "type": "Feature",
  "properties": {
    "gn:admin1_code":"17.0",
    "gn:asciiname":"Butkent",
    "gn:country_code":"RU",
    "gn:dem":783,
    "gn:feature_class":"P",
    "gn:feature_code":"PPL",
    "gn:name":"Butkent",
    "gn:population":0,
    "gn:timezone":"Europe/Moscow",
    "iso:country":"RU",
    "name:rus_x_preferred":[
        "\u0411\u0443\u0442\u043a\u0435\u043d\u0442"
    ],
    "name:und_x_variant":[
        "Butkend",
        "Butken",
        "Butkent"
    ],
    "wof:name":"Butkent",
    "wof:placetype":"locality"
},
  "geometry": {"coordinates":[48.17998,41.60008],"type":"Point"}
}