{
  "type": "Feature",
  "properties": {
    "gn:admin1_code":"70",
    "gn:asciiname":"Yugo-Vostochnyy",
    "gn:country_code":"RU",
    "gn:dem":115,
    "gn:feature_class":"P",
    "gn:feature_code":"PPL",
    "gn:name":"Yugo-Vostochnyy",
    "gn:population":0,
    "gn:timezone":"Europe/Moscow",
    "iso:country":"RU",
    "name:eng_x_preferred":[
        "Yugo-Vostochnyy"
    ],
    "name:nor_x_preferred":[
        "Jugo-Vostotsjnyj"
    ],
    "name:rus_x_preferred":[
        "\u042e\u0433\u043e-\u0412\u043e\u0441\u0442\u043e\u0447\u043d\u044b\u0439"
    ],
    "wof:name":"Yugo-Vostochnyy",
    "wof:placetype":"locality"
},
  "geometry": {"coordinates":[44.73333,44.22889],"type":"Point"}
}