{
  "type": "Feature",
  "properties": {
    "gn:admin1_code":"33",
    "gn:asciiname":"Pervomayskoye",
    "gn:country_code":"RU",
    "gn:dem":132,
    "gn:feature_class":"P",
    "gn:feature_code":"PPL",
    "gn:name":"Pervomayskoye",
    "gn:population":0,
    "gn:timezone":"Europe/Kirov",
    "iso:country":"RU",
    "name:eng_x_preferred":[
        "Pervomayskoye"
    ],
    "name:nor_x_preferred":[
        "Pervomajskoje"
    ],
    "name:rus_x_preferred":[
        "\u041f\u0435\u0440\u0432\u043e\u043c\u0430\u0439\u0441\u043a\u043e\u0435"
    ],
    "name:und_x_variant":[
        "Pervomayskiy",
        "\u041f\u0435\u0440\u0432\u043e\u043c\u0430\u0439\u0441\u043a\u043e\u0435",
        "Pervomayskoye"
    ],
    "wof:name":"Pervomayskoye",
    "wof:placetype":"locality"
},
  "geometry": {"coordinates":[47.56416,57.14034],"type":"Point"}
}