{
  "type": "Feature",
  "properties": {
    "gn:admin1_code":"56",
    "gn:asciiname":"Klevtsovo",
    "gn:country_code":"RU",
    "gn:dem":187,
    "gn:feature_class":"P",
    "gn:feature_code":"PPL",
    "gn:name":"Klevtsovo",
    "gn:population":0,
    "gn:timezone":"Europe/Moscow",
    "iso:country":"RU",
    "name:rus_x_preferred":[
        "\u041a\u043b\u0435\u0432\u0446\u043e\u0432\u043e"
    ],
    "wof:name":"Klevtsovo",
    "wof:placetype":"locality"
},
  "geometry": {"coordinates":[37.04445,52.25232000000001],"type":"Point"}
}