{
  "type": "Feature",
  "properties": {
    "gn:admin1_code":"37",
    "gn:asciiname":"Sivkovo",
    "gn:country_code":"RU",
    "gn:dem":120,
    "gn:feature_class":"P",
    "gn:feature_code":"PPL",
    "gn:name":"Sivkovo",
    "gn:population":0,
    "gn:timezone":"Europe/Moscow",
    "iso:country":"RU",
    "name:rus_x_preferred":[
        "\u0421\u0438\u0432\u043a\u043e\u0432\u043e"
    ],
    "name:und_x_variant":[
        "\u0421\u0438\u0432\u043a\u043e\u0432\u043e"
    ],
    "wof:name":"Sivkovo",
    "wof:placetype":"locality"
},
  "geometry": {"coordinates":[43.82746,58.05936],"type":"Point"}
}