{
  "type": "Feature",
  "properties": {
    "gn:admin1_code":"60",
    "gn:asciiname":"Krasnoye Soson'ye",
    "gn:country_code":"RU",
    "gn:dem":134,
    "gn:feature_class":"P",
    "gn:feature_code":"PPL",
    "gn:name":"Krasnoye Soson\u2019ye",
    "gn:population":0,
    "gn:timezone":"Europe/Moscow",
    "iso:country":"RU",
    "name:rus_x_preferred":[
        "\u041a\u0440\u0430\u0441\u043d\u043e\u0435 \u0421\u043e\u0441\u043e\u043d\u044c\u0435"
    ],
    "name:und_x_variant":[
        "Krasnoye Soson\u2019ye"
    ],
    "wof:name":"Krasnoye Soson'ye",
    "wof:placetype":"locality"
},
  "geometry": {"coordinates":[29.10083,57.41437],"type":"Point"}
}