{
  "type": "Feature",
  "properties": {
    "gn:admin1_code":"33",
    "gn:asciiname":"Savinovo",
    "gn:country_code":"RU",
    "gn:dem":108,
    "gn:feature_class":"P",
    "gn:feature_code":"PPL",
    "gn:name":"Savinovo",
    "gn:population":0,
    "gn:timezone":"Europe/Kirov",
    "iso:country":"RU",
    "name:eng_x_preferred":[
        "Savinovo"
    ],
    "name:nor_x_preferred":[
        "Savinovo"
    ],
    "name:rus_x_preferred":[
        "\u0421\u0430\u0432\u0438\u043d\u043e\u0432\u043e"
    ],
    "name:und_x_variant":[
        "\u0421\u0430\u0432\u0438\u043d\u043e\u0432\u043e",
        "Savinovo"
    ],
    "wof:name":"Savinovo",
    "wof:placetype":"locality"
},
  "geometry": {"coordinates":[50.11786,56.96183000000001],"type":"Point"}
}