{
  "type": "Feature",
  "properties": {
    "gn:admin1_code":"6.0",
    "gn:asciiname":"Voronovskaya",
    "gn:country_code":"RU",
    "gn:dem":70,
    "gn:feature_class":"P",
    "gn:feature_code":"PPL",
    "gn:name":"Voronovskaya",
    "gn:population":484,
    "gn:timezone":"Europe/Moscow",
    "iso:country":"RU",
    "name:che_x_preferred":[
        "\u0412\u043e\u0440\u043e\u043d\u043e\u0432\u0441\u043a\u0438"
    ],
    "name:eng_x_preferred":[
        "Voronovskaya"
    ],
    "name:ita_x_preferred":[
        "Voronovskaja"
    ],
    "name:rus_x_preferred":[
        "\u0412\u043e\u0440\u043e\u043d\u043e\u0432\u0441\u043a\u0430\u044f"
    ],
    "name:tat_x_preferred":[
        "\u0412\u043e\u0440\u043e\u043d\u043e\u0432\u0441\u043a\u0430\u044f"
    ],
    "name:tgk_x_preferred":[
        "\u0412\u043e\u0440\u043e\u043d\u043e\u0432\u0441\u043a\u0430\u044f"
    ],
    "wof:name":"Voronovskaya",
    "wof:placetype":"locality",
    "wof:population":484
},
  "geometry": {"coordinates":[42.11858,61.09247],"type":"Point"}
}