{
  "type": "Feature",
  "properties": {
    "gn:admin1_code":"9",
    "gn:asciiname":"Samarino",
    "gn:country_code":"RU",
    "gn:dem":163,
    "gn:feature_class":"P",
    "gn:feature_code":"PPL",
    "gn:name":"Samarino",
    "gn:population":0,
    "gn:timezone":"Europe/Moscow",
    "iso:country":"RU",
    "name:bak_x_preferred":[
        "\u0421\u0430\u043c\u0430\u0440\u0438\u043d"
    ],
    "name:che_x_preferred":[
        "\u0421\u0430\u043c\u0430\u0440\u0438\u043d\u043e"
    ],
    "name:hye_x_preferred":[
        "\u054d\u0561\u0574\u0561\u0580\u056b\u0576\u0578"
    ],
    "name:kaz_x_preferred":[
        "\u0421\u0430\u043c\u0430\u0440\u0438\u043d\u043e"
    ],
    "name:kir_x_preferred":[
        "\u0421\u0430\u043c\u0430\u0440\u0438\u043d\u043e"
    ],
    "name:rus_x_preferred":[
        "\u0421\u0430\u043c\u0430\u0440\u0438\u043d\u043e"
    ],
    "name:tat_x_preferred":[
        "\u0421\u0430\u043c\u0430\u0440\u0438\u043d\u043e"
    ],
    "wof:name":"Samarino",
    "wof:placetype":"locality"
},
  "geometry": {"coordinates":[35.9753,51.1227],"type":"Point"}
}