{
  "type": "Feature",
  "properties": {
    "gn:admin1_code":"17.0",
    "gn:asciiname":"Leninkent",
    "gn:country_code":"RU",
    "gn:dem":267,
    "gn:feature_class":"P",
    "gn:feature_code":"PPL",
    "gn:name":"Leninkent",
    "gn:population":0,
    "gn:timezone":"Europe/Moscow",
    "iso:country":"RU",
    "name:eng_x_preferred":[
        "Leninkent"
    ],
    "name:nor_x_preferred":[
        "Leninkent"
    ],
    "name:rus_x_preferred":[
        "\u041b\u0435\u043d\u0438\u043d\u043a\u0435\u043d\u0442"
    ],
    "wof:name":"Leninkent",
    "wof:placetype":"locality"
},
  "geometry": {"coordinates":[47.75425,42.48318],"type":"Point"}
}