{
  "type": "Feature",
  "properties": {
    "gn:admin1_code":"62",
    "gn:asciiname":"Shumash'",
    "gn:country_code":"RU",
    "gn:dem":103,
    "gn:feature_class":"P",
    "gn:feature_code":"PPL",
    "gn:name":"Shumash\u2019",
    "gn:population":0,
    "gn:timezone":"Europe/Moscow",
    "iso:country":"RU",
    "name:eng_x_preferred":[
        "Shumash'"
    ],
    "name:nor_x_preferred":[
        "Sjumasj"
    ],
    "name:rus_x_preferred":[
        "\u0428\u0443\u043c\u0430\u0448\u044c"
    ],
    "name:und_x_variant":[
        "Shumoshch\u2019",
        "Shumash\u2019"
    ],
    "wof:name":"Shumash'",
    "wof:placetype":"locality"
},
  "geometry": {"coordinates":[39.81558,54.66773000000001],"type":"Point"}
}