{
  "type": "Feature",
  "properties": {
    "gn:admin1_code":"17.0",
    "gn:asciiname":"Abay",
    "gn:country_code":"RU",
    "gn:dem":438,
    "gn:feature_class":"P",
    "gn:feature_code":"PPL",
    "gn:name":"Abay",
    "gn:population":0,
    "gn:timezone":"Europe/Moscow",
    "iso:country":"RU",
    "name:nor_x_preferred":[
        "Abaj"
    ],
    "name:rus_x_preferred":[
        "\u0410\u0431\u0430\u0439"
    ],
    "wof:name":"Abay",
    "wof:placetype":"locality"
},
  "geometry": {"coordinates":[47.66667,42.51667],"type":"Point"}
}