{
  "type": "Feature",
  "properties": {
    "gn:admin1_code":"52",
    "gn:asciiname":"Obluch'ye",
    "gn:country_code":"RU",
    "gn:dem":25,
    "gn:feature_class":"P",
    "gn:feature_code":"PPL",
    "gn:name":"Obluch\u2019ye",
    "gn:population":0,
    "gn:timezone":"Europe/Moscow",
    "iso:country":"RU",
    "name:rus_x_preferred":[
        "\u041e\u0431\u043b\u0443\u0447\u044c\u0435"
    ],
    "name:und_x_variant":[
        "Obluch\u2019ye"
    ],
    "wof:name":"Obluch'ye",
    "wof:placetype":"locality"
},
  "geometry": {"coordinates":[32.18166,59.30161],"type":"Point"}
}