{
  "type": "Feature",
  "properties": {
    "gn:admin1_code":"41",
    "gn:asciiname":"Pena",
    "gn:cc2":"RU",
    "gn:country_code":"RU",
    "gn:dem":160,
    "gn:feature_class":"P",
    "gn:feature_code":"PPL",
    "gn:name":"Pena",
    "gn:population":0,
    "gn:timezone":"Europe/Moscow",
    "iso:country":"RU",
    "name:ast_x_preferred":[
        "Pena"
    ],
    "name:cat_x_preferred":[
        "Pena"
    ],
    "name:ceb_x_preferred":[
        "Pena"
    ],
    "name:ces_x_preferred":[
        "Pena"
    ],
    "name:che_x_preferred":[
        "\u042f\u0437\u043e\u043b\u0433"
    ],
    "name:deu_x_preferred":[
        "Pena"
    ],
    "name:fin_x_preferred":[
        "Pena"
    ],
    "name:fra_x_preferred":[
        "Pena"
    ],
    "name:glg_x_preferred":[
        "Pena"
    ],
    "name:ita_x_preferred":[
        "Pena"
    ],
    "name:nld_x_preferred":[
        "Pena"
    ],
    "name:por_x_preferred":[
        "Pena"
    ],
    "name:rus_x_preferred":[
        "\u041f\u0435\u043d\u0430"
    ],
    "name:slk_x_preferred":[
        "Pena"
    ],
    "name:spa_x_preferred":[
        "Pena"
    ],
    "name:srp_x_preferred":[
        "\u041f\u0435\u043d\u0430"
    ],
    "name:swe_x_preferred":[
        "Pena"
    ],
    "name:ukr_x_preferred":[
        "\u041f\u0435\u043d\u0430"
    ],
    "name:und_x_variant":[
        "Peny",
        "Pena",
        "\u041f\u0435\u043d\u0430"
    ],
    "wof:name":"Pena",
    "wof:placetype":"locality"
},
  "geometry": {"coordinates":[35.48917,51.60722],"type":"Point"}
}