{
  "type": "Feature",
  "properties": {
    "gn:admin1_code":"69",
    "gn:asciiname":"Ladenka",
    "gn:country_code":"RU",
    "gn:dem":189,
    "gn:feature_class":"P",
    "gn:feature_code":"PPL",
    "gn:name":"Ladenka",
    "gn:population":0,
    "gn:timezone":"Europe/Moscow",
    "iso:country":"RU",
    "name:rus_x_preferred":[
        "\u041b\u0430\u0434\u0435\u043d\u043a\u0430"
    ],
    "wof:name":"Ladenka",
    "wof:placetype":"locality"
},
  "geometry": {"coordinates":[34.70135,55.74728],"type":"Point"}
}