{
  "type": "Feature",
  "properties": {
    "gn:admin1_code":"73",
    "gn:asciiname":"Kzyl-Yar",
    "gn:country_code":"RU",
    "gn:dem":116,
    "gn:feature_class":"P",
    "gn:feature_code":"PPL",
    "gn:name":"Kzyl-Yar",
    "gn:population":0,
    "gn:timezone":"Europe/Moscow",
    "iso:country":"RU",
    "name:rus_x_preferred":[
        "\u041a\u0437\u044b\u043b-\u042f\u0440"
    ],
    "name:und_x_variant":[
        "\u041a\u0437\u044b\u043b-\u042f\u0440"
    ],
    "wof:name":"Kzyl-Yar",
    "wof:placetype":"locality"
},
  "geometry": {"coordinates":[51.6426,55.4076],"type":"Point"}
}