{
  "type": "Feature",
  "properties": {
    "gn:admin1_code":"69",
    "gn:asciiname":"Gorlovo",
    "gn:country_code":"RU",
    "gn:dem":228,
    "gn:feature_class":"P",
    "gn:feature_code":"PPL",
    "gn:name":"Gorlovo",
    "gn:population":0,
    "gn:timezone":"Europe/Moscow",
    "iso:country":"RU",
    "wof:name":"Gorlovo",
    "wof:placetype":"locality"
},
  "geometry": {"coordinates":[34.24891,55.40163],"type":"Point"}
}