{
  "type": "Feature",
  "properties": {
    "gn:admin1_code":"20",
    "gn:asciiname":"Barkhatova",
    "gn:country_code":"RU",
    "gn:dem":450,
    "gn:feature_class":"P",
    "gn:feature_code":"PPL",
    "gn:name":"Barkhatova",
    "gn:population":0,
    "gn:timezone":"Asia/Irkutsk",
    "iso:country":"RU",
    "name:eng_x_preferred":[
        "Barkhatova"
    ],
    "name:nor_x_preferred":[
        "Barkhatova"
    ],
    "name:rus_x_preferred":[
        "\u0411\u0430\u0440\u0445\u0430\u0442\u043e\u0432\u0430"
    ],
    "name:und_x_variant":[
        "Barkhatovo"
    ],
    "wof:name":"Barkhatova",
    "wof:placetype":"locality"
},
  "geometry": {"coordinates":[103.35194,53.00833000000001],"type":"Point"}
}