{
  "type": "Feature",
  "properties": {
    "gn:admin1_code":"25.0",
    "gn:asciiname":"Bayevo",
    "gn:country_code":"RU",
    "gn:dem":171,
    "gn:feature_class":"P",
    "gn:feature_code":"PPL",
    "gn:name":"Bayevo",
    "gn:population":0,
    "gn:timezone":"Europe/Moscow",
    "iso:country":"RU",
    "name:nor_x_preferred":[
        "Bajevo"
    ],
    "name:rus_x_preferred":[
        "\u0411\u0430\u0435\u0432\u043e"
    ],
    "name:und_x_variant":[
        "Boyevo",
        "Bayevo"
    ],
    "wof:name":"Bayevo",
    "wof:placetype":"locality"
},
  "geometry": {"coordinates":[36.81667,55.05],"type":"Point"}
}