{
  "type": "Feature",
  "properties": {
    "gn:admin1_code":"33",
    "gn:asciiname":"Maradykovo",
    "gn:country_code":"RU",
    "gn:dem":124,
    "gn:feature_class":"P",
    "gn:feature_code":"PPL",
    "gn:name":"Maradykovo",
    "gn:population":0,
    "gn:timezone":"Europe/Kirov",
    "iso:country":"RU",
    "name:rus_x_preferred":[
        "\u041c\u0430\u0440\u0430\u0434\u044b\u043a\u043e\u0432\u043e"
    ],
    "wof:name":"Maradykovo",
    "wof:placetype":"locality"
},
  "geometry": {"coordinates":[48.70848,58.33843],"type":"Point"}
}