{
  "type": "Feature",
  "properties": {
    "gn:admin1_code":"73",
    "gn:asciiname":"Yasashno-Baryshevo",
    "gn:country_code":"RU",
    "gn:dem":66,
    "gn:feature_class":"P",
    "gn:feature_code":"PPL",
    "gn:name":"Yasashno-Baryshevo",
    "gn:population":0,
    "gn:timezone":"Europe/Moscow",
    "iso:country":"RU",
    "name:eng_x_preferred":[
        "Yasashno-Baryshevo"
    ],
    "name:nor_x_preferred":[
        "Bolsjije Kokuzy"
    ],
    "name:rus_x_preferred":[
        "\u0411\u043e\u043b\u044c\u0448\u0438\u0435 \u041a\u043e\u043a\u0443\u0437\u044b"
    ],
    "name:und_x_variant":[
        "Bol\u2019shiye Kokuzy",
        "Yasash-Baryshevo",
        "Yasashno-Baryshevo"
    ],
    "wof:name":"Yasashno-Baryshevo",
    "wof:placetype":"locality"
},
  "geometry": {"coordinates":[48.70359000000001,55.31049],"type":"Point"}
}