{
  "type": "Feature",
  "properties": {
    "gn:admin1_code":"1.0",
    "gn:asciiname":"Kruglyak",
    "gn:country_code":"RU",
    "gn:dem":744,
    "gn:feature_class":"P",
    "gn:feature_code":"PPL",
    "gn:name":"Kruglyak",
    "gn:population":0,
    "gn:timezone":"Europe/Moscow",
    "iso:country":"RU",
    "wof:name":"Kruglyak",
    "wof:placetype":"locality"
},
  "geometry": {"coordinates":[40.29917,44.29139],"type":"Point"}
}