{
  "type": "Feature",
  "properties": {
    "gn:admin1_code":"83.0",
    "gn:asciiname":"Ryzhkovo",
    "gn:country_code":"RU",
    "gn:dem":129,
    "gn:feature_class":"P",
    "gn:feature_code":"PPL",
    "gn:name":"Ryzhkovo",
    "gn:population":0,
    "gn:timezone":"Europe/Moscow",
    "iso:country":"RU",
    "name:rus_x_preferred":[
        "\u0420\u044b\u0436\u043a\u043e\u0432\u043e"
    ],
    "wof:name":"Ryzhkovo",
    "wof:placetype":"locality"
},
  "geometry": {"coordinates":[40.05516,56.15678000000001],"type":"Point"}
}