{
  "type": "Feature",
  "properties": {
    "gn:admin1_code":"91",
    "gn:asciiname":"Novoselovo",
    "gn:country_code":"RU",
    "gn:dem":89,
    "gn:feature_class":"P",
    "gn:feature_code":"PPL",
    "gn:name":"Novos\u00eblovo",
    "gn:population":0,
    "gn:timezone":"Asia/Krasnoyarsk",
    "iso:country":"RU",
    "name:eng_x_preferred":[
        "Novos\u00eblovo"
    ],
    "name:nor_x_preferred":[
        "Novoselovo"
    ],
    "name:rus_x_preferred":[
        "\u041d\u043e\u0432\u043e\u0441\u0435\u043b\u043e\u0432\u043e"
    ],
    "name:rus_x_variant":[
        "\u041d\u043e\u0432\u043e\u0441\u0451\u043b\u043e\u0432\u043e"
    ],
    "name:und_x_variant":[
        "Novos\u00eblovo"
    ],
    "wof:name":"Novoselovo",
    "wof:placetype":"locality"
},
  "geometry": {"coordinates":[88.71666999999999,62.61666999999999],"type":"Point"}
}