{
  "type": "Feature",
  "properties": {
    "gn:admin1_code":"42.0",
    "gn:asciiname":"Bol'shoye Konovalovo",
    "gn:country_code":"RU",
    "gn:dem":54,
    "gn:feature_class":"P",
    "gn:feature_code":"PPL",
    "gn:name":"Bol\u2019shoye Konovalovo",
    "gn:population":0,
    "gn:timezone":"Europe/Moscow",
    "iso:country":"RU",
    "name:fin_x_preferred":[
        "H\u00e4nnisi"
    ],
    "name:nor_x_preferred":[
        "Bolsjoje Konovalovo"
    ],
    "name:rus_x_preferred":[
        "\u0411\u043e\u043b\u044c\u0448\u043e\u0435 \u041a\u043e\u043d\u043e\u0432\u0430\u043b\u043e\u0432\u043e"
    ],
    "name:und_x_variant":[
        "Bol\u2019shoye Konovalovo"
    ],
    "wof:name":"Bol'shoye Konovalovo",
    "wof:placetype":"locality"
},
  "geometry": {"coordinates":[29.67173,59.88197],"type":"Point"}
}