{
  "type": "Feature",
  "properties": {
    "gn:admin1_code":"51",
    "gn:asciiname":"Vostochnoye-Yegorovskoye",
    "gn:country_code":"RU",
    "gn:dem":131,
    "gn:feature_class":"P",
    "gn:feature_code":"PPL",
    "gn:name":"Vostochnoye-Yegorovskoye",
    "gn:population":0,
    "gn:timezone":"Europe/Moscow",
    "iso:country":"RU",
    "name:rus_x_preferred":[
        "\u0412\u043e\u0441\u0442\u043e\u0447\u043d\u043e\u0435-\u0415\u0433\u043e\u0440\u043e\u0432\u0441\u043a\u043e\u0435"
    ],
    "wof:name":"Vostochnoye-Yegorovskoye",
    "wof:placetype":"locality"
},
  "geometry": {"coordinates":[46.5841,57.4503],"type":"Point"}
}