{
  "type": "Feature",
  "properties": {
    "gn:admin1_code":"49",
    "gn:asciiname":"Retinskoye",
    "gn:country_code":"RU",
    "gn:dem":1,
    "gn:feature_class":"P",
    "gn:feature_code":"PPL",
    "gn:name":"Retinskoye",
    "gn:population":2,
    "gn:timezone":"Europe/Moscow",
    "iso:country":"RU",
    "name:che_x_preferred":[
        "\u0420\u0435\u0442\u0438\u043d\u0441\u043a\u0438"
    ],
    "name:eng_x_preferred":[
        "Retinskoye"
    ],
    "name:hye_x_preferred":[
        "\u054c\u0565\u057f\u056b\u0576\u057d\u056f\u0578\u0565"
    ],
    "name:nor_x_preferred":[
        "Retinskoje"
    ],
    "name:rus_x_preferred":[
        "\u0420\u0435\u0442\u0438\u043d\u0441\u043a\u043e\u0435"
    ],
    "wof:name":"Retinskoye",
    "wof:placetype":"locality",
    "wof:population":2
},
  "geometry": {"coordinates":[33.37344,69.11277],"type":"Point"}
}