{
  "type": "Feature",
  "properties": {
    "gn:admin1_code":"86.0",
    "gn:asciiname":"Krasnaya Zarya",
    "gn:country_code":"RU",
    "gn:dem":127,
    "gn:feature_class":"P",
    "gn:feature_code":"PPL",
    "gn:name":"Krasnaya Zarya",
    "gn:population":0,
    "gn:timezone":"Europe/Moscow",
    "iso:country":"RU",
    "name:bel_x_preferred":[
        "\u041a\u0440\u0430\u0441\u043d\u0430\u044f \u0417\u0430\u0440\u0430"
    ],
    "name:deu_x_preferred":[
        "Krasnaja Sarja"
    ],
    "name:hye_x_preferred":[
        "\u053f\u0580\u0561\u057d\u0576\u0561\u0575\u0561 \u0536\u0561\u0580\u0575\u0561"
    ],
    "name:rus_x_preferred":[
        "\u041a\u0440\u0430\u0441\u043d\u0430\u044f \u0417\u0430\u0440\u044f"
    ],
    "name:spa_x_preferred":[
        "Kr\u00e1snaya Zari\u00e1"
    ],
    "name:ukr_x_preferred":[
        "\u041a\u0440\u0430\u0441\u043d\u0430 \u0417\u043e\u0440\u044f"
    ],
    "name:und_x_variant":[
        "\u041a\u0440\u0430\u0441\u043d\u0430\u044f \u0417\u0430\u0440\u044f"
    ],
    "wof:name":"Krasnaya Zarya",
    "wof:placetype":"locality"
},
  "geometry": {"coordinates":[40.28917,51.26389],"type":"Point"}
}