{
  "type": "Feature",
  "properties": {
    "gn:admin1_code":"52",
    "gn:asciiname":"Gostevshchina",
    "gn:country_code":"RU",
    "gn:dem":115,
    "gn:feature_class":"P",
    "gn:feature_code":"PPL",
    "gn:name":"Gostevshchina",
    "gn:population":0,
    "gn:timezone":"Europe/Moscow",
    "iso:country":"RU",
    "name:rus_x_preferred":[
        "\u0413\u043e\u0441\u0442\u0435\u0432\u0449\u0438\u043d\u0430"
    ],
    "wof:name":"Gostevshchina",
    "wof:placetype":"locality"
},
  "geometry": {"coordinates":[32.73369,57.98523],"type":"Point"}
}