{
  "type": "Feature",
  "properties": {
    "gn:admin1_code":"37",
    "gn:asciiname":"Malaya Svyatitsa",
    "gn:country_code":"RU",
    "gn:dem":163,
    "gn:feature_class":"P",
    "gn:feature_code":"PPL",
    "gn:name":"Malaya Svyatitsa",
    "gn:population":0,
    "gn:timezone":"Europe/Moscow",
    "iso:country":"RU",
    "name:rus_x_preferred":[
        "\u041c\u0430\u043b\u0430\u044f \u0421\u0432\u044f\u0442\u0438\u0446\u0430"
    ],
    "wof:name":"Malaya Svyatitsa",
    "wof:placetype":"locality"
},
  "geometry": {"coordinates":[42.6937,58.8157],"type":"Point"}
}