{
  "type": "Feature",
  "properties": {
    "gn:admin1_code":"47",
    "gn:asciiname":"Stepanchikovo",
    "gn:country_code":"RU",
    "gn:dem":151,
    "gn:feature_class":"P",
    "gn:feature_code":"PPL",
    "gn:name":"Stepanchikovo",
    "gn:population":0,
    "gn:timezone":"Europe/Moscow",
    "iso:country":"RU",
    "name:rus_x_preferred":[
        "\u0421\u0442\u0435\u043f\u0430\u043d\u0447\u0438\u043a\u043e\u0432\u043e"
    ],
    "wof:name":"Stepanchikovo",
    "wof:placetype":"locality"
},
  "geometry": {"coordinates":[37.85967,55.36125],"type":"Point"}
}