{
  "type": "Feature",
  "properties": {
    "gn:admin1_code":"33",
    "gn:asciiname":"Shitovy",
    "gn:country_code":"RU",
    "gn:dem":144,
    "gn:feature_class":"P",
    "gn:feature_code":"PPL",
    "gn:name":"Shitovy",
    "gn:population":0,
    "gn:timezone":"Europe/Kirov",
    "iso:country":"RU",
    "name:eng_x_preferred":[
        "Shitovy"
    ],
    "name:nor_x_preferred":[
        "Sjitovo"
    ],
    "name:rus_x_preferred":[
        "\u0428\u0438\u0442\u043e\u0432\u043e"
    ],
    "name:rus_x_variant":[
        "\u0428\u0438\u0442\u043e\u0432\u044b"
    ],
    "name:und_x_variant":[
        "Shitovo"
    ],
    "wof:name":"Shitovy",
    "wof:placetype":"locality"
},
  "geometry": {"coordinates":[50.88722,58.89278],"type":"Point"}
}