{
  "type": "Feature",
  "properties": {
    "gn:admin1_code":"60",
    "gn:asciiname":"Ilovo",
    "gn:country_code":"RU",
    "gn:dem":126,
    "gn:feature_class":"P",
    "gn:feature_code":"PPL",
    "gn:name":"Ilovo",
    "gn:population":0,
    "gn:timezone":"Europe/Moscow",
    "iso:country":"RU",
    "name:rus_x_preferred":[
        "\u0418\u043b\u043e\u0432\u043e"
    ],
    "wof:name":"Ilovo",
    "wof:placetype":"locality"
},
  "geometry": {"coordinates":[28.4518,56.2727],"type":"Point"}
}