{
  "type": "Feature",
  "properties": {
    "gn:admin1_code":"23",
    "gn:asciiname":"Shatrovo",
    "gn:country_code":"RU",
    "gn:dem":20,
    "gn:feature_class":"P",
    "gn:feature_code":"PPL",
    "gn:name":"Shatrovo",
    "gn:population":0,
    "gn:timezone":"Europe/Kaliningrad",
    "iso:country":"RU",
    "name:rus_x_preferred":[
        "\u0428\u0430\u0442\u0440\u043e\u0432\u043e"
    ],
    "wof:name":"Shatrovo",
    "wof:placetype":"locality"
},
  "geometry": {"coordinates":[20.51616,54.8483],"type":"Point"}
}