{
  "type": "Feature",
  "properties": {
    "gn:admin1_code":"76",
    "gn:asciiname":"Il'inka Pervaya",
    "gn:country_code":"RU",
    "gn:dem":200,
    "gn:feature_class":"P",
    "gn:feature_code":"PPL",
    "gn:name":"Il\u2019inka Pervaya",
    "gn:population":0,
    "gn:timezone":"Europe/Moscow",
    "iso:country":"RU",
    "name:rus_x_preferred":[
        "\u0418\u043b\u044c\u0438\u043d\u043a\u0430 \u041f\u0435\u0440\u0432\u0430\u044f"
    ],
    "name:und_x_variant":[
        "Il\u2019inka Pervaya",
        "Il\u2019inskoye",
        "Il\u2019inka"
    ],
    "wof:name":"Il'inka Pervaya",
    "wof:placetype":"locality"
},
  "geometry": {"coordinates":[38.19278,54.06151],"type":"Point"}
}