{
  "type": "Feature",
  "properties": {
    "gn:admin1_code":"42.0",
    "gn:asciiname":"Pudomyagi",
    "gn:country_code":"RU",
    "gn:dem":73,
    "gn:feature_class":"P",
    "gn:feature_code":"PPL",
    "gn:name":"Pudomyagi",
    "gn:population":0,
    "gn:timezone":"Europe/Moscow",
    "iso:country":"RU",
    "name:fin_x_preferred":[
        "Patam\u00e4ki"
    ],
    "name:rus_x_preferred":[
        "\u041f\u0443\u0434\u043e\u043c\u044f\u0433\u0438"
    ],
    "name:und_x_variant":[
        "\u041f\u0443\u0434\u043e\u043c\u044f\u0433\u0438"
    ],
    "wof:name":"Pudomyagi",
    "wof:placetype":"locality"
},
  "geometry": {"coordinates":[30.32778,59.605],"type":"Point"}
}