{
  "type": "Feature",
  "properties": {
    "gn:admin1_code":"77",
    "gn:asciiname":"Lyakhovo",
    "gn:country_code":"RU",
    "gn:dem":205,
    "gn:feature_class":"P",
    "gn:feature_code":"PPL",
    "gn:name":"Lyakhovo",
    "gn:population":0,
    "gn:timezone":"Europe/Moscow",
    "iso:country":"RU",
    "name:rus_x_preferred":[
        "\u041b\u044f\u0445\u043e\u0432\u043e"
    ],
    "name:und_x_variant":[
        "\u041b\u044f\u0445\u043e\u0432\u043e"
    ],
    "wof:name":"Lyakhovo",
    "wof:placetype":"locality"
},
  "geometry": {"coordinates":[34.90111,56.97556],"type":"Point"}
}