{
  "type": "Feature",
  "properties": {
    "gn:admin1_code":"45.0",
    "gn:asciiname":"Bol'shoy Lombenur",
    "gn:country_code":"RU",
    "gn:dem":102,
    "gn:feature_class":"P",
    "gn:feature_code":"PPL",
    "gn:name":"Bol\u2019shoy Lombenur",
    "gn:population":0,
    "gn:timezone":"Europe/Moscow",
    "iso:country":"RU",
    "name:rus_x_preferred":[
        "\u0411\u043e\u043b\u044c\u0448\u043e\u0439 \u041b\u043e\u043c\u0431\u0435\u043d\u0443\u0440"
    ],
    "name:und_x_variant":[
        "Bol\u2019shoy Lombenur"
    ],
    "wof:name":"Bol'shoy Lombenur",
    "wof:placetype":"locality"
},
  "geometry": {"coordinates":[46.83366,56.84378],"type":"Point"}
}