{
  "type": "Feature",
  "properties": {
    "gn:admin1_code":"72",
    "gn:asciiname":"Malaya Fedorovka",
    "gn:country_code":"RU",
    "gn:dem":141,
    "gn:feature_class":"P",
    "gn:feature_code":"PPL",
    "gn:name":"Malaya F\u00ebdorovka",
    "gn:population":0,
    "gn:timezone":"Europe/Moscow",
    "iso:country":"RU",
    "name:rus_x_preferred":[
        "\u041c\u0430\u043b\u0430\u044f \u0424\u0451\u0434\u043e\u0440\u043e\u0432\u043a\u0430"
    ],
    "name:und_x_variant":[
        "Malaya F\u00ebdorovka",
        "Malaya Federovka"
    ],
    "wof:name":"Malaya Fedorovka",
    "wof:placetype":"locality"
},
  "geometry": {"coordinates":[40.8642,53.0262],"type":"Point"}
}