{
  "type": "Feature",
  "properties": {
    "gn:admin1_code":"24",
    "gn:asciiname":"Krasnosel'skiy",
    "gn:country_code":"RU",
    "gn:dem":8,
    "gn:feature_class":"P",
    "gn:feature_code":"PPL",
    "gn:name":"Krasnosel\u2019skiy",
    "gn:population":0,
    "gn:timezone":"Europe/Moscow",
    "iso:country":"RU",
    "name:rus_x_preferred":[
        "\u041a\u0440\u0430\u0441\u043d\u043e\u0441\u0435\u043b\u044c\u0441\u043a\u0438\u0439"
    ],
    "name:und_x_variant":[
        "Krasnosel\u2019skiy",
        "\u041a\u0440\u0430\u0441\u043d\u043e\u0441\u0435\u043b\u044c\u0441\u043a\u0438\u0439"
    ],
    "wof:name":"Krasnosel'skiy",
    "wof:placetype":"locality"
},
  "geometry": {"coordinates":[45.43037,47.85258],"type":"Point"}
}