{
  "type": "Feature",
  "properties": {
    "gn:admin1_code":"60",
    "gn:asciiname":"Vorsuli",
    "gn:country_code":"RU",
    "gn:dem":93,
    "gn:feature_class":"P",
    "gn:feature_code":"PPL",
    "gn:name":"Vorsuli",
    "gn:population":0,
    "gn:timezone":"Europe/Moscow",
    "iso:country":"RU",
    "name:rus_x_preferred":[
        "\u0412\u043e\u0440\u0441\u0443\u043b\u0438"
    ],
    "wof:name":"Vorsuli",
    "wof:placetype":"locality"
},
  "geometry": {"coordinates":[28.49136,57.01544000000001],"type":"Point"}
}