{
  "type": "Feature",
  "properties": {
    "gn:admin1_code":"77",
    "gn:asciiname":"Dubenka",
    "gn:country_code":"RU",
    "gn:dem":230,
    "gn:feature_class":"P",
    "gn:feature_code":"PPL",
    "gn:name":"Dub\u00ebnka",
    "gn:population":0,
    "gn:timezone":"Europe/Moscow",
    "iso:country":"RU",
    "name:rus_x_preferred":[
        "\u0414\u0443\u0431\u0435\u043d\u043a\u0430"
    ],
    "name:und_x_variant":[
        "Dub\u00ebnka"
    ],
    "wof:name":"Dubenka",
    "wof:placetype":"locality"
},
  "geometry": {"coordinates":[33.25519,57.25547],"type":"Point"}
}