{
  "type": "Feature",
  "properties": {
    "gn:admin1_code":"34",
    "gn:asciiname":"Tarkoita",
    "gn:cc2":"RU",
    "gn:country_code":"RU",
    "gn:dem":170,
    "gn:feature_class":"P",
    "gn:feature_code":"PPL",
    "gn:name":"Tarkoita",
    "gn:population":0,
    "gn:timezone":"Europe/Moscow",
    "iso:country":"RU",
    "name:und_x_variant":[
        "Pestraya",
        "Tarkoita"
    ],
    "wof:name":"Tarkoita",
    "wof:placetype":"locality"
},
  "geometry": {"coordinates":[54.43333000000001,64.95],"type":"Point"}
}