{
  "type": "Feature",
  "properties": {
    "gn:admin1_code":"76",
    "gn:asciiname":"Botvin'yevo",
    "gn:country_code":"RU",
    "gn:dem":208,
    "gn:feature_class":"P",
    "gn:feature_code":"PPL",
    "gn:name":"Botvin\u2019yevo",
    "gn:population":0,
    "gn:timezone":"Europe/Moscow",
    "iso:country":"RU",
    "name:rus_x_preferred":[
        "\u0411\u043e\u0442\u0432\u0438\u043d\u044c\u0435\u0432\u043e"
    ],
    "name:und_x_variant":[
        "Botvin\u2019yevo"
    ],
    "wof:name":"Botvin'yevo",
    "wof:placetype":"locality"
},
  "geometry": {"coordinates":[37.0375,53.71694],"type":"Point"}
}