{
  "type": "Feature",
  "properties": {
    "gn:admin1_code":"85",
    "gn:asciiname":"Chabino",
    "gn:country_code":"RU",
    "gn:dem":175,
    "gn:feature_class":"P",
    "gn:feature_code":"PPL",
    "gn:name":"Chabino",
    "gn:population":0,
    "gn:timezone":"Europe/Moscow",
    "iso:country":"RU",
    "name:rus_x_preferred":[
        "\u0427\u0430\u0431\u0438\u043d\u043e"
    ],
    "name:und_x_variant":[
        "\u0427\u0430\u0431\u0438\u043d\u043e"
    ],
    "wof:name":"Chabino",
    "wof:placetype":"locality"
},
  "geometry": {"coordinates":[38.35742,58.9705],"type":"Point"}
}