{
  "type": "Feature",
  "properties": {
    "gn:admin1_code":"28.0",
    "gn:asciiname":"Gachkino",
    "gn:cc2":"RU",
    "gn:country_code":"RU",
    "gn:dem":56,
    "gn:feature_class":"P",
    "gn:feature_code":"PPL",
    "gn:name":"Gachkino",
    "gn:population":0,
    "gn:timezone":"Europe/Moscow",
    "iso:country":"RU",
    "name:rus_x_preferred":[
        "\u0413\u0430\u0447\u043a\u0438\u043d\u043e"
    ],
    "name:und_x_variant":[
        "Gachkina",
        "Gachkino",
        "\u0413\u0430\u0447\u043a\u0438\u043d\u043e"
    ],
    "wof:name":"Gachkino",
    "wof:placetype":"locality"
},
  "geometry": {"coordinates":[33.71667,62.61666999999999],"type":"Point"}
}