{
  "type": "Feature",
  "properties": {
    "gn:admin1_code":"60",
    "gn:asciiname":"Samokhvalovo",
    "gn:country_code":"RU",
    "gn:dem":208,
    "gn:feature_class":"P",
    "gn:feature_code":"PPL",
    "gn:name":"Samokhvalovo",
    "gn:population":0,
    "gn:timezone":"Europe/Moscow",
    "iso:country":"RU",
    "name:rus_x_preferred":[
        "\u0421\u0430\u043c\u043e\u0445\u0432\u0430\u043b\u043e\u0432\u043e"
    ],
    "wof:name":"Samokhvalovo",
    "wof:placetype":"locality"
},
  "geometry": {"coordinates":[29.8528,56.6029],"type":"Point"}
}