{
  "type": "Feature",
  "properties": {
    "gn:admin1_code":"11",
    "gn:asciiname":"Tokuren",
    "gn:country_code":"RU",
    "gn:dem":710,
    "gn:feature_class":"P",
    "gn:feature_code":"PPL",
    "gn:name":"Tokuren",
    "gn:population":0,
    "gn:timezone":"Asia/Irkutsk",
    "iso:country":"RU",
    "wof:name":"Tokuren",
    "wof:placetype":"locality"
},
  "geometry": {"coordinates":[102.53333000000001,51.75],"type":"Point"}
}