{
  "type": "Feature",
  "properties": {
    "gn:admin1_code":"85",
    "gn:asciiname":"Kolkach",
    "gn:country_code":"RU",
    "gn:dem":159,
    "gn:feature_class":"P",
    "gn:feature_code":"PPL",
    "gn:name":"Kolkach",
    "gn:population":0,
    "gn:timezone":"Europe/Moscow",
    "iso:country":"RU",
    "name:eng_x_preferred":[
        "Kolkan"
    ],
    "name:nor_x_preferred":[
        "Kolkatsj"
    ],
    "name:rus_x_preferred":[
        "\u041a\u043e\u043b\u043a\u0430\u0447"
    ],
    "name:und_x_variant":[
        "Kolkach"
    ],
    "wof:name":"Kolkach",
    "wof:placetype":"locality"
},
  "geometry": {"coordinates":[38.8792,59.6879],"type":"Point"}
}