{
  "type": "Feature",
  "properties": {
    "gn:admin1_code":"86",
    "gn:asciiname":"Mikhinskiy",
    "gn:country_code":"RU",
    "gn:dem":186,
    "gn:feature_class":"P",
    "gn:feature_code":"PPL",
    "gn:name":"Mikhinskiy",
    "gn:population":0,
    "gn:timezone":"Europe/Moscow",
    "iso:country":"RU",
    "name:rus_x_preferred":[
        "\u041c\u0438\u0445\u0438\u043d\u0441\u043a\u0438\u0439"
    ],
    "name:und_x_variant":[
        "Mikhino",
        "Mikhinskiy"
    ],
    "wof:name":"Mikhinskiy",
    "wof:placetype":"locality"
},
  "geometry": {"coordinates":[40.7021,50.99800000000001],"type":"Point"}
}