{
  "type": "Feature",
  "properties": {
    "gn:admin1_code":"80.0",
    "gn:asciiname":"Denisenki",
    "gn:country_code":"RU",
    "gn:dem":281,
    "gn:feature_class":"P",
    "gn:feature_code":"PPL",
    "gn:name":"Denisenki",
    "gn:population":0,
    "gn:timezone":"Europe/Samara",
    "iso:country":"RU",
    "name:rus_x_preferred":[
        "\u0414\u0435\u043d\u0438\u0441\u0435\u043d\u043a\u0438"
    ],
    "wof:name":"Denisenki",
    "wof:placetype":"locality"
},
  "geometry": {"coordinates":[53.3781,58.233],"type":"Point"}
}