{
  "type": "Feature",
  "properties": {
    "gn:admin1_code":"77",
    "gn:asciiname":"Vasyukovo",
    "gn:country_code":"RU",
    "gn:dem":242,
    "gn:feature_class":"P",
    "gn:feature_code":"PPLL",
    "gn:name":"Vasyukovo",
    "gn:population":0,
    "gn:timezone":"Europe/Moscow",
    "iso:country":"RU",
    "name:rus_x_preferred":[
        "\u0412\u0430\u0441\u044e\u043a\u043e\u0432\u043e"
    ],
    "name:und_x_variant":[
        "\u0412\u0430\u0441\u044e\u043a\u043e\u0432\u043e"
    ],
    "wof:name":"Vasyukovo",
    "wof:placetype":"locality"
},
  "geometry": {"coordinates":[31.53158,56.80844],"type":"Point"}
}