{
  "type": "Feature",
  "properties": {
    "gn:admin1_code":"84",
    "gn:asciiname":"Orly",
    "gn:country_code":"RU",
    "gn:dem":84,
    "gn:feature_class":"P",
    "gn:feature_code":"PPL",
    "gn:name":"Orly",
    "gn:population":0,
    "gn:timezone":"Europe/Volgograd",
    "iso:country":"RU",
    "name:rus_x_preferred":[
        "\u041e\u0440\u043b\u044b"
    ],
    "name:und_x_variant":[
        "Orlovskiy",
        "Orly"
    ],
    "wof:name":"Orly",
    "wof:placetype":"locality"
},
  "geometry": {"coordinates":[43.7208,50.2208],"type":"Point"}
}