{
  "type": "Feature",
  "properties": {
    "gn:admin1_code":"60.0",
    "gn:asciiname":"Chernevo",
    "gn:country_code":"RU",
    "gn:dem":86,
    "gn:feature_class":"P",
    "gn:feature_code":"PPL",
    "gn:name":"Chern\u00ebvo",
    "gn:population":0,
    "gn:timezone":"Europe/Moscow",
    "iso:country":"RU",
    "name:rus_x_preferred":[
        "\u0427\u0435\u0440\u043d\u0451\u0432\u043e"
    ],
    "name:und_x_variant":[
        "Cherneva",
        "Chern\u00ebvo"
    ],
    "wof:name":"Chernevo",
    "wof:placetype":"locality"
},
  "geometry": {"coordinates":[30.37568,57.61082],"type":"Point"}
}