{
  "type": "Feature",
  "properties": {
    "gn:admin1_code":"33",
    "gn:asciiname":"Zhukovlyane",
    "gn:country_code":"RU",
    "gn:dem":133,
    "gn:feature_class":"P",
    "gn:feature_code":"PPL",
    "gn:name":"Zhukovlyane",
    "gn:population":0,
    "gn:timezone":"Europe/Kirov",
    "iso:country":"RU",
    "name:rus_x_preferred":[
        "\u0416\u0443\u043a\u043e\u0432\u043b\u044f\u043d\u0435"
    ],
    "wof:name":"Zhukovlyane",
    "wof:placetype":"locality"
},
  "geometry": {"coordinates":[48.0134,58.2991],"type":"Point"}
}