{
  "type": "Feature",
  "properties": {
    "gn:admin1_code":"43",
    "gn:asciiname":"Luk'yanovka",
    "gn:country_code":"RU",
    "gn:dem":230,
    "gn:feature_class":"P",
    "gn:feature_code":"PPL",
    "gn:name":"Luk\u2019yanovka",
    "gn:population":0,
    "gn:timezone":"Europe/Moscow",
    "iso:country":"RU",
    "name:rus_x_preferred":[
        "\u041b\u0443\u043a\u044c\u044f\u043d\u043e\u0432\u043a\u0430"
    ],
    "name:und_x_variant":[
        "Babarykino",
        "Luk\u2019yanovka"
    ],
    "wof:name":"Luk'yanovka",
    "wof:placetype":"locality"
},
  "geometry": {"coordinates":[38.25151,52.96335],"type":"Point"}
}