{
  "type": "Feature",
  "properties": {
    "gn:admin1_code":"88",
    "gn:asciiname":"Nikolo-Korma",
    "gn:country_code":"RU",
    "gn:dem":117,
    "gn:feature_class":"P",
    "gn:feature_code":"PPL",
    "gn:name":"Nikolo-Korma",
    "gn:population":76,
    "gn:timezone":"Europe/Moscow",
    "iso:country":"RU",
    "name:eng_x_preferred":[
        "Nikolo-Korma"
    ],
    "name:nor_x_preferred":[
        "Nikola-Korma"
    ],
    "name:rus_x_preferred":[
        "\u041d\u0438\u043a\u043e\u043b\u0430-\u041a\u043e\u0440\u043c\u0430"
    ],
    "name:rus_x_variant":[
        "\u041d\u0438\u043a\u043e\u043b\u043e-\u041a\u043e\u0440\u043c\u0430"
    ],
    "name:und_x_variant":[
        "Nikola-Korma",
        "Nikol\u2019skaya",
        "Nikolo-Korma",
        "\u041d\u0438\u043a\u043e\u043b\u043e-\u041a\u043e\u0440\u043c\u0430"
    ],
    "wof:name":"Nikolo-Korma",
    "wof:placetype":"locality",
    "wof:population":76
},
  "geometry": {"coordinates":[38.54371,57.89828000000001],"type":"Point"}
}