{
  "type": "Feature",
  "properties": {
    "gn:admin1_code":"63",
    "gn:asciiname":"Yaroslavskiy",
    "gn:country_code":"RU",
    "gn:dem":200,
    "gn:feature_class":"P",
    "gn:feature_code":"PPL",
    "gn:name":"Yaroslavskiy",
    "gn:population":0,
    "gn:timezone":"Asia/Yakutsk",
    "iso:country":"RU",
    "name:eng_x_preferred":[
        "Yaroslavskiy"
    ],
    "name:nor_x_preferred":[
        "Jaroslavskij"
    ],
    "name:rus_x_preferred":[
        "\u042f\u0440\u043e\u0441\u043b\u0430\u0432\u0441\u043a\u0438\u0439"
    ],
    "wof:name":"Yaroslavskiy",
    "wof:placetype":"locality"
},
  "geometry": {"coordinates":[113.93311,60.15524],"type":"Point"}
}