{
  "type": "Feature",
  "properties": {
    "gn:admin1_code":"05",
    "gn:asciiname":"Khomyakovskiy",
    "gn:country_code":"RU",
    "gn:dem":149,
    "gn:feature_class":"P",
    "gn:feature_code":"PPL",
    "gn:name":"Khomyakovskiy",
    "gn:population":0,
    "gn:timezone":"Asia/Yakutsk",
    "iso:country":"RU",
    "name:rus_x_preferred":[
        "\u0425\u043e\u043c\u044f\u043a\u043e\u0432\u0441\u043a\u0438\u0439"
    ],
    "name:und_x_variant":[
        "\u0425\u043e\u043c\u044f\u043a\u043e\u0432\u0441\u043a\u0438\u0439"
    ],
    "wof:name":"Khomyakovskiy",
    "wof:placetype":"locality"
},
  "geometry": {"coordinates":[128.78333000000001,49.86667],"type":"Point"}
}