{
  "type": "Feature",
  "properties": {
    "gn:admin1_code":"65.0",
    "gn:asciiname":"Flera",
    "gn:country_code":"RU",
    "gn:dem":103,
    "gn:feature_class":"P",
    "gn:feature_code":"PPL",
    "gn:name":"Fl\u00ebra",
    "gn:population":0,
    "gn:timezone":"Europe/Samara",
    "iso:country":"RU",
    "name:rus_x_preferred":[
        "\u0424\u043b\u0451\u0440\u0430"
    ],
    "name:und_x_variant":[
        "Fl\u00ebra",
        "\u0424\u043b\u0451\u0440\u0430"
    ],
    "wof:name":"Flera",
    "wof:placetype":"locality"
},
  "geometry": {"coordinates":[50.96667,52.03333],"type":"Point"}
}