{
  "type": "Feature",
  "properties": {
    "gn:admin1_code":"54",
    "gn:asciiname":"Bekmes",
    "gn:country_code":"RU",
    "gn:dem":135,
    "gn:feature_class":"P",
    "gn:feature_code":"PPL",
    "gn:name":"Bekmes",
    "gn:population":0,
    "gn:timezone":"Asia/Omsk",
    "iso:country":"RU",
    "name:nor_x_preferred":[
        "Bekmes"
    ],
    "name:rus_x_preferred":[
        "\u0411\u0435\u043a\u043c\u0435\u0441"
    ],
    "wof:name":"Bekmes",
    "wof:placetype":"locality"
},
  "geometry": {"coordinates":[74.96666999999999,56.65],"type":"Point"}
}