{
  "type": "Feature",
  "properties": {
    "gn:admin1_code":"50",
    "gn:asciiname":"Nes'",
    "gn:country_code":"RU",
    "gn:dem":17,
    "gn:feature_class":"P",
    "gn:feature_code":"PPL",
    "gn:name":"Nes\u2019",
    "gn:population":0,
    "gn:timezone":"Europe/Moscow",
    "iso:country":"RU",
    "name:rus_x_preferred":[
        "\u041d\u0435\u0441\u044c"
    ],
    "name:und_x_variant":[
        "Derevnya Nes\u2019",
        "Nez",
        "Nes\u2019"
    ],
    "wof:name":"Nes'",
    "wof:placetype":"locality"
},
  "geometry": {"coordinates":[44.68094,66.60039999999999],"type":"Point"}
}