{
  "type": "Feature",
  "properties": {
    "gn:admin1_code":"51",
    "gn:asciiname":"Skorodumovo",
    "gn:country_code":"RU",
    "gn:dem":122,
    "gn:feature_class":"P",
    "gn:feature_code":"PPL",
    "gn:name":"Skorodumovo",
    "gn:population":0,
    "gn:timezone":"Europe/Moscow",
    "iso:country":"RU",
    "name:rus_x_preferred":[
        "\u0421\u043a\u043e\u0440\u043e\u0434\u0443\u043c\u043e\u0432\u043e"
    ],
    "wof:name":"Skorodumovo",
    "wof:placetype":"locality"
},
  "geometry": {"coordinates":[46.4364,57.7405],"type":"Point"}
}