{
  "type": "Feature",
  "properties": {
    "gn:admin1_code":"28",
    "gn:asciiname":"Mishin Sel'ga",
    "gn:country_code":"RU",
    "gn:dem":105,
    "gn:feature_class":"P",
    "gn:feature_code":"PPL",
    "gn:name":"Mishin Sel\u2019ga",
    "gn:population":0,
    "gn:timezone":"Europe/Moscow",
    "iso:country":"RU",
    "name:fin_x_preferred":[
        "Misinselk\u00e4"
    ],
    "name:rus_x_preferred":[
        "\u041c\u0438\u0448\u0438\u043d \u0421\u0435\u043b\u044c\u0433\u0430"
    ],
    "name:und_x_variant":[
        "Mishin Sel\u2019ga"
    ],
    "wof:name":"Mishin Sel'ga",
    "wof:placetype":"locality"
},
  "geometry": {"coordinates":[33.15305,61.72221],"type":"Point"}
}