{
  "type": "Feature",
  "properties": {
    "gn:admin1_code":"16.0",
    "gn:asciiname":"Chubayevo",
    "gn:country_code":"RU",
    "gn:dem":147,
    "gn:feature_class":"P",
    "gn:feature_code":"PPL",
    "gn:name":"Chubayevo",
    "gn:population":0,
    "gn:timezone":"Europe/Moscow",
    "iso:country":"RU",
    "name:eng_x_preferred":[
        "Chubayevo"
    ],
    "name:nor_x_preferred":[
        "Tsjubajevo"
    ],
    "name:rus_x_preferred":[
        "\u0427\u0443\u0431\u0430\u0435\u0432\u043e"
    ],
    "wof:name":"Chubayevo",
    "wof:placetype":"locality"
},
  "geometry": {"coordinates":[47.87107,55.67135],"type":"Point"}
}