{
  "type": "Feature",
  "properties": {
    "gn:admin1_code":"62.0",
    "gn:asciiname":"Bychek",
    "gn:cc2":"RU",
    "gn:country_code":"RU",
    "gn:dem":159,
    "gn:feature_class":"P",
    "gn:feature_code":"PPL",
    "gn:name":"Bych\u00ebk",
    "gn:population":0,
    "gn:timezone":"Europe/Moscow",
    "iso:country":"RU",
    "name:rus_x_preferred":[
        "\u0411\u044b\u0447\u0451\u043a"
    ],
    "name:und_x_variant":[
        "Bychki",
        "Bych\u00ebk",
        "\u0411\u044b\u0447\u0451\u043a"
    ],
    "wof:name":"Bychek",
    "wof:placetype":"locality"
},
  "geometry": {"coordinates":[39.36667,54.11666999999999],"type":"Point"}
}