{
  "type": "Feature",
  "properties": {
    "gn:admin1_code":"61",
    "gn:asciiname":"Ryabukhin",
    "gn:country_code":"RU",
    "gn:dem":67,
    "gn:feature_class":"P",
    "gn:feature_code":"PPL",
    "gn:name":"Ryabukhin",
    "gn:population":0,
    "gn:timezone":"Europe/Moscow",
    "iso:country":"RU",
    "name:rus_x_preferred":[
        "\u0420\u044f\u0431\u0443\u0445\u0438\u043d"
    ],
    "wof:name":"Ryabukhin",
    "wof:placetype":"locality"
},
  "geometry": {"coordinates":[42.2102,48.89497],"type":"Point"}
}