{
  "type": "Feature",
  "properties": {
    "gn:admin1_code":"69",
    "gn:asciiname":"Novo Sokol'niki",
    "gn:country_code":"RU",
    "gn:dem":212,
    "gn:feature_class":"P",
    "gn:feature_code":"PPL",
    "gn:name":"Novo Sokol\u2019niki",
    "gn:population":0,
    "gn:timezone":"Europe/Moscow",
    "iso:country":"RU",
    "wof:name":"Novo Sokol'niki",
    "wof:placetype":"locality"
},
  "geometry": {"coordinates":[33.09472,54.4775],"type":"Point"}
}