{
  "type": "Feature",
  "properties": {
    "gn:admin1_code":"63",
    "gn:asciiname":"Labadze",
    "gn:cc2":"RU",
    "gn:country_code":"RU",
    "gn:dem":415,
    "gn:feature_class":"P",
    "gn:feature_code":"PPL",
    "gn:name":"Labadze",
    "gn:population":0,
    "gn:timezone":"Asia/Yakutsk",
    "iso:country":"RU",
    "name:rus_x_preferred":[
        "\u041b\u0430\u0431\u0430\u0434\u0437\u0435"
    ],
    "name:und_x_variant":[
        "Zimov\u2019ye Labadze",
        "Labadze",
        "\u041b\u0430\u0431\u0430\u0434\u0437\u0435"
    ],
    "wof:name":"Labadze",
    "wof:placetype":"locality"
},
  "geometry": {"coordinates":[124.01667,59.11666999999999],"type":"Point"}
}