{
  "type": "Feature",
  "properties": {
    "gn:admin1_code":"25",
    "gn:asciiname":"Pesochnya",
    "gn:country_code":"RU",
    "gn:dem":226,
    "gn:feature_class":"P",
    "gn:feature_code":"PPL",
    "gn:name":"Pesochnya",
    "gn:population":0,
    "gn:timezone":"Europe/Moscow",
    "iso:country":"RU",
    "name:rus_x_preferred":[
        "\u041f\u0435\u0441\u043e\u0447\u043d\u044f"
    ],
    "name:und_x_variant":[
        "\u041f\u0435\u0441\u043e\u0447\u043d\u044f"
    ],
    "wof:name":"Pesochnya",
    "wof:placetype":"locality"
},
  "geometry": {"coordinates":[35.08389,54.32833],"type":"Point"}
}