{
  "type": "Feature",
  "properties": {
    "gn:admin1_code":"28.0",
    "gn:asciiname":"El'mitozero",
    "gn:country_code":"RU",
    "gn:dem":109,
    "gn:feature_class":"P",
    "gn:feature_code":"PPL",
    "gn:name":"El\u2019mitozero",
    "gn:population":0,
    "gn:timezone":"Europe/Moscow",
    "iso:country":"RU",
    "name:fin_x_preferred":[
        "Elmitj\u00e4rvi"
    ],
    "name:rus_x_preferred":[
        "\u042d\u043b\u044c\u043c\u0438\u0442\u043e\u0437\u0435\u0440\u043e"
    ],
    "name:und_x_variant":[
        "El\u2019mitozero",
        "\u042d\u043b\u044c\u043c\u0438\u0442\u043e\u0437\u0435\u0440\u043e"
    ],
    "wof:name":"El'mitozero",
    "wof:placetype":"locality"
},
  "geometry": {"coordinates":[33.21667,62.08333],"type":"Point"}
}