{
  "type": "Feature",
  "properties": {
    "gn:country":"RU",
    "gn:fcode":"PPL",
    "gn:population":3928,
    "iso:country":"RU",
    "name:ara_x_preferred":[
        "\u0644\u0627\u062f\u0648\u0634\u0643\u064a\u0646"
    ],
    "name:azb_x_preferred":[
        "\u0644\u0627\u062f\u0648\u0634\u06a9\u06cc\u0646"
    ],
    "name:aze_x_preferred":[
        "Ladu\u015fkin"
    ],
    "name:bel_x_preferred":[
        "\u041b\u0430\u0434\u0443\u0448\u043a\u0456\u043d"
    ],
    "name:bul_x_preferred":[
        "\u041b\u0430\u0434\u0443\u0448\u043a\u0438\u043d"
    ],
    "name:ceb_x_preferred":[
        "Ladushkin"
    ],
    "name:chv_x_preferred":[
        "\u041b\u0430\u0434\u0443\u0448\u043a\u0438\u043d"
    ],
    "name:deu_x_preferred":[
        "Ludwigsort"
    ],
    "name:deu_x_variant":[
        "Laduschkin"
    ],
    "name:diq_x_preferred":[
        "Ladushkin"
    ],
    "name:eng_x_preferred":[
        "Ladushkin"
    ],
    "name:epo_x_preferred":[
        "Ladu\u015dkin"
    ],
    "name:est_x_preferred":[
        "Ladu\u0161kin"
    ],
    "name:fas_x_preferred":[
        "\u0644\u0627\u062f\u0648\u0634\u06a9\u06cc\u0646"
    ],
    "name:fin_x_preferred":[
        "Ladu\u0161kin"
    ],
    "name:fra_x_preferred":[
        "Ladouchkine"
    ],
    "name:hsb_x_preferred":[
        "Ladu\u0161kin"
    ],
    "name:hun_x_preferred":[
        "Laduskin"
    ],
    "name:ita_x_preferred":[
        "Ladu\u0161kin"
    ],
    "name:jpn_x_preferred":[
        "\u30e9\u30fc\u30c9\u30a5\u30b7\u30ad\u30f3"
    ],
    "name:kor_x_preferred":[
        "\ub77c\ub450\uc2dc\ud0a8"
    ],
    "name:lav_x_preferred":[
        "Ladu\u0161kina"
    ],
    "name:lit_x_historical":[
        "Liudvigsortas"
    ],
    "name:lit_x_preferred":[
        "Liudvigsortas"
    ],
    "name:lit_x_variant":[
        "Ladu\u0161kinas"
    ],
    "name:nld_x_preferred":[
        "Ladoesjkin"
    ],
    "name:nno_x_preferred":[
        "Ladusjkin"
    ],
    "name:nob_x_preferred":[
        "Ladusjkin"
    ],
    "name:nor_x_preferred":[
        "Ladusjkin"
    ],
    "name:pol_x_preferred":[
        "\u0141aduszkin"
    ],
    "name:rus_x_preferred":[
        "\u041b\u0430\u0434\u0443\u0448\u043a\u0438\u043d"
    ],
    "name:spa_x_preferred":[
        "Ladushkin"
    ],
    "name:srp_x_preferred":[
        "\u041b\u0430\u0434\u0443\u0448\u043a\u0438\u043d"
    ],
    "name:tat_x_preferred":[
        "\u041b\u0430\u0434\u0443\u0448\u043a\u0438\u043d"
    ],
    "name:tgk_x_preferred":[
        "\u041b\u0430\u0434\u0443\u0448\u043a\u0438\u043d"
    ],
    "name:tgl_x_preferred":[
        "Ladushkin"
    ],
    "name:tur_x_preferred":[
        "Ladu\u015fkin"
    ],
    "name:ukr_x_preferred":[
        "\u041b\u0430\u0434\u0443\u0448\u043a\u0456\u043d"
    ],
    "name:und_x_variant":[
        "Lyudvigsort"
    ],
    "name:vep_x_preferred":[
        "Ladu\u0161kin"
    ],
    "name:war_x_preferred":[
        "Ladushkin"
    ],
    "name:zho_x_preferred":[
        "\u62c9\u675c\u4ec0\u91d1"
    ],
    "qs:name":"Ladushkin",
    "qs:name_adm0":"Russia",
    "qs:name_adm1":"Kaliningrad Oblast",
    "qs:photos_9k":1,
    "qs:photos_9r":1,
    "qs:photos_all":10,
    "qs:photos_sr":0,
    "qs:placetype":"Town",
    "qs:pop_sr":"4",
    "wd:wordcount":739,
    "wof:name":"Ladushkin",
    "wof:placetype":"locality",
    "wof:population":3928
},
  "geometry": {"coordinates":[20.17099,54.57025],"type":"Point"}
}