{
  "type": "Feature",
  "properties": {
    "gn:admin1_code":"75",
    "gn:asciiname":"Kiselevka",
    "gn:cc2":"RU",
    "gn:country_code":"RU",
    "gn:dem":122,
    "gn:feature_class":"P",
    "gn:feature_code":"PPL",
    "gn:name":"Kisel\u00ebvka",
    "gn:population":0,
    "gn:timezone":"Asia/Tomsk",
    "iso:country":"RU",
    "name:rus_x_preferred":[
        "\u041a\u0438\u0441\u0435\u043b\u0451\u0432\u043a\u0430"
    ],
    "name:und_x_variant":[
        "Kiselevskiy",
        "Kisel\u00ebvka"
    ],
    "wof:name":"Kiselevka",
    "wof:placetype":"locality"
},
  "geometry": {"coordinates":[87.00194,57.44028],"type":"Point"}
}