{
  "type": "Feature",
  "properties": {
    "gn:admin1_code":"69.0",
    "gn:asciiname":"Falileyevo",
    "gn:country_code":"RU",
    "gn:dem":232,
    "gn:feature_class":"P",
    "gn:feature_code":"PPL",
    "gn:name":"Falileyevo",
    "gn:population":0,
    "gn:timezone":"Europe/Moscow",
    "iso:country":"RU",
    "name:rus_x_preferred":[
        "\u0424\u0430\u043b\u0438\u043b\u0435\u0435\u0432\u043e"
    ],
    "name:und_x_variant":[
        "\u0424\u0430\u043b\u0438\u043b\u0435\u0435\u0432\u043e",
        "Faleyevo"
    ],
    "wof:name":"Falileyevo",
    "wof:placetype":"locality"
},
  "geometry": {"coordinates":[34.81667,55.23541],"type":"Point"}
}