{
  "type": "Feature",
  "properties": {
    "gn:admin1_code":"88",
    "gn:asciiname":"Kulakovo",
    "gn:country_code":"RU",
    "gn:dem":162,
    "gn:feature_class":"P",
    "gn:feature_code":"PPL",
    "gn:name":"Kulakovo",
    "gn:population":38,
    "gn:timezone":"Europe/Moscow",
    "iso:country":"RU",
    "name:rus_x_preferred":[
        "\u041a\u0443\u043b\u0430\u043a\u043e\u0432\u043e"
    ],
    "wof:name":"Kulakovo",
    "wof:placetype":"locality",
    "wof:population":38
},
  "geometry": {"coordinates":[39.10858,56.89895],"type":"Point"}
}