{
  "type": "Feature",
  "properties": {
    "gn:admin1_code":"44",
    "gn:asciiname":"Dzhigudzhak",
    "gn:cc2":"RU",
    "gn:country_code":"RU",
    "gn:dem":315,
    "gn:feature_class":"P",
    "gn:feature_code":"PPL",
    "gn:name":"Dzhigudzhak",
    "gn:population":0,
    "gn:timezone":"Asia/Magadan",
    "iso:country":"RU",
    "name:rus_x_preferred":[
        "\u0414\u0436\u0438\u0433\u0443\u0434\u0436\u0430\u043a"
    ],
    "name:und_x_variant":[
        "Povarnya Dzhigudzhak",
        "Dzhigudzhak"
    ],
    "wof:name":"Dzhigudzhak",
    "wof:placetype":"locality"
},
  "geometry": {"coordinates":[157.23333,64.59999999999999],"type":"Point"}
}