{
  "type": "Feature",
  "properties": {
    "gn:country":"RU",
    "gn:fcode":"PPL",
    "gn:population":1951,
    "iso:country":"RU",
    "name:rus_x_preferred":[
        "\u0427\u0443\u043f\u0440\u044f\u043a\u043e\u0432\u043e"
    ],
    "qs:name":"Chupryakovo",
    "qs:name_adm0":"Russia",
    "qs:name_adm1":"Moscow Oblast",
    "qs:photos_9k":1,
    "qs:photos_9r":1,
    "qs:photos_all":3,
    "qs:photos_sr":0,
    "qs:placetype":"Town",
    "qs:pop_sr":"3",
    "wof:name":"Chupryakovo",
    "wof:placetype":"locality",
    "wof:population":1951
},
  "geometry": {"coordinates":[36.62721,55.55282],"type":"Point"}
}