{
  "type": "Feature",
  "properties": {
    "gn:admin1_code":"47",
    "gn:asciiname":"Berkunovo",
    "gn:country_code":"RU",
    "gn:dem":162,
    "gn:feature_class":"P",
    "gn:feature_code":"PPL",
    "gn:name":"Berkunovo",
    "gn:population":0,
    "gn:timezone":"Europe/Moscow",
    "iso:country":"RU",
    "name:nor_x_preferred":[
        "Berkunovo"
    ],
    "name:rus_x_preferred":[
        "\u0411\u0435\u0440\u043a\u0443\u043d\u043e\u0432\u043e"
    ],
    "wof:name":"Berkunovo",
    "wof:placetype":"locality"
},
  "geometry": {"coordinates":[35.69445,56.10966],"type":"Point"}
}