{
  "type": "Feature",
  "properties": {
    "gn:admin1_code":"60",
    "gn:asciiname":"Meretinitsy",
    "gn:cc2":"RU",
    "gn:country_code":"RU",
    "gn:dem":245,
    "gn:feature_class":"P",
    "gn:feature_code":"PPL",
    "gn:name":"Meretinitsy",
    "gn:population":0,
    "gn:timezone":"Europe/Moscow",
    "iso:country":"RU",
    "name:rus_x_preferred":[
        "\u041c\u0435\u0440\u0435\u0442\u0438\u043d\u0438\u0446\u044b"
    ],
    "name:und_x_variant":[
        "Maretinitsy",
        "Meretinitsy"
    ],
    "wof:name":"Meretinitsy",
    "wof:placetype":"locality"
},
  "geometry": {"coordinates":[29.73333,56.65],"type":"Point"}
}