{
  "type": "Feature",
  "properties": {
    "gn:admin1_code":"6.0",
    "gn:asciiname":"Churozgora",
    "gn:country_code":"RU",
    "gn:dem":27,
    "gn:feature_class":"P",
    "gn:feature_code":"PPL",
    "gn:name":"Churozgora",
    "gn:population":0,
    "gn:timezone":"Europe/Moscow",
    "iso:country":"RU",
    "name:eng_x_preferred":[
        "Churozgora"
    ],
    "name:nor_x_preferred":[
        "Tsjuroz-Gora"
    ],
    "name:rus_x_preferred":[
        "\u0427\u0443\u0440\u043e\u0437-\u0413\u043e\u0440\u0430"
    ],
    "name:rus_x_variant":[
        "\u0427\u0443\u0440\u043e\u0437\u0433\u043e\u0440\u0430"
    ],
    "name:und_x_variant":[
        "Churayagora",
        "Churazgora",
        "Churozgora",
        "\u0427\u0443\u0440\u043e\u0437\u0433\u043e\u0440\u0430"
    ],
    "wof:name":"Churozgora",
    "wof:placetype":"locality"
},
  "geometry": {"coordinates":[41.50346,63.09585],"type":"Point"}
}