{
  "type": "Feature",
  "properties": {
    "gn:admin1_code":"9.0",
    "gn:asciiname":"Foshchevatoye",
    "gn:country_code":"RU",
    "gn:dem":206,
    "gn:feature_class":"P",
    "gn:feature_code":"PPL",
    "gn:name":"Foshchevatoye",
    "gn:population":0,
    "gn:timezone":"Europe/Moscow",
    "iso:country":"RU",
    "name:rus_x_preferred":[
        "\u0424\u043e\u0449\u0435\u0432\u0430\u0442\u043e\u0435"
    ],
    "name:und_x_variant":[
        "\u0424\u043e\u0449\u0435\u0432\u0430\u0442\u043e\u0435"
    ],
    "wof:name":"Foshchevatoye",
    "wof:placetype":"locality"
},
  "geometry": {"coordinates":[38.29611,50.17222],"type":"Point"}
}