{
  "type": "Feature",
  "properties": {
    "gn:admin1_code":"4",
    "gn:asciiname":"Urozhaynoye",
    "gn:country_code":"RU",
    "gn:dem":209,
    "gn:feature_class":"P",
    "gn:feature_code":"PPL",
    "gn:name":"Urozhaynoye",
    "gn:population":0,
    "gn:timezone":"Asia/Barnaul",
    "iso:country":"RU",
    "name:che_x_preferred":[
        "\u0423\u0440\u043e\u0436\u0430\u0439\u043d\u0438"
    ],
    "name:eng_x_preferred":[
        "Urozhaynoye"
    ],
    "name:nor_x_preferred":[
        "Urozjajnoje"
    ],
    "name:rus_x_preferred":[
        "\u0423\u0440\u043e\u0436\u0430\u0439\u043d\u043e\u0435"
    ],
    "name:und_x_variant":[
        "Urozhaynyy",
        "Urozhaynoye"
    ],
    "wof:name":"Urozhaynoye",
    "wof:placetype":"locality"
},
  "geometry": {"coordinates":[85.64936999999998,52.30637],"type":"Point"}
}