{
  "type": "Feature",
  "properties": {
    "gn:admin1_code":"91",
    "gn:asciiname":"Istok",
    "gn:country_code":"RU",
    "gn:dem":113,
    "gn:feature_class":"P",
    "gn:feature_code":"PPL",
    "gn:name":"Istok",
    "gn:population":0,
    "gn:timezone":"Asia/Krasnoyarsk",
    "iso:country":"RU",
    "name:cat_x_preferred":[
        "Burimi"
    ],
    "name:deu_x_preferred":[
        "Istog"
    ],
    "name:eng_x_preferred":[
        "Istok"
    ],
    "name:est_x_preferred":[
        "Istog"
    ],
    "name:fas_x_preferred":[
        "\u0627\u06cc\u0633\u062a\u0648\u06a9"
    ],
    "name:fra_x_preferred":[
        "Burimi"
    ],
    "name:hrv_x_preferred":[
        "Istok"
    ],
    "name:ita_x_preferred":[
        "Istok"
    ],
    "name:lit_x_preferred":[
        "Istokas"
    ],
    "name:mkd_x_preferred":[
        "\u0418\u0441\u0442\u043e\u043a"
    ],
    "name:nld_x_preferred":[
        "Istog"
    ],
    "name:nor_x_preferred":[
        "Istok"
    ],
    "name:pol_x_preferred":[
        "Istok"
    ],
    "name:rus_x_preferred":[
        "\u0418\u0441\u0442\u043e\u043a"
    ],
    "name:sqi_x_preferred":[
        "Burimi"
    ],
    "name:srp_x_preferred":[
        "\u0418\u0441\u0442\u043e\u043a"
    ],
    "name:swe_x_preferred":[
        "Istok"
    ],
    "name:tur_x_preferred":[
        "\u0130stok"
    ],
    "name:zho_x_preferred":[
        "\u4f0a\u65af\u6258\u514b"
    ],
    "wof:name":"Istok",
    "wof:placetype":"locality"
},
  "geometry": {"coordinates":[93.70028000000001,56.60361],"type":"Point"}
}