{
  "type": "Feature",
  "properties": {
    "gn:admin1_code":"91",
    "gn:asciiname":"Istok",
    "gn:country_code":"RU",
    "gn:dem":113,
    "gn:feature_class":"P",
    "gn:feature_code":"PPL",
    "gn:name":"Istok",
    "gn:population":0,
    "gn:timezone":"Asia/Krasnoyarsk",
    "iso:country":"RU",
    "name:eng_x_preferred":[
        "Istok"
    ],
    "name:nor_x_preferred":[
        "Istok"
    ],
    "name:rus_x_preferred":[
        "\u0418\u0441\u0442\u043e\u043a"
    ],
    "wof:name":"Istok",
    "wof:placetype":"locality"
},
  "geometry": {"coordinates":[93.70028000000001,56.60361],"type":"Point"}
}