{
  "type": "Feature",
  "properties": {
    "gn:admin1_code":"17.0",
    "gn:admin2_code":"557977",
    "gn:asciiname":"Batsada",
    "gn:country_code":"RU",
    "gn:dem":1538,
    "gn:feature_class":"P",
    "gn:feature_code":"PPL",
    "gn:name":"Batsada",
    "gn:population":0,
    "gn:timezone":"Europe/Moscow",
    "iso:country":"RU",
    "name:eng_x_preferred":[
        "Batsada"
    ],
    "name:nor_x_preferred":[
        "Batsada"
    ],
    "name:rus_x_preferred":[
        "\u0411\u0430\u0446\u0430\u0434\u0430"
    ],
    "wof:name":"Batsada",
    "wof:placetype":"locality"
},
  "geometry": {"coordinates":[46.90997,42.30561],"type":"Point"}
}