{
  "type": "Feature",
  "properties": {
    "gn:admin1_code":"6.0",
    "gn:asciiname":"Shestoy Post",
    "gn:country_code":"RU",
    "gn:dem":218,
    "gn:feature_class":"P",
    "gn:feature_code":"PPL",
    "gn:name":"Shestoy Post",
    "gn:population":0,
    "gn:timezone":"Europe/Moscow",
    "iso:country":"RU",
    "name:rus_x_preferred":[
        "\u0428\u0435\u0441\u0442\u043e\u0439 \u041f\u043e\u0441\u0442"
    ],
    "wof:name":"Shestoy Post",
    "wof:placetype":"locality"
},
  "geometry": {"coordinates":[41.2175,62.3227],"type":"Point"}
}