{
  "type": "Feature",
  "properties": {
    "gn:admin1_code":"61",
    "gn:asciiname":"Kalmykovka",
    "gn:country_code":"RU",
    "gn:dem":55,
    "gn:feature_class":"P",
    "gn:feature_code":"PPL",
    "gn:name":"Kalmykovka",
    "gn:population":0,
    "gn:timezone":"Europe/Moscow",
    "iso:country":"RU",
    "name:rus_x_preferred":[
        "\u041a\u0430\u043b\u043c\u044b\u043a\u043e\u0432\u043a\u0430"
    ],
    "wof:name":"Kalmykovka",
    "wof:placetype":"locality"
},
  "geometry": {"coordinates":[39.82833,49.04985],"type":"Point"}
}