{
  "type": "Feature",
  "properties": {
    "gn:admin1_code":"28",
    "gn:asciiname":"Ropruchey-Klimovo",
    "gn:country_code":"RU",
    "gn:dem":23,
    "gn:feature_class":"P",
    "gn:feature_code":"PPL",
    "gn:name":"Ropruchey-Klimovo",
    "gn:population":0,
    "gn:timezone":"Europe/Moscow",
    "iso:country":"RU",
    "name:rus_x_preferred":[
        "\u0420\u043e\u043f\u0440\u0443\u0447\u0435\u0439-\u041a\u043b\u0438\u043c\u043e\u0432\u043e"
    ],
    "wof:name":"Ropruchey-Klimovo",
    "wof:placetype":"locality"
},
  "geometry": {"coordinates":[35.52979000000001,61.2836],"type":"Point"}
}