{
  "type": "Feature",
  "properties": {
    "gn:admin1_code":"42",
    "gn:asciiname":"Pagolda",
    "gn:country_code":"RU",
    "gn:dem":61,
    "gn:feature_class":"P",
    "gn:feature_code":"PPL",
    "gn:name":"Pagolda",
    "gn:population":0,
    "gn:timezone":"Europe/Moscow",
    "iso:country":"RU",
    "name:rus_x_preferred":[
        "\u041f\u0430\u0433\u043e\u043b\u0434\u0430"
    ],
    "name:und_x_variant":[
        "\u041f\u0430\u0433\u043e\u043b\u0434\u0430"
    ],
    "wof:name":"Pagolda",
    "wof:placetype":"locality"
},
  "geometry": {"coordinates":[33.5979,59.65158],"type":"Point"}
}