{
  "type": "Feature",
  "properties": {
    "gn:admin1_code":"4",
    "gn:asciiname":"Ust'-Talovka",
    "gn:country_code":"RU",
    "gn:dem":272,
    "gn:feature_class":"P",
    "gn:feature_code":"PPL",
    "gn:name":"Ust\u2019-Talovka",
    "gn:population":0,
    "gn:timezone":"Asia/Barnaul",
    "iso:country":"RU",
    "name:eng_x_preferred":[
        "Ust'-Talovka"
    ],
    "name:nor_x_preferred":[
        "Ust-Talovka"
    ],
    "name:rus_x_preferred":[
        "\u0423\u0441\u0442\u044c-\u0422\u0430\u043b\u043e\u0432\u043a\u0430"
    ],
    "name:und_x_variant":[
        "Ust\u2019-Talovskoye",
        "Ust\u2019-Talovka"
    ],
    "wof:name":"Ust'-Talovka",
    "wof:placetype":"locality"
},
  "geometry": {"coordinates":[82.28953,51.49095],"type":"Point"}
}