{
  "type": "Feature",
  "properties": {
    "gn:admin1_code":"63",
    "gn:asciiname":"Sygannakh",
    "gn:cc2":"RU",
    "gn:country_code":"RU",
    "gn:dem":45,
    "gn:feature_class":"P",
    "gn:feature_code":"PPL",
    "gn:name":"Sygannakh",
    "gn:population":0,
    "gn:timezone":"Asia/Magadan",
    "iso:country":"RU",
    "name:und_x_variant":[
        "Syagaannaakh",
        "Sygannakh"
    ],
    "wof:name":"Sygannakh",
    "wof:placetype":"locality"
},
  "geometry": {"coordinates":[144.19999999999999,67.78333000000001],"type":"Point"}
}