{
  "type": "Feature",
  "properties": {
    "gn:admin1_code":"9.0",
    "gn:asciiname":"Dol'giy",
    "gn:country_code":"RU",
    "gn:dem":239,
    "gn:feature_class":"P",
    "gn:feature_code":"PPL",
    "gn:name":"Dol\u2019giy",
    "gn:population":0,
    "gn:timezone":"Europe/Moscow",
    "iso:country":"RU",
    "name:rus_x_preferred":[
        "\u0414\u043e\u043b\u044c\u0433\u0438\u0439"
    ],
    "name:und_x_variant":[
        "Dol\u2019giy"
    ],
    "wof:name":"Dol'giy",
    "wof:placetype":"locality"
},
  "geometry": {"coordinates":[36.19833,50.93611],"type":"Point"}
}