{
  "type": "Feature",
  "properties": {
    "gn:admin1_code":"77",
    "gn:asciiname":"Ratcha",
    "gn:country_code":"RU",
    "gn:dem":238,
    "gn:feature_class":"P",
    "gn:feature_code":"PPL",
    "gn:name":"Ratcha",
    "gn:population":0,
    "gn:timezone":"Europe/Moscow",
    "iso:country":"RU",
    "name:rus_x_preferred":[
        "\u0420\u0430\u0442\u0447\u0430"
    ],
    "name:und_x_variant":[
        "Bol\u2019shaya Ratcha",
        "Ratcha",
        "\u0420\u0430\u0442\u0447\u0430"
    ],
    "wof:name":"Ratcha",
    "wof:placetype":"locality"
},
  "geometry": {"coordinates":[31.76477,56.82594],"type":"Point"}
}