{
  "type": "Feature",
  "properties": {
    "gn:admin1_code":"90",
    "gn:asciiname":"Tanyp",
    "gn:country_code":"RU",
    "gn:dem":163,
    "gn:feature_class":"P",
    "gn:feature_code":"PPL",
    "gn:name":"Tanyp",
    "gn:population":0,
    "gn:timezone":"Asia/Yekaterinburg",
    "iso:country":"RU",
    "name:eng_x_preferred":[
        "Tanyp"
    ],
    "name:nor_x_preferred":[
        "Tanyp"
    ],
    "name:rus_x_preferred":[
        "\u0422\u0430\u043d\u044b\u043f"
    ],
    "wof:name":"Tanyp",
    "wof:placetype":"locality"
},
  "geometry": {"coordinates":[55.8429,56.7729],"type":"Point"}
}