{
  "type": "Feature",
  "properties": {
    "gn:admin1_code":"61.0",
    "gn:asciiname":"Maloye Zverevo",
    "gn:country_code":"RU",
    "gn:dem":203,
    "gn:feature_class":"P",
    "gn:feature_code":"PPL",
    "gn:name":"Maloye Zverevo",
    "gn:population":0,
    "gn:timezone":"Europe/Moscow",
    "iso:country":"RU",
    "name:rus_x_preferred":[
        "\u041c\u0430\u043b\u043e\u0435 \u0417\u0432\u0435\u0440\u0435\u0432\u043e"
    ],
    "name:und_x_variant":[
        "Maloye Zvero",
        "Maloye Zverevo",
        "\u041c\u0430\u043b\u043e\u0435 \u0417\u0432\u0435\u0440\u0435\u0432\u043e"
    ],
    "wof:name":"Maloye Zverevo",
    "wof:placetype":"locality"
},
  "geometry": {"coordinates":[40.14509,48.01252],"type":"Point"}
}