{
  "type": "Feature",
  "properties": {
    "gn:admin1_code":"83",
    "gn:asciiname":"Krasnoznamenskiy",
    "gn:country_code":"RU",
    "gn:dem":100,
    "gn:feature_class":"P",
    "gn:feature_code":"PPL",
    "gn:name":"Krasnoznamenskiy",
    "gn:population":0,
    "gn:timezone":"Europe/Moscow",
    "iso:country":"RU",
    "name:rus_x_preferred":[
        "\u041a\u0440\u0430\u0441\u043d\u043e\u0437\u043d\u0430\u043c\u0435\u043d\u0441\u043a\u0438\u0439"
    ],
    "wof:name":"Krasnoznamenskiy",
    "wof:placetype":"locality"
},
  "geometry": {"coordinates":[40.9922,56.4569],"type":"Point"}
}