{
  "type": "Feature",
  "properties": {
    "gn:admin1_code":"16",
    "gn:asciiname":"Novyye Chelkasy",
    "gn:country_code":"RU",
    "gn:dem":95,
    "gn:feature_class":"P",
    "gn:feature_code":"PPL",
    "gn:name":"Novyye Chelkasy",
    "gn:population":0,
    "gn:timezone":"Europe/Moscow",
    "iso:country":"RU",
    "name:rus_x_preferred":[
        "\u041d\u043e\u0432\u044b\u0435 \u0427\u0435\u043b\u043a\u0430\u0441\u044b"
    ],
    "name:und_x_variant":[
        "Novyye Chelkosy",
        "Novyye Chelkasy",
        "\u041d\u043e\u0432\u044b\u0435 \u0427\u0435\u043b\u043a\u0430\u0441\u044b"
    ],
    "wof:name":"Novyye Chelkasy",
    "wof:placetype":"locality"
},
  "geometry": {"coordinates":[47.26889,55.52908000000001],"type":"Point"}
}