{
  "type": "Feature",
  "properties": {
    "gn:admin1_code":"52",
    "gn:asciiname":"Oputi",
    "gn:country_code":"RU",
    "gn:dem":53,
    "gn:feature_class":"P",
    "gn:feature_code":"PPL",
    "gn:name":"Oputi",
    "gn:population":0,
    "gn:timezone":"Europe/Moscow",
    "iso:country":"RU",
    "name:rus_x_preferred":[
        "\u041e\u043f\u0443\u0442\u0438"
    ],
    "name:und_x_variant":[
        "\u041e\u043f\u0443\u0442\u0438"
    ],
    "wof:name":"Oputi",
    "wof:placetype":"locality"
},
  "geometry": {"coordinates":[32.82778,58.79532],"type":"Point"}
}