{
  "type": "Feature",
  "properties": {
    "gn:admin1_code":"91",
    "gn:asciiname":"Nizhniy Kuvay",
    "gn:country_code":"RU",
    "gn:dem":612,
    "gn:feature_class":"P",
    "gn:feature_code":"PPL",
    "gn:name":"Nizhniy Kuvay",
    "gn:population":0,
    "gn:timezone":"Asia/Krasnoyarsk",
    "iso:country":"RU",
    "wof:name":"Nizhniy Kuvay",
    "wof:placetype":"locality"
},
  "geometry": {"coordinates":[93.42694,55.01722],"type":"Point"}
}