{
  "type": "Feature",
  "properties": {
    "gn:admin1_code":"75",
    "gn:asciiname":"Zavarzino",
    "gn:country_code":"RU",
    "gn:dem":100,
    "gn:feature_class":"P",
    "gn:feature_code":"PPL",
    "gn:name":"Zavarzino",
    "gn:population":0,
    "gn:timezone":"Asia/Tomsk",
    "iso:country":"RU",
    "name:eng_x_preferred":[
        "Zavarzino"
    ],
    "name:nor_x_preferred":[
        "Zavarzino"
    ],
    "name:rus_x_preferred":[
        "\u0417\u0430\u0432\u0430\u0440\u0437\u0438\u043d\u043e"
    ],
    "name:und_x_variant":[
        "Zavarzina"
    ],
    "wof:name":"Zavarzino",
    "wof:placetype":"locality"
},
  "geometry": {"coordinates":[85.09945,56.46909],"type":"Point"}
}