{
  "type": "Feature",
  "properties": {
    "gn:admin1_code":"47.0",
    "gn:asciiname":"Filimonovo",
    "gn:country_code":"RU",
    "gn:dem":227,
    "gn:feature_class":"P",
    "gn:feature_code":"PPL",
    "gn:name":"Filimonovo",
    "gn:population":0,
    "gn:timezone":"Europe/Moscow",
    "iso:country":"RU",
    "name:rus_x_preferred":[
        "\u0424\u0438\u043b\u0438\u043c\u043e\u043d\u043e\u0432\u043e"
    ],
    "wof:name":"Filimonovo",
    "wof:placetype":"locality"
},
  "geometry": {"coordinates":[37.67557,56.1807],"type":"Point"}
}