{
  "type": "Feature",
  "properties": {
    "gn:admin1_code":"52",
    "gn:asciiname":"Nekhotilovka",
    "gn:country_code":"RU",
    "gn:dem":67,
    "gn:feature_class":"P",
    "gn:feature_code":"PPL",
    "gn:name":"Nekhotilovka",
    "gn:population":0,
    "gn:timezone":"Europe/Moscow",
    "iso:country":"RU",
    "name:rus_x_preferred":[
        "\u041d\u0435\u0445\u043e\u0442\u0438\u043b\u043e\u0432\u043a\u0430"
    ],
    "wof:name":"Nekhotilovka",
    "wof:placetype":"locality"
},
  "geometry": {"coordinates":[30.76755,58.06338],"type":"Point"}
}