{
  "type": "Feature",
  "properties": {
    "gn:admin1_code":"20",
    "gn:asciiname":"Aver'yanovka",
    "gn:country_code":"RU",
    "gn:dem":537,
    "gn:feature_class":"P",
    "gn:feature_code":"PPL",
    "gn:name":"Aver\u2019yanovka",
    "gn:population":0,
    "gn:timezone":"Asia/Irkutsk",
    "iso:country":"RU",
    "name:nor_x_preferred":[
        "Averjanovka"
    ],
    "name:rus_x_preferred":[
        "\u0410\u0432\u0435\u0440\u044c\u044f\u043d\u043e\u0432\u043a\u0430"
    ],
    "name:und_x_variant":[
        "Aver\u2019yanovka"
    ],
    "wof:name":"Aver'yanovka",
    "wof:placetype":"locality"
},
  "geometry": {"coordinates":[100.07225,54.5719],"type":"Point"}
}