{
  "type": "Feature",
  "properties": {
    "gn:admin1_code":"17.0",
    "gn:asciiname":"Gubdentyz",
    "gn:country_code":"RU",
    "gn:dem":59,
    "gn:feature_class":"P",
    "gn:feature_code":"PPL",
    "gn:name":"Gubdentyz",
    "gn:population":0,
    "gn:timezone":"Europe/Moscow",
    "iso:country":"RU",
    "name:rus_x_preferred":[
        "\u0413\u0443\u0431\u0434\u0435\u043d\u0442\u044b\u0437"
    ],
    "name:und_x_variant":[
        "\u0413\u0443\u0431\u0434\u0435\u043d\u0442\u044b\u0437"
    ],
    "wof:name":"Gubdentyz",
    "wof:placetype":"locality"
},
  "geometry": {"coordinates":[47.6775,42.73028],"type":"Point"}
}