{
  "type": "Feature",
  "properties": {
    "gn:admin1_code":"80",
    "gn:asciiname":"Kychinskiy",
    "gn:country_code":"RU",
    "gn:dem":153,
    "gn:feature_class":"P",
    "gn:feature_code":"PPL",
    "gn:name":"Kychinskiy",
    "gn:population":0,
    "gn:timezone":"Europe/Samara",
    "iso:country":"RU",
    "name:rus_x_preferred":[
        "\u041a\u044b\u0447\u0438\u043d\u0441\u043a\u0438\u0439"
    ],
    "name:und_x_variant":[
        "Pochinok-Kachinskiy",
        "Pochinok-Kichinskiy",
        "Kychinskiy"
    ],
    "wof:name":"Kychinskiy",
    "wof:placetype":"locality"
},
  "geometry": {"coordinates":[51.93721,58.21144],"type":"Point"}
}