{
  "type": "Feature",
  "properties": {
    "gn:admin1_code":"65",
    "gn:asciiname":"Karmalo-Adelyakovo",
    "gn:country_code":"RU",
    "gn:dem":120,
    "gn:feature_class":"P",
    "gn:feature_code":"PPL",
    "gn:name":"Karmalo-Adelyakovo",
    "gn:population":0,
    "gn:timezone":"Europe/Samara",
    "iso:country":"RU",
    "name:eng_x_preferred":[
        "Karmala-Adelyakovo"
    ],
    "name:nor_x_preferred":[
        "Karmalo-Adeljakovo"
    ],
    "name:rus_x_preferred":[
        "\u041a\u0430\u0440\u043c\u0430\u043b\u043e-\u0410\u0434\u0435\u043b\u044f\u043a\u043e\u0432\u043e"
    ],
    "wof:name":"Karmalo-Adelyakovo",
    "wof:placetype":"locality"
},
  "geometry": {"coordinates":[51.39919,53.85026],"type":"Point"}
}