{
  "type": "Feature",
  "properties": {
    "gn:admin1_code":"16",
    "gn:asciiname":"Maloye Yangil'dino",
    "gn:country_code":"RU",
    "gn:dem":167,
    "gn:feature_class":"P",
    "gn:feature_code":"PPL",
    "gn:name":"Maloye Yangil\u2019dino",
    "gn:population":0,
    "gn:timezone":"Europe/Moscow",
    "iso:country":"RU",
    "name:rus_x_preferred":[
        "\u041c\u0430\u043b\u043e\u0435 \u042f\u043d\u0433\u0438\u043b\u044c\u0434\u0438\u043d\u043e"
    ],
    "name:und_x_variant":[
        "Maloye Yangil\u2019dino",
        "\u041c\u0430\u043b\u043e\u0435 \u042f\u043d\u0433\u0438\u043b\u044c\u0434\u0438\u043d\u043e"
    ],
    "wof:name":"Maloye Yangil'dino",
    "wof:placetype":"locality"
},
  "geometry": {"coordinates":[47.15374,56.0561],"type":"Point"}
}