{
  "type": "Feature",
  "properties": {
    "gn:admin1_code":"29",
    "gn:asciiname":"Antonovka",
    "gn:country_code":"RU",
    "gn:dem":179,
    "gn:feature_class":"P",
    "gn:feature_code":"PPL",
    "gn:name":"Antonovka",
    "gn:population":0,
    "gn:timezone":"Asia/Novokuznetsk",
    "iso:country":"RU",
    "name:nor_x_preferred":[
        "Antonovka"
    ],
    "name:rus_x_preferred":[
        "\u0410\u043d\u0442\u043e\u043d\u043e\u0432\u043a\u0430"
    ],
    "wof:name":"Antonovka",
    "wof:placetype":"locality"
},
  "geometry": {"coordinates":[86.25951999999999,56.10796],"type":"Point"}
}