{
  "type": "Feature",
  "properties": {
    "gn:admin1_code":"29",
    "gn:asciiname":"Antonovka",
    "gn:country_code":"RU",
    "gn:dem":179,
    "gn:feature_class":"P",
    "gn:feature_code":"PPL",
    "gn:name":"Antonovka",
    "gn:population":0,
    "gn:timezone":"Asia/Novokuznetsk",
    "iso:country":"RU",
    "name:bak_x_preferred":[
        "\u0410\u043d\u0442\u043e\u043d\u043e\u0432\u043a\u0430 \u0430\u043b\u043c\u0430\u0493\u0430\u0441\u044b"
    ],
    "name:ces_x_preferred":[
        "Antonovka"
    ],
    "name:deu_x_preferred":[
        "Antonowka"
    ],
    "name:est_x_preferred":[
        "Antoonovka"
    ],
    "name:fra_x_preferred":[
        "Antonovka"
    ],
    "name:lav_x_preferred":[
        "Antonovka"
    ],
    "name:lit_x_preferred":[
        "Antaniniai"
    ],
    "name:nor_x_preferred":[
        "Antonovka"
    ],
    "name:pol_x_preferred":[
        "Anton\u00f3wka"
    ],
    "name:rus_x_preferred":[
        "\u0410\u043d\u0442\u043e\u043d\u043e\u0432\u043a\u0430"
    ],
    "name:swe_x_preferred":[
        "Antonovka"
    ],
    "name:ukr_x_preferred":[
        "\u0410\u043d\u0442\u043e\u043d\u0456\u0432\u043a\u0430 \u0437\u0432\u0438\u0447\u0430\u0439\u043d\u0430"
    ],
    "name:vie_x_preferred":[
        "T\u00e1o Antonovka"
    ],
    "wof:name":"Antonovka",
    "wof:placetype":"locality"
},
  "geometry": {"coordinates":[86.25951999999999,56.10796],"type":"Point"}
}