{
  "type": "Feature",
  "properties": {
    "gn:admin1_code":"9",
    "gn:asciiname":"Lubyanoye Pervoye",
    "gn:country_code":"RU",
    "gn:dem":217,
    "gn:feature_class":"P",
    "gn:feature_code":"PPL",
    "gn:name":"Lubyanoye Pervoye",
    "gn:population":0,
    "gn:timezone":"Europe/Moscow",
    "iso:country":"RU",
    "name:rus_x_preferred":[
        "\u041b\u0443\u0431\u044f\u043d\u043e\u0435 \u041f\u0435\u0440\u0432\u043e\u0435"
    ],
    "name:und_x_variant":[
        "Lubyannoye",
        "Lubyanoye",
        "Lubyanoye Pervoye"
    ],
    "wof:name":"Lubyanoye Pervoye",
    "wof:placetype":"locality"
},
  "geometry": {"coordinates":[38.2414,50.9564],"type":"Point"}
}