{
  "type": "Feature",
  "properties": {
    "gn:admin1_code":"73",
    "gn:asciiname":"Tatarskoye Bulyarovo",
    "gn:country_code":"RU",
    "gn:dem":151,
    "gn:feature_class":"P",
    "gn:feature_code":"PPL",
    "gn:name":"Tatarskoye Bulyarovo",
    "gn:population":0,
    "gn:timezone":"Europe/Moscow",
    "iso:country":"RU",
    "name:rus_x_preferred":[
        "\u0422\u0430\u0442\u0430\u0440\u0441\u043a\u043e\u0435 \u0411\u0443\u043b\u044f\u0440\u043e\u0432\u043e"
    ],
    "name:und_x_variant":[
        "Tatarskiy Bulyar",
        "Tatarskoye Bulyarovo",
        "\u0422\u0430\u0442\u0430\u0440\u0441\u043a\u043e\u0435 \u0411\u0443\u043b\u044f\u0440\u043e\u0432\u043e"
    ],
    "wof:name":"Tatarskoye Bulyarovo",
    "wof:placetype":"locality"
},
  "geometry": {"coordinates":[53.57095,55.44353],"type":"Point"}
}