{
  "type": "Feature",
  "properties": {
    "gn:admin1_code":"60",
    "gn:asciiname":"Orekhovichi",
    "gn:country_code":"RU",
    "gn:dem":58,
    "gn:feature_class":"P",
    "gn:feature_code":"PPL",
    "gn:name":"Orekhovichi",
    "gn:population":0,
    "gn:timezone":"Europe/Moscow",
    "iso:country":"RU",
    "name:eng_x_preferred":[
        "Orekhovichi"
    ],
    "name:nor_x_preferred":[
        "Orekhovitsji"
    ],
    "name:rus_x_preferred":[
        "\u041e\u0440\u0435\u0445\u043e\u0432\u0438\u0447\u0438"
    ],
    "wof:name":"Orekhovichi",
    "wof:placetype":"locality"
},
  "geometry": {"coordinates":[28.53774,57.62506],"type":"Point"}
}