{
  "type": "Feature",
  "properties": {
    "gn:admin1_code":"77.0",
    "gn:asciiname":"Afim'ino",
    "gn:country_code":"RU",
    "gn:dem":173,
    "gn:feature_class":"P",
    "gn:feature_code":"PPL",
    "gn:name":"Afim\u2019ino",
    "gn:population":0,
    "gn:timezone":"Europe/Moscow",
    "iso:country":"RU",
    "name:eng_x_preferred":[
        "Afim'ino"
    ],
    "name:nor_x_preferred":[
        "Afimino"
    ],
    "name:rus_x_preferred":[
        "\u0410\u0444\u0438\u043c\u044c\u0438\u043d\u043e"
    ],
    "name:und_x_variant":[
        "Afim\u2019ino"
    ],
    "wof:name":"Afim'ino",
    "wof:placetype":"locality"
},
  "geometry": {"coordinates":[34.72181,57.46961999999999],"type":"Point"}
}