{
  "type": "Feature",
  "properties": {
    "gn:admin1_code":"91",
    "gn:asciiname":"Verkhnebel'sk",
    "gn:country_code":"RU",
    "gn:dem":166,
    "gn:feature_class":"P",
    "gn:feature_code":"PPL",
    "gn:name":"Verkhnebel\u2019sk",
    "gn:population":0,
    "gn:timezone":"Asia/Krasnoyarsk",
    "iso:country":"RU",
    "name:eng_x_preferred":[
        "Verkhnebel'sk"
    ],
    "name:nor_x_preferred":[
        "Verkhnebelsk"
    ],
    "name:rus_x_preferred":[
        "\u0412\u0435\u0440\u0445\u043d\u0435\u0431\u0435\u043b\u044c\u0441\u043a"
    ],
    "name:und_x_variant":[
        "Zhivotnovod",
        "Verkhnebel\u2019sk"
    ],
    "wof:name":"Verkhnebel'sk",
    "wof:placetype":"locality"
},
  "geometry": {"coordinates":[92.3468,58.1007],"type":"Point"}
}