{
  "type": "Feature",
  "properties": {
    "gn:admin1_code":"91",
    "gn:asciiname":"Sigovo",
    "gn:cc2":"RU",
    "gn:country_code":"RU",
    "gn:dem":48,
    "gn:feature_class":"P",
    "gn:feature_code":"PPL",
    "gn:name":"Sigovo",
    "gn:population":0,
    "gn:timezone":"Asia/Krasnoyarsk",
    "iso:country":"RU",
    "name:rus_x_preferred":[
        "\u0421\u0438\u0433\u043e\u0432\u043e"
    ],
    "name:und_x_variant":[
        "Toches",
        "Sigovaya",
        "Sigovo"
    ],
    "wof:name":"Sigovo",
    "wof:placetype":"locality"
},
  "geometry": {"coordinates":[87.05,62.73333],"type":"Point"}
}