{
  "type": "Feature",
  "properties": {
    "gn:admin1_code":"71",
    "gn:asciiname":"Mishina",
    "gn:country_code":"RU",
    "gn:dem":69,
    "gn:feature_class":"P",
    "gn:feature_code":"PPL",
    "gn:name":"Mishina",
    "gn:population":0,
    "gn:timezone":"Asia/Yekaterinburg",
    "iso:country":"RU",
    "name:eng_x_preferred":[
        "Mishino"
    ],
    "name:nor_x_preferred":[
        "Misjina"
    ],
    "name:rus_x_preferred":[
        "\u041c\u0438\u0448\u0438\u043d\u0430"
    ],
    "name:und_x_variant":[
        "Mishino",
        "Mishina"
    ],
    "wof:name":"Mishina",
    "wof:placetype":"locality"
},
  "geometry": {"coordinates":[61.90537,59.18044],"type":"Point"}
}