{
  "type": "Feature",
  "properties": {
    "iso:country":"RU",
    "name:rus_x_preferred":[
        "\u041f\u043e\u0441\u0430\u0434\u0441\u043a\u0438\u0439"
    ],
    "wof:name":"Posadsky",
    "wof:placetype":"neighbourhood"
},
  "geometry": {"coordinates":[30.32827548814048,59.95877002033559],"type":"Point"}
}