{
  "type": "Feature",
  "properties": {
    "gn:admin1_code":"56",
    "gn:asciiname":"Golovinskiy",
    "gn:country_code":"RU",
    "gn:dem":270,
    "gn:feature_class":"P",
    "gn:feature_code":"PPL",
    "gn:name":"Golovinskiy",
    "gn:population":0,
    "gn:timezone":"Europe/Moscow",
    "iso:country":"RU",
    "name:rus_x_preferred":[
        "\u0413\u043e\u043b\u043e\u0432\u0438\u043d\u0441\u043a\u0438\u0439"
    ],
    "name:und_x_variant":[
        "\u0413\u043e\u043b\u043e\u0432\u0438\u043d\u0441\u043a\u0438\u0439"
    ],
    "wof:name":"Golovinskiy",
    "wof:placetype":"locality"
},
  "geometry": {"coordinates":[37.51667,52.98333],"type":"Point"}
}