{
  "type": "Feature",
  "properties": {
    "gn:admin1_code":"28",
    "gn:asciiname":"Myandusel'ga",
    "gn:country_code":"RU",
    "gn:dem":167,
    "gn:feature_class":"P",
    "gn:feature_code":"PPL",
    "gn:name":"Myandusel\u2019ga",
    "gn:population":0,
    "gn:timezone":"Europe/Moscow",
    "iso:country":"RU",
    "name:eng_x_preferred":[
        "Myandusel'ga"
    ],
    "name:fin_x_preferred":[
        "M\u00e4ntyselk\u00e4"
    ],
    "name:nor_x_preferred":[
        "Mjanduselga"
    ],
    "name:rus_x_preferred":[
        "\u041c\u044f\u043d\u0434\u0443\u0441\u0435\u043b\u044c\u0433\u0430"
    ],
    "name:und_x_variant":[
        "Myandusel\u2019ga"
    ],
    "wof:name":"Myandusel'ga",
    "wof:placetype":"locality"
},
  "geometry": {"coordinates":[33.73496,62.88699],"type":"Point"}
}