{
  "type": "Feature",
  "properties": {
    "gn:admin1_code":"8",
    "gn:asciiname":"Klyuchevka",
    "gn:country_code":"RU",
    "gn:dem":273,
    "gn:feature_class":"P",
    "gn:feature_code":"PPL",
    "gn:name":"Klyuch\u00ebvka",
    "gn:population":0,
    "gn:timezone":"Asia/Yekaterinburg",
    "iso:country":"RU",
    "name:eng_x_preferred":[
        "Klyuch\u00ebvka"
    ],
    "name:nor_x_preferred":[
        "Kljutsjevka"
    ],
    "name:rus_x_preferred":[
        "\u041a\u043b\u044e\u0447\u0435\u0432\u043a\u0430"
    ],
    "name:rus_x_variant":[
        "\u041a\u043b\u044e\u0447\u0451\u0432\u043a\u0430"
    ],
    "name:und_x_variant":[
        "Klyuch\u00ebvka"
    ],
    "wof:name":"Klyuchevka",
    "wof:placetype":"locality"
},
  "geometry": {"coordinates":[55.522,53.0675],"type":"Point"}
}