{
  "type": "Feature",
  "properties": {
    "gn:admin1_code":"41",
    "gn:asciiname":"Krasnozavodskoy",
    "gn:country_code":"RU",
    "gn:dem":182,
    "gn:feature_class":"P",
    "gn:feature_code":"PPL",
    "gn:name":"Krasnozavodskoy",
    "gn:population":0,
    "gn:timezone":"Europe/Moscow",
    "iso:country":"RU",
    "name:rus_x_preferred":[
        "\u041a\u0440\u0430\u0441\u043d\u043e\u0437\u0430\u0432\u043e\u0434\u0441\u043a\u043e\u0439"
    ],
    "wof:name":"Krasnozavodskoy",
    "wof:placetype":"locality"
},
  "geometry": {"coordinates":[35.4464,51.7557],"type":"Point"}
}