{
  "type": "Feature",
  "properties": {
    "gn:admin1_code":"57.0",
    "gn:asciiname":"Azarapino",
    "gn:country_code":"RU",
    "gn:dem":132,
    "gn:feature_class":"P",
    "gn:feature_code":"PPL",
    "gn:name":"Azarapino",
    "gn:population":0,
    "gn:timezone":"Europe/Moscow",
    "iso:country":"RU",
    "name:nor_x_preferred":[
        "Azarapino"
    ],
    "name:rus_x_preferred":[
        "\u0410\u0437\u0430\u0440\u0430\u043f\u0438\u043d\u043e"
    ],
    "wof:name":"Azarapino",
    "wof:placetype":"locality"
},
  "geometry": {"coordinates":[43.78103,53.93391999999999],"type":"Point"}
}