{
  "type": "Feature",
  "properties": {
    "gn:admin1_code":"23",
    "gn:asciiname":"Kosmodem'yanskoye",
    "gn:country_code":"RU",
    "gn:dem":18,
    "gn:feature_class":"P",
    "gn:feature_code":"PPL",
    "gn:name":"Kosmodem\u2019yanskoye",
    "gn:population":0,
    "gn:timezone":"Europe/Kaliningrad",
    "iso:country":"RU",
    "name:rus_x_preferred":[
        "\u041a\u043e\u0441\u043c\u043e\u0434\u0435\u043c\u044c\u044f\u043d\u0441\u043a\u043e\u0435"
    ],
    "name:und_x_variant":[
        "Kosmodem\u2019yanskoye"
    ],
    "wof:name":"Kosmodem'yanskoye",
    "wof:placetype":"locality"
},
  "geometry": {"coordinates":[20.69434,54.82272],"type":"Point"}
}