{
  "type": "Feature",
  "properties": {
    "gn:admin1_code":"71",
    "gn:asciiname":"Guseva",
    "gn:country_code":"RU",
    "gn:dem":241,
    "gn:feature_class":"P",
    "gn:feature_code":"PPL",
    "gn:name":"Guseva",
    "gn:population":0,
    "gn:timezone":"Asia/Yekaterinburg",
    "iso:country":"RU",
    "name:rus_x_preferred":[
        "\u0413\u0443\u0441\u0435\u0432\u0430"
    ],
    "wof:name":"Guseva",
    "wof:placetype":"locality"
},
  "geometry": {"coordinates":[61.1599,56.7141],"type":"Point"}
}