{
  "type": "Feature",
  "properties": {
    "gn:admin1_code":"77",
    "gn:asciiname":"Maloye Kuchino",
    "gn:country_code":"RU",
    "gn:dem":199,
    "gn:feature_class":"P",
    "gn:feature_code":"PPL",
    "gn:name":"Maloye Kuchino",
    "gn:population":0,
    "gn:timezone":"Europe/Moscow",
    "iso:country":"RU",
    "name:rus_x_preferred":[
        "\u041c\u0430\u043b\u043e\u0435 \u041a\u0443\u0447\u0438\u043d\u043e"
    ],
    "wof:name":"Maloye Kuchino",
    "wof:placetype":"locality"
},
  "geometry": {"coordinates":[32.25111,56.15389],"type":"Point"}
}