{
  "type": "Feature",
  "properties": {
    "gn:admin1_code":"33",
    "gn:asciiname":"Kolesniki",
    "gn:country_code":"RU",
    "gn:dem":103,
    "gn:feature_class":"P",
    "gn:feature_code":"PPL",
    "gn:name":"Kolesniki",
    "gn:population":0,
    "gn:timezone":"Europe/Kirov",
    "iso:country":"RU",
    "name:rus_x_preferred":[
        "\u041a\u043e\u043b\u0435\u0441\u043d\u0438\u043a\u0438"
    ],
    "wof:name":"Kolesniki",
    "wof:placetype":"locality"
},
  "geometry": {"coordinates":[47.3118,57.3544],"type":"Point"}
}