{
  "type": "Feature",
  "properties": {
    "gn:admin1_code":"29.0",
    "gn:asciiname":"Tayginskiy Lespromkhoz",
    "gn:country_code":"RU",
    "gn:dem":343,
    "gn:feature_class":"P",
    "gn:feature_code":"PPL",
    "gn:name":"Tayginskiy Lespromkhoz",
    "gn:population":0,
    "gn:timezone":"Asia/Novokuznetsk",
    "iso:country":"RU",
    "name:rus_x_preferred":[
        "\u0422\u0430\u0439\u0433\u0438\u043d\u0441\u043a\u0438\u0439 \u041b\u0435\u0441\u043f\u0440\u043e\u043c\u0445\u043e\u0437"
    ],
    "name:und_x_variant":[
        "Zolotaya Tayga Vtoraya"
    ],
    "wof:name":"Tayginskiy Lespromkhoz",
    "wof:placetype":"locality"
},
  "geometry": {"coordinates":[85.1216,54.504],"type":"Point"}
}