{
  "type": "Feature",
  "properties": {
    "gn:admin1_code":"69",
    "gn:asciiname":"Yegor'yevskaya",
    "gn:country_code":"RU",
    "gn:dem":213,
    "gn:feature_class":"P",
    "gn:feature_code":"PPL",
    "gn:name":"Yegor\u2019yevskaya",
    "gn:population":0,
    "gn:timezone":"Europe/Moscow",
    "iso:country":"RU",
    "wof:name":"Yegor'yevskaya",
    "wof:placetype":"locality"
},
  "geometry": {"coordinates":[32.94917,55.05778000000001],"type":"Point"}
}