{
  "type": "Feature",
  "properties": {
    "gn:admin1_code":"17.0",
    "gn:asciiname":"Lyakhe",
    "gn:country_code":"RU",
    "gn:dem":820,
    "gn:feature_class":"P",
    "gn:feature_code":"PPL",
    "gn:name":"Lyakhe",
    "gn:population":0,
    "gn:timezone":"Europe/Moscow",
    "iso:country":"RU",
    "name:rus_x_preferred":[
        "\u041b\u044f\u0445\u0435"
    ],
    "wof:name":"Lyakhe",
    "wof:placetype":"locality"
},
  "geometry": {"coordinates":[47.91322,41.95118],"type":"Point"}
}