{
  "type": "Feature",
  "properties": {
    "gn:admin1_code":"85.0",
    "gn:asciiname":"Bol'shoy Gorokh",
    "gn:country_code":"RU",
    "gn:dem":135,
    "gn:feature_class":"P",
    "gn:feature_code":"PPL",
    "gn:name":"Bol\u2019shoy Gorokh",
    "gn:population":0,
    "gn:timezone":"Europe/Moscow",
    "iso:country":"RU",
    "name:rus_x_preferred":[
        "\u0411\u043e\u043b\u044c\u0448\u043e\u0439 \u0413\u043e\u0440\u043e\u0445"
    ],
    "name:und_x_variant":[
        "Bol\u2019shoy Gorokh",
        "\u0411\u043e\u043b\u044c\u0448\u043e\u0439 \u0413\u043e\u0440\u043e\u0445"
    ],
    "wof:name":"Bol'shoy Gorokh",
    "wof:placetype":"locality"
},
  "geometry": {"coordinates":[42.53816,59.75595],"type":"Point"}
}