{
  "type": "Feature",
  "properties": {
    "gn:admin1_code":"47.0",
    "gn:asciiname":"Suschevo",
    "gn:country_code":"RU",
    "gn:dem":132,
    "gn:feature_class":"P",
    "gn:feature_code":"PPL",
    "gn:name":"Suschevo",
    "gn:population":10,
    "gn:timezone":"Europe/Moscow",
    "iso:country":"RU",
    "name:eng_x_preferred":[
        "Suschevo"
    ],
    "name:rus_x_preferred":[
        "\u0421\u0443\u0449\u0451\u0432\u043e"
    ],
    "wof:name":"Suschevo",
    "wof:placetype":"locality",
    "wof:population":10
},
  "geometry": {"coordinates":[37.75812,56.57566],"type":"Point"}
}