{
  "type": "Feature",
  "properties": {
    "gn:admin1_code":"41",
    "gn:asciiname":"Petrovy Budy",
    "gn:country_code":"RU",
    "gn:dem":204,
    "gn:feature_class":"P",
    "gn:feature_code":"PPL",
    "gn:name":"Petrovy Budy",
    "gn:population":0,
    "gn:timezone":"Europe/Moscow",
    "iso:country":"RU",
    "name:rus_x_preferred":[
        "\u041f\u0435\u0442\u0440\u043e\u0432\u044b \u0411\u0443\u0434\u044b"
    ],
    "name:und_x_variant":[
        "\u041f\u0435\u0442\u0440\u043e\u0432\u044b \u0411\u0443\u0434\u044b"
    ],
    "wof:name":"Petrovy Budy",
    "wof:placetype":"locality"
},
  "geometry": {"coordinates":[35.7148,51.18899999999999],"type":"Point"}
}