{
  "type": "Feature",
  "properties": {
    "gn:admin1_code":"81.0",
    "gn:asciiname":"Echkayun",
    "gn:country_code":"RU",
    "gn:dem":137,
    "gn:feature_class":"P",
    "gn:feature_code":"PPL",
    "gn:name":"Echkayun",
    "gn:population":0,
    "gn:timezone":"Europe/Ulyanovsk",
    "iso:country":"RU",
    "name:rus_x_preferred":[
        "\u042d\u0447\u043a\u0430\u044e\u043d"
    ],
    "wof:name":"Echkayun",
    "wof:placetype":"locality"
},
  "geometry": {"coordinates":[50.15337,54.17413000000001],"type":"Point"}
}