{
  "type": "Feature",
  "properties": {
    "gn:admin1_code":"4",
    "gn:asciiname":"Malaya Kyrkyla",
    "gn:country_code":"RU",
    "gn:dem":636,
    "gn:feature_class":"P",
    "gn:feature_code":"PPL",
    "gn:name":"Malaya Kyrkyla",
    "gn:population":0,
    "gn:timezone":"Asia/Barnaul",
    "iso:country":"RU",
    "name:rus_x_preferred":[
        "\u041c\u0430\u043b\u0430\u044f \u041a\u044b\u0440\u043a\u044b\u043b\u0430"
    ],
    "wof:name":"Malaya Kyrkyla",
    "wof:placetype":"locality"
},
  "geometry": {"coordinates":[85.43333,51.81667],"type":"Point"}
}