{
  "type": "Feature",
  "properties": {
    "gn:admin1_code":"42",
    "gn:asciiname":"Zayatskaya",
    "gn:country_code":"RU",
    "gn:dem":111,
    "gn:feature_class":"P",
    "gn:feature_code":"PPL",
    "gn:name":"Zayatskaya",
    "gn:population":0,
    "gn:timezone":"Europe/Moscow",
    "iso:country":"RU",
    "name:eng_x_preferred":[
        "Zayatskaya"
    ],
    "name:nor_x_preferred":[
        "Zajatskaja"
    ],
    "name:rus_x_preferred":[
        "\u0417\u0430\u044f\u0446\u043a\u0430\u044f"
    ],
    "wof:name":"Zayatskaya",
    "wof:placetype":"locality"
},
  "geometry": {"coordinates":[34.92038,60.81303000000001],"type":"Point"}
}