{
  "type": "Feature",
  "properties": {
    "gn:admin1_code":"8",
    "gn:asciiname":"Sartkamysh",
    "gn:country_code":"RU",
    "gn:dem":292,
    "gn:feature_class":"P",
    "gn:feature_code":"PPL",
    "gn:name":"Sartkamysh",
    "gn:population":0,
    "gn:timezone":"Asia/Yekaterinburg",
    "iso:country":"RU",
    "name:rus_x_preferred":[
        "\u0421\u0430\u0440\u0442\u043a\u0430\u043c\u044b\u0448"
    ],
    "wof:name":"Sartkamysh",
    "wof:placetype":"locality"
},
  "geometry": {"coordinates":[58.36666999999999,51.78333],"type":"Point"}
}