{
  "type": "Feature",
  "properties": {
    "gn:admin1_code":"73",
    "gn:asciiname":"Anakovo",
    "gn:country_code":"RU",
    "gn:dem":145,
    "gn:feature_class":"P",
    "gn:feature_code":"PPL",
    "gn:name":"Anakovo",
    "gn:population":0,
    "gn:timezone":"Europe/Moscow",
    "iso:country":"RU",
    "name:rus_x_preferred":[
        "\u0410\u043d\u0430\u043a\u043e\u0432\u043e"
    ],
    "wof:name":"Anakovo",
    "wof:placetype":"locality"
},
  "geometry": {"coordinates":[52.5812,55.1555],"type":"Point"}
}