{
  "type": "Feature",
  "properties": {
    "gn:admin1_code":"59",
    "gn:asciiname":"Smyalichi",
    "gn:country_code":"RU",
    "gn:dem":156,
    "gn:feature_class":"P",
    "gn:feature_code":"PPL",
    "gn:name":"Smyalichi",
    "gn:population":0,
    "gn:timezone":"Asia/Vladivostok",
    "iso:country":"RU",
    "name:rus_x_preferred":[
        "\u0421\u043c\u044f\u043b\u0438\u0447\u0438"
    ],
    "name:und_x_variant":[
        "Smelichi",
        "Smyalichi",
        "\u0421\u043c\u044f\u043b\u0438\u0447\u0438"
    ],
    "wof:name":"Smyalichi",
    "wof:placetype":"locality"
},
  "geometry": {"coordinates":[132.69036,43.32433],"type":"Point"}
}