{
  "type": "Feature",
  "properties": {
    "gn:admin1_code":"60",
    "gn:asciiname":"Ignatkovo",
    "gn:country_code":"RU",
    "gn:dem":157,
    "gn:feature_class":"P",
    "gn:feature_code":"PPL",
    "gn:name":"Ignatkovo",
    "gn:population":0,
    "gn:timezone":"Europe/Moscow",
    "iso:country":"RU",
    "name:rus_x_preferred":[
        "\u0418\u0433\u043d\u0430\u0442\u043a\u043e\u0432\u043e"
    ],
    "wof:name":"Ignatkovo",
    "wof:placetype":"locality"
},
  "geometry": {"coordinates":[30.0203,56.0037],"type":"Point"}
}