{
  "type": "Feature",
  "properties": {
    "gn:admin1_code":"73",
    "gn:asciiname":"Nizhniye Luzy",
    "gn:country_code":"RU",
    "gn:dem":84,
    "gn:feature_class":"P",
    "gn:feature_code":"PPL",
    "gn:name":"Nizhniye Luzy",
    "gn:population":0,
    "gn:timezone":"Europe/Moscow",
    "iso:country":"RU",
    "name:rus_x_preferred":[
        "\u041d\u0438\u0436\u043d\u0438\u0435 \u041b\u0443\u0437\u044b"
    ],
    "wof:name":"Nizhniye Luzy",
    "wof:placetype":"locality"
},
  "geometry": {"coordinates":[52.0104,55.4447],"type":"Point"}
}