{
  "type": "Feature",
  "properties": {
    "gn:admin1_code":"43",
    "gn:asciiname":"Pol'skoye",
    "gn:country_code":"RU",
    "gn:dem":235,
    "gn:feature_class":"P",
    "gn:feature_code":"PPL",
    "gn:name":"Pol\u2019skoye",
    "gn:population":0,
    "gn:timezone":"Europe/Moscow",
    "iso:country":"RU",
    "name:rus_x_preferred":[
        "\u041f\u043e\u043b\u044c\u0441\u043a\u043e\u0435"
    ],
    "name:und_x_variant":[
        "Pol\u2019skoye",
        "\u041f\u043e\u043b\u044c\u0441\u043a\u043e\u0435",
        "Pol\u2019skaya"
    ],
    "wof:name":"Pol'skoye",
    "wof:placetype":"locality"
},
  "geometry": {"coordinates":[38.08288,52.81100000000001],"type":"Point"}
}