{
  "type": "Feature",
  "properties": {
    "gn:admin1_code":"78",
    "gn:asciiname":"Dorozhnyy",
    "gn:country_code":"RU",
    "gn:dem":62,
    "gn:feature_class":"P",
    "gn:feature_code":"PPL",
    "gn:name":"Dorozhnyy",
    "gn:population":0,
    "gn:timezone":"Asia/Yekaterinburg",
    "iso:country":"RU",
    "name:rus_x_preferred":[
        "\u0414\u043e\u0440\u043e\u0436\u043d\u044b\u0439"
    ],
    "name:und_x_variant":[
        "\u0414\u043e\u0440\u043e\u0436\u043d\u044b\u0439"
    ],
    "wof:name":"Dorozhnyy",
    "wof:placetype":"locality"
},
  "geometry": {"coordinates":[65.6574,57.169],"type":"Point"}
}