{
  "type": "Feature",
  "properties": {
    "gn:admin1_code":"10",
    "gn:asciiname":"Kharichi",
    "gn:country_code":"RU",
    "gn:dem":188,
    "gn:feature_class":"P",
    "gn:feature_code":"PPL",
    "gn:name":"Kharichi",
    "gn:population":0,
    "gn:timezone":"Europe/Moscow",
    "iso:country":"RU",
    "name:rus_x_preferred":[
        "\u0425\u0430\u0440\u0438\u0447\u0438"
    ],
    "wof:name":"Kharichi",
    "wof:placetype":"locality"
},
  "geometry": {"coordinates":[33.24139,53.73833000000001],"type":"Point"}
}