{
  "type": "Feature",
  "properties": {
    "gn:admin1_code":"20",
    "gn:asciiname":"Galdun",
    "gn:country_code":"RU",
    "gn:dem":569,
    "gn:feature_class":"P",
    "gn:feature_code":"PPL",
    "gn:name":"Galdun",
    "gn:population":0,
    "gn:timezone":"Asia/Irkutsk",
    "iso:country":"RU",
    "name:rus_x_preferred":[
        "\u0413\u0430\u043b\u0434\u0443\u043d"
    ],
    "wof:name":"Galdun",
    "wof:placetype":"locality"
},
  "geometry": {"coordinates":[99.78333000000001,54.18333000000001],"type":"Point"}
}