{
  "type": "Feature",
  "properties": {
    "gn:admin1_code":"56",
    "gn:asciiname":"Ugol'noye",
    "gn:country_code":"RU",
    "gn:dem":213,
    "gn:feature_class":"P",
    "gn:feature_code":"PPL",
    "gn:name":"Ugol\u2019noye",
    "gn:population":0,
    "gn:timezone":"Europe/Moscow",
    "iso:country":"RU",
    "name:und_x_variant":[
        "Ugol\u2019naya",
        "Ugol\u2019nyy",
        "Ugol\u2019noye"
    ],
    "wof:name":"Ugol'noye",
    "wof:placetype":"locality"
},
  "geometry": {"coordinates":[37.33561,52.45123],"type":"Point"}
}