{
  "type": "Feature",
  "properties": {
    "gn:admin1_code":"45",
    "gn:asciiname":"Polevaya",
    "gn:country_code":"RU",
    "gn:dem":60,
    "gn:feature_class":"P",
    "gn:feature_code":"PPL",
    "gn:name":"Polevaya",
    "gn:population":0,
    "gn:timezone":"Europe/Moscow",
    "iso:country":"RU",
    "name:eng_x_preferred":[
        "Polevaya"
    ],
    "name:nor_x_preferred":[
        "Polevaja"
    ],
    "name:rus_x_preferred":[
        "\u041f\u043e\u043b\u0435\u0432\u0430\u044f"
    ],
    "name:und_x_variant":[
        "\u041f\u043e\u043b\u0435\u0432\u0430\u044f",
        "Polevaya"
    ],
    "wof:name":"Polevaya",
    "wof:placetype":"locality"
},
  "geometry": {"coordinates":[48.34306,56.02083],"type":"Point"}
}