{
  "type": "Feature",
  "properties": {
    "gn:admin1_code":"28",
    "gn:asciiname":"Verkhniy Konets",
    "gn:country_code":"RU",
    "gn:dem":17,
    "gn:feature_class":"P",
    "gn:feature_code":"PPL",
    "gn:name":"Verkhniy Konets",
    "gn:population":0,
    "gn:timezone":"Europe/Moscow",
    "iso:country":"RU",
    "name:fin_x_preferred":[
        "Yl\u00e4p\u00e4\u00e4"
    ],
    "name:fin_x_variant":[
        "Yl\u00e4akja"
    ],
    "wof:name":"Verkhniy Konets",
    "wof:placetype":"locality"
},
  "geometry": {"coordinates":[32.66667,61.13333000000001],"type":"Point"}
}