{
  "type": "Feature",
  "properties": {
    "gn:admin1_code":"38",
    "gn:asciiname":"Kraynyaya Shchel'",
    "gn:country_code":"RU",
    "gn:dem":215,
    "gn:feature_class":"P",
    "gn:feature_code":"PPL",
    "gn:name":"Kraynyaya Shchel\u2019",
    "gn:population":0,
    "gn:timezone":"Europe/Moscow",
    "iso:country":"RU",
    "name:rus_x_preferred":[
        "\u041a\u0440\u0430\u0439\u043d\u044f\u044f \u0429\u0435\u043b\u044c"
    ],
    "name:und_x_variant":[
        "Urochishche Kraynyaya Shchel\u2019",
        "Kraynyaya Shchel\u2019",
        "\u041a\u0440\u0430\u0439\u043d\u044f\u044f \u0429\u0435\u043b\u044c"
    ],
    "wof:name":"Kraynyaya Shchel'",
    "wof:placetype":"locality"
},
  "geometry": {"coordinates":[39.1986,44.3509],"type":"Point"}
}