{
  "type": "Feature",
  "properties": {
    "gn:admin1_code":"90",
    "gn:asciiname":"Imeni Voroshilova",
    "gn:country_code":"RU",
    "gn:dem":296,
    "gn:feature_class":"P",
    "gn:feature_code":"PPL",
    "gn:name":"Imeni Voroshilova",
    "gn:population":0,
    "gn:timezone":"Asia/Yekaterinburg",
    "iso:country":"RU",
    "name:rus_x_preferred":[
        "\u0418\u043c\u0435\u043d\u0438 \u0412\u043e\u0440\u043e\u0448\u0438\u043b\u043e\u0432\u0430"
    ],
    "name:und_x_variant":[
        "\u0418\u043c\u0435\u043d\u0438 \u0412\u043e\u0440\u043e\u0448\u0438\u043b\u043e\u0432\u0430"
    ],
    "wof:name":"Imeni Voroshilova",
    "wof:placetype":"locality"
},
  "geometry": {"coordinates":[57.15,56.55],"type":"Point"}
}