{
  "type": "Feature",
  "properties": {
    "gn:admin1_code":"41.0",
    "gn:asciiname":"Khuligya",
    "gn:country_code":"RU",
    "gn:dem":193,
    "gn:feature_class":"P",
    "gn:feature_code":"PPL",
    "gn:name":"Khuligya",
    "gn:population":0,
    "gn:timezone":"Europe/Moscow",
    "iso:country":"RU",
    "name:rus_x_preferred":[
        "\u0425\u0443\u043b\u0438\u0433\u044f"
    ],
    "name:und_x_variant":[
        "\u0425\u0443\u043b\u0438\u0433\u044f"
    ],
    "wof:name":"Khuligya",
    "wof:placetype":"locality"
},
  "geometry": {"coordinates":[36.80373,51.59192],"type":"Point"}
}