{
  "type": "Feature",
  "properties": {
    "gn:admin1_code":"16",
    "gn:asciiname":"Lashch-Tayaba",
    "gn:country_code":"RU",
    "gn:dem":141,
    "gn:feature_class":"P",
    "gn:feature_code":"PPL",
    "gn:name":"Lashch-Tayaba",
    "gn:population":0,
    "gn:timezone":"Europe/Moscow",
    "iso:country":"RU",
    "name:rus_x_preferred":[
        "\u041b\u0430\u0449-\u0422\u0430\u044f\u0431\u0430"
    ],
    "name:und_x_variant":[
        "Lash-Tayba",
        "Lash-Tayaba",
        "Lash-Toyaba",
        "Lashch-Tayaba",
        "\u041b\u0430\u0449-\u0422\u0430\u044f\u0431\u0430"
    ],
    "wof:name":"Lashch-Tayaba",
    "wof:placetype":"locality"
},
  "geometry": {"coordinates":[47.9937,55.0298],"type":"Point"}
}