{
  "type": "Feature",
  "properties": {
    "gn:admin1_code":"42.0",
    "gn:asciiname":"Cheklo",
    "gn:country_code":"RU",
    "gn:dem":76,
    "gn:feature_class":"P",
    "gn:feature_code":"PPL",
    "gn:name":"Cheklo",
    "gn:population":0,
    "gn:timezone":"Europe/Moscow",
    "iso:country":"RU",
    "name:rus_x_preferred":[
        "\u0427\u0435\u043a\u043b\u043e"
    ],
    "wof:name":"Cheklo",
    "wof:placetype":"locality"
},
  "geometry": {"coordinates":[29.96667,58.51667],"type":"Point"}
}