{
  "type": "Feature",
  "properties": {
    "gn:admin1_code":"93",
    "gn:asciiname":"Talakan",
    "gn:country_code":"RU",
    "gn:dem":774,
    "gn:feature_class":"P",
    "gn:feature_code":"PPL",
    "gn:name":"Talakan",
    "gn:population":0,
    "gn:timezone":"Asia/Chita",
    "iso:country":"RU",
    "name:ceb_x_preferred":[
        "Talakan"
    ],
    "name:che_x_preferred":[
        "\u0422\u0430\u043b\u0430\u043a\u0430\u043d"
    ],
    "name:deu_x_preferred":[
        "Talakan"
    ],
    "name:hye_x_preferred":[
        "\u054f\u0561\u056c\u0561\u056f\u0561\u0576"
    ],
    "name:ita_x_preferred":[
        "Talakan"
    ],
    "name:rus_x_preferred":[
        "\u0422\u0430\u043b\u0430\u043a\u0430\u043d"
    ],
    "name:tgk_x_preferred":[
        "\u0422\u0430\u043b\u0430\u043a\u0430\u043d"
    ],
    "wof:name":"Talakan",
    "wof:placetype":"locality"
},
  "geometry": {"coordinates":[115.90000000000001,52.75],"type":"Point"}
}