{
  "type": "Feature",
  "properties": {
    "gn:admin1_code":"93",
    "gn:asciiname":"Talakan",
    "gn:country_code":"RU",
    "gn:dem":774,
    "gn:feature_class":"P",
    "gn:feature_code":"PPL",
    "gn:name":"Talakan",
    "gn:population":0,
    "gn:timezone":"Asia/Chita",
    "iso:country":"RU",
    "wof:name":"Talakan",
    "wof:placetype":"locality"
},
  "geometry": {"coordinates":[115.90000000000001,52.75],"type":"Point"}
}