{
  "type": "Feature",
  "properties": {
    "gn:admin1_code":"59.0",
    "gn:asciiname":"Kaymanovka",
    "gn:country_code":"RU",
    "gn:dem":81,
    "gn:feature_class":"P",
    "gn:feature_code":"PPL",
    "gn:name":"Kaymanovka",
    "gn:population":0,
    "gn:timezone":"Asia/Vladivostok",
    "iso:country":"RU",
    "name:rus_x_preferred":[
        "\u041a\u0430\u0439\u043c\u0430\u043d\u043e\u0432\u043a\u0430"
    ],
    "wof:name":"Kaymanovka",
    "wof:placetype":"locality"
},
  "geometry": {"coordinates":[132.23308,43.63073],"type":"Point"}
}