{
  "type": "Feature",
  "properties": {
    "gn:admin1_code":"51",
    "gn:asciiname":"Glushka",
    "gn:country_code":"RU",
    "gn:dem":145,
    "gn:feature_class":"P",
    "gn:feature_code":"PPL",
    "gn:name":"Glushka",
    "gn:population":0,
    "gn:timezone":"Europe/Moscow",
    "iso:country":"RU",
    "name:rus_x_preferred":[
        "\u0413\u043b\u0443\u0448\u043a\u0430"
    ],
    "name:und_x_variant":[
        "\u0413\u043b\u0443\u0448\u043a\u0430"
    ],
    "wof:name":"Glushka",
    "wof:placetype":"locality"
},
  "geometry": {"coordinates":[45.8682,57.9764],"type":"Point"}
}