{
  "type": "Feature",
  "properties": {
    "gn:admin1_code":"41",
    "gn:asciiname":"Chernyanka",
    "gn:country_code":"RU",
    "gn:dem":207,
    "gn:feature_class":"P",
    "gn:feature_code":"PPL",
    "gn:name":"Chernyanka",
    "gn:population":0,
    "gn:timezone":"Europe/Moscow",
    "iso:country":"RU",
    "name:rus_x_preferred":[
        "\u0427\u0435\u0440\u043d\u044f\u043d\u043a\u0430"
    ],
    "wof:name":"Chernyanka",
    "wof:placetype":"locality"
},
  "geometry": {"coordinates":[37.3325,51.9063],"type":"Point"}
}