{
  "type": "Feature",
  "properties": {
    "gn:admin1_code":"32",
    "gn:asciiname":"Seliyarovo",
    "gn:cc2":"RU",
    "gn:country_code":"RU",
    "gn:dem":36,
    "gn:feature_class":"P",
    "gn:feature_code":"PPL",
    "gn:name":"Seliyarovo",
    "gn:population":0,
    "gn:timezone":"Asia/Yekaterinburg",
    "iso:country":"RU",
    "name:eng_x_preferred":[
        "Seliyarovo"
    ],
    "name:nor_x_preferred":[
        "Selijarovo"
    ],
    "name:rus_x_preferred":[
        "\u0421\u0435\u043b\u0438\u044f\u0440\u043e\u0432\u043e"
    ],
    "name:und_x_variant":[
        "Seliyarskoye",
        "\u0421\u0435\u043b\u0438\u044f\u0440\u043e\u0432\u043e",
        "Seliyarovo"
    ],
    "wof:name":"Seliyarovo",
    "wof:placetype":"locality"
},
  "geometry": {"coordinates":[70.3425,61.29056],"type":"Point"}
}