{
  "type": "Feature",
  "properties": {
    "gn:admin1_code":"69.0",
    "gn:asciiname":"Novoye Rozhnovo",
    "gn:country_code":"RU",
    "gn:dem":227,
    "gn:feature_class":"P",
    "gn:feature_code":"PPL",
    "gn:name":"Novoye Rozhnovo",
    "gn:population":0,
    "gn:timezone":"Europe/Moscow",
    "iso:country":"RU",
    "name:rus_x_preferred":[
        "\u041d\u043e\u0432\u043e\u0435 \u0420\u043e\u0436\u043d\u043e\u0432\u043e"
    ],
    "name:und_x_variant":[
        "Chervonoye-Rozhnovo"
    ],
    "wof:name":"Novoye Rozhnovo",
    "wof:placetype":"locality"
},
  "geometry": {"coordinates":[34.44764,55.11829],"type":"Point"}
}