{
  "type": "Feature",
  "properties": {
    "gn:admin1_code":"77.0",
    "gn:asciiname":"Bitelevo",
    "gn:country_code":"RU",
    "gn:dem":165,
    "gn:feature_class":"P",
    "gn:feature_code":"PPL",
    "gn:name":"Bitel\u00ebvo",
    "gn:population":0,
    "gn:timezone":"Europe/Moscow",
    "iso:country":"RU",
    "name:rus_x_preferred":[
        "\u0411\u0438\u0442\u0435\u043b\u0451\u0432\u043e"
    ],
    "name:und_x_variant":[
        "Bitel\u00ebvo",
        "\u0411\u0438\u0442\u0435\u043b\u0451\u0432\u043e"
    ],
    "wof:name":"Bitelevo",
    "wof:placetype":"locality"
},
  "geometry": {"coordinates":[38.06667,56.83333],"type":"Point"}
}