{
  "type": "Feature",
  "properties": {
    "gn:country":"RU",
    "gn:fcode":"PPL",
    "gn:population":0,
    "iso:country":"RU",
    "name:eng_x_preferred":[
        "Kochnevskoye"
    ],
    "name:nor_x_preferred":[
        "Kotsjnevskoje"
    ],
    "name:rus_x_preferred":[
        "\u041a\u043e\u0447\u043d\u0435\u0432\u0441\u043a\u043e\u0435"
    ],
    "qs:name":"Kochnevskoye",
    "qs:name_adm0":"Russia",
    "qs:name_adm1":"Sverdlovsk Oblast",
    "qs:photos_9r":0,
    "qs:photos_sr":0,
    "qs:placetype":"Town",
    "qs:pop_sr":"3",
    "wof:name":"Kochnevskoye",
    "wof:placetype":"locality",
    "wof:population":0
},
  "geometry": {"coordinates":[62.47219,57.08627],"type":"Point"}
}