{
  "type": "Feature",
  "properties": {
    "gn:admin1_code":"76",
    "gn:asciiname":"Ignatovka",
    "gn:country_code":"RU",
    "gn:dem":223,
    "gn:feature_class":"P",
    "gn:feature_code":"PPL",
    "gn:name":"Ignatovka",
    "gn:population":0,
    "gn:timezone":"Europe/Moscow",
    "iso:country":"RU",
    "name:rus_x_preferred":[
        "\u0418\u0433\u043d\u0430\u0442\u043e\u0432\u043a\u0430"
    ],
    "name:und_x_variant":[
        "\u0418\u0433\u043d\u0430\u0442\u043e\u0432\u043a\u0430"
    ],
    "wof:name":"Ignatovka",
    "wof:placetype":"locality"
},
  "geometry": {"coordinates":[37.00149,54.39483000000001],"type":"Point"}
}