{
  "type": "Feature",
  "properties": {
    "gn:admin1_code":"28",
    "gn:asciiname":"Kirozero",
    "gn:country_code":"RU",
    "gn:dem":237,
    "gn:feature_class":"P",
    "gn:feature_code":"PPL",
    "gn:name":"Kirozero",
    "gn:population":0,
    "gn:timezone":"Europe/Moscow",
    "iso:country":"RU",
    "name:fin_x_preferred":[
        "Tiiro"
    ],
    "name:rus_x_preferred":[
        "\u041a\u0438\u0440\u043e\u0437\u0435\u0440\u043e"
    ],
    "name:und_x_variant":[
        "Kitozero",
        "Kirozero",
        "\u041a\u0438\u0440\u043e\u0437\u0435\u0440\u043e",
        "Koljola"
    ],
    "wof:name":"Kirozero",
    "wof:placetype":"locality"
},
  "geometry": {"coordinates":[29.94564,65.58309],"type":"Point"}
}