{
  "type": "Feature",
  "properties": {
    "gn:admin1_code":"30",
    "gn:asciiname":"Goreloye",
    "gn:cc2":"RU",
    "gn:country_code":"RU",
    "gn:dem":107,
    "gn:feature_class":"P",
    "gn:feature_code":"PPL",
    "gn:name":"Goreloye",
    "gn:population":0,
    "gn:timezone":"Asia/Vladivostok",
    "iso:country":"RU",
    "name:rus_x_preferred":[
        "\u0413\u043e\u0440\u0435\u043b\u043e\u0435"
    ],
    "name:und_x_variant":[
        "Stoibishche Goreloye",
        "Fedorovskaya",
        "Goreloye",
        "\u0413\u043e\u0440\u0435\u043b\u043e\u0435"
    ],
    "wof:name":"Goreloye",
    "wof:placetype":"locality"
},
  "geometry": {"coordinates":[136.19999999999999,52.48333],"type":"Point"}
}