{
  "type": "Feature",
  "properties": {
    "gn:admin1_code":"71",
    "gn:asciiname":"Kishkinskoye",
    "gn:country_code":"RU",
    "gn:dem":88,
    "gn:feature_class":"P",
    "gn:feature_code":"PPL",
    "gn:name":"Kishkinskoye",
    "gn:population":0,
    "gn:timezone":"Asia/Yekaterinburg",
    "iso:country":"RU",
    "name:eng_x_preferred":[
        "Kishkinskoye"
    ],
    "name:nor_x_preferred":[
        "Kisjkinskoje"
    ],
    "name:rus_x_preferred":[
        "\u041a\u0438\u0448\u043a\u0438\u043d\u0441\u043a\u043e\u0435"
    ],
    "name:und_x_variant":[
        "Kashkinskoye"
    ],
    "wof:name":"Kishkinskoye",
    "wof:placetype":"locality"
},
  "geometry": {"coordinates":[61.88391,58.4599],"type":"Point"}
}