{
  "type": "Feature",
  "properties": {
    "gn:admin1_code":"55",
    "gn:asciiname":"Kozlovka",
    "gn:country_code":"RU",
    "gn:dem":133,
    "gn:feature_class":"P",
    "gn:feature_code":"PPL",
    "gn:name":"Kozlovka",
    "gn:population":0,
    "gn:timezone":"Asia/Yekaterinburg",
    "iso:country":"RU",
    "name:ara_x_preferred":[
        "\u0643\u0648\u0632\u0644\u0648\u0641\u0643\u0627"
    ],
    "name:eng_x_preferred":[
        "Kozlovka"
    ],
    "name:nor_x_preferred":[
        "Kozlovka"
    ],
    "name:rus_x_preferred":[
        "\u041a\u043e\u0437\u043b\u043e\u0432\u043a\u0430"
    ],
    "name:und_x_variant":[
        "\u041a\u043e\u0437\u043b\u043e\u0432\u043a\u0430",
        "Kozlovka"
    ],
    "wof:name":"Kozlovka",
    "wof:placetype":"locality"
},
  "geometry": {"coordinates":[53.8127,52.0118],"type":"Point"}
}