{
  "type": "Feature",
  "properties": {
    "gn:admin1_code":"54",
    "gn:asciiname":"Tarnaly",
    "gn:country_code":"RU",
    "gn:dem":107,
    "gn:feature_class":"P",
    "gn:feature_code":"PPL",
    "gn:name":"Tarnaly",
    "gn:population":0,
    "gn:timezone":"Asia/Omsk",
    "iso:country":"RU",
    "name:eng_x_preferred":[
        "Tarnaly"
    ],
    "name:nor_x_preferred":[
        "Tarnaly"
    ],
    "name:rus_x_preferred":[
        "\u0422\u0430\u0440\u043d\u0430\u043b\u044b"
    ],
    "wof:name":"Tarnaly",
    "wof:placetype":"locality"
},
  "geometry": {"coordinates":[72.66984000000002,54.5962],"type":"Point"}
}