{
  "type": "Feature",
  "properties": {
    "gn:admin1_code":"47",
    "gn:asciiname":"Arin'kino",
    "gn:country_code":"RU",
    "gn:dem":162,
    "gn:feature_class":"P",
    "gn:feature_code":"PPL",
    "gn:name":"Arin\u2019kino",
    "gn:population":0,
    "gn:timezone":"Europe/Moscow",
    "iso:country":"RU",
    "name:nor_x_preferred":[
        "Arinkino"
    ],
    "name:rus_x_preferred":[
        "\u0410\u0440\u0438\u043d\u044c\u043a\u0438\u043d\u043e"
    ],
    "name:und_x_variant":[
        "Arin\u2019kino"
    ],
    "wof:name":"Arin'kino",
    "wof:placetype":"locality"
},
  "geometry": {"coordinates":[35.50998,56.36097],"type":"Point"}
}