{
  "type": "Feature",
  "properties": {
    "gn:admin1_code":"88",
    "gn:asciiname":"Lytkovo",
    "gn:country_code":"RU",
    "gn:dem":233,
    "gn:feature_class":"P",
    "gn:feature_code":"PPL",
    "gn:name":"Lytkovo",
    "gn:population":0,
    "gn:timezone":"Europe/Moscow",
    "iso:country":"RU",
    "name:rus_x_preferred":[
        "\u041b\u044b\u0442\u043a\u043e\u0432\u043e"
    ],
    "name:und_x_variant":[
        "\u041b\u044b\u0442\u043a\u043e\u0432\u043e"
    ],
    "wof:name":"Lytkovo",
    "wof:placetype":"locality"
},
  "geometry": {"coordinates":[38.6435,57.0794],"type":"Point"}
}