{
  "type": "Feature",
  "properties": {
    "gn:admin1_code":"9.0",
    "gn:asciiname":"Kalasnoye",
    "gn:country_code":"RU",
    "gn:dem":185,
    "gn:feature_class":"P",
    "gn:feature_code":"PPL",
    "gn:name":"Kalasnoye",
    "gn:population":0,
    "gn:timezone":"Europe/Moscow",
    "iso:country":"RU",
    "name:rus_x_preferred":[
        "\u041a\u0430\u043b\u0430\u0441\u043d\u043e\u0435"
    ],
    "wof:name":"Kalasnoye",
    "wof:placetype":"locality"
},
  "geometry": {"coordinates":[36.26861,50.86417],"type":"Point"}
}