{
  "type": "Feature",
  "properties": {
    "gn:admin1_code":"84",
    "gn:asciiname":"Kosorotov",
    "gn:cc2":"RU",
    "gn:country_code":"RU",
    "gn:dem":72,
    "gn:feature_class":"P",
    "gn:feature_code":"PPL",
    "gn:name":"Kosorotov",
    "gn:population":0,
    "gn:timezone":"Europe/Volgograd",
    "iso:country":"RU",
    "name:rus_x_preferred":[
        "\u041a\u043e\u0441\u043e\u0440\u043e\u0442\u043e\u0432"
    ],
    "name:und_x_variant":[
        "Khutor Kosorotov",
        "Kosorotovskiy",
        "Kosorotov"
    ],
    "wof:name":"Kosorotov",
    "wof:placetype":"locality"
},
  "geometry": {"coordinates":[42.42611,49.96222],"type":"Point"}
}