{
  "type": "Feature",
  "properties": {
    "gn:admin1_code":"33.0",
    "gn:asciiname":"Kolevatovy",
    "gn:country_code":"RU",
    "gn:dem":133,
    "gn:feature_class":"P",
    "gn:feature_code":"PPL",
    "gn:name":"Kolevatovy",
    "gn:population":0,
    "gn:timezone":"Europe/Kirov",
    "iso:country":"RU",
    "name:rus_x_preferred":[
        "\u041a\u043e\u043b\u0435\u0432\u0430\u0442\u043e\u0432\u044b"
    ],
    "wof:name":"Kolevatovy",
    "wof:placetype":"locality"
},
  "geometry": {"coordinates":[48.68489,58.5718],"type":"Point"}
}