{
  "type": "Feature",
  "properties": {
    "gn:admin1_code":"69",
    "gn:asciiname":"Ivanovo-Gudino",
    "gn:country_code":"RU",
    "gn:dem":203,
    "gn:feature_class":"P",
    "gn:feature_code":"PPL",
    "gn:name":"Ivanovo-Gudino",
    "gn:population":0,
    "gn:timezone":"Europe/Moscow",
    "iso:country":"RU",
    "name:eng_x_preferred":[
        "Ivanovo-Gudino"
    ],
    "name:nor_x_preferred":[
        "Ivano-Gudino"
    ],
    "name:rus_x_preferred":[
        "\u0418\u0432\u0430\u043d\u043e-\u0413\u0443\u0434\u0438\u043d\u043e"
    ],
    "name:rus_x_variant":[
        "\u0418\u0432\u0430\u043d\u043e\u0432\u043e-\u0413\u0443\u0434\u0438\u043d\u043e"
    ],
    "name:und_x_variant":[
        "Gudino"
    ],
    "wof:name":"Ivanovo-Gudino",
    "wof:placetype":"locality"
},
  "geometry": {"coordinates":[33.40995,54.6432],"type":"Point"}
}