{
  "type": "Feature",
  "properties": {
    "gn:admin1_code":"62.0",
    "gn:asciiname":"Malaya Vitusha",
    "gn:country_code":"RU",
    "gn:dem":164,
    "gn:feature_class":"P",
    "gn:feature_code":"PPL",
    "gn:name":"Malaya Vitusha",
    "gn:population":0,
    "gn:timezone":"Europe/Moscow",
    "iso:country":"RU",
    "name:rus_x_preferred":[
        "\u041c\u0430\u043b\u0430\u044f \u0412\u0438\u0442\u0443\u0448\u0430"
    ],
    "wof:name":"Malaya Vitusha",
    "wof:placetype":"locality"
},
  "geometry": {"coordinates":[40.9816,53.511],"type":"Point"}
}