{
  "type": "Feature",
  "properties": {
    "gn:admin1_code":"33.0",
    "gn:asciiname":"Monastyrek",
    "gn:country_code":"RU",
    "gn:dem":168,
    "gn:feature_class":"P",
    "gn:feature_code":"PPL",
    "gn:name":"Monastyr\u00ebk",
    "gn:population":0,
    "gn:timezone":"Europe/Kirov",
    "iso:country":"RU",
    "name:rus_x_preferred":[
        "\u041c\u043e\u043d\u0430\u0441\u0442\u044b\u0440\u0451\u043a"
    ],
    "name:und_x_variant":[
        "Monastyr\u00ebk"
    ],
    "wof:name":"Monastyrek",
    "wof:placetype":"locality"
},
  "geometry": {"coordinates":[50.08407,58.63608000000001],"type":"Point"}
}