{
  "type": "Feature",
  "properties": {
    "gn:admin1_code":"56",
    "gn:asciiname":"Krivcheil'inskiy",
    "gn:country_code":"RU",
    "gn:dem":179,
    "gn:feature_class":"P",
    "gn:feature_code":"PPL",
    "gn:name":"Krivcheil\u2019inskiy",
    "gn:population":0,
    "gn:timezone":"Europe/Moscow",
    "iso:country":"RU",
    "name:rus_x_preferred":[
        "\u041a\u0440\u0438\u0432\u0447\u0435\u0438\u043b\u044c\u0438\u043d\u0441\u043a\u0438\u0439"
    ],
    "name:und_x_variant":[
        "Krivchevskiy",
        "Krivcheil\u2019inskiy"
    ],
    "wof:name":"Krivcheil'inskiy",
    "wof:placetype":"locality"
},
  "geometry": {"coordinates":[35.93121,53.32908000000001],"type":"Point"}
}