{
  "type": "Feature",
  "properties": {
    "gn:admin1_code":"17",
    "gn:asciiname":"Rosslambeyka",
    "gn:cc2":"RU",
    "gn:country_code":"RU",
    "gn:dem":-24,
    "gn:feature_class":"P",
    "gn:feature_code":"PPL",
    "gn:name":"Rosslambeyka",
    "gn:population":0,
    "gn:timezone":"Europe/Moscow",
    "iso:country":"RU",
    "name:rus_x_preferred":[
        "\u0420\u043e\u0441\u0441\u043b\u0430\u043c\u0431\u0435\u0439\u043a\u0430"
    ],
    "name:und_x_variant":[
        "Raslambeychik",
        "Rosslambeyka",
        "\u0420\u043e\u0441\u0441\u043b\u0430\u043c\u0431\u0435\u0439\u043a\u0430"
    ],
    "wof:name":"Rosslambeyka",
    "wof:placetype":"locality"
},
  "geometry": {"coordinates":[47.44917,43.69472],"type":"Point"}
}