{
  "type": "Feature",
  "properties": {
    "gn:admin1_code":"61",
    "gn:asciiname":"Golubovka",
    "gn:country_code":"RU",
    "gn:dem":102,
    "gn:feature_class":"P",
    "gn:feature_code":"PPL",
    "gn:name":"Golubovka",
    "gn:population":0,
    "gn:timezone":"Europe/Moscow",
    "iso:country":"RU",
    "name:eng_x_preferred":[
        "Golubovka"
    ],
    "name:nor_x_preferred":[
        "Golubovka"
    ],
    "name:rus_x_preferred":[
        "\u0413\u043e\u043b\u0443\u0431\u043e\u0432\u043a\u0430"
    ],
    "wof:name":"Golubovka",
    "wof:placetype":"locality"
},
  "geometry": {"coordinates":[40.79942,46.90588],"type":"Point"}
}