{
  "type": "Feature",
  "properties": {
    "gn:admin1_code":"54",
    "gn:asciiname":"Torat",
    "gn:country_code":"RU",
    "gn:dem":123,
    "gn:feature_class":"P",
    "gn:feature_code":"PPL",
    "gn:name":"Torat",
    "gn:population":0,
    "gn:timezone":"Asia/Omsk",
    "iso:country":"RU",
    "wof:name":"Torat",
    "wof:placetype":"locality"
},
  "geometry": {"coordinates":[71.17988000000003,54.75174000000001],"type":"Point"}
}