{
  "type": "Feature",
  "properties": {
    "gn:country":"RU",
    "gn:fcode":"PPL",
    "gn:pop":83,
    "iso:country":"RU",
    "name:rus_x_preferred":[
        "\u0412\u0435\u0441\u044c\u043a\u043e\u0432\u043e"
    ],
    "qs:name":"Ves'kovo",
    "qs:photos_9r":0,
    "qs:photos_sr":0,
    "qs:pop_sr":"1",
    "wof:name":"Ves'kovo",
    "wof:placetype":"locality",
    "wof:population":83
},
  "geometry": {"coordinates":[38.78247,56.72149],"type":"Point"}
}