{
  "type": "Feature",
  "properties": {
    "gn:admin1_code":"45.0",
    "gn:asciiname":"Pistash",
    "gn:country_code":"RU",
    "gn:dem":172,
    "gn:feature_class":"P",
    "gn:feature_code":"PPL",
    "gn:name":"Pistash",
    "gn:population":0,
    "gn:timezone":"Europe/Moscow",
    "iso:country":"RU",
    "name:rus_x_preferred":[
        "\u041f\u0438\u0441\u0442\u0430\u0448"
    ],
    "name:und_x_variant":[
        "\u041f\u0438\u0441\u0442\u0430\u0448"
    ],
    "wof:name":"Pistash",
    "wof:placetype":"locality"
},
  "geometry": {"coordinates":[48.85,56.855],"type":"Point"}
}