{
  "type": "Feature",
  "properties": {
    "gn:admin1_code":"83",
    "gn:asciiname":"Panteleyevo",
    "gn:country_code":"RU",
    "gn:dem":200,
    "gn:feature_class":"P",
    "gn:feature_code":"PPL",
    "gn:name":"Panteleyevo",
    "gn:population":0,
    "gn:timezone":"Europe/Moscow",
    "iso:country":"RU",
    "name:rus_x_preferred":[
        "\u041f\u0430\u043d\u0442\u0435\u043b\u0435\u0435\u0432\u043e"
    ],
    "wof:name":"Panteleyevo",
    "wof:placetype":"locality"
},
  "geometry": {"coordinates":[39.4081,56.2089],"type":"Point"}
}