{
  "type": "Feature",
  "properties": {
    "gn:admin1_code":"91",
    "gn:asciiname":"Novopoltavka",
    "gn:country_code":"RU",
    "gn:dem":305,
    "gn:feature_class":"P",
    "gn:feature_code":"PPL",
    "gn:name":"Novopoltavka",
    "gn:population":0,
    "gn:timezone":"Asia/Krasnoyarsk",
    "iso:country":"RU",
    "name:ceb_x_preferred":[
        "Novopoltavka"
    ],
    "name:eng_x_preferred":[
        "Novopoltavka"
    ],
    "name:nor_x_preferred":[
        "Novopoltavka"
    ],
    "name:ron_x_preferred":[
        "Novopoltavka"
    ],
    "name:rus_x_preferred":[
        "\u041d\u043e\u0432\u043e\u043f\u043e\u043b\u0442\u0430\u0432\u043a\u0430"
    ],
    "name:ukr_x_preferred":[
        "\u041d\u043e\u0432\u043e\u043f\u043e\u043b\u0442\u0430\u0432\u043a\u0430"
    ],
    "name:zho_x_preferred":[
        "\u65b0\u6ce2\u723e\u5854\u592b\u5361"
    ],
    "wof:name":"Novopoltavka",
    "wof:placetype":"locality"
},
  "geometry": {"coordinates":[92.61667,53.31667],"type":"Point"}
}