{
  "type": "Feature",
  "properties": {
    "gn:admin1_code":"77",
    "gn:asciiname":"Kozulino",
    "gn:country_code":"RU",
    "gn:dem":232,
    "gn:feature_class":"P",
    "gn:feature_code":"PPL",
    "gn:name":"Kozulino",
    "gn:population":0,
    "gn:timezone":"Europe/Moscow",
    "iso:country":"RU",
    "name:rus_x_preferred":[
        "\u041a\u043e\u0437\u0443\u043b\u0438\u043d\u043e"
    ],
    "wof:name":"Kozulino",
    "wof:placetype":"locality"
},
  "geometry": {"coordinates":[33.30556,55.72971999999999],"type":"Point"}
}