{
  "type": "Feature",
  "properties": {
    "gn:admin1_code":"31",
    "gn:asciiname":"Borets",
    "gn:country_code":"RU",
    "gn:dem":392,
    "gn:feature_class":"P",
    "gn:feature_code":"PPL",
    "gn:name":"Borets",
    "gn:population":0,
    "gn:timezone":"Asia/Krasnoyarsk",
    "iso:country":"RU",
    "name:eng_x_preferred":[
        "Borets"
    ],
    "name:nor_x_preferred":[
        "Borets"
    ],
    "name:rus_x_preferred":[
        "\u0411\u043e\u0440\u0435\u0446"
    ],
    "wof:name":"Borets",
    "wof:placetype":"locality"
},
  "geometry": {"coordinates":[90.36778,54.46471999999999],"type":"Point"}
}