{
  "type": "Feature",
  "properties": {
    "gn:admin1_code":"45",
    "gn:asciiname":"Yersola",
    "gn:country_code":"RU",
    "gn:dem":165,
    "gn:feature_class":"P",
    "gn:feature_code":"PPL",
    "gn:name":"Yersola",
    "gn:population":0,
    "gn:timezone":"Europe/Moscow",
    "iso:country":"RU",
    "name:rus_x_preferred":[
        "\u0415\u0440\u0441\u043e\u043b\u0430"
    ],
    "wof:name":"Yersola",
    "wof:placetype":"locality"
},
  "geometry": {"coordinates":[48.765,56.48139000000001],"type":"Point"}
}