{
  "type": "Feature",
  "properties": {
    "gn:admin1_code":"78",
    "gn:asciiname":"Novyy Turtas",
    "gn:country_code":"RU",
    "gn:dem":59,
    "gn:feature_class":"P",
    "gn:feature_code":"PPL",
    "gn:name":"Novyy Turtas",
    "gn:population":0,
    "gn:timezone":"Asia/Yekaterinburg",
    "iso:country":"RU",
    "name:eng_x_preferred":[
        "Novyy Turtas"
    ],
    "name:nor_x_preferred":[
        "Nov.Turtas"
    ],
    "name:rus_x_preferred":[
        "\u041d\u043e\u0432.\u0422\u0443\u0440\u0442\u0430\u0441"
    ],
    "name:rus_x_variant":[
        "\u041d\u043e\u0432\u044b\u0439 \u0422\u0443\u0440\u0442\u0430\u0441"
    ],
    "name:und_x_variant":[
        "\u041d\u043e\u0432\u044b\u0439 \u0422\u0443\u0440\u0442\u0430\u0441"
    ],
    "wof:name":"Novyy Turtas",
    "wof:placetype":"locality"
},
  "geometry": {"coordinates":[69.56917,58.70111],"type":"Point"}
}