{
  "type": "Feature",
  "properties": {
    "gn:country":"RU",
    "gn:fcode":"PPL",
    "gn:pop":4552,
    "iso:country":"RU",
    "name:eng_x_preferred":[
        "Kurmanayevka"
    ],
    "name:nor_x_preferred":[
        "Kurmanajevka"
    ],
    "name:rus_x_preferred":[
        "\u041a\u0443\u0440\u043c\u0430\u043d\u0430\u0435\u0432\u043a\u0430"
    ],
    "name:unk_x_variant":[
        "Kurmanayevo"
    ],
    "qs:name":"Kurmanayevka",
    "qs:photos_9r":0,
    "qs:photos_sr":0,
    "qs:pop_sr":"4",
    "wd:wordcount":952,
    "wof:name":"Kurmanayevka",
    "wof:placetype":"locality",
    "wof:population":4552
},
  "geometry": {"coordinates":[52.0675,52.5093],"type":"Point"}
}