{
  "type": "Feature",
  "properties": {
    "gn:country":"RU",
    "gn:fcode":"PPL",
    "gn:population":4552,
    "iso:country":"RU",
    "name:bak_x_preferred":[
        "\u041a\u0443\u0440\u043c\u0430\u043d\u0430\u0439 \u0440\u0430\u0439\u043e\u043d\u044b"
    ],
    "name:bel_x_preferred":[
        "\u041a\u0443\u0440\u043c\u0430\u043d\u0430\u0435\u045e\u0441\u043a\u0456 \u0440\u0430\u0451\u043d"
    ],
    "name:che_x_preferred":[
        "\u041a\u0443\u0440\u043c\u0430\u043d\u0430\u0435\u0432\u043a\u0430\u043d \u043a\u04c0\u043e\u0448\u0442"
    ],
    "name:chv_x_preferred":[
        "\u041a\u0443\u0440\u043c\u0430\u043d\u0430\u0439 \u0440\u0430\u0439\u043e\u043d\u0115"
    ],
    "name:deu_x_preferred":[
        "Kurmanaewski rajon"
    ],
    "name:eng_x_preferred":[
        "Kurmanayevka"
    ],
    "name:eng_x_variant":[
        "Kurmanayevsky District"
    ],
    "name:hun_x_preferred":[
        "Kurmanajevkai j\u00e1r\u00e1s"
    ],
    "name:hye_x_preferred":[
        "\u053f\u0578\u0582\u0580\u0574\u0561\u0576\u0561\u0587\u057d\u056f\u056b \u0577\u0580\u057b\u0561\u0576"
    ],
    "name:ita_x_preferred":[
        "Kurmanaevskij rajon"
    ],
    "name:myv_x_preferred":[
        "\u041a\u0443\u0440\u043c\u0430\u043d\u0430\u0435\u0432\u043a\u0430\u043d\u044c \u0431\u0443\u0435"
    ],
    "name:nan_x_preferred":[
        "Kurmanayevsky Ko\u0101n"
    ],
    "name:nld_x_preferred":[
        "Kurmanayevsky District"
    ],
    "name:nor_x_preferred":[
        "Kurmanajevka"
    ],
    "name:rus_x_preferred":[
        "\u041a\u0443\u0440\u043c\u0430\u043d\u0430\u0435\u0432\u043a\u0430"
    ],
    "name:rus_x_variant":[
        "\u041a\u0443\u0440\u043c\u0430\u043d\u0430\u0435\u0432\u0441\u043a\u0438\u0439 \u0440\u0430\u0439\u043e\u043d"
    ],
    "name:tat_x_preferred":[
        "\u041a\u043e\u0440\u043c\u0430\u043d\u0430\u0439 \u0440\u0430\u0439\u043e\u043d\u044b"
    ],
    "name:ukr_x_preferred":[
        "\u041a\u0443\u0440\u043c\u0430\u043d\u0430\u0454\u0432\u0441\u044c\u043a\u0438\u0439 \u0440\u0430\u0439\u043e\u043d"
    ],
    "name:und_x_variant":[
        "Kurmanayevo"
    ],
    "name:uzb_x_preferred":[
        "Kurmanayevskiy tumani"
    ],
    "name:vie_x_preferred":[
        "Kurmanaevsky"
    ],
    "name:zho_x_preferred":[
        "\u5eab\u723e\u99ac\u7d0d\u57c3\u592b\u65af\u57fa\u5340"
    ],
    "qs:name":"Kurmanayevka",
    "qs:photos_9r":0,
    "qs:photos_sr":0,
    "qs:pop_sr":"4",
    "wd:wordcount":952,
    "wof:name":"Kurmanayevka",
    "wof:placetype":"locality",
    "wof:population":4552
},
  "geometry": {"coordinates":[52.0675,52.5093],"type":"Point"}
}