{
  "type": "Feature",
  "properties": {
    "gn:admin1_code":"16",
    "gn:asciiname":"Verkhneye Devlizerovo",
    "gn:country_code":"RU",
    "gn:dem":135,
    "gn:feature_class":"P",
    "gn:feature_code":"PPL",
    "gn:name":"Verkhneye Devlizerovo",
    "gn:population":0,
    "gn:timezone":"Europe/Moscow",
    "iso:country":"RU",
    "name:rus_x_preferred":[
        "\u0412\u0435\u0440\u0445\u043d\u0435\u0435 \u0414\u0435\u0432\u043b\u0438\u0437\u0435\u0440\u043e\u0432\u043e"
    ],
    "name:und_x_variant":[
        "Verkhne Devlizerovo",
        "Verkhneye Devlizerovo"
    ],
    "wof:name":"Verkhneye Devlizerovo",
    "wof:placetype":"locality"
},
  "geometry": {"coordinates":[47.53523,55.59938],"type":"Point"}
}