{
  "type": "Feature",
  "properties": {
    "gn:admin1_code":"41.0",
    "gn:asciiname":"Bychki",
    "gn:country_code":"RU",
    "gn:dem":193,
    "gn:feature_class":"P",
    "gn:feature_code":"PPL",
    "gn:name":"Bychki",
    "gn:population":0,
    "gn:timezone":"Europe/Moscow",
    "iso:country":"RU",
    "name:rus_x_preferred":[
        "\u0411\u044b\u0447\u043a\u0438"
    ],
    "wof:name":"Bychki",
    "wof:placetype":"locality"
},
  "geometry": {"coordinates":[35.8142,52.1758],"type":"Point"}
}