{
  "type": "Feature",
  "properties": {
    "gn:admin1_code":"60",
    "gn:asciiname":"Baydakovo",
    "gn:country_code":"RU",
    "gn:dem":38,
    "gn:feature_class":"P",
    "gn:feature_code":"PPL",
    "gn:name":"Baydakovo",
    "gn:population":0,
    "gn:timezone":"Europe/Moscow",
    "iso:country":"RU",
    "name:nor_x_preferred":[
        "Bajdakovo"
    ],
    "name:rus_x_preferred":[
        "\u0411\u0430\u0439\u0434\u0430\u043a\u043e\u0432\u043e"
    ],
    "wof:name":"Baydakovo",
    "wof:placetype":"locality"
},
  "geometry": {"coordinates":[27.81276,58.81374],"type":"Point"}
}