{
  "type": "Feature",
  "properties": {
    "gn:admin1_code":"85.0",
    "gn:asciiname":"Bol'shoye Krasnovo",
    "gn:country_code":"RU",
    "gn:dem":171,
    "gn:feature_class":"P",
    "gn:feature_code":"PPL",
    "gn:name":"Bol\u2019shoye Krasnovo",
    "gn:population":0,
    "gn:timezone":"Europe/Moscow",
    "iso:country":"RU",
    "name:rus_x_preferred":[
        "\u0411\u043e\u043b\u044c\u0448\u043e\u0435 \u041a\u0440\u0430\u0441\u043d\u043e\u0432\u043e"
    ],
    "name:und_x_variant":[
        "Bol\u2019shoye Krasnovo",
        "\u0411\u043e\u043b\u044c\u0448\u043e\u0435 \u041a\u0440\u0430\u0441\u043d\u043e\u0432\u043e"
    ],
    "wof:name":"Bol'shoye Krasnovo",
    "wof:placetype":"locality"
},
  "geometry": {"coordinates":[38.13515,59.44538000000001],"type":"Point"}
}