{
  "type": "Feature",
  "properties": {
    "gn:admin1_code":"20",
    "gn:asciiname":"Zady",
    "gn:country_code":"RU",
    "gn:dem":558,
    "gn:feature_class":"P",
    "gn:feature_code":"PPL",
    "gn:name":"Zady",
    "gn:population":0,
    "gn:timezone":"Asia/Irkutsk",
    "iso:country":"RU",
    "name:eng_x_preferred":[
        "Zady"
    ],
    "name:nor_x_preferred":[
        "Zady"
    ],
    "name:rus_x_preferred":[
        "\u0417\u0430\u0434\u044b"
    ],
    "name:und_x_variant":[
        "Zada"
    ],
    "wof:name":"Zady",
    "wof:placetype":"locality"
},
  "geometry": {"coordinates":[104.5692,52.7663],"type":"Point"}
}