{
  "type": "Feature",
  "properties": {
    "gn:admin1_code":"6",
    "gn:asciiname":"Verkhnyaya Sergiyevskaya",
    "gn:country_code":"RU",
    "gn:dem":80,
    "gn:feature_class":"P",
    "gn:feature_code":"PPL",
    "gn:name":"Verkhnyaya Sergiyevskaya",
    "gn:population":0,
    "gn:timezone":"Europe/Moscow",
    "iso:country":"RU",
    "name:und_x_variant":[
        "Sergiyevskaya Verkhnyaya",
        "Verkhnyaya Sergiyevskaya"
    ],
    "wof:name":"Verkhnyaya Sergiyevskaya",
    "wof:placetype":"locality"
},
  "geometry": {"coordinates":[45.41662,61.69739000000001],"type":"Point"}
}