{
  "type": "Feature",
  "properties": {
    "gn:admin1_code":"80.0",
    "gn:asciiname":"Doma 17 km",
    "gn:country_code":"RU",
    "gn:dem":85,
    "gn:feature_class":"P",
    "gn:feature_code":"PPL",
    "gn:name":"Doma 17 km",
    "gn:population":0,
    "gn:timezone":"Europe/Samara",
    "iso:country":"RU",
    "wof:name":"Doma 17 km",
    "wof:placetype":"locality"
},
  "geometry": {"coordinates":[53.11373,56.65828000000001],"type":"Point"}
}