{
  "type": "Feature",
  "properties": {
    "gn:admin1_code":"85",
    "gn:asciiname":"Olino",
    "gn:country_code":"RU",
    "gn:dem":221,
    "gn:feature_class":"P",
    "gn:feature_code":"PPL",
    "gn:name":"Olino",
    "gn:population":0,
    "gn:timezone":"Europe/Moscow",
    "iso:country":"RU",
    "name:rus_x_preferred":[
        "\u041e\u043b\u0438\u043d\u043e"
    ],
    "name:und_x_variant":[
        "\u041e\u043b\u0438\u043d\u043e"
    ],
    "wof:name":"Olino",
    "wof:placetype":"locality"
},
  "geometry": {"coordinates":[37.21667,59.85],"type":"Point"}
}