{
  "type": "Feature",
  "properties": {
    "gn:admin1_code":"88",
    "gn:asciiname":"Sudnikovo",
    "gn:country_code":"RU",
    "gn:dem":142,
    "gn:feature_class":"P",
    "gn:feature_code":"PPL",
    "gn:name":"Sudnikovo",
    "gn:population":0,
    "gn:timezone":"Europe/Moscow",
    "iso:country":"RU",
    "name:rus_x_preferred":[
        "\u0421\u0443\u0434\u043d\u0438\u043a\u043e\u0432\u043e"
    ],
    "name:und_x_variant":[
        "\u0421\u0443\u0434\u043d\u0438\u043a\u043e\u0432\u043e"
    ],
    "wof:name":"Sudnikovo",
    "wof:placetype":"locality"
},
  "geometry": {"coordinates":[37.669,57.9536],"type":"Point"}
}