{
  "type": "Feature",
  "properties": {
    "gn:admin1_code":"73.0",
    "gn:asciiname":"Bol'shoye Khodyashevo",
    "gn:country_code":"RU",
    "gn:dem":85,
    "gn:feature_class":"P",
    "gn:feature_code":"PPL",
    "gn:name":"Bol\u2019shoye Khodyash\u00ebvo",
    "gn:population":0,
    "gn:timezone":"Europe/Moscow",
    "iso:country":"RU",
    "name:eng_x_preferred":[
        "Bol'shoye Khodyash\u00ebvo"
    ],
    "name:nor_x_preferred":[
        "Bolsjoje Khodjasjevo"
    ],
    "name:rus_x_preferred":[
        "\u0411\u043e\u043b\u044c\u0448\u043e\u0435 \u0425\u043e\u0434\u044f\u0448\u0435\u0432\u043e"
    ],
    "name:und_x_variant":[
        "Khodyashevo",
        "Bol\u2019shoye Khodyash\u00ebvo"
    ],
    "wof:name":"Bol'shoye Khodyashevo",
    "wof:placetype":"locality"
},
  "geometry": {"coordinates":[48.47089,55.732],"type":"Point"}
}