{
  "type": "Feature",
  "properties": {
    "gn:admin1_code":"52",
    "gn:asciiname":"Gornyye Moriny",
    "gn:country_code":"RU",
    "gn:dem":26,
    "gn:feature_class":"P",
    "gn:feature_code":"PPL",
    "gn:name":"Gornyye Moriny",
    "gn:population":0,
    "gn:timezone":"Europe/Moscow",
    "iso:country":"RU",
    "name:rus_x_preferred":[
        "\u0413\u043e\u0440\u043d\u044b\u0435 \u041c\u043e\u0440\u0438\u043d\u044b"
    ],
    "name:und_x_variant":[
        "\u0413\u043e\u0440\u043d\u044b\u0435 \u041c\u043e\u0440\u0438\u043d\u044b"
    ],
    "wof:name":"Gornyye Moriny",
    "wof:placetype":"locality"
},
  "geometry": {"coordinates":[31.22621,58.42401],"type":"Point"}
}