{
  "type": "Feature",
  "properties": {
    "gn:admin1_code":"52.0",
    "gn:asciiname":"Dvorets",
    "gn:country_code":"RU",
    "gn:dem":62,
    "gn:feature_class":"P",
    "gn:feature_code":"PPL",
    "gn:name":"Dvorets",
    "gn:population":0,
    "gn:timezone":"Europe/Moscow",
    "iso:country":"RU",
    "name:rus_x_preferred":[
        "\u0414\u0432\u043e\u0440\u0435\u0446"
    ],
    "name:und_x_variant":[
        "\u0414\u0432\u043e\u0440\u0435\u0446"
    ],
    "wof:name":"Dvorets",
    "wof:placetype":"locality"
},
  "geometry": {"coordinates":[31.93118,57.99083],"type":"Point"}
}