{
  "type": "Feature",
  "properties": {
    "gn:admin1_code":"77",
    "gn:asciiname":"Bol'shiye Bredniki",
    "gn:country_code":"RU",
    "gn:dem":239,
    "gn:feature_class":"P",
    "gn:feature_code":"PPL",
    "gn:name":"Bol\u2019shiye Bredniki",
    "gn:population":0,
    "gn:timezone":"Europe/Moscow",
    "iso:country":"RU",
    "name:rus_x_preferred":[
        "\u0411\u043e\u043b\u044c\u0448\u0438\u0435 \u0411\u0440\u0435\u0434\u043d\u0438\u043a\u0438"
    ],
    "name:und_x_variant":[
        "Bol\u2019shiye Bredniki",
        "\u0411\u043e\u043b\u044c\u0448\u0438\u0435 \u0411\u0440\u0435\u0434\u043d\u0438\u043a\u0438"
    ],
    "wof:name":"Bol'shiye Bredniki",
    "wof:placetype":"locality"
},
  "geometry": {"coordinates":[33.66395,56.40578000000001],"type":"Point"}
}