{
  "type": "Feature",
  "properties": {
    "gn:admin1_code":"54",
    "gn:asciiname":"Malobutakovo",
    "gn:country_code":"RU",
    "gn:dem":66,
    "gn:feature_class":"P",
    "gn:feature_code":"PPL",
    "gn:name":"Malobutakovo",
    "gn:population":0,
    "gn:timezone":"Asia/Omsk",
    "iso:country":"RU",
    "name:eng_x_preferred":[
        "Malobutakovo"
    ],
    "name:nor_x_preferred":[
        "Malobutakovo"
    ],
    "name:rus_x_preferred":[
        "\u041c\u0430\u043b\u043e\u0431\u0443\u0442\u0430\u043a\u043e\u0432\u043e"
    ],
    "name:und_x_variant":[
        "\u041c\u0430\u043b\u043e\u0431\u0443\u0442\u0430\u043a\u043e\u0432\u043e",
        "Malobutakovo"
    ],
    "wof:name":"Malobutakovo",
    "wof:placetype":"locality"
},
  "geometry": {"coordinates":[73.5595,57.2133],"type":"Point"}
}