{
  "type": "Feature",
  "properties": {
    "gn:admin1_code":"60",
    "gn:asciiname":"Mitroshino",
    "gn:country_code":"RU",
    "gn:dem":202,
    "gn:feature_class":"P",
    "gn:feature_code":"PPL",
    "gn:name":"Mitroshino",
    "gn:population":0,
    "gn:timezone":"Europe/Moscow",
    "iso:country":"RU",
    "name:rus_x_preferred":[
        "\u041c\u0438\u0442\u0440\u043e\u0448\u0438\u043d\u043e"
    ],
    "wof:name":"Mitroshino",
    "wof:placetype":"locality"
},
  "geometry": {"coordinates":[29.5348,56.8452],"type":"Point"}
}