{
  "type": "Feature",
  "properties": {
    "gn:admin1_code":"6",
    "gn:asciiname":"Klubokovskaya",
    "gn:country_code":"RU",
    "gn:dem":105,
    "gn:feature_class":"P",
    "gn:feature_code":"PPL",
    "gn:name":"Klubokovskaya",
    "gn:population":0,
    "gn:timezone":"Europe/Moscow",
    "iso:country":"RU",
    "name:rus_x_preferred":[
        "\u041a\u043b\u0443\u0431\u043e\u043a\u043e\u0432\u0441\u043a\u0430\u044f"
    ],
    "wof:name":"Klubokovskaya",
    "wof:placetype":"locality"
},
  "geometry": {"coordinates":[48.36763,61.19828],"type":"Point"}
}