{
  "type": "Feature",
  "properties": {
    "gn:admin1_code":"76.0",
    "gn:asciiname":"Filimonovka",
    "gn:country_code":"RU",
    "gn:dem":174,
    "gn:feature_class":"P",
    "gn:feature_code":"PPL",
    "gn:name":"Filimonovka",
    "gn:population":0,
    "gn:timezone":"Europe/Moscow",
    "iso:country":"RU",
    "name:rus_x_preferred":[
        "\u0424\u0438\u043b\u0438\u043c\u043e\u043d\u043e\u0432\u043a\u0430"
    ],
    "wof:name":"Filimonovka",
    "wof:placetype":"locality"
},
  "geometry": {"coordinates":[37.40345,54.58548],"type":"Point"}
}