{
  "type": "Feature",
  "properties": {
    "gn:admin1_code":"17",
    "gn:admin2_code":"583776",
    "gn:asciiname":"Verkhneye Inkhelo",
    "gn:country_code":"RU",
    "gn:dem":1372,
    "gn:feature_class":"P",
    "gn:feature_code":"PPL",
    "gn:name":"Verkhneye Inkhelo",
    "gn:population":0,
    "gn:timezone":"Europe/Moscow",
    "iso:country":"RU",
    "name:rus_x_preferred":[
        "\u0412\u0435\u0440\u0445\u043d\u0435\u0435 \u0418\u043d\u0445\u0435\u043b\u043e"
    ],
    "name:und_x_variant":[
        "\u0412\u0435\u0440\u0445\u043d\u0435\u0435 \u0418\u043d\u0445\u0435\u043b\u043e"
    ],
    "wof:name":"Verkhneye Inkhelo",
    "wof:placetype":"locality"
},
  "geometry": {"coordinates":[46.33226,42.62079],"type":"Point"}
}