{
  "type": "Feature",
  "properties": {
    "gn:admin1_code":"60",
    "gn:asciiname":"Podbornoye",
    "gn:country_code":"RU",
    "gn:dem":74,
    "gn:feature_class":"P",
    "gn:feature_code":"PPL",
    "gn:name":"Podbornoye",
    "gn:population":0,
    "gn:timezone":"Europe/Moscow",
    "iso:country":"RU",
    "name:rus_x_preferred":[
        "\u041f\u043e\u0434\u0431\u043e\u0440\u043d\u043e\u0435"
    ],
    "wof:name":"Podbornoye",
    "wof:placetype":"locality"
},
  "geometry": {"coordinates":[28.74981,57.14982],"type":"Point"}
}