{
  "type": "Feature",
  "properties": {
    "gn:admin1_code":"16",
    "gn:asciiname":"Yaroslavka",
    "gn:country_code":"RU",
    "gn:dem":171,
    "gn:feature_class":"P",
    "gn:feature_code":"PPL",
    "gn:name":"Yaroslavka",
    "gn:population":0,
    "gn:timezone":"Europe/Moscow",
    "iso:country":"RU",
    "name:rus_x_preferred":[
        "\u042f\u0440\u043e\u0441\u043b\u0430\u0432\u043a\u0430"
    ],
    "wof:name":"Yaroslavka",
    "wof:placetype":"locality"
},
  "geometry": {"coordinates":[46.60748,55.9937],"type":"Point"}
}