{
  "type": "Feature",
  "properties": {
    "gn:admin1_code":"47",
    "gn:asciiname":"Shchapovo",
    "gn:country_code":"RU",
    "gn:dem":176,
    "gn:feature_class":"P",
    "gn:feature_code":"PPL",
    "gn:name":"Shchapovo",
    "gn:population":32,
    "gn:timezone":"Europe/Moscow",
    "iso:country":"RU",
    "name:eng_x_preferred":[
        "Shchapovo"
    ],
    "name:nor_x_preferred":[
        "Sjtsjapovo"
    ],
    "name:rus_x_preferred":[
        "\u0429\u0430\u043f\u043e\u0432\u043e"
    ],
    "name:und_x_variant":[
        "Shapovo"
    ],
    "wof:name":"Shchapovo",
    "wof:placetype":"locality",
    "wof:population":32
},
  "geometry": {"coordinates":[38.18278,55.15856],"type":"Point"}
}