{
  "type": "Feature",
  "properties": {
    "gn:admin1_code":"73",
    "gn:asciiname":"Kileyevo",
    "gn:country_code":"RU",
    "gn:dem":115,
    "gn:feature_class":"P",
    "gn:feature_code":"PPL",
    "gn:name":"Kileyevo",
    "gn:population":0,
    "gn:timezone":"Europe/Moscow",
    "iso:country":"RU",
    "name:rus_x_preferred":[
        "\u041a\u0438\u043b\u0435\u0435\u0432\u043e"
    ],
    "name:und_x_variant":[
        "\u041a\u0438\u043b\u0435\u0435\u0432\u043e"
    ],
    "wof:name":"Kileyevo",
    "wof:placetype":"locality"
},
  "geometry": {"coordinates":[50.2951,56.3046],"type":"Point"}
}