{
  "type": "Feature",
  "properties": {
    "gn:admin1_code":"73",
    "gn:asciiname":"Kileyevo",
    "gn:country_code":"RU",
    "gn:dem":115,
    "gn:feature_class":"P",
    "gn:feature_code":"PPL",
    "gn:name":"Kileyevo",
    "gn:population":0,
    "gn:timezone":"Europe/Moscow",
    "iso:country":"RU",
    "name:aze_x_preferred":[
        "Kil\u0259y"
    ],
    "name:bak_x_preferred":[
        "\u041a\u0438\u043b\u04d9\u0439"
    ],
    "name:hye_x_preferred":[
        "\u053f\u056b\u056c\u0565\u0587\u0578"
    ],
    "name:kaz_x_preferred":[
        "\u041a\u0438\u043b\u0435"
    ],
    "name:kir_x_preferred":[
        "\u041a\u0438\u043b\u0435"
    ],
    "name:rus_x_preferred":[
        "\u041a\u0438\u043b\u0435\u0435\u0432\u043e"
    ],
    "name:tat_x_preferred":[
        "\u041a\u0438\u043b\u04d9\u0439"
    ],
    "wof:name":"Kileyevo",
    "wof:placetype":"locality"
},
  "geometry": {"coordinates":[50.2951,56.3046],"type":"Point"}
}