{
  "type": "Feature",
  "properties": {
    "gn:admin1_code":"71",
    "gn:asciiname":"Mezhevaya",
    "gn:country_code":"RU",
    "gn:dem":205,
    "gn:feature_class":"P",
    "gn:feature_code":"PPL",
    "gn:name":"Mezhevaya",
    "gn:population":0,
    "gn:timezone":"Asia/Yekaterinburg",
    "iso:country":"RU",
    "name:rus_x_preferred":[
        "\u041c\u0435\u0436\u0435\u0432\u0430\u044f"
    ],
    "wof:name":"Mezhevaya",
    "wof:placetype":"locality"
},
  "geometry": {"coordinates":[57.8402,56.64232],"type":"Point"}
}