{
  "type": "Feature",
  "properties": {
    "gn:admin1_code":"43.0",
    "gn:asciiname":"Georgiyevka",
    "gn:country_code":"RU",
    "gn:dem":137,
    "gn:feature_class":"P",
    "gn:feature_code":"PPL",
    "gn:name":"Georgiyevka",
    "gn:population":0,
    "gn:timezone":"Europe/Moscow",
    "iso:country":"RU",
    "name:rus_x_preferred":[
        "\u0413\u0435\u043e\u0440\u0433\u0438\u0435\u0432\u043a\u0430"
    ],
    "wof:name":"Georgiyevka",
    "wof:placetype":"locality"
},
  "geometry": {"coordinates":[40.3225,51.9811],"type":"Point"}
}