{
  "type": "Feature",
  "properties": {
    "gn:admin1_code":"8",
    "gn:asciiname":"Novyye Karatavly",
    "gn:country_code":"RU",
    "gn:dem":271,
    "gn:feature_class":"P",
    "gn:feature_code":"PPL",
    "gn:name":"Novyye Karatavly",
    "gn:population":0,
    "gn:timezone":"Asia/Yekaterinburg",
    "iso:country":"RU",
    "name:eng_x_preferred":[
        "Novyye Karatavly"
    ],
    "name:nor_x_preferred":[
        "Nov.Karatavly"
    ],
    "name:rus_x_preferred":[
        "\u041d\u043e\u0432.\u041a\u0430\u0440\u0430\u0442\u0430\u0432\u043b\u044b"
    ],
    "name:rus_x_variant":[
        "\u041d\u043e\u0432\u044b\u0435 \u041a\u0430\u0440\u0430\u0442\u0430\u0432\u043b\u044b"
    ],
    "name:und_x_variant":[
        "Novokartaly",
        "Novokarataly",
        "Novokaratavly"
    ],
    "wof:name":"Novyye Karatavly",
    "wof:placetype":"locality"
},
  "geometry": {"coordinates":[58.1415,55.1369],"type":"Point"}
}