{
  "type": "Feature",
  "properties": {
    "gn:admin1_code":"33",
    "gn:asciiname":"Gorokhovy",
    "gn:country_code":"RU",
    "gn:dem":115,
    "gn:feature_class":"P",
    "gn:feature_code":"PPL",
    "gn:name":"Gorokhovy",
    "gn:population":0,
    "gn:timezone":"Europe/Kirov",
    "iso:country":"RU",
    "name:rus_x_preferred":[
        "\u0413\u043e\u0440\u043e\u0445\u043e\u0432\u044b"
    ],
    "wof:name":"Gorokhovy",
    "wof:placetype":"locality"
},
  "geometry": {"coordinates":[48.29092,58.06342],"type":"Point"}
}