{
  "type": "Feature",
  "properties": {
    "gn:admin1_code":"6",
    "gn:asciiname":"Romanovo",
    "gn:country_code":"RU",
    "gn:dem":36,
    "gn:feature_class":"P",
    "gn:feature_code":"PPL",
    "gn:name":"Romanovo",
    "gn:population":0,
    "gn:timezone":"Europe/Moscow",
    "iso:country":"RU",
    "name:rus_x_preferred":[
        "\u0420\u043e\u043c\u0430\u043d\u043e\u0432\u043e"
    ],
    "wof:name":"Romanovo",
    "wof:placetype":"locality"
},
  "geometry": {"coordinates":[39.01667,63.51667],"type":"Point"}
}