{
  "type": "Feature",
  "properties": {
    "gn:admin1_code":"77",
    "gn:asciiname":"Pchel'nikovo",
    "gn:country_code":"RU",
    "gn:dem":139,
    "gn:feature_class":"P",
    "gn:feature_code":"PPL",
    "gn:name":"Pchel\u2019nikovo",
    "gn:population":0,
    "gn:timezone":"Europe/Moscow",
    "iso:country":"RU",
    "name:rus_x_preferred":[
        "\u041f\u0447\u0435\u043b\u044c\u043d\u0438\u043a\u043e\u0432\u043e"
    ],
    "name:und_x_variant":[
        "Pchel\u2019nikovo"
    ],
    "wof:name":"Pchel'nikovo",
    "wof:placetype":"locality"
},
  "geometry": {"coordinates":[36.0837,56.9478],"type":"Point"}
}