{
  "type": "Feature",
  "properties": {
    "gn:admin1_code":"43",
    "gn:asciiname":"Saprykino",
    "gn:country_code":"RU",
    "gn:dem":150,
    "gn:feature_class":"P",
    "gn:feature_code":"PPL",
    "gn:name":"Saprykino",
    "gn:population":0,
    "gn:timezone":"Europe/Moscow",
    "iso:country":"RU",
    "name:rus_x_preferred":[
        "\u0421\u0430\u043f\u0440\u044b\u043a\u0438\u043d\u043e"
    ],
    "wof:name":"Saprykino",
    "wof:placetype":"locality"
},
  "geometry": {"coordinates":[38.6734,52.9682],"type":"Point"}
}