{
  "type": "Feature",
  "properties": {
    "gn:admin1_code":"71",
    "gn:asciiname":"Pavinskaya",
    "gn:country_code":"RU",
    "gn:dem":65,
    "gn:feature_class":"P",
    "gn:feature_code":"PPL",
    "gn:name":"Pavinskaya",
    "gn:population":0,
    "gn:timezone":"Asia/Yekaterinburg",
    "iso:country":"RU",
    "name:eng_x_preferred":[
        "Pavinskaya"
    ],
    "name:nor_x_preferred":[
        "Pavinskaja"
    ],
    "name:rus_x_preferred":[
        "\u041f\u0430\u0432\u0438\u043d\u0441\u043a\u0430\u044f"
    ],
    "name:und_x_variant":[
        "Pavinskiy"
    ],
    "wof:name":"Pavinskaya",
    "wof:placetype":"locality"
},
  "geometry": {"coordinates":[64.05979000000001,58.93196999999999],"type":"Point"}
}