{
  "type": "Feature",
  "properties": {
    "gn:admin1_code":"60",
    "gn:asciiname":"Ushitsy",
    "gn:country_code":"RU",
    "gn:dem":118,
    "gn:feature_class":"P",
    "gn:feature_code":"PPL",
    "gn:name":"Ushitsy",
    "gn:population":0,
    "gn:timezone":"Europe/Moscow",
    "iso:country":"RU",
    "name:eng_x_preferred":[
        "Ushitsy"
    ],
    "name:nor_x_preferred":[
        "Usjitsy"
    ],
    "name:rus_x_preferred":[
        "\u0423\u0448\u0438\u0446\u044b"
    ],
    "name:und_x_variant":[
        "\u0423\u0448\u0438\u0446\u044b"
    ],
    "wof:name":"Ushitsy",
    "wof:placetype":"locality"
},
  "geometry": {"coordinates":[30.79121,56.27839],"type":"Point"}
}