{
  "type": "Feature",
  "properties": {
    "gn:admin1_code":"11",
    "gn:asciiname":"Zagza",
    "gn:country_code":"RU",
    "gn:dem":517,
    "gn:feature_class":"P",
    "gn:feature_code":"PPL",
    "gn:name":"Zagza",
    "gn:population":0,
    "gn:timezone":"Asia/Irkutsk",
    "iso:country":"RU",
    "wof:name":"Zagza",
    "wof:placetype":"locality"
},
  "geometry": {"coordinates":[107.06667,52.51667],"type":"Point"}
}