{
  "type": "Feature",
  "properties": {
    "gn:admin1_code":"79",
    "gn:asciiname":"Malinovka",
    "gn:country_code":"RU",
    "gn:dem":876,
    "gn:feature_class":"P",
    "gn:feature_code":"PPL",
    "gn:name":"Malinovka",
    "gn:population":0,
    "gn:timezone":"Asia/Krasnoyarsk",
    "iso:country":"RU",
    "name:bel_x_preferred":[
        "\u041c\u0430\u043b\u0456\u043d\u0430\u045e\u043a\u0430"
    ],
    "name:ceb_x_preferred":[
        "Malinovka"
    ],
    "name:ces_x_preferred":[
        "Malinovka"
    ],
    "name:deu_x_preferred":[
        "Malinowka"
    ],
    "name:eng_x_preferred":[
        "Malinovka"
    ],
    "name:hye_x_preferred":[
        "\u0544\u0561\u056c\u056b\u0576\u0578\u057e\u056f\u0561"
    ],
    "name:lit_x_preferred":[
        "Malinovka"
    ],
    "name:nor_x_preferred":[
        "Malinovka"
    ],
    "name:ron_x_preferred":[
        "Malinovka"
    ],
    "name:rus_x_preferred":[
        "\u041c\u0430\u043b\u0438\u043d\u043e\u0432\u043a\u0430"
    ],
    "name:swe_x_preferred":[
        "Malinovka"
    ],
    "name:tat_x_preferred":[
        "\u041c\u0430\u043b\u0438\u043d\u043e\u0432\u043a\u0430"
    ],
    "name:ukr_x_preferred":[
        "\u041c\u0430\u043b\u0438\u043d\u043e\u0432\u043a\u0430"
    ],
    "name:und_x_variant":[
        "\u041c\u0430\u043b\u0438\u043d\u043e\u0432\u043a\u0430",
        "Malinovka"
    ],
    "wof:name":"Malinovka",
    "wof:placetype":"locality"
},
  "geometry": {"coordinates":[93.36667,51.98333],"type":"Point"}
}