{
  "type": "Feature",
  "properties": {
    "gn:admin1_code":"73",
    "gn:admin2_code":"569314",
    "gn:asciiname":"Staroye Kadeyevo",
    "gn:country_code":"RU",
    "gn:dem":124,
    "gn:feature_class":"P",
    "gn:feature_code":"PPL",
    "gn:name":"Staroye Kadeyevo",
    "gn:population":0,
    "gn:timezone":"Europe/Moscow",
    "iso:country":"RU",
    "name:eng_x_preferred":[
        "Staroye Kadeyevo"
    ],
    "name:nor_x_preferred":[
        "Staroje Kadejevo"
    ],
    "name:rus_x_preferred":[
        "\u0421\u0442\u0430\u0440\u043e\u0435 \u041a\u0430\u0434\u0435\u0435\u0432\u043e"
    ],
    "name:und_x_variant":[
        "\u0421\u0442\u0430\u0440\u043e\u0435 \u041a\u0430\u0434\u0435\u0435\u0432\u043e",
        "Staroye Kadeyevo"
    ],
    "wof:name":"Staroye Kadeyevo",
    "wof:placetype":"locality"
},
  "geometry": {"coordinates":[51.1796,54.74043],"type":"Point"}
}