{
  "type": "Feature",
  "properties": {
    "gn:admin1_code":"41",
    "gn:asciiname":"Malaya Troitskaya",
    "gn:country_code":"RU",
    "gn:dem":188,
    "gn:feature_class":"P",
    "gn:feature_code":"PPL",
    "gn:name":"Malaya Troitskaya",
    "gn:population":0,
    "gn:timezone":"Europe/Moscow",
    "iso:country":"RU",
    "name:rus_x_preferred":[
        "\u041c\u0430\u043b\u0430\u044f \u0422\u0440\u043e\u0438\u0446\u043a\u0430\u044f"
    ],
    "name:und_x_variant":[
        "Malo-Troitskoye",
        "Malo-Troitskaya",
        "Malaya Troitskaya",
        "Malaya Troitsa"
    ],
    "wof:name":"Malaya Troitskaya",
    "wof:placetype":"locality"
},
  "geometry": {"coordinates":[38.3034,51.9007],"type":"Point"}
}