{
  "type": "Feature",
  "properties": {
    "gn:admin1_code":"69",
    "gn:asciiname":"Novyy Stan",
    "gn:country_code":"RU",
    "gn:dem":183,
    "gn:feature_class":"P",
    "gn:feature_code":"PPL",
    "gn:name":"Novyy Stan",
    "gn:population":0,
    "gn:timezone":"Europe/Moscow",
    "iso:country":"RU",
    "name:rus_x_preferred":[
        "\u041d\u043e\u0432\u044b\u0439 \u0421\u0442\u0430\u043d"
    ],
    "wof:name":"Novyy Stan",
    "wof:placetype":"locality"
},
  "geometry": {"coordinates":[32.44734,53.75202],"type":"Point"}
}