{
  "type": "Feature",
  "properties": {
    "gn:admin1_code":"86",
    "gn:asciiname":"Ternovskiy",
    "gn:country_code":"RU",
    "gn:dem":136,
    "gn:feature_class":"P",
    "gn:feature_code":"PPL",
    "gn:name":"Ternovskiy",
    "gn:population":0,
    "gn:timezone":"Europe/Moscow",
    "iso:country":"RU",
    "name:eng_x_preferred":[
        "Ternovskiy"
    ],
    "name:nor_x_preferred":[
        "Ternovskij"
    ],
    "name:rus_x_preferred":[
        "\u0422\u0435\u0440\u043d\u043e\u0432\u0441\u043a\u0438\u0439"
    ],
    "wof:name":"Ternovskiy",
    "wof:placetype":"locality"
},
  "geometry": {"coordinates":[41.0989,51.0941],"type":"Point"}
}