{
  "type": "Feature",
  "properties": {
    "gn:admin1_code":"52",
    "gn:asciiname":"Kokorino",
    "gn:country_code":"RU",
    "gn:dem":66,
    "gn:feature_class":"P",
    "gn:feature_code":"PPL",
    "gn:name":"Kokorino",
    "gn:population":0,
    "gn:timezone":"Europe/Moscow",
    "iso:country":"RU",
    "name:rus_x_preferred":[
        "\u041a\u043e\u043a\u043e\u0440\u0438\u043d\u043e"
    ],
    "name:und_x_variant":[
        "Kokorina",
        "Kokorino",
        "\u041a\u043e\u043a\u043e\u0440\u0438\u043d\u043e"
    ],
    "wof:name":"Kokorino",
    "wof:placetype":"locality"
},
  "geometry": {"coordinates":[31.17161,57.71516999999999],"type":"Point"}
}