{
  "type": "Feature",
  "properties": {
    "gn:admin1_code":"4",
    "gn:asciiname":"Akulovo",
    "gn:country_code":"RU",
    "gn:dem":151,
    "gn:feature_class":"P",
    "gn:feature_code":"PPL",
    "gn:name":"Akulovo",
    "gn:population":0,
    "gn:timezone":"Asia/Barnaul",
    "iso:country":"RU",
    "name:eng_x_preferred":[
        "Okulovo"
    ],
    "name:nor_x_preferred":[
        "Akulovo"
    ],
    "name:rus_x_preferred":[
        "\u0410\u043a\u0443\u043b\u043e\u0432\u043e"
    ],
    "name:und_x_variant":[
        "\u0410\u043a\u0443\u043b\u043e\u0432\u043e",
        "Okulovo",
        "Akulovo"
    ],
    "wof:name":"Akulovo",
    "wof:placetype":"locality"
},
  "geometry": {"coordinates":[84.023,53.9168],"type":"Point"}
}