{
  "type": "Feature",
  "properties": {
    "gn:country":"RU",
    "gn:fcode":"PPL",
    "gn:population":7924,
    "iso:country":"RU",
    "name:azb_x_preferred":[
        "\u06a9\u0631\u0627\u0633\u0646\u0627\u06cc\u0627 \u06cc\u0627\u0631\u0648\u0642\u0627"
    ],
    "name:bel_x_preferred":[
        "\u041a\u0440\u0430\u0441\u043d\u0430\u044f \u042f\u0440\u0443\u0433\u0430"
    ],
    "name:ceb_x_preferred":[
        "Krasnaya Yaruga"
    ],
    "name:che_x_preferred":[
        "\u041a\u0440\u0430\u0441\u043d\u0430\u044f \u042f\u0440\u0443\u0433\u0430"
    ],
    "name:che_x_variant":[
        "\u041a\u0440\u0430\u0441\u043d\u0438 \u042f\u0440\u0443\u0433\u0430"
    ],
    "name:crh_x_preferred":[
        "Krasnaya Yaruga"
    ],
    "name:deu_x_preferred":[
        "Krasnaja Jaruga"
    ],
    "name:eng_x_preferred":[
        "Krasnaya Yaruga"
    ],
    "name:hun_x_preferred":[
        "Krasznaja Jaruga"
    ],
    "name:ita_x_preferred":[
        "Krasnaja Jaruga"
    ],
    "name:nld_x_preferred":[
        "Krasnaja Jaroega"
    ],
    "name:nor_x_preferred":[
        "Krasnaja Jaruga"
    ],
    "name:pol_x_preferred":[
        "Krasnaja Jaruga"
    ],
    "name:rus_x_preferred":[
        "\u041a\u0440\u0430\u0441\u043d\u0430\u044f \u042f\u0440\u0443\u0433\u0430"
    ],
    "name:tgk_x_preferred":[
        "\u041a\u0440\u0430\u0441\u043d\u0430\u044f \u042f\u0440\u0443\u0433\u0430"
    ],
    "name:ukr_x_preferred":[
        "\u041a\u0440\u0430\u0441\u043d\u0430 \u042f\u0440\u0443\u0433\u0430"
    ],
    "name:zho_x_preferred":[
        "\u7ea2\u4e9a\u9c81\u52a0"
    ],
    "qs:name":"Krasnaya Yaruga",
    "qs:photos_9r":0,
    "qs:photos_sr":0,
    "qs:pop_sr":"5",
    "wd:wordcount":908,
    "wof:name":"Krasnaya Yaruga",
    "wof:placetype":"locality",
    "wof:population":7924
},
  "geometry": {"coordinates":[35.65833,50.80083],"type":"Point"}
}