{
  "type": "Feature",
  "properties": {
    "gn:country":"RU",
    "gn:fcode":"PPL",
    "gn:pop":7924,
    "iso:country":"RU",
    "name:che_x_preferred":[
        "\u041a\u0440\u0430\u0441\u043d\u0430\u044f \u042f\u0440\u0443\u0433\u0430"
    ],
    "name:deu_x_preferred":[
        "Krasnaja Jaruga"
    ],
    "name:eng_x_preferred":[
        "Krasnaya Yaruga"
    ],
    "name:ita_x_preferred":[
        "Krasnaja Jaruga"
    ],
    "name:nld_x_preferred":[
        "Krasnaja Jaroega"
    ],
    "name:nor_x_preferred":[
        "Krasnaja Jaruga"
    ],
    "name:rus_x_preferred":[
        "\u041a\u0440\u0430\u0441\u043d\u0430\u044f \u042f\u0440\u0443\u0433\u0430"
    ],
    "name:ukr_x_preferred":[
        "\u041a\u0440\u0430\u0441\u043d\u0430 \u042f\u0440\u0443\u0433\u0430"
    ],
    "name:unk_x_variant":[
        "\u041a\u0440\u0430\u0441\u043d\u0430\u044f \u042f\u0440\u0443\u0433\u0430"
    ],
    "qs:name":"Krasnaya Yaruga",
    "qs:photos_9r":0,
    "qs:photos_sr":0,
    "qs:pop_sr":"5",
    "wd:wordcount":908,
    "wof:name":"Krasnaya Yaruga",
    "wof:placetype":"locality",
    "wof:population":7924
},
  "geometry": {"coordinates":[35.65833,50.80083],"type":"Point"}
}