{
  "type": "Feature",
  "properties": {
    "gn:admin1_code":"21",
    "gn:asciiname":"Potekhino",
    "gn:country_code":"RU",
    "gn:dem":115,
    "gn:feature_class":"P",
    "gn:feature_code":"PPL",
    "gn:name":"Potekhino",
    "gn:population":0,
    "gn:timezone":"Europe/Moscow",
    "iso:country":"RU",
    "name:rus_x_preferred":[
        "\u041f\u043e\u0442\u0435\u0445\u0438\u043d\u043e"
    ],
    "name:und_x_variant":[
        "\u041f\u043e\u0442\u0435\u0445\u0438\u043d\u043e"
    ],
    "wof:name":"Potekhino",
    "wof:placetype":"locality"
},
  "geometry": {"coordinates":[41.94011,57.27025],"type":"Point"}
}