{
  "type": "Feature",
  "properties": {
    "gn:admin1_code":"54",
    "gn:asciiname":"Freganka",
    "gn:country_code":"RU",
    "gn:dem":51,
    "gn:feature_class":"P",
    "gn:feature_code":"PPL",
    "gn:name":"Freganka",
    "gn:population":0,
    "gn:timezone":"Asia/Omsk",
    "iso:country":"RU",
    "name:rus_x_preferred":[
        "\u0424\u0440\u0435\u0433\u0430\u043d\u043a\u0430"
    ],
    "name:und_x_variant":[
        "Freyganskiy",
        "Freganka",
        "\u0424\u0440\u0435\u0433\u0430\u043d\u043a\u0430"
    ],
    "wof:name":"Freganka",
    "wof:placetype":"locality"
},
  "geometry": {"coordinates":[71.27079999999999,57.657],"type":"Point"}
}