{
  "type": "Feature",
  "properties": {
    "gn:admin1_code":"85",
    "gn:asciiname":"Veselaya",
    "gn:country_code":"RU",
    "gn:dem":162,
    "gn:feature_class":"P",
    "gn:feature_code":"PPL",
    "gn:name":"Ves\u00eblaya",
    "gn:population":0,
    "gn:timezone":"Europe/Moscow",
    "iso:country":"RU",
    "name:rus_x_preferred":[
        "\u0412\u0435\u0441\u0451\u043b\u0430\u044f"
    ],
    "name:und_x_variant":[
        "Ves\u00eblaya",
        "\u0412\u0435\u0441\u0451\u043b\u0430\u044f"
    ],
    "wof:name":"Veselaya",
    "wof:placetype":"locality"
},
  "geometry": {"coordinates":[46.3887,59.9092],"type":"Point"}
}