{
  "type": "Feature",
  "properties": {
    "gn:admin1_code":"73.0",
    "gn:asciiname":"Shipshek",
    "gn:country_code":"RU",
    "gn:dem":136,
    "gn:feature_class":"P",
    "gn:feature_code":"PPL",
    "gn:name":"Shipshek",
    "gn:population":0,
    "gn:timezone":"Europe/Moscow",
    "iso:country":"RU",
    "name:rus_x_preferred":[
        "\u0428\u0438\u043f\u0448\u0435\u043a"
    ],
    "name:und_x_variant":[
        "\u0428\u0438\u043f\u0448\u0435\u043a"
    ],
    "wof:name":"Shipshek",
    "wof:placetype":"locality"
},
  "geometry": {"coordinates":[49.23972,56.14417],"type":"Point"}
}