{
  "type": "Feature",
  "properties": {
    "gn:admin1_code":"8.0",
    "gn:asciiname":"Demskoye",
    "gn:country_code":"RU",
    "gn:dem":124,
    "gn:feature_class":"P",
    "gn:feature_code":"PPL",
    "gn:name":"D\u00ebmskoye",
    "gn:population":0,
    "gn:timezone":"Asia/Yekaterinburg",
    "iso:country":"RU",
    "name:rus_x_preferred":[
        "\u0414\u0451\u043c\u0441\u043a\u043e\u0435"
    ],
    "name:und_x_variant":[
        "D\u00ebmovskoye",
        "D\u00ebmskoye"
    ],
    "wof:name":"Demskoye",
    "wof:placetype":"locality"
},
  "geometry": {"coordinates":[54.96666999999999,53.96666999999999],"type":"Point"}
}