{
  "type": "Feature",
  "properties": {
    "gn:admin1_code":"37",
    "gn:asciiname":"Telegino",
    "gn:country_code":"RU",
    "gn:dem":203,
    "gn:feature_class":"P",
    "gn:feature_code":"PPL",
    "gn:name":"Telegino",
    "gn:population":0,
    "gn:timezone":"Europe/Moscow",
    "iso:country":"RU",
    "name:eng_x_preferred":[
        "Telegino"
    ],
    "name:nor_x_preferred":[
        "Telegino"
    ],
    "name:rus_x_preferred":[
        "\u0422\u0435\u043b\u0435\u0433\u0438\u043d\u043e"
    ],
    "name:und_x_variant":[
        "\u0422\u0435\u043b\u0435\u0433\u0438\u043d\u043e",
        "Telegino"
    ],
    "wof:name":"Telegino",
    "wof:placetype":"locality"
},
  "geometry": {"coordinates":[43.64012,58.72185],"type":"Point"}
}