{
  "type": "Feature",
  "properties": {
    "gn:admin1_code":"60",
    "gn:asciiname":"Zuyevo",
    "gn:country_code":"RU",
    "gn:dem":99,
    "gn:feature_class":"P",
    "gn:feature_code":"PPL",
    "gn:name":"Zuyevo",
    "gn:population":0,
    "gn:timezone":"Europe/Moscow",
    "iso:country":"RU",
    "name:che_x_preferred":[
        "\u0417\u0443\u0435\u0432\u043e"
    ],
    "name:rus_x_preferred":[
        "\u0417\u0443\u0435\u0432\u043e"
    ],
    "name:und_x_variant":[
        "\u0417\u0443\u0435\u0432\u043e",
        "Zuyevskaya Dacha"
    ],
    "wof:name":"Zuyevo",
    "wof:placetype":"locality"
},
  "geometry": {"coordinates":[30.66426,56.53193],"type":"Point"}
}