{
  "type": "Feature",
  "properties": {
    "gn:admin1_code":"85",
    "gn:asciiname":"Starkova",
    "gn:cc2":"RU",
    "gn:country_code":"RU",
    "gn:dem":222,
    "gn:feature_class":"P",
    "gn:feature_code":"PPL",
    "gn:name":"Starkova",
    "gn:population":0,
    "gn:timezone":"Europe/Moscow",
    "iso:country":"RU",
    "name:rus_x_preferred":[
        "\u0421\u0442\u0430\u0440\u043a\u043e\u0432\u0430"
    ],
    "name:und_x_variant":[
        "Starkovo",
        "Starkova",
        "\u0421\u0442\u0430\u0440\u043a\u043e\u0432\u0430"
    ],
    "wof:name":"Starkova",
    "wof:placetype":"locality"
},
  "geometry": {"coordinates":[36.91667,61.45],"type":"Point"}
}