{
  "type": "Feature",
  "properties": {
    "gn:country":"RU",
    "gn:fcode":"PPL",
    "gn:population":0,
    "iso:country":"RU",
    "name:rus_x_preferred":[
        "\u0411\u0443\u0433\u0440\u043e\u0432\u043e"
    ],
    "qs:name":"Bugrovo",
    "qs:name_adm0":"Russia",
    "qs:name_adm1":"Pskov Oblast",
    "qs:photos_9r":0,
    "qs:photos_sr":0,
    "qs:placetype":"Town",
    "qs:pop_sr":"0",
    "wof:name":"Bugrovo",
    "wof:placetype":"locality",
    "wof:population":0
},
  "geometry": {"coordinates":[28.9149,57.04501],"type":"Point"}
}