{
  "type": "Feature",
  "properties": {
    "gn:admin1_code":"63",
    "gn:asciiname":"Imeni Stalina",
    "gn:country_code":"RU",
    "gn:dem":804,
    "gn:feature_class":"P",
    "gn:feature_code":"PPL",
    "gn:name":"Imeni Stalina",
    "gn:population":0,
    "gn:timezone":"Asia/Magadan",
    "iso:country":"RU",
    "name:rus_x_preferred":[
        "\u0418\u043c\u0435\u043d\u0438 \u0421\u0442\u0430\u043b\u0438\u043d\u0430"
    ],
    "name:und_x_variant":[
        "\u0418\u043c\u0435\u043d\u0438 \u0421\u0442\u0430\u043b\u0438\u043d\u0430"
    ],
    "wof:name":"Imeni Stalina",
    "wof:placetype":"locality"
},
  "geometry": {"coordinates":[144.03333000000001,63.08333],"type":"Point"}
}