{
  "type": "Feature",
  "properties": {
    "gn:country":"RU",
    "gn:fcode":"PPL",
    "gn:pop":0,
    "iso:country":"RU",
    "name:cat_x_preferred":[
        "Kalinovo"
    ],
    "name:ces_x_preferred":[
        "Kalinovo"
    ],
    "name:deu_x_preferred":[
        "Kalinovo"
    ],
    "name:eng_x_preferred":[
        "Kalinovo"
    ],
    "name:epo_x_preferred":[
        "Kalinovo"
    ],
    "name:eus_x_preferred":[
        "Kalinovo"
    ],
    "name:fra_x_preferred":[
        "Kalinovo"
    ],
    "name:hun_x_preferred":[
        "K\u00e1ln\u00f3"
    ],
    "name:ita_x_preferred":[
        "Kalinovo"
    ],
    "name:msa_x_preferred":[
        "Kalinovo"
    ],
    "name:nld_x_preferred":[
        "Kalinovo"
    ],
    "name:nor_x_preferred":[
        "Kalinovo"
    ],
    "name:pol_x_preferred":[
        "Kalinovo"
    ],
    "name:ron_x_preferred":[
        "Kalinovo"
    ],
    "name:rus_x_preferred":[
        "\u041a\u0430\u043b\u0438\u043d\u043e\u0432\u043e"
    ],
    "name:slk_x_preferred":[
        "Kalinovo"
    ],
    "name:spa_x_preferred":[
        "Kalinovo"
    ],
    "name:srp_x_preferred":[
        "\u041a\u0430\u043b\u0438\u043d\u043e\u0432\u043e"
    ],
    "name:ukr_x_preferred":[
        "\u041a\u0430\u043b\u0456\u043d\u043e\u0432\u043e"
    ],
    "name:war_x_preferred":[
        "Kalinovo"
    ],
    "qs:name":"Kalinovo",
    "qs:name_adm0":"Russia",
    "qs:name_adm1":"Moscow Oblast",
    "qs:photos":105,
    "qs:photos_1k":21,
    "qs:photos_9k":1,
    "qs:photos_9r":3,
    "qs:photos_all":105,
    "qs:photos_sr":3,
    "qs:placetype":"Town",
    "qs:pop_sr":"0",
    "wd:wordcount":100,
    "wof:name":"Kalinovo",
    "wof:placetype":"locality",
    "wof:population":0
},
  "geometry": {"coordinates":[37.29122,54.89463],"type":"Point"}
}