{
  "type": "Feature",
  "properties": {
    "gn:admin1_code":"69",
    "gn:asciiname":"Pokroye",
    "gn:country_code":"RU",
    "gn:dem":209,
    "gn:feature_class":"P",
    "gn:feature_code":"PPL",
    "gn:name":"Pokroye",
    "gn:population":0,
    "gn:timezone":"Europe/Moscow",
    "iso:country":"RU",
    "name:rus_x_preferred":[
        "\u041f\u043e\u043a\u0440\u043e\u0435"
    ],
    "name:und_x_variant":[
        "Pokrovka",
        "Pokroye"
    ],
    "wof:name":"Pokroye",
    "wof:placetype":"locality"
},
  "geometry": {"coordinates":[32.15702,54.55143],"type":"Point"}
}