{
  "type": "Feature",
  "properties": {
    "gn:admin1_code":"77.0",
    "gn:asciiname":"Filitovo",
    "gn:country_code":"RU",
    "gn:dem":204,
    "gn:feature_class":"P",
    "gn:feature_code":"PPL",
    "gn:name":"Filitovo",
    "gn:population":0,
    "gn:timezone":"Europe/Moscow",
    "iso:country":"RU",
    "name:eng_x_preferred":[
        "Filitovo"
    ],
    "name:nor_x_preferred":[
        "Filitovo"
    ],
    "name:rus_x_preferred":[
        "\u0424\u0438\u043b\u0438\u0442\u043e\u0432\u043e"
    ],
    "name:und_x_variant":[
        "Felitovo"
    ],
    "wof:name":"Filitovo",
    "wof:placetype":"locality"
},
  "geometry": {"coordinates":[34.68024,56.82114],"type":"Point"}
}