{
  "type": "Feature",
  "properties": {
    "gn:admin1_code":"40",
    "gn:asciiname":"Zhilina",
    "gn:country_code":"RU",
    "gn:dem":80,
    "gn:feature_class":"P",
    "gn:feature_code":"PPL",
    "gn:name":"Zhilina",
    "gn:population":0,
    "gn:timezone":"Asia/Yekaterinburg",
    "iso:country":"RU",
    "name:eng_x_preferred":[
        "Zhilina"
    ],
    "name:nor_x_preferred":[
        "Zjilina"
    ],
    "name:rus_x_preferred":[
        "\u0416\u0438\u043b\u0438\u043d\u0430"
    ],
    "wof:name":"Zhilina",
    "wof:placetype":"locality"
},
  "geometry": {"coordinates":[64.34639,55.91194],"type":"Point"}
}