{
  "type": "Feature",
  "properties": {
    "gn:admin1_code":"37",
    "gn:asciiname":"Pochinok-Aristov",
    "gn:country_code":"RU",
    "gn:dem":147,
    "gn:feature_class":"P",
    "gn:feature_code":"PPL",
    "gn:name":"Pochinok-Aristov",
    "gn:population":0,
    "gn:timezone":"Europe/Moscow",
    "iso:country":"RU",
    "name:rus_x_preferred":[
        "\u041f\u043e\u0447\u0438\u043d\u043e\u043a-\u0410\u0440\u0438\u0441\u0442\u043e\u0432"
    ],
    "wof:name":"Pochinok-Aristov",
    "wof:placetype":"locality"
},
  "geometry": {"coordinates":[43.2965,58.3149],"type":"Point"}
}