{
  "type": "Feature",
  "properties": {
    "gn:admin1_code":"90.0",
    "gn:asciiname":"Arkhipovskiye Baraki",
    "gn:country_code":"RU",
    "gn:dem":131,
    "gn:feature_class":"P",
    "gn:feature_code":"PPL",
    "gn:name":"Arkhipovskiye Baraki",
    "gn:population":0,
    "gn:timezone":"Asia/Yekaterinburg",
    "iso:country":"RU",
    "name:nor_x_preferred":[
        "Arkhipovskije Baraki"
    ],
    "name:rus_x_preferred":[
        "\u0410\u0440\u0445\u0438\u043f\u043e\u0432\u0441\u043a\u0438\u0435 \u0411\u0430\u0440\u0430\u043a\u0438"
    ],
    "wof:name":"Arkhipovskiye Baraki",
    "wof:placetype":"locality"
},
  "geometry": {"coordinates":[57.8901,58.2674],"type":"Point"}
}