{
  "type": "Feature",
  "properties": {
    "gn:admin1_code":"43",
    "gn:asciiname":"Tuzhilovka",
    "gn:country_code":"RU",
    "gn:dem":185,
    "gn:feature_class":"P",
    "gn:feature_code":"PPL",
    "gn:name":"Tuzhilovka",
    "gn:population":0,
    "gn:timezone":"Europe/Moscow",
    "iso:country":"RU",
    "name:rus_x_preferred":[
        "\u0422\u0443\u0436\u0438\u043b\u043e\u0432\u043a\u0430"
    ],
    "name:und_x_variant":[
        "\u0422\u0443\u0436\u0438\u043b\u043e\u0432\u043a\u0430"
    ],
    "wof:name":"Tuzhilovka",
    "wof:placetype":"locality"
},
  "geometry": {"coordinates":[39.4322,52.7263],"type":"Point"}
}