{
  "type": "Feature",
  "properties": {
    "gn:admin1_code":"46",
    "gn:asciiname":"Malyy Umys",
    "gn:country_code":"RU",
    "gn:dem":216,
    "gn:feature_class":"P",
    "gn:feature_code":"PPL",
    "gn:name":"Malyy Umys",
    "gn:population":0,
    "gn:timezone":"Europe/Moscow",
    "iso:country":"RU",
    "name:che_x_preferred":[
        "\u041c\u0430\u043b\u0438 \u0423\u043c\u044b\u0441"
    ],
    "name:rus_x_preferred":[
        "\u041c\u0430\u043b\u044b\u0439 \u0423\u043c\u044b\u0441"
    ],
    "wof:name":"Malyy Umys",
    "wof:placetype":"locality"
},
  "geometry": {"coordinates":[45.47776,53.96004],"type":"Point"}
}