{
  "type": "Feature",
  "properties": {
    "gn:admin1_code":"91",
    "gn:asciiname":"Novokamala",
    "gn:country_code":"RU",
    "gn:dem":251,
    "gn:feature_class":"P",
    "gn:feature_code":"PPL",
    "gn:name":"Novokamala",
    "gn:population":0,
    "gn:timezone":"Asia/Krasnoyarsk",
    "iso:country":"RU",
    "name:eng_x_preferred":[
        "Novokamala"
    ],
    "name:nor_x_preferred":[
        "Novokamala"
    ],
    "name:rus_x_preferred":[
        "\u041d\u043e\u0432\u043e\u043a\u0430\u043c\u0430\u043b\u0430"
    ],
    "name:und_x_variant":[
        "Kamala",
        "Kamali",
        "Novokamala"
    ],
    "wof:name":"Novokamala",
    "wof:placetype":"locality"
},
  "geometry": {"coordinates":[95.0115,55.9682],"type":"Point"}
}