{
  "type": "Feature",
  "properties": {
    "gn:country":"RU",
    "gn:fcode":"PPL",
    "gn:population":6111,
    "iso:country":"RU",
    "name:azb_x_preferred":[
        "\u062a\u0645\u06cc\u0698\u0628\u06a9\u0633\u06a9\u0627\u06cc\u0627"
    ],
    "name:cat_x_preferred":[
        "Temijb\u00e9kskaia"
    ],
    "name:ceb_x_preferred":[
        "Temizhbekskaya"
    ],
    "name:che_x_preferred":[
        "\u0422\u0435\u043c\u0438\u0436\u0431\u0435\u043a\u0441\u043a\u0430\u044f"
    ],
    "name:eng_x_preferred":[
        "Temizhbekskaya"
    ],
    "name:nor_x_preferred":[
        "Temizjbekskaja"
    ],
    "name:rus_x_preferred":[
        "\u0422\u0435\u043c\u0438\u0436\u0431\u0435\u043a\u0441\u043a\u0430\u044f"
    ],
    "name:spa_x_preferred":[
        "Temizhb\u00e9kskaya"
    ],
    "name:srp_x_preferred":[
        "\u0422\u0435\u043c\u0438\u0436\u0431\u0435\u043a\u0441\u043a\u0430\u0458\u0430"
    ],
    "name:ukr_x_preferred":[
        "\u0422\u0435\u043c\u0456\u0436\u0431\u0435\u043a\u0441\u044c\u043a\u0430"
    ],
    "name:und_x_variant":[
        "Tyemizhbekskaya"
    ],
    "qs_pg:aaroncc":"RU",
    "qs_pg:gn_country":"RU",
    "qs_pg:gn_fcode":"PPL",
    "qs_pg:gn_pop":6111,
    "qs_pg:name":"Temizhbekskaya",
    "qs_pg:photos_9r":0,
    "qs_pg:photos_sr":0,
    "qs_pg:pop_sr":5,
    "qs_pg:qs_pg_placetype":"locality",
    "wof:name":"Temizhbekskaya",
    "wof:placetype":"locality",
    "wof:population":6111
},
  "geometry": {"coordinates":[40.845,45.44556],"type":"Point"}
}