{
  "type": "Feature",
  "properties": {
    "gn:admin1_code":"21.0",
    "gn:asciiname":"Borisenki",
    "gn:country_code":"RU",
    "gn:dem":104,
    "gn:feature_class":"P",
    "gn:feature_code":"PPL",
    "gn:name":"Borisenki",
    "gn:population":0,
    "gn:timezone":"Europe/Moscow",
    "iso:country":"RU",
    "name:und_x_variant":[
        "\u0411\u043e\u0440\u0438\u0441\u0435\u043d\u043a\u0438",
        "Borisenki"
    ],
    "wof:name":"Borisenki",
    "wof:placetype":"locality"
},
  "geometry": {"coordinates":[43.14766,56.96438000000001],"type":"Point"}
}