{
  "type": "Feature",
  "properties": {
    "gn:admin1_code":"43",
    "gn:asciiname":"Khvorostyanka",
    "gn:country_code":"RU",
    "gn:dem":151,
    "gn:feature_class":"P",
    "gn:feature_code":"PPL",
    "gn:name":"Khvorostyanka",
    "gn:population":0,
    "gn:timezone":"Europe/Moscow",
    "iso:country":"RU",
    "name:eng_x_preferred":[
        "Khvorostyanka"
    ],
    "name:nor_x_preferred":[
        "Khvorostjanka"
    ],
    "name:rus_x_preferred":[
        "\u0425\u0432\u043e\u0440\u043e\u0441\u0442\u044f\u043d\u043a\u0430"
    ],
    "name:und_x_variant":[
        "\u0425\u0432\u043e\u0440\u043e\u0441\u0442\u044f\u043d\u043a\u0430",
        "Khvorostyanka"
    ],
    "wof:name":"Khvorostyanka",
    "wof:placetype":"locality"
},
  "geometry": {"coordinates":[40.2341,52.3223],"type":"Point"}
}