{
  "type": "Feature",
  "properties": {
    "gn:admin1_code":"33.0",
    "gn:asciiname":"Petrushi",
    "gn:country_code":"RU",
    "gn:dem":165,
    "gn:feature_class":"P",
    "gn:feature_code":"PPL",
    "gn:name":"Petrushi",
    "gn:population":0,
    "gn:timezone":"Europe/Kirov",
    "iso:country":"RU",
    "name:rus_x_preferred":[
        "\u041f\u0435\u0442\u0440\u0443\u0448\u0438"
    ],
    "name:und_x_variant":[
        "Bol\u2019shiye Patrushi",
        "Petrushi"
    ],
    "wof:name":"Petrushi",
    "wof:placetype":"locality"
},
  "geometry": {"coordinates":[48.10996,58.41197],"type":"Point"}
}