{
  "type": "Feature",
  "properties": {
    "gn:admin1_code":"37",
    "gn:asciiname":"Isayevo",
    "gn:country_code":"RU",
    "gn:dem":156,
    "gn:feature_class":"P",
    "gn:feature_code":"PPL",
    "gn:name":"Isayevo",
    "gn:population":0,
    "gn:timezone":"Europe/Moscow",
    "iso:country":"RU",
    "name:nor_x_preferred":[
        "Isajevo"
    ],
    "name:rus_x_preferred":[
        "\u0418\u0441\u0430\u0435\u0432\u043e"
    ],
    "wof:name":"Isayevo",
    "wof:placetype":"locality"
},
  "geometry": {"coordinates":[41.8632,58.13015],"type":"Point"}
}