{
  "type": "Feature",
  "properties": {
    "gn:admin1_code":"33.0",
    "gn:asciiname":"Urbezh-Kurbatovo",
    "gn:country_code":"RU",
    "gn:dem":138,
    "gn:feature_class":"P",
    "gn:feature_code":"PPL",
    "gn:name":"Urbezh-Kurbatovo",
    "gn:population":0,
    "gn:timezone":"Europe/Kirov",
    "iso:country":"RU",
    "name:rus_x_preferred":[
        "\u0423\u0440\u0431\u0435\u0436-\u041a\u0443\u0440\u0431\u0430\u0442\u043e\u0432\u043e"
    ],
    "wof:name":"Urbezh-Kurbatovo",
    "wof:placetype":"locality"
},
  "geometry": {"coordinates":[48.11278,57.04722],"type":"Point"}
}