{
  "type": "Feature",
  "properties": {
    "gn:admin1_code":"57",
    "gn:asciiname":"Mordovskiy Kachim",
    "gn:country_code":"RU",
    "gn:dem":250,
    "gn:feature_class":"P",
    "gn:feature_code":"PPL",
    "gn:name":"Mordovskiy Kachim",
    "gn:population":0,
    "gn:timezone":"Europe/Moscow",
    "iso:country":"RU",
    "name:eng_x_preferred":[
        "Mordovskiy Kachim"
    ],
    "name:nor_x_preferred":[
        "Mordov Katsjim"
    ],
    "name:rus_x_preferred":[
        "\u041c\u043e\u0440\u0434\u043e\u0432 \u041a\u0430\u0447\u0438\u043c"
    ],
    "name:rus_x_variant":[
        "\u041c\u043e\u0440\u0434\u043e\u0432\u0441\u043a\u0438\u0439 \u041a\u0430\u0447\u0438\u043c"
    ],
    "name:und_x_variant":[
        "Malyy Kachim",
        "Mordovskiy Kachim",
        "\u041c\u043e\u0440\u0434\u043e\u0432\u0441\u043a\u0438\u0439 \u041a\u0430\u0447\u0438\u043c"
    ],
    "wof:name":"Mordovskiy Kachim",
    "wof:placetype":"locality"
},
  "geometry": {"coordinates":[46.64597,53.39158000000001],"type":"Point"}
}