{
  "type": "Feature",
  "properties": {
    "gn:admin1_code":"33",
    "gn:asciiname":"Trapitsyny",
    "gn:country_code":"RU",
    "gn:dem":114,
    "gn:feature_class":"P",
    "gn:feature_code":"PPL",
    "gn:name":"Trapitsyny",
    "gn:population":0,
    "gn:timezone":"Europe/Kirov",
    "iso:country":"RU",
    "name:rus_x_preferred":[
        "\u0422\u0440\u0430\u043f\u0438\u0446\u044b\u043d\u044b"
    ],
    "wof:name":"Trapitsyny",
    "wof:placetype":"locality"
},
  "geometry": {"coordinates":[49.31415,58.42744],"type":"Point"}
}