{
  "type": "Feature",
  "properties": {
    "gn:admin1_code":"77",
    "gn:asciiname":"Uvarovo",
    "gn:country_code":"RU",
    "gn:dem":89,
    "gn:feature_class":"P",
    "gn:feature_code":"PPL",
    "gn:name":"Uvarovo",
    "gn:population":0,
    "gn:timezone":"Europe/Moscow",
    "iso:country":"RU",
    "name:rus_x_preferred":[
        "\u0423\u0432\u0430\u0440\u043e\u0432\u043e"
    ],
    "wof:name":"Uvarovo",
    "wof:placetype":"locality"
},
  "geometry": {"coordinates":[30.92335,56.79334],"type":"Point"}
}