{
  "type": "Feature",
  "properties": {
    "gn:admin1_code":"77",
    "gn:asciiname":"Dalekushi",
    "gn:country_code":"RU",
    "gn:dem":221,
    "gn:feature_class":"P",
    "gn:feature_code":"PPL",
    "gn:name":"Dalekushi",
    "gn:population":0,
    "gn:timezone":"Europe/Moscow",
    "iso:country":"RU",
    "name:rus_x_preferred":[
        "\u0414\u0430\u043b\u0435\u043a\u0443\u0448\u0438"
    ],
    "name:und_x_variant":[
        "\u0414\u0430\u043b\u0435\u043a\u0443\u0448\u0438"
    ],
    "wof:name":"Dalekushi",
    "wof:placetype":"locality"
},
  "geometry": {"coordinates":[34.44282,56.91919],"type":"Point"}
}