{
  "type": "Feature",
  "properties": {
    "gn:admin1_code":"63",
    "gn:asciiname":"Atakh-Yuryakh",
    "gn:country_code":"RU",
    "gn:dem":281,
    "gn:feature_class":"P",
    "gn:feature_code":"PPL",
    "gn:name":"Atakh-Yuryakh",
    "gn:population":0,
    "gn:timezone":"Asia/Yakutsk",
    "iso:country":"RU",
    "name:nor_x_preferred":[
        "Atakh-Jurjakh"
    ],
    "name:rus_x_preferred":[
        "\u0410\u0442\u0430\u0445-\u042e\u0440\u044f\u0445"
    ],
    "wof:name":"Atakh-Yuryakh",
    "wof:placetype":"locality"
},
  "geometry": {"coordinates":[119.09999999999999,61.03333000000001],"type":"Point"}
}