{
  "type": "Feature",
  "properties": {
    "gn:admin1_code":"38",
    "gn:asciiname":"Neftepromyslovyy",
    "gn:country_code":"RU",
    "gn:dem":42,
    "gn:feature_class":"P",
    "gn:feature_code":"PPL",
    "gn:name":"Neftepromyslovyy",
    "gn:population":0,
    "gn:timezone":"Europe/Moscow",
    "iso:country":"RU",
    "name:rus_x_preferred":[
        "\u041d\u0435\u0444\u0442\u0435\u043f\u0440\u043e\u043c\u044b\u0441\u043b\u043e\u0432\u044b\u0439"
    ],
    "wof:name":"Neftepromyslovyy",
    "wof:placetype":"locality"
},
  "geometry": {"coordinates":[37.71196,45.06936],"type":"Point"}
}