{
  "type": "Feature",
  "properties": {
    "gn:admin1_code":"13",
    "gn:asciiname":"Kushtaba",
    "gn:country_code":"RU",
    "gn:dem":307,
    "gn:feature_class":"P",
    "gn:feature_code":"PPL",
    "gn:name":"Kushtaba",
    "gn:population":0,
    "gn:timezone":"Asia/Yekaterinburg",
    "iso:country":"RU",
    "name:rus_x_preferred":[
        "\u041a\u0443\u0448\u0442\u0430\u0431\u0430"
    ],
    "name:und_x_variant":[
        "\u041a\u0443\u0448\u0442\u0430\u0431\u0430"
    ],
    "wof:name":"Kushtaba",
    "wof:placetype":"locality"
},
  "geometry": {"coordinates":[60.41667,54.61666999999999],"type":"Point"}
}