{
  "type": "Feature",
  "properties": {
    "gn:admin1_code":"67",
    "gn:asciiname":"Rozovka",
    "gn:country_code":"RU",
    "gn:dem":56,
    "gn:feature_class":"P",
    "gn:feature_code":"PPL",
    "gn:name":"Rozovka",
    "gn:population":0,
    "gn:timezone":"Europe/Saratov",
    "iso:country":"RU",
    "name:rus_x_preferred":[
        "\u0420\u043e\u0437\u043e\u0432\u043a\u0430"
    ],
    "name:und_x_variant":[
        "Rozental\u2019",
        "Rosental",
        "Rozovka"
    ],
    "wof:name":"Rozovka",
    "wof:placetype":"locality"
},
  "geometry": {"coordinates":[47.1912,51.098],"type":"Point"}
}