{
  "type": "Feature",
  "properties": {
    "gn:admin1_code":"85",
    "gn:asciiname":"Kirgody",
    "gn:country_code":"RU",
    "gn:dem":123,
    "gn:feature_class":"P",
    "gn:feature_code":"PPL",
    "gn:name":"Kirgody",
    "gn:population":0,
    "gn:timezone":"Europe/Moscow",
    "iso:country":"RU",
    "name:rus_x_preferred":[
        "\u041a\u0438\u0440\u0433\u043e\u0434\u044b"
    ],
    "name:und_x_variant":[
        "\u041a\u0438\u0440\u0433\u043e\u0434\u044b"
    ],
    "wof:name":"Kirgody",
    "wof:placetype":"locality"
},
  "geometry": {"coordinates":[38.38201,59.57138000000001],"type":"Point"}
}