{
  "type": "Feature",
  "properties": {
    "gn:admin1_code":"85",
    "gn:asciiname":"Vysokaya Griva",
    "gn:country_code":"RU",
    "gn:dem":170,
    "gn:feature_class":"P",
    "gn:feature_code":"PPL",
    "gn:name":"Vysokaya Griva",
    "gn:population":0,
    "gn:timezone":"Europe/Moscow",
    "iso:country":"RU",
    "name:eng_x_preferred":[
        "Vysokaya Griva"
    ],
    "name:nor_x_preferred":[
        "Vysokaja Griva"
    ],
    "name:rus_x_preferred":[
        "\u0412\u044b\u0441\u043e\u043a\u0430\u044f \u0413\u0440\u0438\u0432\u0430"
    ],
    "name:und_x_variant":[
        "Pochinok Vysokaya Griva",
        "Vysokaya Griva"
    ],
    "wof:name":"Vysokaya Griva",
    "wof:placetype":"locality"
},
  "geometry": {"coordinates":[45.74602,60.16781],"type":"Point"}
}