{
  "type": "Feature",
  "properties": {
    "gn:admin1_code":"73",
    "gn:asciiname":"Staryy Pukshiner",
    "gn:country_code":"RU",
    "gn:dem":174,
    "gn:feature_class":"P",
    "gn:feature_code":"PPL",
    "gn:name":"Staryy Pukshiner",
    "gn:population":0,
    "gn:timezone":"Europe/Moscow",
    "iso:country":"RU",
    "name:rus_x_preferred":[
        "\u0421\u0442\u0430\u0440\u044b\u0439 \u041f\u0443\u043a\u0448\u0438\u043d\u0435\u0440"
    ],
    "wof:name":"Staryy Pukshiner",
    "wof:placetype":"locality"
},
  "geometry": {"coordinates":[50.2839,56.6149],"type":"Point"}
}