{
  "type": "Feature",
  "properties": {
    "gn:admin1_code":"44",
    "gn:asciiname":"Ayaks",
    "gn:country_code":"RU",
    "gn:dem":666,
    "gn:feature_class":"P",
    "gn:feature_code":"PPL",
    "gn:name":"Ayaks",
    "gn:population":0,
    "gn:timezone":"Asia/Magadan",
    "iso:country":"RU",
    "name:eng_x_preferred":[
        "Ayaks"
    ],
    "name:nor_x_preferred":[
        "Ajaks"
    ],
    "name:rus_x_preferred":[
        "\u0410\u044f\u043a\u0441"
    ],
    "name:und_x_variant":[
        "\u0410\u044f\u043a\u0441",
        "Ayaks"
    ],
    "wof:name":"Ayaks",
    "wof:placetype":"locality"
},
  "geometry": {"coordinates":[155.43333000000001,62.81667],"type":"Point"}
}