{
  "type": "Feature",
  "properties": {
    "gn:admin1_code":"75",
    "gn:asciiname":"Kurolino",
    "gn:country_code":"RU",
    "gn:dem":95,
    "gn:feature_class":"P",
    "gn:feature_code":"PPL",
    "gn:name":"Kurolino",
    "gn:population":0,
    "gn:timezone":"Asia/Tomsk",
    "iso:country":"RU",
    "name:eng_x_preferred":[
        "Kurolino"
    ],
    "name:nor_x_preferred":[
        "Kurolino"
    ],
    "name:rus_x_preferred":[
        "\u041a\u0443\u0440\u043e\u043b\u0438\u043d\u043e"
    ],
    "name:und_x_variant":[
        "\u041a\u0443\u0440\u043e\u043b\u0438\u043d\u043e",
        "Kurolino"
    ],
    "wof:name":"Kurolino",
    "wof:placetype":"locality"
},
  "geometry": {"coordinates":[84.49389000000002,58.72472],"type":"Point"}
}