{
  "type": "Feature",
  "properties": {
    "gn:admin1_code":"90",
    "gn:asciiname":"Gorbunovo",
    "gn:country_code":"RU",
    "gn:dem":122,
    "gn:feature_class":"P",
    "gn:feature_code":"PPL",
    "gn:name":"Gorbunovo",
    "gn:population":0,
    "gn:timezone":"Asia/Yekaterinburg",
    "iso:country":"RU",
    "name:che_x_preferred":[
        "\u0413\u043e\u0440\u0431\u0443\u043d\u043e\u0432\u043e"
    ],
    "name:rus_x_preferred":[
        "\u0413\u043e\u0440\u0431\u0443\u043d\u043e\u0432\u043e"
    ],
    "name:und_x_variant":[
        "\u0413\u043e\u0440\u0431\u0443\u043d\u043e\u0432\u043e"
    ],
    "wof:name":"Gorbunovo",
    "wof:placetype":"locality"
},
  "geometry": {"coordinates":[56.3742,57.8389],"type":"Point"}
}