{
  "type": "Feature",
  "properties": {
    "gn:admin1_code":"69",
    "gn:asciiname":"Koty",
    "gn:country_code":"RU",
    "gn:dem":195,
    "gn:feature_class":"P",
    "gn:feature_code":"PPL",
    "gn:name":"Koty",
    "gn:population":0,
    "gn:timezone":"Europe/Moscow",
    "iso:country":"RU",
    "name:rus_x_preferred":[
        "\u041a\u043e\u0442\u044b"
    ],
    "name:und_x_variant":[
        "Kety",
        "Koty",
        "\u041a\u043e\u0442\u044b"
    ],
    "wof:name":"Koty",
    "wof:placetype":"locality"
},
  "geometry": {"coordinates":[30.88587,54.78593000000001],"type":"Point"}
}