{
  "type": "Feature",
  "properties": {
    "gn:admin1_code":"23",
    "gn:asciiname":"Nekrasovo",
    "gn:country_code":"RU",
    "gn:dem":52,
    "gn:feature_class":"P",
    "gn:feature_code":"PPL",
    "gn:name":"Nekrasovo",
    "gn:population":0,
    "gn:timezone":"Europe/Kaliningrad",
    "iso:country":"RU",
    "name:che_x_preferred":[
        "\u041d\u0435\u043a\u0440\u0430\u0441\u043e\u0432\u043e"
    ],
    "name:rus_x_preferred":[
        "\u041d\u0435\u043a\u0440\u0430\u0441\u043e\u0432\u043e"
    ],
    "name:und_x_variant":[
        "\u041d\u0435\u043a\u0440\u0430\u0441\u043e\u0432\u043e"
    ],
    "wof:name":"Nekrasovo",
    "wof:placetype":"locality"
},
  "geometry": {"coordinates":[22.36583,54.61666999999999],"type":"Point"}
}