{
  "type": "Feature",
  "properties": {
    "gn:admin1_code":"42",
    "gn:asciiname":"Murula",
    "gn:country_code":"RU",
    "gn:dem":9,
    "gn:feature_class":"P",
    "gn:feature_code":"PPL",
    "gn:name":"Murula",
    "gn:population":0,
    "gn:timezone":"Europe/Moscow",
    "iso:country":"RU",
    "name:rus_x_preferred":[
        "\u041c\u0443\u0440\u0443\u043b\u0430"
    ],
    "name:und_x_variant":[
        "\u041c\u0443\u0440\u0443\u043b\u0430"
    ],
    "wof:name":"Murula",
    "wof:placetype":"locality"
},
  "geometry": {"coordinates":[28.71174,60.64214000000001],"type":"Point"}
}