{
  "type": "Feature",
  "properties": {
    "gn:admin1_code":"13",
    "gn:asciiname":"Maloyaz",
    "gn:country_code":"RU",
    "gn:dem":303,
    "gn:feature_class":"P",
    "gn:feature_code":"PPL",
    "gn:name":"Maloyaz",
    "gn:population":0,
    "gn:timezone":"Asia/Yekaterinburg",
    "iso:country":"RU",
    "name:rus_x_preferred":[
        "\u041c\u0430\u043b\u043e\u044f\u0437"
    ],
    "name:und_x_variant":[
        "\u041c\u0430\u043b\u043e\u044f\u0437"
    ],
    "wof:name":"Maloyaz",
    "wof:placetype":"locality"
},
  "geometry": {"coordinates":[58.1121,55.2047],"type":"Point"}
}