{
  "type": "Feature",
  "properties": {
    "gn:admin1_code":"21",
    "gn:asciiname":"Khudynskoye",
    "gn:country_code":"RU",
    "gn:dem":106,
    "gn:feature_class":"P",
    "gn:feature_code":"PPL",
    "gn:name":"Khudynskoye",
    "gn:population":0,
    "gn:timezone":"Europe/Moscow",
    "iso:country":"RU",
    "name:eng_x_preferred":[
        "Khudynskoye"
    ],
    "name:nor_x_preferred":[
        "Khudynskoje"
    ],
    "name:rus_x_preferred":[
        "\u0425\u0443\u0434\u044b\u043d\u0441\u043a\u043e\u0435"
    ],
    "wof:name":"Khudynskoye",
    "wof:placetype":"locality"
},
  "geometry": {"coordinates":[42.26955,56.96281],"type":"Point"}
}