{
  "type": "Feature",
  "properties": {
    "gn:admin1_code":"21",
    "gn:asciiname":"Yakshino",
    "gn:country_code":"RU",
    "gn:dem":150,
    "gn:feature_class":"P",
    "gn:feature_code":"PPL",
    "gn:name":"Yakshino",
    "gn:population":0,
    "gn:timezone":"Europe/Moscow",
    "iso:country":"RU",
    "name:eng_x_preferred":[
        "Yakshino"
    ],
    "name:nor_x_preferred":[
        "Jaksjino"
    ],
    "name:rus_x_preferred":[
        "\u042f\u043a\u0448\u0438\u043d\u043e"
    ],
    "wof:name":"Yakshino",
    "wof:placetype":"locality"
},
  "geometry": {"coordinates":[40.13837,57.0827],"type":"Point"}
}