{
  "type": "Feature",
  "properties": {
    "gn:admin1_code":"60",
    "gn:asciiname":"Susanino",
    "gn:country_code":"RU",
    "gn:dem":112,
    "gn:feature_class":"P",
    "gn:feature_code":"PPL",
    "gn:name":"Susanino",
    "gn:population":0,
    "gn:timezone":"Europe/Moscow",
    "iso:country":"RU",
    "name:rus_x_preferred":[
        "\u0421\u0443\u0441\u0430\u043d\u0438\u043d\u043e"
    ],
    "wof:name":"Susanino",
    "wof:placetype":"locality"
},
  "geometry": {"coordinates":[28.11762,56.972],"type":"Point"}
}