{
  "type": "Feature",
  "properties": {
    "gn:admin1_code":"80",
    "gn:asciiname":"Polom",
    "gn:country_code":"RU",
    "gn:dem":177,
    "gn:feature_class":"P",
    "gn:feature_code":"PPL",
    "gn:name":"Polom",
    "gn:population":0,
    "gn:timezone":"Europe/Samara",
    "iso:country":"RU",
    "name:bos_x_preferred":[
        "Polom"
    ],
    "name:ceb_x_preferred":[
        "Polom"
    ],
    "name:ces_x_preferred":[
        "Polom"
    ],
    "name:deu_x_preferred":[
        "Polom"
    ],
    "name:eng_x_preferred":[
        "Polom"
    ],
    "name:fra_x_preferred":[
        "Polom"
    ],
    "name:ita_x_preferred":[
        "Polom"
    ],
    "name:nld_x_preferred":[
        "Polom"
    ],
    "name:nor_x_preferred":[
        "Polom"
    ],
    "name:pol_x_preferred":[
        "Polom"
    ],
    "name:rus_x_preferred":[
        "\u041f\u043e\u043b\u043e\u043c"
    ],
    "name:slk_x_preferred":[
        "Polom"
    ],
    "name:slv_x_preferred":[
        "Polom"
    ],
    "name:srp_x_preferred":[
        "\u041f\u043e\u043b\u043e\u043c"
    ],
    "name:swe_x_preferred":[
        "Polom"
    ],
    "name:ukr_x_preferred":[
        "\u041f\u043e\u043b\u043e\u043c"
    ],
    "wof:name":"Polom",
    "wof:placetype":"locality"
},
  "geometry": {"coordinates":[53.4598,57.7743],"type":"Point"}
}