{
  "type": "Feature",
  "properties": {
    "gn:admin1_code":"69",
    "gn:asciiname":"Savino",
    "gn:country_code":"RU",
    "gn:dem":248,
    "gn:feature_class":"P",
    "gn:feature_code":"PPL",
    "gn:name":"Savino",
    "gn:population":0,
    "gn:timezone":"Europe/Moscow",
    "iso:country":"RU",
    "name:rus_x_preferred":[
        "\u0421\u0430\u0432\u0438\u043d\u043e"
    ],
    "name:und_x_variant":[
        "\u0421\u0430\u0432\u0438\u043d\u043e"
    ],
    "wof:name":"Savino",
    "wof:placetype":"locality"
},
  "geometry": {"coordinates":[32.15,54.93333000000001],"type":"Point"}
}