{
  "type": "Feature",
  "properties": {
    "gn:admin1_code":"63",
    "gn:asciiname":"Ebyakh",
    "gn:country_code":"RU",
    "gn:dem":33,
    "gn:feature_class":"P",
    "gn:feature_code":"PPL",
    "gn:name":"Ebyakh",
    "gn:population":0,
    "gn:timezone":"Asia/Magadan",
    "iso:country":"RU",
    "name:rus_x_preferred":[
        "\u042d\u0431\u044f\u0445"
    ],
    "name:und_x_variant":[
        "Ebakh",
        "Ebeekh",
        "Ebyakh",
        "\u042d\u0431\u044f\u0445"
    ],
    "wof:name":"Ebyakh",
    "wof:placetype":"locality"
},
  "geometry": {"coordinates":[150.74743999999995,68.39484],"type":"Point"}
}