{
  "type": "Feature",
  "properties": {
    "gn:admin1_code":"45.0",
    "gn:asciiname":"Kupuner",
    "gn:country_code":"RU",
    "gn:dem":131,
    "gn:feature_class":"P",
    "gn:feature_code":"PPL",
    "gn:name":"Kupuner",
    "gn:population":0,
    "gn:timezone":"Europe/Moscow",
    "iso:country":"RU",
    "name:rus_x_preferred":[
        "\u041a\u0443\u043f\u0443\u043d\u0435\u0440"
    ],
    "wof:name":"Kupuner",
    "wof:placetype":"locality"
},
  "geometry": {"coordinates":[48.50472,57.09333],"type":"Point"}
}