{
  "type": "Feature",
  "properties": {
    "gn:admin1_code":"85.0",
    "gn:asciiname":"Chernyakovo",
    "gn:country_code":"RU",
    "gn:dem":117,
    "gn:feature_class":"P",
    "gn:feature_code":"PPL",
    "gn:name":"Chernyakovo",
    "gn:population":0,
    "gn:timezone":"Europe/Moscow",
    "iso:country":"RU",
    "name:rus_x_preferred":[
        "\u0427\u0435\u0440\u043d\u044f\u043a\u043e\u0432\u043e"
    ],
    "name:und_x_variant":[
        "\u0427\u0435\u0440\u043d\u044f\u043a\u043e\u0432\u043e"
    ],
    "wof:name":"Chernyakovo",
    "wof:placetype":"locality"
},
  "geometry": {"coordinates":[42.79285,59.96951],"type":"Point"}
}