{
  "type": "Feature",
  "properties": {
    "gn:admin1_code":"33.0",
    "gn:asciiname":"Bol'shoy Gazek",
    "gn:country_code":"RU",
    "gn:dem":122,
    "gn:feature_class":"P",
    "gn:feature_code":"PPL",
    "gn:name":"Bol\u2019shoy Gazek",
    "gn:population":0,
    "gn:timezone":"Europe/Kirov",
    "iso:country":"RU",
    "name:rus_x_preferred":[
        "\u0411\u043e\u043b\u044c\u0448\u043e\u0439 \u0413\u0430\u0437\u0435\u043a"
    ],
    "name:und_x_variant":[
        "Bol\u2019shoy Gazek"
    ],
    "wof:name":"Bol'shoy Gazek",
    "wof:placetype":"locality"
},
  "geometry": {"coordinates":[51.20148,57.07186],"type":"Point"}
}