{
  "type": "Feature",
  "properties": {
    "gn:admin1_code":"17",
    "gn:asciiname":"Tsurmakhi",
    "gn:country_code":"RU",
    "gn:dem":1159,
    "gn:feature_class":"P",
    "gn:feature_code":"PPL",
    "gn:name":"Tsurmakhi",
    "gn:population":0,
    "gn:timezone":"Europe/Moscow",
    "iso:country":"RU",
    "wof:name":"Tsurmakhi",
    "wof:placetype":"locality"
},
  "geometry": {"coordinates":[47.57516,42.31845],"type":"Point"}
}