{
  "type": "Feature",
  "properties": {
    "gn:admin1_code":"28",
    "gn:asciiname":"Kolezhma",
    "gn:country_code":"RU",
    "gn:dem":11,
    "gn:feature_class":"P",
    "gn:feature_code":"PPL",
    "gn:name":"Kolezhma",
    "gn:population":0,
    "gn:timezone":"Europe/Moscow",
    "iso:country":"RU",
    "name:fin_x_preferred":[
        "Kuolisma"
    ],
    "name:rus_x_preferred":[
        "\u041a\u043e\u043b\u0435\u0436\u043c\u0430"
    ],
    "name:und_x_variant":[
        "Kolejma",
        "Kole\u017ema",
        "Koleshma",
        "Kolezhma",
        "\u041a\u043e\u043b\u0435\u0436\u043c\u0430"
    ],
    "wof:name":"Kolezhma",
    "wof:placetype":"locality"
},
  "geometry": {"coordinates":[35.87637,64.23713000000001],"type":"Point"}
}