{
  "type": "Feature",
  "properties": {
    "gn:admin1_code":"61",
    "gn:asciiname":"Kislitsyn",
    "gn:country_code":"RU",
    "gn:dem":84,
    "gn:feature_class":"P",
    "gn:feature_code":"PPL",
    "gn:name":"Kislitsyn",
    "gn:population":0,
    "gn:timezone":"Europe/Moscow",
    "iso:country":"RU",
    "name:rus_x_preferred":[
        "\u041a\u0438\u0441\u043b\u0438\u0446\u044b\u043d"
    ],
    "wof:name":"Kislitsyn",
    "wof:placetype":"locality"
},
  "geometry": {"coordinates":[41.32111,46.29861],"type":"Point"}
}