{
  "type": "Feature",
  "properties": {
    "gn:admin1_code":"63",
    "gn:asciiname":"Petrova",
    "gn:country_code":"RU",
    "gn:dem":7,
    "gn:feature_class":"P",
    "gn:feature_code":"PPL",
    "gn:name":"Petrova",
    "gn:population":0,
    "gn:timezone":"Asia/Magadan",
    "iso:country":"RU",
    "name:rus_x_preferred":[
        "\u041f\u0435\u0442\u0440\u043e\u0432\u0430"
    ],
    "wof:name":"Petrova",
    "wof:placetype":"locality"
},
  "geometry": {"coordinates":[155.31225000000001,67.62796999999999],"type":"Point"}
}