{
  "type": "Feature",
  "properties": {
    "gn:admin1_code":"22.0",
    "gn:asciiname":"Budayevskiy",
    "gn:cc2":"RU",
    "gn:country_code":"RU",
    "gn:dem":1539,
    "gn:feature_class":"P",
    "gn:feature_code":"PPL",
    "gn:name":"Budayevskiy",
    "gn:population":0,
    "gn:timezone":"Europe/Moscow",
    "iso:country":"RU",
    "name:rus_x_preferred":[
        "\u0411\u0443\u0434\u0430\u0435\u0432\u0441\u043a\u0438\u0439"
    ],
    "name:und_x_variant":[
        "Nizhniy Chalmas",
        "Budayevskiy"
    ],
    "wof:name":"Budayevskiy",
    "wof:placetype":"locality"
},
  "geometry": {"coordinates":[42.85139,43.34278],"type":"Point"}
}