{
  "type": "Feature",
  "properties": {
    "gn:admin1_code":"54",
    "gn:asciiname":"Kirillovka",
    "gn:country_code":"RU",
    "gn:dem":108,
    "gn:feature_class":"P",
    "gn:feature_code":"PPL",
    "gn:name":"Kirillovka",
    "gn:population":0,
    "gn:timezone":"Asia/Omsk",
    "iso:country":"RU",
    "name:che_x_preferred":[
        "\u041a\u0438\u0440\u0438\u043b\u043b\u043e\u0432\u043a\u0430"
    ],
    "name:eng_x_preferred":[
        "Kirillovka"
    ],
    "name:nor_x_preferred":[
        "Kirillovka"
    ],
    "name:rus_x_preferred":[
        "\u041a\u0438\u0440\u0438\u043b\u043b\u043e\u0432\u043a\u0430"
    ],
    "name:und_x_variant":[
        "Kirillovskiy",
        "\u041a\u0438\u0440\u0438\u043b\u043b\u043e\u0432\u043a\u0430",
        "Kirillovka"
    ],
    "wof:name":"Kirillovka",
    "wof:placetype":"locality"
},
  "geometry": {"coordinates":[75.17964000000001,54.64871],"type":"Point"}
}