{
  "type": "Feature",
  "properties": {
    "gn:admin1_code":"88.0",
    "gn:asciiname":"Averinskaya",
    "gn:country_code":"RU",
    "gn:dem":143,
    "gn:feature_class":"P",
    "gn:feature_code":"PPL",
    "gn:name":"Averinskaya",
    "gn:population":0,
    "gn:timezone":"Europe/Moscow",
    "iso:country":"RU",
    "name:nor_x_preferred":[
        "Averinskaja"
    ],
    "name:rus_x_preferred":[
        "\u0410\u0432\u0435\u0440\u0438\u043d\u0441\u043a\u0430\u044f"
    ],
    "wof:name":"Averinskaya",
    "wof:placetype":"locality"
},
  "geometry": {"coordinates":[38.33333,57.25],"type":"Point"}
}