{
  "type": "Feature",
  "properties": {
    "gn:admin1_code":"88.0",
    "gn:asciiname":"Bol'shoye Bryakishevo",
    "gn:country_code":"RU",
    "gn:dem":118,
    "gn:feature_class":"P",
    "gn:feature_code":"PPL",
    "gn:name":"Bol\u2019shoye Bryakishevo",
    "gn:population":0,
    "gn:timezone":"Europe/Moscow",
    "iso:country":"RU",
    "name:rus_x_preferred":[
        "\u0411\u043e\u043b\u044c\u0448\u043e\u0435 \u0411\u0440\u044f\u043a\u0438\u0448\u0435\u0432\u043e"
    ],
    "name:und_x_variant":[
        "Bol\u2019shoye Bryakishevo"
    ],
    "wof:name":"Bol'shoye Bryakishevo",
    "wof:placetype":"locality"
},
  "geometry": {"coordinates":[40.29139,58.06778000000001],"type":"Point"}
}