{
  "type": "Feature",
  "properties": {
    "gn:admin1_code":"57",
    "gn:asciiname":"Kamyshleyka",
    "gn:country_code":"RU",
    "gn:dem":262,
    "gn:feature_class":"P",
    "gn:feature_code":"PPL",
    "gn:name":"Kamyshleyka",
    "gn:population":0,
    "gn:timezone":"Europe/Moscow",
    "iso:country":"RU",
    "name:rus_x_preferred":[
        "\u041a\u0430\u043c\u044b\u0448\u043b\u0435\u0439\u043a\u0430"
    ],
    "wof:name":"Kamyshleyka",
    "wof:placetype":"locality"
},
  "geometry": {"coordinates":[46.50192,52.72194],"type":"Point"}
}