{
  "type": "Feature",
  "properties": {
    "gn:admin1_code":"72",
    "gn:asciiname":"Novikovo",
    "gn:country_code":"RU",
    "gn:dem":149,
    "gn:feature_class":"P",
    "gn:feature_code":"PPL",
    "gn:name":"Novikovo",
    "gn:population":0,
    "gn:timezone":"Europe/Moscow",
    "iso:country":"RU",
    "name:rus_x_preferred":[
        "\u041d\u043e\u0432\u0438\u043a\u043e\u0432\u043e"
    ],
    "wof:name":"Novikovo",
    "wof:placetype":"locality"
},
  "geometry": {"coordinates":[40.5968,53.3422],"type":"Point"}
}