{
  "type": "Feature",
  "properties": {
    "gn:admin1_code":"23",
    "gn:asciiname":"Solnechnoye",
    "gn:country_code":"RU",
    "gn:dem":101,
    "gn:feature_class":"P",
    "gn:feature_code":"PPL",
    "gn:name":"Solnechnoye",
    "gn:population":0,
    "gn:timezone":"Europe/Kaliningrad",
    "iso:country":"RU",
    "name:deu_x_historical":[
        "Szameitschen"
    ],
    "name:deu_x_preferred":[
        "Szameitschen"
    ],
    "name:rus_x_preferred":[
        "\u0421\u043e\u043b\u043d\u0435\u0447\u043d\u043e\u0435"
    ],
    "name:und_x_variant":[
        "\u0421\u043e\u043b\u043d\u0435\u0447\u043d\u043e\u0435"
    ],
    "wof:name":"Solnechnoye",
    "wof:placetype":"locality"
},
  "geometry": {"coordinates":[22.15917,54.4075],"type":"Point"}
}