{
  "type": "Feature",
  "properties": {
    "gn:admin1_code":"88.0",
    "gn:asciiname":"Butovo",
    "gn:country_code":"RU",
    "gn:dem":85,
    "gn:feature_class":"P",
    "gn:feature_code":"PPL",
    "gn:name":"Butovo",
    "gn:population":0,
    "gn:timezone":"Europe/Moscow",
    "iso:country":"RU",
    "name:rus_x_preferred":[
        "\u0411\u0443\u0442\u043e\u0432\u043e"
    ],
    "name:ukr_x_preferred":[
        "\u0411\u0443\u0442\u043e\u0432\u043e"
    ],
    "wof:name":"Butovo",
    "wof:placetype":"locality"
},
  "geometry": {"coordinates":[40.50709000000001,57.80988000000001],"type":"Point"}
}