{
  "type": "Feature",
  "properties": {
    "gn:admin1_code":"56",
    "gn:asciiname":"Terekhovka",
    "gn:country_code":"RU",
    "gn:dem":221,
    "gn:feature_class":"P",
    "gn:feature_code":"PPL",
    "gn:name":"Terekhovka",
    "gn:population":0,
    "gn:timezone":"Europe/Moscow",
    "iso:country":"RU",
    "name:rus_x_preferred":[
        "\u0422\u0435\u0440\u0435\u0445\u043e\u0432\u043a\u0430"
    ],
    "wof:name":"Terekhovka",
    "wof:placetype":"locality"
},
  "geometry": {"coordinates":[35.0341,52.6413],"type":"Point"}
}