{
  "type": "Feature",
  "properties": {
    "gn:admin1_code":"51",
    "gn:asciiname":"Korelka",
    "gn:country_code":"RU",
    "gn:dem":121,
    "gn:feature_class":"P",
    "gn:feature_code":"PPL",
    "gn:name":"Korelka",
    "gn:population":0,
    "gn:timezone":"Europe/Moscow",
    "iso:country":"RU",
    "name:rus_x_preferred":[
        "\u041a\u043e\u0440\u0435\u043b\u043a\u0430"
    ],
    "name:und_x_variant":[
        "\u041a\u043e\u0440\u0435\u043b\u043a\u0430"
    ],
    "wof:name":"Korelka",
    "wof:placetype":"locality"
},
  "geometry": {"coordinates":[44.03498,56.83191],"type":"Point"}
}