{
  "type": "Feature",
  "properties": {
    "gn:admin1_code":"40",
    "gn:asciiname":"Skilyagina",
    "gn:country_code":"RU",
    "gn:dem":113,
    "gn:feature_class":"P",
    "gn:feature_code":"PPL",
    "gn:name":"Skilyagina",
    "gn:population":0,
    "gn:timezone":"Asia/Yekaterinburg",
    "iso:country":"RU",
    "name:eng_x_preferred":[
        "Skilyagina"
    ],
    "name:nor_x_preferred":[
        "Skiljagina"
    ],
    "name:rus_x_preferred":[
        "\u0421\u043a\u0438\u043b\u044f\u0433\u0438\u043d\u0430"
    ],
    "name:und_x_variant":[
        "Skilyagino",
        "\u0421\u043a\u0438\u043b\u044f\u0433\u0438\u043d\u0430",
        "Skilyagina"
    ],
    "wof:name":"Skilyagina",
    "wof:placetype":"locality"
},
  "geometry": {"coordinates":[62.6908,55.9502],"type":"Point"}
}