{
  "type": "Feature",
  "properties": {
    "gn:admin1_code":"57",
    "gn:asciiname":"Otorma",
    "gn:country_code":"RU",
    "gn:dem":136,
    "gn:feature_class":"P",
    "gn:feature_code":"PPL",
    "gn:name":"Otorma",
    "gn:population":0,
    "gn:timezone":"Europe/Moscow",
    "iso:country":"RU",
    "name:eng_x_preferred":[
        "Otorma"
    ],
    "name:nor_x_preferred":[
        "Otorma"
    ],
    "name:rus_x_preferred":[
        "\u041e\u0442\u043e\u0440\u043c\u0430"
    ],
    "wof:name":"Otorma",
    "wof:placetype":"locality"
},
  "geometry": {"coordinates":[42.51083,53.53738000000001],"type":"Point"}
}