{
  "type": "Feature",
  "properties": {
    "gn:admin1_code":"42",
    "gn:asciiname":"Kologrivo",
    "gn:country_code":"RU",
    "gn:dem":61,
    "gn:feature_class":"P",
    "gn:feature_code":"PPL",
    "gn:name":"Kologrivo",
    "gn:population":0,
    "gn:timezone":"Europe/Moscow",
    "iso:country":"RU",
    "name:rus_x_preferred":[
        "\u041a\u043e\u043b\u043e\u0433\u0440\u0438\u0432\u043e"
    ],
    "name:und_x_variant":[
        "\u041a\u043e\u043b\u043e\u0433\u0440\u0438\u0432\u043e"
    ],
    "wof:name":"Kologrivo",
    "wof:placetype":"locality"
},
  "geometry": {"coordinates":[28.50281,59.02746],"type":"Point"}
}