{
  "type": "Feature",
  "properties": {
    "gn:admin1_code":"85",
    "gn:asciiname":"Smerdomskiy",
    "gn:country_code":"RU",
    "gn:dem":139,
    "gn:feature_class":"P",
    "gn:feature_code":"PPL",
    "gn:name":"Smerdomskiy",
    "gn:population":0,
    "gn:timezone":"Europe/Moscow",
    "iso:country":"RU",
    "name:eng_x_preferred":[
        "Smerdomskiy"
    ],
    "name:nor_x_preferred":[
        "Smerdomskij"
    ],
    "name:rus_x_preferred":[
        "\u0421\u043c\u0435\u0440\u0434\u043e\u043c\u0441\u043a\u0438\u0439"
    ],
    "name:und_x_variant":[
        "Pos\u00eblok Smerdoml\u2019skogo Zavoda",
        "Smerdomskiy Steklozavod",
        "Pos\u00eblok Smerdoml\u2019skiy",
        "Smerdoml\u2019skiy",
        "\u0421\u043c\u0435\u0440\u0434\u043e\u043c\u0441\u043a\u0438\u0439",
        "Smerdomskiy"
    ],
    "wof:name":"Smerdomskiy",
    "wof:placetype":"locality"
},
  "geometry": {"coordinates":[35.0585,59.1759],"type":"Point"}
}