{
  "type": "Feature",
  "properties": {
    "gn:admin1_code":"47",
    "gn:asciiname":"Maloye Rogachevo",
    "gn:country_code":"RU",
    "gn:dem":159,
    "gn:feature_class":"P",
    "gn:feature_code":"PPL",
    "gn:name":"Maloye Rogach\u00ebvo",
    "gn:population":0,
    "gn:timezone":"Europe/Moscow",
    "iso:country":"RU",
    "name:rus_x_preferred":[
        "\u041c\u0430\u043b\u043e\u0435 \u0420\u043e\u0433\u0430\u0447\u0451\u0432\u043e"
    ],
    "name:und_x_variant":[
        "Maloye Rogach\u00ebvo"
    ],
    "wof:name":"Maloye Rogachevo",
    "wof:placetype":"locality"
},
  "geometry": {"coordinates":[37.16667,56.41667],"type":"Point"}
}