{
  "type": "Feature",
  "properties": {
    "gn:admin1_code":"43.0",
    "gn:asciiname":"Aleksandro-Bibikovskiye Vyselki",
    "gn:country_code":"RU",
    "gn:dem":166,
    "gn:feature_class":"P",
    "gn:feature_code":"PPL",
    "gn:name":"Aleksandro-Bibikovskiye Vyselki",
    "gn:population":0,
    "gn:timezone":"Europe/Moscow",
    "iso:country":"RU",
    "name:nor_x_preferred":[
        "Aleksandro-Bibikovskije Vyselki"
    ],
    "name:rus_x_preferred":[
        "\u0410\u043b\u0435\u043a\u0441\u0430\u043d\u0434\u0440\u043e-\u0411\u0438\u0431\u0438\u043a\u043e\u0432\u0441\u043a\u0438\u0435 \u0412\u044b\u0441\u0435\u043b\u043a\u0438"
    ],
    "wof:name":"Aleksandro-Bibikovskiye Vyselki",
    "wof:placetype":"locality"
},
  "geometry": {"coordinates":[38.26667,52.01667],"type":"Point"}
}