{
  "type": "Feature",
  "properties": {
    "gn:admin1_code":"41.0",
    "gn:asciiname":"Turayevka",
    "gn:country_code":"RU",
    "gn:dem":175,
    "gn:feature_class":"P",
    "gn:feature_code":"PPL",
    "gn:name":"Turayevka",
    "gn:population":0,
    "gn:timezone":"Europe/Moscow",
    "iso:country":"RU",
    "name:rus_x_preferred":[
        "\u0422\u0443\u0440\u0430\u0435\u0432\u043a\u0430"
    ],
    "wof:name":"Turayevka",
    "wof:placetype":"locality"
},
  "geometry": {"coordinates":[35.3643,51.8648],"type":"Point"}
}