{
  "type": "Feature",
  "properties": {
    "gn:admin1_code":"8",
    "gn:asciiname":"Krasnopol'ye",
    "gn:country_code":"RU",
    "gn:dem":363,
    "gn:feature_class":"P",
    "gn:feature_code":"PPL",
    "gn:name":"Krasnopol\u2019ye",
    "gn:population":0,
    "gn:timezone":"Asia/Yekaterinburg",
    "iso:country":"RU",
    "name:rus_x_preferred":[
        "\u041a\u0440\u0430\u0441\u043d\u043e\u043f\u043e\u043b\u044c\u0435"
    ],
    "name:und_x_variant":[
        "Krasnopol\u2019ye",
        "\u041a\u0440\u0430\u0441\u043d\u043e\u043f\u043e\u043b\u044c\u0435"
    ],
    "wof:name":"Krasnopol'ye",
    "wof:placetype":"locality"
},
  "geometry": {"coordinates":[58.13333000000001,55.05],"type":"Point"}
}