{
  "type": "Feature",
  "properties": {
    "gn:admin1_code":"55",
    "gn:asciiname":"Polevoy",
    "gn:country_code":"RU",
    "gn:dem":266,
    "gn:feature_class":"P",
    "gn:feature_code":"PPL",
    "gn:name":"Polevoy",
    "gn:population":0,
    "gn:timezone":"Asia/Yekaterinburg",
    "iso:country":"RU",
    "name:eng_x_preferred":[
        "Polevoy"
    ],
    "name:nor_x_preferred":[
        "Polevoj"
    ],
    "name:rus_x_preferred":[
        "\u041f\u043e\u043b\u0435\u0432\u043e\u0439"
    ],
    "name:und_x_variant":[
        "\u041f\u043e\u043b\u0435\u0432\u043e\u0439",
        "Polevoy"
    ],
    "wof:name":"Polevoy",
    "wof:placetype":"locality"
},
  "geometry": {"coordinates":[61.34083,50.87556],"type":"Point"}
}