{
  "type": "Feature",
  "properties": {
    "gn:admin1_code":"30",
    "gn:asciiname":"Iorik",
    "gn:cc2":"RU",
    "gn:country_code":"RU",
    "gn:dem":468,
    "gn:feature_class":"P",
    "gn:feature_code":"PPL",
    "gn:name":"Iorik",
    "gn:population":0,
    "gn:timezone":"Asia/Vladivostok",
    "iso:country":"RU",
    "name:eng_x_preferred":[
        "Iorik"
    ],
    "name:nor_x_preferred":[
        "Jerik"
    ],
    "name:rus_x_preferred":[
        "\u0415\u0440\u0438\u043a"
    ],
    "name:rus_x_variant":[
        "\u0418\u043e\u0440\u0438\u043a"
    ],
    "name:und_x_variant":[
        "Yerik"
    ],
    "wof:name":"Iorik",
    "wof:placetype":"locality"
},
  "geometry": {"coordinates":[133.18333000000001,51.53333],"type":"Point"}
}