{
  "type": "Feature",
  "properties": {
    "gn:admin1_code":"20.0",
    "gn:asciiname":"Srednyaya Gogolevka",
    "gn:country_code":"RU",
    "gn:dem":240,
    "gn:feature_class":"P",
    "gn:feature_code":"PPL",
    "gn:name":"Srednyaya Gogolevka",
    "gn:population":0,
    "gn:timezone":"Asia/Irkutsk",
    "iso:country":"RU",
    "name:rus_x_preferred":[
        "\u0421\u0440\u0435\u0434\u043d\u044f\u044f \u0413\u043e\u0433\u043e\u043b\u0435\u0432\u043a\u0430"
    ],
    "wof:name":"Srednyaya Gogolevka",
    "wof:placetype":"locality"
},
  "geometry": {"coordinates":[98.2379,56.0392],"type":"Point"}
}