{
  "type": "Feature",
  "properties": {
    "gn:admin1_code":"77.0",
    "gn:asciiname":"Fomino",
    "gn:country_code":"RU",
    "gn:dem":192,
    "gn:feature_class":"P",
    "gn:feature_code":"PPL",
    "gn:name":"Fomino",
    "gn:population":0,
    "gn:timezone":"Europe/Moscow",
    "iso:country":"RU",
    "name:rus_x_preferred":[
        "\u0424\u043e\u043c\u0438\u043d\u043e"
    ],
    "name:und_x_variant":[
        "\u0424\u043e\u043c\u0438\u043d\u043e"
    ],
    "wof:name":"Fomino",
    "wof:placetype":"locality"
},
  "geometry": {"coordinates":[34.60028,57.06645],"type":"Point"}
}