{
  "type": "Feature",
  "properties": {
    "gn:admin1_code":"6.0",
    "gn:asciiname":"Temnaya",
    "gn:country_code":"RU",
    "gn:dem":126,
    "gn:feature_class":"P",
    "gn:feature_code":"PPL",
    "gn:name":"T\u00ebmnaya",
    "gn:population":0,
    "gn:timezone":"Europe/Moscow",
    "iso:country":"RU",
    "name:rus_x_preferred":[
        "T\u00ebmnaya"
    ],
    "name:rus_x_variant":[
        "\u0422\u0451\u043c\u043d\u0430\u044f"
    ],
    "wof:name":"Temnaya",
    "wof:placetype":"locality"
},
  "geometry": {"coordinates":[41.3675,61.2623],"type":"Point"}
}