{
  "type": "Feature",
  "properties": {
    "gn:admin1_code":"23",
    "gn:asciiname":"Kutuzovo",
    "gn:cc2":"RU",
    "gn:country_code":"RU",
    "gn:dem":40,
    "gn:feature_class":"P",
    "gn:feature_code":"PPL",
    "gn:name":"Kutuzovo",
    "gn:population":0,
    "gn:timezone":"Europe/Kaliningrad",
    "iso:country":"RU",
    "name:deu_x_preferred":[
        "Kutusowo"
    ],
    "name:hye_x_preferred":[
        "\u053f\u0578\u0582\u057f\u0578\u0582\u0566\u0578\u057e\u0578"
    ],
    "name:lit_x_historical":[
        "\u0160irvinta"
    ],
    "name:lit_x_preferred":[
        "\u0160irvinta"
    ],
    "name:rus_x_preferred":[
        "\u041a\u0443\u0442\u0443\u0437\u043e\u0432\u043e"
    ],
    "name:und_x_variant":[
        "Shirvindt",
        "Kumuzovo",
        "Schirwindt",
        "Kutuzovo",
        "\u041a\u0443\u0442\u0443\u0437\u043e\u0432\u043e"
    ],
    "wof:name":"Kutuzovo",
    "wof:placetype":"locality"
},
  "geometry": {"coordinates":[22.845,54.78222],"type":"Point"}
}