{
  "type": "Feature",
  "properties": {
    "gn:admin1_code":"37.0",
    "gn:asciiname":"Davydovo",
    "gn:country_code":"RU",
    "gn:dem":131,
    "gn:feature_class":"P",
    "gn:feature_code":"PPL",
    "gn:name":"Davydovo",
    "gn:population":0,
    "gn:timezone":"Europe/Moscow",
    "iso:country":"RU",
    "name:eng_x_preferred":[
        "Davydovo"
    ],
    "name:nor_x_preferred":[
        "Davydovo"
    ],
    "name:rus_x_preferred":[
        "\u0414\u0430\u0432\u044b\u0434\u043e\u0432\u043e"
    ],
    "name:und_x_variant":[
        "\u0414\u0430\u0432\u044b\u0434\u043e\u0432\u043e",
        "Davydovo"
    ],
    "wof:name":"Davydovo",
    "wof:placetype":"locality"
},
  "geometry": {"coordinates":[44.34883,58.10829],"type":"Point"}
}