{
  "type": "Feature",
  "properties": {
    "gn:admin1_code":"53",
    "gn:asciiname":"Itkul'",
    "gn:country_code":"RU",
    "gn:dem":143,
    "gn:feature_class":"P",
    "gn:feature_code":"PPL",
    "gn:name":"Itkul\u2019",
    "gn:population":0,
    "gn:timezone":"Asia/Novosibirsk",
    "iso:country":"RU",
    "name:eng_x_preferred":[
        "Itkul'"
    ],
    "name:nor_x_preferred":[
        "Itkul"
    ],
    "name:rus_x_preferred":[
        "\u0418\u0442\u043a\u0443\u043b\u044c"
    ],
    "name:und_x_variant":[
        "Itkul\u2019"
    ],
    "wof:name":"Itkul'",
    "wof:placetype":"locality"
},
  "geometry": {"coordinates":[81.0252,55.082],"type":"Point"}
}