{
  "type": "Feature",
  "properties": {
    "gn:admin1_code":"91",
    "gn:asciiname":"Krasinka",
    "gn:cc2":"RU",
    "gn:country_code":"RU",
    "gn:dem":194,
    "gn:feature_class":"P",
    "gn:feature_code":"PPL",
    "gn:name":"Krasinka",
    "gn:population":0,
    "gn:timezone":"Asia/Krasnoyarsk",
    "iso:country":"RU",
    "name:eng_x_preferred":[
        "Krasinka"
    ],
    "name:nor_x_preferred":[
        "Krasinka"
    ],
    "name:rus_x_preferred":[
        "\u041a\u0440\u0430\u0441\u0438\u043d\u043a\u0430"
    ],
    "name:und_x_variant":[
        "Krasnyy",
        "Krasinka"
    ],
    "wof:name":"Krasinka",
    "wof:placetype":"locality"
},
  "geometry": {"coordinates":[89.38722,56.85583000000001],"type":"Point"}
}