{
  "type": "Feature",
  "properties": {
    "gn:admin1_code":"51.0",
    "gn:asciiname":"Ol'yevka",
    "gn:country_code":"RU",
    "gn:dem":155,
    "gn:feature_class":"P",
    "gn:feature_code":"PPL",
    "gn:name":"Ol\u2019yevka",
    "gn:population":0,
    "gn:timezone":"Europe/Moscow",
    "iso:country":"RU",
    "name:rus_x_preferred":[
        "\u041e\u043b\u044c\u0435\u0432\u043a\u0430"
    ],
    "name:und_x_variant":[
        "Ol\u2019yevka",
        "\u041e\u043b\u044c\u0435\u0432\u043a\u0430"
    ],
    "wof:name":"Ol'yevka",
    "wof:placetype":"locality"
},
  "geometry": {"coordinates":[43.68329,55.50229],"type":"Point"}
}