{
  "type": "Feature",
  "properties": {
    "gn:admin1_code":"33",
    "gn:asciiname":"Pislegi",
    "gn:country_code":"RU",
    "gn:dem":174,
    "gn:feature_class":"P",
    "gn:feature_code":"PPL",
    "gn:name":"Pislegi",
    "gn:population":0,
    "gn:timezone":"Europe/Kirov",
    "iso:country":"RU",
    "name:rus_x_preferred":[
        "\u041f\u0438\u0441\u043b\u0435\u0433\u0438"
    ],
    "wof:name":"Pislegi",
    "wof:placetype":"locality"
},
  "geometry": {"coordinates":[51.35,57.73333],"type":"Point"}
}