{
  "type": "Feature",
  "properties": {
    "gn:admin1_code":"90.0",
    "gn:asciiname":"Bryushinina",
    "gn:country_code":"RU",
    "gn:dem":177,
    "gn:feature_class":"P",
    "gn:feature_code":"PPL",
    "gn:name":"Bryushinina",
    "gn:population":0,
    "gn:timezone":"Asia/Yekaterinburg",
    "iso:country":"RU",
    "name:rus_x_preferred":[
        "\u0411\u0440\u044e\u0448\u0438\u043d\u0438\u043d\u0430"
    ],
    "wof:name":"Bryushinina",
    "wof:placetype":"locality"
},
  "geometry": {"coordinates":[54.8757,58.7444],"type":"Point"}
}