{
  "type": "Feature",
  "properties": {
    "gn:admin1_code":"37.0",
    "gn:asciiname":"Ovsyannikovo",
    "gn:country_code":"RU",
    "gn:dem":158,
    "gn:feature_class":"P",
    "gn:feature_code":"PPL",
    "gn:name":"Ovsyannikovo",
    "gn:population":200,
    "gn:timezone":"Europe/Moscow",
    "iso:country":"RU",
    "wof:name":"Ovsyannikovo",
    "wof:placetype":"locality",
    "wof:population":200
},
  "geometry": {"coordinates":[44.11388,58.94917],"type":"Point"}
}