{
  "type": "Feature",
  "properties": {
    "gn:admin1_code":"43",
    "gn:asciiname":"Ploskaya Vershina",
    "gn:country_code":"RU",
    "gn:dem":152,
    "gn:feature_class":"P",
    "gn:feature_code":"PPL",
    "gn:name":"Ploskaya Vershina",
    "gn:population":0,
    "gn:timezone":"Europe/Moscow",
    "iso:country":"RU",
    "name:rus_x_preferred":[
        "\u041f\u043b\u043e\u0441\u043a\u0430\u044f \u0412\u0435\u0440\u0448\u0438\u043d\u0430"
    ],
    "name:und_x_variant":[
        "Popovka",
        "Ploskaya Vershina",
        "\u041f\u043b\u043e\u0441\u043a\u0430\u044f \u0412\u0435\u0440\u0448\u0438\u043d\u0430"
    ],
    "wof:name":"Ploskaya Vershina",
    "wof:placetype":"locality"
},
  "geometry": {"coordinates":[40.2541,51.9957],"type":"Point"}
}