{
  "type": "Feature",
  "properties": {
    "gn:admin1_code":"71",
    "gn:asciiname":"Berezovaya Gar'",
    "gn:country_code":"RU",
    "gn:dem":169,
    "gn:feature_class":"P",
    "gn:feature_code":"PPL",
    "gn:name":"Ber\u00ebzovaya Gar\u2019",
    "gn:population":0,
    "gn:timezone":"Asia/Yekaterinburg",
    "iso:country":"RU",
    "name:nor_x_preferred":[
        "Berjozovaja Gar"
    ],
    "name:rus_x_preferred":[
        "\u0411\u0435\u0440\u0451\u0437\u043e\u0432\u0430\u044f \u0413\u0430\u0440\u044c"
    ],
    "name:und_x_variant":[
        "Ber\u00ebzovaya Gar\u2019"
    ],
    "wof:name":"Berezovaya Gar'",
    "wof:placetype":"locality"
},
  "geometry": {"coordinates":[60.46666999999999,60.21666999999999],"type":"Point"}
}