{
  "type": "Feature",
  "properties": {
    "gn:admin1_code":"42",
    "gn:asciiname":"Sirkiyansari",
    "gn:cc2":"RU",
    "gn:country_code":"RU",
    "gn:dem":55,
    "gn:feature_class":"P",
    "gn:feature_code":"PPL",
    "gn:name":"Sirkiyansari",
    "gn:population":0,
    "gn:timezone":"Europe/Moscow",
    "iso:country":"RU",
    "name:fin_x_preferred":[
        "Sirki\u00e4nsaari"
    ],
    "name:rus_x_preferred":[
        "\u0421\u0438\u0440\u043a\u0438\u044f\u043d\u0441\u0430\u0440\u0438"
    ],
    "name:und_x_variant":[
        "Sirkiyancari",
        "Sirkiyansari"
    ],
    "wof:name":"Sirkiyansari",
    "wof:placetype":"locality"
},
  "geometry": {"coordinates":[30.45,60.45],"type":"Point"}
}