{
  "type": "Feature",
  "properties": {
    "gn:admin1_code":"54",
    "gn:asciiname":"Alekseyevskiy",
    "gn:country_code":"RU",
    "gn:dem":120,
    "gn:feature_class":"P",
    "gn:feature_code":"PPL",
    "gn:name":"Alekseyevskiy",
    "gn:population":0,
    "gn:timezone":"Asia/Omsk",
    "iso:country":"RU",
    "name:rus_x_preferred":[
        "\u0410\u043b\u0435\u043a\u0441\u0435\u0435\u0432\u0441\u043a\u0438\u0439"
    ],
    "wof:name":"Alekseyevskiy",
    "wof:placetype":"locality"
},
  "geometry": {"coordinates":[72.00579999999999,55.3277],"type":"Point"}
}