{
  "type": "Feature",
  "properties": {
    "gn:admin1_code":"77",
    "gn:asciiname":"Krapivnitsy",
    "gn:country_code":"RU",
    "gn:dem":141,
    "gn:feature_class":"P",
    "gn:feature_code":"PPL",
    "gn:name":"Krapivnitsy",
    "gn:population":0,
    "gn:timezone":"Europe/Moscow",
    "iso:country":"RU",
    "name:rus_x_preferred":[
        "\u041a\u0440\u0430\u043f\u0438\u0432\u043d\u0438\u0446\u044b"
    ],
    "wof:name":"Krapivnitsy",
    "wof:placetype":"locality"
},
  "geometry": {"coordinates":[35.86319,58.30109],"type":"Point"}
}