{
  "type": "Feature",
  "properties": {
    "gn:admin1_code":"85",
    "gn:asciiname":"Vozdvizhenskoye",
    "gn:country_code":"RU",
    "gn:dem":154,
    "gn:feature_class":"P",
    "gn:feature_code":"PPL",
    "gn:name":"Vozdvizhenskoye",
    "gn:population":0,
    "gn:timezone":"Europe/Moscow",
    "iso:country":"RU",
    "name:eng_x_preferred":[
        "Vozdvizhenskoye"
    ],
    "name:nor_x_preferred":[
        "Vozdvizjenskoje"
    ],
    "name:rus_x_preferred":[
        "\u0412\u043e\u0437\u0434\u0432\u0438\u0436\u0435\u043d\u0441\u043a\u043e\u0435"
    ],
    "wof:name":"Vozdvizhenskoye",
    "wof:placetype":"locality"
},
  "geometry": {"coordinates":[39.91456,58.79987],"type":"Point"}
}