{
  "type": "Feature",
  "properties": {
    "gn:admin1_code":"34",
    "gn:asciiname":"Bed'vozh",
    "gn:country_code":"RU",
    "gn:dem":172,
    "gn:feature_class":"P",
    "gn:feature_code":"PPL",
    "gn:name":"Bed\u2019vozh",
    "gn:population":0,
    "gn:timezone":"Europe/Moscow",
    "iso:country":"RU",
    "name:eng_x_preferred":[
        "Bed'vozh"
    ],
    "name:nor_x_preferred":[
        "Bedvozj"
    ],
    "name:rus_x_preferred":[
        "\u0411\u0435\u0434\u044c\u0432\u043e\u0436"
    ],
    "name:und_x_variant":[
        "Bed\u2019vozh"
    ],
    "wof:name":"Bed'vozh",
    "wof:placetype":"locality"
},
  "geometry": {"coordinates":[49.36343,60.03211999999999],"type":"Point"}
}