{
  "type": "Feature",
  "properties": {
    "gn:admin1_code":"38",
    "gn:asciiname":"Priazovskiy",
    "gn:country_code":"RU",
    "gn:dem":84,
    "gn:feature_class":"P",
    "gn:feature_code":"PPL",
    "gn:name":"Priazovskiy",
    "gn:population":0,
    "gn:timezone":"Europe/Moscow",
    "iso:country":"RU",
    "name:rus_x_preferred":[
        "\u041f\u0440\u0438\u0430\u0437\u043e\u0432\u0441\u043a\u0438\u0439"
    ],
    "wof:name":"Priazovskiy",
    "wof:placetype":"locality"
},
  "geometry": {"coordinates":[36.83961,45.44222],"type":"Point"}
}