{
  "type": "Feature",
  "properties": {
    "gn:admin1_code":"78",
    "gn:asciiname":"Tyuleshov Bor",
    "gn:country_code":"RU",
    "gn:dem":69,
    "gn:feature_class":"P",
    "gn:feature_code":"PPL",
    "gn:name":"Tyuleshov Bor",
    "gn:population":0,
    "gn:timezone":"Asia/Yekaterinburg",
    "iso:country":"RU",
    "name:rus_x_preferred":[
        "\u0422\u044e\u043b\u0435\u0448\u043e\u0432 \u0411\u043e\u0440"
    ],
    "name:und_x_variant":[
        "Tyulyashev Bor"
    ],
    "wof:name":"Tyuleshov Bor",
    "wof:placetype":"locality"
},
  "geometry": {"coordinates":[70.67284000000002,56.68664],"type":"Point"}
}