{
  "type": "Feature",
  "properties": {
    "gn:admin1_code":"13",
    "gn:asciiname":"Travniki",
    "gn:country_code":"RU",
    "gn:dem":293,
    "gn:feature_class":"P",
    "gn:feature_code":"PPL",
    "gn:name":"Travniki",
    "gn:population":0,
    "gn:timezone":"Asia/Yekaterinburg",
    "iso:country":"RU",
    "name:eng_x_preferred":[
        "Travniki"
    ],
    "name:nor_x_preferred":[
        "Travniki"
    ],
    "name:rus_x_preferred":[
        "\u0422\u0440\u0430\u0432\u043d\u0438\u043a\u0438"
    ],
    "name:und_x_variant":[
        "Travnikovskiy"
    ],
    "wof:name":"Travniki",
    "wof:placetype":"locality"
},
  "geometry": {"coordinates":[60.55889000000001,54.90778],"type":"Point"}
}