{
  "type": "Feature",
  "properties": {
    "gn:admin1_code":"42",
    "gn:asciiname":"Kuttuzi",
    "gn:country_code":"RU",
    "gn:dem":100,
    "gn:feature_class":"P",
    "gn:feature_code":"PPL",
    "gn:name":"Kuttuzi",
    "gn:population":0,
    "gn:timezone":"Europe/Moscow",
    "iso:country":"RU",
    "name:fin_x_preferred":[
        "Kuttusi"
    ],
    "name:rus_x_preferred":[
        "\u041a\u0443\u0442\u0442\u0443\u0437\u0438"
    ],
    "wof:name":"Kuttuzi",
    "wof:placetype":"locality"
},
  "geometry": {"coordinates":[30.06222,59.75556],"type":"Point"}
}