{
  "type": "Feature",
  "properties": {
    "gn:admin1_code":"88",
    "gn:asciiname":"Zabelino",
    "gn:country_code":"RU",
    "gn:dem":166,
    "gn:feature_class":"P",
    "gn:feature_code":"PPL",
    "gn:name":"Zabelino",
    "gn:population":0,
    "gn:timezone":"Europe/Moscow",
    "iso:country":"RU",
    "name:rus_x_preferred":[
        "\u0417\u0430\u0431\u0435\u043b\u0438\u043d\u043e"
    ],
    "wof:name":"Zabelino",
    "wof:placetype":"locality"
},
  "geometry": {"coordinates":[39.18502,56.72973],"type":"Point"}
}