{
  "type": "Feature",
  "properties": {
    "gn:admin1_code":"60",
    "gn:asciiname":"Derganovo",
    "gn:country_code":"RU",
    "gn:dem":97,
    "gn:feature_class":"P",
    "gn:feature_code":"PPL",
    "gn:name":"Derganovo",
    "gn:population":0,
    "gn:timezone":"Europe/Moscow",
    "iso:country":"RU",
    "name:rus_x_preferred":[
        "\u0414\u0435\u0440\u0433\u0430\u043d\u043e\u0432\u043e"
    ],
    "wof:name":"Derganovo",
    "wof:placetype":"locality"
},
  "geometry": {"coordinates":[28.79144,56.67936],"type":"Point"}
}