{
  "type": "Feature",
  "properties": {
    "gn:admin1_code":"64",
    "gn:asciiname":"Nikol'skoye",
    "gn:country_code":"RU",
    "gn:dem":13,
    "gn:feature_class":"P",
    "gn:feature_code":"PPL",
    "gn:name":"Nikol\u2019skoye",
    "gn:population":0,
    "gn:timezone":"Asia/Sakhalin",
    "iso:country":"RU",
    "name:eng_x_preferred":[
        "Nikol'skoye"
    ],
    "name:nor_x_preferred":[
        "Nikolskoje"
    ],
    "name:rus_x_preferred":[
        "\u041d\u0438\u043a\u043e\u043b\u044c\u0441\u043a\u043e\u0435"
    ],
    "name:und_x_variant":[
        "Nakakanta",
        "\u041d\u0438\u043a\u043e\u043b\u044c\u0441\u043a\u043e\u0435",
        "Nikol\u2019skoye"
    ],
    "wof:name":"Nikol'skoye",
    "wof:placetype":"locality"
},
  "geometry": {"coordinates":[142.15000000000001,49.01667],"type":"Point"}
}