{
  "type": "Feature",
  "properties": {
    "gn:admin1_code":"60",
    "gn:asciiname":"Mokrova",
    "gn:country_code":"RU",
    "gn:dem":105,
    "gn:feature_class":"P",
    "gn:feature_code":"PPL",
    "gn:name":"Mokrova",
    "gn:population":0,
    "gn:timezone":"Europe/Moscow",
    "iso:country":"RU",
    "name:rus_x_preferred":[
        "\u041c\u043e\u043a\u0440\u043e\u0432\u0430"
    ],
    "wof:name":"Mokrova",
    "wof:placetype":"locality"
},
  "geometry": {"coordinates":[30.05,57.03333000000001],"type":"Point"}
}