{
  "type": "Feature",
  "properties": {
    "gn:admin1_code":"20",
    "gn:asciiname":"Kardoy",
    "gn:country_code":"RU",
    "gn:dem":411,
    "gn:feature_class":"P",
    "gn:feature_code":"PPL",
    "gn:name":"Kardoy",
    "gn:population":0,
    "gn:timezone":"Asia/Irkutsk",
    "iso:country":"RU",
    "name:eng_x_preferred":[
        "Kardoy"
    ],
    "name:nor_x_preferred":[
        "Kardoj"
    ],
    "name:rus_x_preferred":[
        "\u041a\u0430\u0440\u0434\u043e\u0439"
    ],
    "name:und_x_variant":[
        "Kordoy",
        "\u041a\u0430\u0440\u0434\u043e\u0439",
        "Kardoy"
    ],
    "wof:name":"Kardoy",
    "wof:placetype":"locality"
},
  "geometry": {"coordinates":[100.57875,55.21227],"type":"Point"}
}