{
  "type": "Feature",
  "properties": {
    "gn:admin1_code":"84",
    "gn:asciiname":"Tarasinskiy",
    "gn:country_code":"RU",
    "gn:dem":37,
    "gn:feature_class":"P",
    "gn:feature_code":"PPL",
    "gn:name":"Tarasinskiy",
    "gn:population":0,
    "gn:timezone":"Europe/Volgograd",
    "iso:country":"RU",
    "wof:name":"Tarasinskiy",
    "wof:placetype":"locality"
},
  "geometry": {"coordinates":[42.88333,48.21667],"type":"Point"}
}