{
  "type": "Feature",
  "properties": {
    "gn:admin1_code":"33",
    "gn:asciiname":"Ral'niki",
    "gn:country_code":"RU",
    "gn:dem":155,
    "gn:feature_class":"P",
    "gn:feature_code":"PPL",
    "gn:name":"Ral\u2019niki",
    "gn:population":0,
    "gn:timezone":"Europe/Kirov",
    "iso:country":"RU",
    "name:rus_x_preferred":[
        "\u0420\u0430\u043b\u044c\u043d\u0438\u043a\u0438"
    ],
    "name:und_x_variant":[
        "Ral\u2019nikovy",
        "Ral\u2019niki",
        "\u0420\u0430\u043b\u044c\u043d\u0438\u043a\u0438"
    ],
    "wof:name":"Ral'niki",
    "wof:placetype":"locality"
},
  "geometry": {"coordinates":[49.3983,58.4688],"type":"Point"}
}