{
  "type": "Feature",
  "properties": {
    "gn:admin1_code":"17",
    "gn:asciiname":"Gumi",
    "gn:country_code":"RU",
    "gn:dem":1076,
    "gn:feature_class":"P",
    "gn:feature_code":"PPL",
    "gn:name":"Gumi",
    "gn:population":0,
    "gn:timezone":"Europe/Moscow",
    "iso:country":"RU",
    "name:ceb_x_preferred":[
        "Gumi"
    ],
    "name:eng_x_preferred":[
        "Gumi"
    ],
    "name:fra_x_preferred":[
        "Gumi"
    ],
    "name:jpn_x_preferred":[
        "\u30b0\u30df"
    ],
    "name:kor_x_preferred":[
        "\uad6c\ubbf8"
    ],
    "name:nor_x_preferred":[
        "Gumi"
    ],
    "name:pol_x_preferred":[
        "Gumi"
    ],
    "name:rus_x_preferred":[
        "\u0413\u0443\u043c\u0438"
    ],
    "name:swe_x_preferred":[
        "Gumi"
    ],
    "name:ukr_x_preferred":[
        "\u0413\u0443\u043c\u0456"
    ],
    "name:und_x_variant":[
        "Kumi",
        "Gumi"
    ],
    "wof:name":"Gumi",
    "wof:placetype":"locality"
},
  "geometry": {"coordinates":[47.86878,41.89542],"type":"Point"}
}