{
  "type": "Feature",
  "properties": {
    "gn:admin1_code":"65",
    "gn:asciiname":"Solov'yevo",
    "gn:country_code":"RU",
    "gn:dem":87,
    "gn:feature_class":"P",
    "gn:feature_code":"PPL",
    "gn:name":"Solov\u2019y\u00ebvo",
    "gn:population":0,
    "gn:timezone":"Europe/Samara",
    "iso:country":"RU",
    "name:rus_x_preferred":[
        "Solov\u2019y\u00ebvo"
    ],
    "name:rus_x_variant":[
        "\u0421\u043e\u043b\u043e\u0432\u044c\u0451\u0432\u043e"
    ],
    "wof:name":"Solov'yevo",
    "wof:placetype":"locality"
},
  "geometry": {"coordinates":[48.9135,52.7939],"type":"Point"}
}