{
  "type": "Feature",
  "properties": {
    "gn:admin1_code":"63",
    "gn:asciiname":"Zelenyy Mys",
    "gn:cc2":"RU",
    "gn:country_code":"RU",
    "gn:dem":178,
    "gn:feature_class":"P",
    "gn:feature_code":"PPL",
    "gn:name":"Zel\u00ebnyy Mys",
    "gn:population":0,
    "gn:timezone":"Asia/Yakutsk",
    "iso:country":"RU",
    "name:und_x_variant":[
        "Kondrat\u2019yeva",
        "Zimov\u2019ye Kondrat\u2019yeva",
        "Zel\u00ebnyy Mys"
    ],
    "wof:name":"Zelenyy Mys",
    "wof:placetype":"locality"
},
  "geometry": {"coordinates":[131.46666999999999,58.93333000000001],"type":"Point"}
}