{
  "type": "Feature",
  "properties": {
    "gn:admin1_code":"52",
    "gn:asciiname":"Zuyevo",
    "gn:cc2":"RU",
    "gn:country_code":"RU",
    "gn:dem":33,
    "gn:feature_class":"P",
    "gn:feature_code":"PPL",
    "gn:name":"Zuyevo",
    "gn:population":0,
    "gn:timezone":"Europe/Moscow",
    "iso:country":"RU",
    "name:che_x_preferred":[
        "\u0417\u0443\u0435\u0432\u043e"
    ],
    "name:eng_x_preferred":[
        "Zuyevo"
    ],
    "name:nor_x_preferred":[
        "Zujevo"
    ],
    "name:rus_x_preferred":[
        "\u0417\u0443\u0435\u0432\u043e"
    ],
    "name:und_x_variant":[
        "Kolomovka",
        "Zuyevo"
    ],
    "wof:name":"Zuyevo",
    "wof:placetype":"locality"
},
  "geometry": {"coordinates":[31.53333,59.18333000000001],"type":"Point"}
}