{
  "type": "Feature",
  "properties": {
    "gn:admin1_code":"62",
    "gn:asciiname":"Vyshgorod",
    "gn:country_code":"RU",
    "gn:dem":112,
    "gn:feature_class":"P",
    "gn:feature_code":"PPL",
    "gn:name":"Vyshgorod",
    "gn:population":0,
    "gn:timezone":"Europe/Moscow",
    "iso:country":"RU",
    "name:eng_x_preferred":[
        "Vyshgorod"
    ],
    "name:nor_x_preferred":[
        "Vysjgorod"
    ],
    "name:rus_x_preferred":[
        "\u0412\u044b\u0448\u0433\u043e\u0440\u043e\u0434"
    ],
    "wof:name":"Vyshgorod",
    "wof:placetype":"locality"
},
  "geometry": {"coordinates":[40.0599,54.519],"type":"Point"}
}