{
  "type": "Feature",
  "properties": {
    "gn:admin1_code":"62",
    "gn:asciiname":"Vyshgorod",
    "gn:country_code":"RU",
    "gn:dem":112,
    "gn:feature_class":"P",
    "gn:feature_code":"PPL",
    "gn:name":"Vyshgorod",
    "gn:population":0,
    "gn:timezone":"Europe/Moscow",
    "iso:country":"RU",
    "name:ceb_x_preferred":[
        "Vyshgorod"
    ],
    "name:chv_x_preferred":[
        "\u0427\u0103\u0432\u0430\u0448-\u0445\u0443\u043b\u0430"
    ],
    "name:eng_x_preferred":[
        "Vyshgorod"
    ],
    "name:hye_x_preferred":[
        "\u054e\u056b\u0577\u0563\u0578\u0580\u0578\u0564"
    ],
    "name:nor_x_preferred":[
        "Vysjgorod"
    ],
    "name:rus_x_preferred":[
        "\u0412\u044b\u0448\u0433\u043e\u0440\u043e\u0434"
    ],
    "name:ukr_x_preferred":[
        "\u0412\u0438\u0448\u0433\u043e\u0440\u043e\u0434"
    ],
    "wof:name":"Vyshgorod",
    "wof:placetype":"locality"
},
  "geometry": {"coordinates":[40.0599,54.519],"type":"Point"}
}