{
  "type": "Feature",
  "properties": {
    "gn:admin1_code":"71",
    "gn:asciiname":"Pal'niki",
    "gn:country_code":"RU",
    "gn:dem":325,
    "gn:feature_class":"P",
    "gn:feature_code":"PPL",
    "gn:name":"Pal\u2019niki",
    "gn:population":0,
    "gn:timezone":"Asia/Yekaterinburg",
    "iso:country":"RU",
    "name:eng_x_preferred":[
        "Pal'niki"
    ],
    "name:nor_x_preferred":[
        "Palniki"
    ],
    "name:rus_x_preferred":[
        "\u041f\u0430\u043b\u044c\u043d\u0438\u043a\u0438"
    ],
    "name:und_x_variant":[
        "Pal\u2019niki"
    ],
    "wof:name":"Pal'niki",
    "wof:placetype":"locality"
},
  "geometry": {"coordinates":[59.8418,57.13931],"type":"Point"}
}