{
  "type": "Feature",
  "properties": {
    "gn:admin1_code":"8",
    "gn:asciiname":"Katargin",
    "gn:country_code":"RU",
    "gn:dem":180,
    "gn:feature_class":"P",
    "gn:feature_code":"PPL",
    "gn:name":"Katargin",
    "gn:population":0,
    "gn:timezone":"Asia/Yekaterinburg",
    "iso:country":"RU",
    "name:rus_x_preferred":[
        "\u041a\u0430\u0442\u0430\u0440\u0433\u0438\u043d"
    ],
    "wof:name":"Katargin",
    "wof:placetype":"locality"
},
  "geometry": {"coordinates":[54.58333,53.56667],"type":"Point"}
}