{
  "type": "Feature",
  "properties": {
    "gn:admin1_code":"90.0",
    "gn:asciiname":"Talitsa",
    "gn:country_code":"RU",
    "gn:dem":128,
    "gn:feature_class":"P",
    "gn:feature_code":"PPL",
    "gn:name":"Talitsa",
    "gn:population":0,
    "gn:timezone":"Asia/Yekaterinburg",
    "iso:country":"RU",
    "name:bel_x_preferred":[
        "\u0422\u0430\u043b\u0456\u0446\u0430"
    ],
    "name:ceb_x_preferred":[
        "Talitsa"
    ],
    "name:nld_x_preferred":[
        "Talitsa"
    ],
    "name:rus_x_preferred":[
        "\u0422\u0430\u043b\u0438\u0446\u0430"
    ],
    "name:swe_x_preferred":[
        "Talitsa"
    ],
    "name:ukr_x_preferred":[
        "\u0422\u0430\u043b\u0438\u0446\u044f"
    ],
    "wof:name":"Talitsa",
    "wof:placetype":"locality"
},
  "geometry": {"coordinates":[55.276,58.0898],"type":"Point"}
}