{
  "type": "Feature",
  "properties": {
    "gn:admin1_code":"56",
    "gn:asciiname":"Sadovoy",
    "gn:country_code":"RU",
    "gn:dem":237,
    "gn:feature_class":"P",
    "gn:feature_code":"PPL",
    "gn:name":"Sadovoy",
    "gn:population":0,
    "gn:timezone":"Europe/Moscow",
    "iso:country":"RU",
    "wof:name":"Sadovoy",
    "wof:placetype":"locality"
},
  "geometry": {"coordinates":[35.37169,52.83276],"type":"Point"}
}