{
  "type": "Feature",
  "properties": {
    "gn:country":"RU",
    "gn:fcode":"PPL",
    "gn:pop":0,
    "iso:country":"RU",
    "name:eng_x_preferred":[
        "Poshchupovo"
    ],
    "name:nor_x_preferred":[
        "Posjtsjupovo"
    ],
    "name:rus_x_preferred":[
        "\u041f\u043e\u0449\u0443\u043f\u043e\u0432\u043e"
    ],
    "name:unk_x_variant":[
        "\u041f\u043e\u0449\u0443\u043f\u043e\u0432\u043e"
    ],
    "qs:name":"Poshchupovo",
    "qs:name_adm0":"Russia",
    "qs:name_adm1":"Ryazan Oblast",
    "qs:photos_9k":1,
    "qs:photos_9r":2,
    "qs:photos_all":46,
    "qs:photos_sr":0,
    "qs:placetype":"Town",
    "qs:pop_sr":"0",
    "wof:name":"Poshchupovo",
    "wof:placetype":"locality",
    "wof:population":0
},
  "geometry": {"coordinates":[39.71799,54.81965],"type":"Point"}
}