{
  "type": "Feature",
  "properties": {
    "gn:admin1_code":"65.0",
    "gn:asciiname":"Zaprudnyy",
    "gn:country_code":"RU",
    "gn:dem":149,
    "gn:feature_class":"P",
    "gn:feature_code":"PPL",
    "gn:name":"Zaprudnyy",
    "gn:population":0,
    "gn:timezone":"Europe/Samara",
    "iso:country":"RU",
    "name:rus_x_preferred":[
        "\u0417\u0430\u043f\u0440\u0443\u0434\u043d\u044b\u0439"
    ],
    "name:und_x_variant":[
        "Novaya Orlovka",
        "Zaprudnyy"
    ],
    "wof:name":"Zaprudnyy",
    "wof:placetype":"locality"
},
  "geometry": {"coordinates":[50.93201,53.73639],"type":"Point"}
}