{
  "type": "Feature",
  "properties": {
    "gn:admin1_code":"78",
    "gn:asciiname":"Tashair",
    "gn:country_code":"RU",
    "gn:dem":56,
    "gn:feature_class":"P",
    "gn:feature_code":"PPL",
    "gn:name":"Tashair",
    "gn:population":0,
    "gn:timezone":"Asia/Yekaterinburg",
    "iso:country":"RU",
    "name:rus_x_preferred":[
        "\u0422\u0430\u0448\u0430\u0438\u0440"
    ],
    "wof:name":"Tashair",
    "wof:placetype":"locality"
},
  "geometry": {"coordinates":[70.77025,57.11372],"type":"Point"}
}