{
  "type": "Feature",
  "properties": {
    "gn:admin1_code":"59",
    "gn:asciiname":"Rasskazovo",
    "gn:country_code":"RU",
    "gn:dem":142,
    "gn:feature_class":"P",
    "gn:feature_code":"PPL",
    "gn:name":"Rasskazovo",
    "gn:population":0,
    "gn:timezone":"Asia/Vladivostok",
    "iso:country":"RU",
    "name:ara_x_preferred":[
        "\u0631\u0627\u0633\u0643\u0627\u0632\u0648\u0641\u0648"
    ],
    "name:azb_x_preferred":[
        "\u0631\u0627\u0633\u06a9\u0627\u0632\u0648\u0641\u0648"
    ],
    "name:aze_x_preferred":[
        "Rasskazovo"
    ],
    "name:bel_x_preferred":[
        "\u0420\u0430\u0441\u043a\u0430\u0437\u0430\u0432\u0430"
    ],
    "name:ceb_x_preferred":[
        "Rasskazovo"
    ],
    "name:deu_x_preferred":[
        "Rasskasowo"
    ],
    "name:eng_x_preferred":[
        "Rasskazovo"
    ],
    "name:epo_x_preferred":[
        "Rasskazovo"
    ],
    "name:est_x_preferred":[
        "Rasskazovo"
    ],
    "name:fas_x_preferred":[
        "\u0631\u0627\u0633\u06a9\u0627\u0632\u0648\u0641\u0648"
    ],
    "name:fra_x_preferred":[
        "Rasskazovo"
    ],
    "name:hsb_x_preferred":[
        "Rasskazowo"
    ],
    "name:ita_x_preferred":[
        "Rasskazovo"
    ],
    "name:nno_x_preferred":[
        "Rasskazovo"
    ],
    "name:nor_x_preferred":[
        "Rasskazovo"
    ],
    "name:pol_x_preferred":[
        "Rasskazowo"
    ],
    "name:rus_x_preferred":[
        "\u0420\u0430\u0441\u0441\u043a\u0430\u0437\u043e\u0432\u043e"
    ],
    "name:srp_x_preferred":[
        "\u0420\u0430\u0441\u043a\u0430\u0437\u043e\u0432\u043e"
    ],
    "name:tat_x_preferred":[
        "\u0420\u0430\u0441\u0441\u043a\u0430\u0437\u043e\u0432\u043e"
    ],
    "name:tgk_x_preferred":[
        "\u0420\u0430\u0441\u0441\u043a\u0430\u0437\u043e\u0432\u043e"
    ],
    "name:tgl_x_preferred":[
        "Rasskazovo"
    ],
    "name:tur_x_preferred":[
        "Rasskazovo"
    ],
    "name:ukr_x_preferred":[
        "\u0420\u043e\u0437\u0441\u043a\u0430\u0437\u043e\u0432\u043e"
    ],
    "name:und_x_variant":[
        "Chervohyy Pogranichnik",
        "Pogranichnyy"
    ],
    "name:vie_x_preferred":[
        "Rasskazovo"
    ],
    "name:war_x_preferred":[
        "Rasskazovo"
    ],
    "name:xal_x_preferred":[
        "\u0420\u0430\u0441\u0441\u043a\u0430\u0437\u043e\u0432\u043e \u0431\u0430\u043b\u04bb\u0441\u043d"
    ],
    "name:zho_x_preferred":[
        "\u62c9\u65af\u5361\u4f50\u6c83"
    ],
    "wof:name":"Rasskazovo",
    "wof:placetype":"locality"
},
  "geometry": {"coordinates":[131.78970000000001,45.18195],"type":"Point"}
}