{
  "type": "Feature",
  "properties": {
    "gn:admin1_code":"69",
    "gn:asciiname":"Katerevo",
    "gn:country_code":"RU",
    "gn:dem":205,
    "gn:feature_class":"P",
    "gn:feature_code":"PPL",
    "gn:name":"Kater\u00ebvo",
    "gn:population":0,
    "gn:timezone":"Europe/Moscow",
    "iso:country":"RU",
    "name:rus_x_preferred":[
        "\u041a\u0430\u0442\u0435\u0440\u0451\u0432\u043e"
    ],
    "name:und_x_variant":[
        "Koterevo",
        "Katergvo",
        "Kater\u00ebvo"
    ],
    "wof:name":"Katerevo",
    "wof:placetype":"locality"
},
  "geometry": {"coordinates":[33.3378,55.00194000000001],"type":"Point"}
}