{
  "type": "Feature",
  "properties": {
    "gn:admin1_code":"43",
    "gn:asciiname":"Skuratovka",
    "gn:country_code":"RU",
    "gn:dem":125,
    "gn:feature_class":"P",
    "gn:feature_code":"PPL",
    "gn:name":"Skuratovka",
    "gn:population":0,
    "gn:timezone":"Europe/Moscow",
    "iso:country":"RU",
    "name:rus_x_preferred":[
        "\u0421\u043a\u0443\u0440\u0430\u0442\u043e\u0432\u043a\u0430"
    ],
    "wof:name":"Skuratovka",
    "wof:placetype":"locality"
},
  "geometry": {"coordinates":[39.6614,53.5352],"type":"Point"}
}