{
  "type": "Feature",
  "properties": {
    "gn:admin1_code":"4",
    "gn:asciiname":"Rassvet",
    "gn:country_code":"RU",
    "gn:dem":206,
    "gn:feature_class":"P",
    "gn:feature_code":"PPL",
    "gn:name":"Rassvet",
    "gn:population":0,
    "gn:timezone":"Asia/Barnaul",
    "iso:country":"RU",
    "name:bel_x_preferred":[
        "\u0420\u0430\u0441\u0441\u0432\u0435\u0442"
    ],
    "name:cat_x_preferred":[
        "Rassvet"
    ],
    "name:ceb_x_preferred":[
        "Rassvet"
    ],
    "name:deu_x_preferred":[
        "Rasswet"
    ],
    "name:hye_x_preferred":[
        "\u054c\u0561\u057d\u057e\u0565\u057f"
    ],
    "name:kaz_x_preferred":[
        "\u0420\u0430\u0441\u0441\u0432\u0435\u0442"
    ],
    "name:rus_x_preferred":[
        "\u0420\u0430\u0441\u0441\u0432\u0435\u0442"
    ],
    "name:spa_x_preferred":[
        "Rasvet"
    ],
    "name:ukr_x_preferred":[
        "\u0420\u043e\u0437\u0441\u0432\u0456\u0442"
    ],
    "name:und_x_variant":[
        "\u0420\u0430\u0441\u0441\u0432\u0435\u0442"
    ],
    "wof:name":"Rassvet",
    "wof:placetype":"locality"
},
  "geometry": {"coordinates":[80.33333,53.45],"type":"Point"}
}