{
  "type": "Feature",
  "properties": {
    "gn:admin1_code":"41",
    "gn:asciiname":"Studenkiy",
    "gn:country_code":"RU",
    "gn:dem":241,
    "gn:feature_class":"P",
    "gn:feature_code":"PPL",
    "gn:name":"Studenkiy",
    "gn:population":0,
    "gn:timezone":"Europe/Moscow",
    "iso:country":"RU",
    "wof:name":"Studenkiy",
    "wof:placetype":"locality"
},
  "geometry": {"coordinates":[35.04778,52.27389],"type":"Point"}
}