{
  "type": "Feature",
  "properties": {
    "gn:admin1_code":"10",
    "gn:asciiname":"Per'kovo",
    "gn:country_code":"RU",
    "gn:dem":220,
    "gn:feature_class":"P",
    "gn:feature_code":"PPL",
    "gn:name":"Per\u2019kovo",
    "gn:population":0,
    "gn:timezone":"Europe/Moscow",
    "iso:country":"RU",
    "name:rus_x_preferred":[
        "\u041f\u0435\u0440\u044c\u043a\u043e\u0432\u043e"
    ],
    "name:und_x_variant":[
        "Perkoyo",
        "Per\u2019kovo"
    ],
    "wof:name":"Per'kovo",
    "wof:placetype":"locality"
},
  "geometry": {"coordinates":[35.08714000000001,53.00075],"type":"Point"}
}