{
  "type": "Feature",
  "properties": {
    "gn:admin1_code":"4",
    "gn:asciiname":"Malaya Povalikha",
    "gn:cc2":"RU",
    "gn:country_code":"RU",
    "gn:dem":231,
    "gn:feature_class":"P",
    "gn:feature_code":"PPL",
    "gn:name":"Malaya Povalikha",
    "gn:population":0,
    "gn:timezone":"Asia/Barnaul",
    "iso:country":"RU",
    "name:eng_x_preferred":[
        "Malaya Povalikha"
    ],
    "name:nor_x_preferred":[
        "Mal.Povalikha"
    ],
    "name:rus_x_preferred":[
        "\u041c\u0430\u043b.\u041f\u043e\u0432\u0430\u043b\u0438\u0445\u0430"
    ],
    "name:rus_x_variant":[
        "\u041c\u0430\u043b\u0430\u044f \u041f\u043e\u0432\u0430\u043b\u0438\u0445\u0430"
    ],
    "name:und_x_variant":[
        "Malopovalikha",
        "Malaya Povalikha",
        "\u041c\u0430\u043b\u0430\u044f \u041f\u043e\u0432\u0430\u043b\u0438\u0445\u0430"
    ],
    "wof:name":"Malaya Povalikha",
    "wof:placetype":"locality"
},
  "geometry": {"coordinates":[84.39278,53.75111],"type":"Point"}
}