{
  "type": "Feature",
  "properties": {
    "gn:admin1_code":"77",
    "gn:asciiname":"Oreshki",
    "gn:country_code":"RU",
    "gn:dem":227,
    "gn:feature_class":"P",
    "gn:feature_code":"PPL",
    "gn:name":"Oreshki",
    "gn:population":0,
    "gn:timezone":"Europe/Moscow",
    "iso:country":"RU",
    "name:eng_x_preferred":[
        "Oreshki"
    ],
    "name:nor_x_preferred":[
        "Oresjki"
    ],
    "name:rus_x_preferred":[
        "\u041e\u0440\u0435\u0448\u043a\u0438"
    ],
    "name:und_x_variant":[
        "\u041e\u0440\u0435\u0448\u043a\u0438",
        "Oreshki"
    ],
    "wof:name":"Oreshki",
    "wof:placetype":"locality"
},
  "geometry": {"coordinates":[34.15464,56.73969],"type":"Point"}
}