{
  "type": "Feature",
  "properties": {
    "gn:admin1_code":"33.0",
    "gn:asciiname":"Fedoseyevskoye",
    "gn:country_code":"RU",
    "gn:dem":117,
    "gn:feature_class":"P",
    "gn:feature_code":"PPL",
    "gn:name":"Fedoseyevskoye",
    "gn:population":0,
    "gn:timezone":"Europe/Kirov",
    "iso:country":"RU",
    "name:rus_x_preferred":[
        "\u0424\u0435\u0434\u043e\u0441\u0435\u0435\u0432\u0441\u043a\u043e\u0435"
    ],
    "name:und_x_variant":[
        "Fedos\u2019yevskoye",
        "Fedoseyevskoye",
        "\u0424\u0435\u0434\u043e\u0441\u0435\u0435\u0432\u0441\u043a\u043e\u0435"
    ],
    "wof:name":"Fedoseyevskoye",
    "wof:placetype":"locality"
},
  "geometry": {"coordinates":[47.6227,58.1473],"type":"Point"}
}