{
  "type": "Feature",
  "properties": {
    "gn:admin1_code":"29",
    "gn:asciiname":"Podkatun'",
    "gn:country_code":"RU",
    "gn:dem":281,
    "gn:feature_class":"P",
    "gn:feature_code":"PPL",
    "gn:name":"Podkatun\u2019",
    "gn:population":0,
    "gn:timezone":"Asia/Novokuznetsk",
    "iso:country":"RU",
    "name:rus_x_preferred":[
        "\u041f\u043e\u0434\u043a\u0430\u0442\u0443\u043d\u044c"
    ],
    "name:und_x_variant":[
        "Podkatun\u2019"
    ],
    "wof:name":"Podkatun'",
    "wof:placetype":"locality"
},
  "geometry": {"coordinates":[87.27030000000001,53.2726],"type":"Point"}
}