{
  "type": "Feature",
  "properties": {
    "gn:admin1_code":"33.0",
    "gn:asciiname":"Toropovy",
    "gn:country_code":"RU",
    "gn:dem":132,
    "gn:feature_class":"P",
    "gn:feature_code":"PPL",
    "gn:name":"Toropovy",
    "gn:population":0,
    "gn:timezone":"Europe/Kirov",
    "iso:country":"RU",
    "name:rus_x_preferred":[
        "\u0422\u043e\u0440\u043e\u043f\u043e\u0432\u044b"
    ],
    "wof:name":"Toropovy",
    "wof:placetype":"locality"
},
  "geometry": {"coordinates":[48.85772,58.51851],"type":"Point"}
}