{
  "type": "Feature",
  "properties": {
    "gn:country":"RU",
    "gn:fcode":"PPL",
    "gn:pop":0,
    "iso:country":"RU",
    "name:rus_x_preferred":[
        "\u0411\u043e\u0433\u043e\u0440\u043e\u0434\u0438\u0446\u043a\u043e\u0435"
    ],
    "qs:name":"Bogoroditskoye",
    "qs:name_adm0":"Russia",
    "qs:name_adm1":"Smolensk Oblast",
    "qs:photos_9k":1,
    "qs:photos_9r":1,
    "qs:photos_all":1,
    "qs:photos_sr":0,
    "qs:placetype":"Town",
    "qs:pop_sr":"0",
    "wd:wordcount":35,
    "wof:name":"Bogoroditskoye",
    "wof:placetype":"locality",
    "wof:population":0
},
  "geometry": {"coordinates":[32.1297,54.73472],"type":"Point"}
}