{
  "type": "Feature",
  "properties": {
    "gn:admin1_code":"57",
    "gn:asciiname":"Siyanovo",
    "gn:country_code":"RU",
    "gn:dem":177,
    "gn:feature_class":"P",
    "gn:feature_code":"PPL",
    "gn:name":"Siyanovo",
    "gn:population":0,
    "gn:timezone":"Europe/Moscow",
    "iso:country":"RU",
    "name:rus_x_preferred":[
        "\u0421\u0438\u044f\u043d\u043e\u0432\u043e"
    ],
    "name:und_x_variant":[
        "\u0421\u0438\u044f\u043d\u043e\u0432\u043e"
    ],
    "wof:name":"Siyanovo",
    "wof:placetype":"locality"
},
  "geometry": {"coordinates":[43.39836,53.85958],"type":"Point"}
}