{
  "type": "Feature",
  "properties": {
    "gn:admin1_code":"76",
    "gn:asciiname":"Zubovka",
    "gn:country_code":"RU",
    "gn:dem":198,
    "gn:feature_class":"P",
    "gn:feature_code":"PPL",
    "gn:name":"Zubovka",
    "gn:population":0,
    "gn:timezone":"Europe/Moscow",
    "iso:country":"RU",
    "name:rus_x_preferred":[
        "\u0417\u0443\u0431\u043e\u0432\u043a\u0430"
    ],
    "wof:name":"Zubovka",
    "wof:placetype":"locality"
},
  "geometry": {"coordinates":[38.57389000000001,54.00778],"type":"Point"}
}