{
  "type": "Feature",
  "properties": {
    "gn:admin1_code":"72",
    "gn:asciiname":"Kalugino",
    "gn:country_code":"RU",
    "gn:dem":143,
    "gn:feature_class":"P",
    "gn:feature_code":"PPL",
    "gn:name":"Kalugino",
    "gn:population":0,
    "gn:timezone":"Europe/Moscow",
    "iso:country":"RU",
    "name:eng_x_preferred":[
        "Kalugino"
    ],
    "name:nor_x_preferred":[
        "Kalugino"
    ],
    "name:rus_x_preferred":[
        "\u041a\u0430\u043b\u0443\u0433\u0438\u043d\u043e"
    ],
    "name:und_x_variant":[
        "\u041a\u0430\u043b\u0443\u0433\u0438\u043d\u043e",
        "Kalugino"
    ],
    "wof:name":"Kalugino",
    "wof:placetype":"locality"
},
  "geometry": {"coordinates":[42.29272,52.40478],"type":"Point"}
}