{
  "type": "Feature",
  "properties": {
    "gn:admin1_code":"77",
    "gn:asciiname":"Kopasy",
    "gn:country_code":"RU",
    "gn:dem":213,
    "gn:feature_class":"P",
    "gn:feature_code":"PPL",
    "gn:name":"Kopasy",
    "gn:population":0,
    "gn:timezone":"Europe/Moscow",
    "iso:country":"RU",
    "name:rus_x_preferred":[
        "\u041a\u043e\u043f\u0430\u0441\u044b"
    ],
    "name:und_x_variant":[
        "\u041a\u043e\u043f\u0430\u0441\u044b"
    ],
    "wof:name":"Kopasy",
    "wof:placetype":"locality"
},
  "geometry": {"coordinates":[31.36667000000001,56.61666999999999],"type":"Point"}
}