{
  "type": "Feature",
  "properties": {
    "gn:admin1_code":"63",
    "gn:asciiname":"Malakachka",
    "gn:cc2":"RU",
    "gn:country_code":"RU",
    "gn:dem":255,
    "gn:feature_class":"P",
    "gn:feature_code":"PPL",
    "gn:name":"Malakachka",
    "gn:population":0,
    "gn:timezone":"Asia/Vladivostok",
    "iso:country":"RU",
    "name:rus_x_preferred":[
        "\u041c\u0430\u043b\u0430\u043a\u0430\u0447\u043a\u0430"
    ],
    "name:und_x_variant":[
        "Malakhanka",
        "Malakachka"
    ],
    "wof:name":"Malakachka",
    "wof:placetype":"locality"
},
  "geometry": {"coordinates":[133.80000000000001,60.91667],"type":"Point"}
}