{
  "type": "Feature",
  "properties": {
    "gn:admin1_code":"71",
    "gn:asciiname":"Revdel'",
    "gn:country_code":"RU",
    "gn:dem":395,
    "gn:feature_class":"P",
    "gn:feature_code":"PPL",
    "gn:name":"Revdel\u2019",
    "gn:population":0,
    "gn:timezone":"Asia/Yekaterinburg",
    "iso:country":"RU",
    "name:eng_x_preferred":[
        "Revdel'"
    ],
    "name:nor_x_preferred":[
        "Revdel"
    ],
    "name:rus_x_preferred":[
        "\u0420\u0435\u0432\u0434\u0435\u043b\u044c"
    ],
    "name:und_x_variant":[
        "Revdinskiy",
        "Revdel\u2019"
    ],
    "wof:name":"Revdel'",
    "wof:placetype":"locality"
},
  "geometry": {"coordinates":[59.52556,56.4575],"type":"Point"}
}