{
  "type": "Feature",
  "properties": {
    "gn:admin1_code":"12.0",
    "gn:asciiname":"Urgan-Kale",
    "gn:country_code":"RU",
    "gn:dem":959,
    "gn:feature_class":"P",
    "gn:feature_code":"PPL",
    "gn:name":"Urgan-Kale",
    "gn:population":0,
    "gn:timezone":"Europe/Moscow",
    "iso:country":"RU",
    "wof:name":"Urgan-Kale",
    "wof:placetype":"locality"
},
  "geometry": {"coordinates":[45.65639,42.75694],"type":"Point"}
}