{
  "type": "Feature",
  "properties": {
    "gn:admin1_code":"20",
    "gn:asciiname":"Listvenichnaya",
    "gn:country_code":"RU",
    "gn:dem":259,
    "gn:feature_class":"P",
    "gn:feature_code":"PPL",
    "gn:name":"Listvenichnaya",
    "gn:population":0,
    "gn:timezone":"Asia/Irkutsk",
    "iso:country":"RU",
    "name:rus_x_preferred":[
        "\u041b\u0438\u0441\u0442\u0432\u0435\u043d\u0438\u0447\u043d\u0430\u044f"
    ],
    "wof:name":"Listvenichnaya",
    "wof:placetype":"locality"
},
  "geometry": {"coordinates":[97.58333,55.95],"type":"Point"}
}