{
  "type": "Feature",
  "properties": {
    "gn:admin1_code":"34",
    "gn:asciiname":"Keres",
    "gn:country_code":"RU",
    "gn:dem":109,
    "gn:feature_class":"P",
    "gn:feature_code":"PPL",
    "gn:name":"Keres",
    "gn:population":0,
    "gn:timezone":"Europe/Moscow",
    "iso:country":"RU",
    "name:eng_x_preferred":[
        "Keres"
    ],
    "name:rus_x_preferred":[
        "\u041a\u0435\u0440\u043e\u0441"
    ],
    "name:rus_x_variant":[
        "\u041c\u0430\u043a\u0430\u0440\u043a\u0435\u0440\u043e\u0441",
        "\u041a\u0435\u0440\u0435\u0441"
    ],
    "name:und_x_variant":[
        "Makar-Keres",
        "Keros",
        "Makarkeros",
        "Keres",
        "\u041a\u0435\u0440\u0435\u0441"
    ],
    "wof:name":"Keres",
    "wof:placetype":"locality"
},
  "geometry": {"coordinates":[52.6632,61.86991999999999],"type":"Point"}
}