{
  "type": "Feature",
  "properties": {
    "gn:admin1_code":"34",
    "gn:asciiname":"Keres",
    "gn:country_code":"RU",
    "gn:dem":109,
    "gn:feature_class":"P",
    "gn:feature_code":"PPL",
    "gn:name":"Keres",
    "gn:population":0,
    "gn:timezone":"Europe/Moscow",
    "iso:country":"RU",
    "name:bel_x_preferred":[
        "\u041a\u0435\u0440\u044b"
    ],
    "name:bul_x_preferred":[
        "\u041a\u0435\u0440\u0438"
    ],
    "name:cat_x_preferred":[
        "Keres"
    ],
    "name:ces_x_preferred":[
        "K\u00e9res"
    ],
    "name:deu_x_preferred":[
        "Ker"
    ],
    "name:ell_x_preferred":[
        "\u039a\u03ae\u03c1\u03b5\u03c2"
    ],
    "name:eng_x_preferred":[
        "Keres"
    ],
    "name:epo_x_preferred":[
        "Keresoj"
    ],
    "name:fas_x_preferred":[
        "\u06a9\u0631\u0647\u0627"
    ],
    "name:fin_x_preferred":[
        "Kerit"
    ],
    "name:fra_x_preferred":[
        "K\u00e8res"
    ],
    "name:hun_x_preferred":[
        "K\u00e9rek"
    ],
    "name:ind_x_preferred":[
        "Ker"
    ],
    "name:ita_x_preferred":[
        "Ker"
    ],
    "name:jpn_x_preferred":[
        "\u30b1\u30fc\u30eb"
    ],
    "name:kor_x_preferred":[
        "\ucf00\ub808\uc2a4"
    ],
    "name:lit_x_preferred":[
        "Ker\u0117s"
    ],
    "name:nld_x_preferred":[
        "Keres"
    ],
    "name:pol_x_preferred":[
        "Kery"
    ],
    "name:por_x_preferred":[
        "Queres"
    ],
    "name:rus_x_preferred":[
        "\u041a\u0435\u0440\u043e\u0441"
    ],
    "name:rus_x_variant":[
        "\u041c\u0430\u043a\u0430\u0440\u043a\u0435\u0440\u043e\u0441",
        "\u041a\u0435\u0440\u0435\u0441",
        "\u041a\u0435\u0440\u044b"
    ],
    "name:slk_x_preferred":[
        "K\u00e9ry"
    ],
    "name:slv_x_preferred":[
        "Ker"
    ],
    "name:spa_x_preferred":[
        "Keres"
    ],
    "name:srp_x_preferred":[
        "\u041a\u0435\u0440\u0435"
    ],
    "name:swe_x_preferred":[
        "Kerer"
    ],
    "name:ukr_x_preferred":[
        "\u041a\u0435\u0440\u0438"
    ],
    "name:und_x_variant":[
        "Makar-Keres",
        "Keros",
        "Makarkeros"
    ],
    "name:zho_x_preferred":[
        "\u514b\u857e\u7d72"
    ],
    "wof:name":"Keres",
    "wof:placetype":"locality"
},
  "geometry": {"coordinates":[52.6632,61.86991999999999],"type":"Point"}
}