{
  "type": "Feature",
  "properties": {
    "gn:admin1_code":"46",
    "gn:asciiname":"Kochkushi",
    "gn:country_code":"RU",
    "gn:dem":216,
    "gn:feature_class":"P",
    "gn:feature_code":"PPL",
    "gn:name":"Kochkushi",
    "gn:population":0,
    "gn:timezone":"Europe/Moscow",
    "iso:country":"RU",
    "name:rus_x_preferred":[
        "\u041a\u043e\u0447\u043a\u0443\u0448\u0438"
    ],
    "name:und_x_variant":[
        "\u041a\u043e\u0447\u043a\u0443\u0448\u0438"
    ],
    "wof:name":"Kochkushi",
    "wof:placetype":"locality"
},
  "geometry": {"coordinates":[45.64374,54.46389],"type":"Point"}
}