{
  "type": "Feature",
  "properties": {
    "gn:admin1_code":"90",
    "gn:asciiname":"Vas'-Pal'nik",
    "gn:country_code":"RU",
    "gn:dem":160,
    "gn:feature_class":"P",
    "gn:feature_code":"PPL",
    "gn:name":"Vas\u2019-Pal\u2019nik",
    "gn:population":0,
    "gn:timezone":"Asia/Yekaterinburg",
    "iso:country":"RU",
    "name:rus_x_preferred":[
        "\u0412\u0430\u0441\u044c-\u041f\u0430\u043b\u044c\u043d\u0438\u043a"
    ],
    "name:und_x_variant":[
        "Vas\u2019-Pal\u2019nik"
    ],
    "wof:name":"Vas'-Pal'nik",
    "wof:placetype":"locality"
},
  "geometry": {"coordinates":[54.54083000000001,59.10611],"type":"Point"}
}