{
  "type": "Feature",
  "properties": {
    "gn:admin1_code":"42",
    "gn:asciiname":"Pustyn'ka",
    "gn:country_code":"RU",
    "gn:dem":35,
    "gn:feature_class":"P",
    "gn:feature_code":"PPL",
    "gn:name":"Pustyn\u2019ka",
    "gn:population":0,
    "gn:timezone":"Europe/Moscow",
    "iso:country":"RU",
    "name:fin_x_preferred":[
        "Puusta"
    ],
    "name:rus_x_preferred":[
        "\u041f\u0443\u0441\u0442\u044b\u043d\u044c\u043a\u0430"
    ],
    "name:und_x_variant":[
        "Pustyn\u2019ka",
        "\u041f\u0443\u0441\u0442\u044b\u043d\u044c\u043a\u0430"
    ],
    "wof:name":"Pustyn'ka",
    "wof:placetype":"locality"
},
  "geometry": {"coordinates":[30.81306,59.66],"type":"Point"}
}