{
  "type": "Feature",
  "properties": {
    "gn:admin1_code":"37",
    "gn:asciiname":"Glushkovskaya Vtoraya",
    "gn:country_code":"RU",
    "gn:dem":145,
    "gn:feature_class":"P",
    "gn:feature_code":"PPL",
    "gn:name":"Glushkovskaya Vtoraya",
    "gn:population":0,
    "gn:timezone":"Europe/Moscow",
    "iso:country":"RU",
    "name:rus_x_preferred":[
        "\u0413\u043b\u0443\u0448\u043a\u043e\u0432\u0441\u043a\u0430\u044f \u0412\u0442\u043e\u0440\u0430\u044f"
    ],
    "name:und_x_variant":[
        "\u0413\u043b\u0443\u0448\u043a\u043e\u0432\u0441\u043a\u0430\u044f \u0412\u0442\u043e\u0440\u0430\u044f"
    ],
    "wof:name":"Glushkovskaya Vtoraya",
    "wof:placetype":"locality"
},
  "geometry": {"coordinates":[47.1306,59.0712],"type":"Point"}
}