{
  "type": "Feature",
  "properties": {
    "gn:admin1_code":"20",
    "gn:asciiname":"Zhuravlinka",
    "gn:country_code":"RU",
    "gn:dem":553,
    "gn:feature_class":"P",
    "gn:feature_code":"PPL",
    "gn:name":"Zhuravlinka",
    "gn:population":0,
    "gn:timezone":"Asia/Irkutsk",
    "iso:country":"RU",
    "name:eng_x_preferred":[
        "Zhuravlinka"
    ],
    "name:nor_x_preferred":[
        "Zjuravlinka"
    ],
    "name:rus_x_preferred":[
        "\u0416\u0443\u0440\u0430\u0432\u043b\u0438\u043d\u043a\u0430"
    ],
    "wof:name":"Zhuravlinka",
    "wof:placetype":"locality"
},
  "geometry": {"coordinates":[100.18333,54.71666999999999],"type":"Point"}
}