{
  "type": "Feature",
  "properties": {
    "gn:admin1_code":"76",
    "gn:asciiname":"Yasenok-Podlubnoye",
    "gn:country_code":"RU",
    "gn:dem":193,
    "gn:feature_class":"P",
    "gn:feature_code":"PPL",
    "gn:name":"Yasenok-Podlubnoye",
    "gn:population":0,
    "gn:timezone":"Europe/Moscow",
    "iso:country":"RU",
    "name:rus_x_preferred":[
        "\u042f\u0441\u0435\u043d\u043e\u043a-\u041f\u043e\u0434\u043b\u0443\u0431\u043d\u043e\u0435"
    ],
    "name:und_x_variant":[
        "Podlubnoye",
        "Yasenok",
        "Yasenok-Podlubnoye"
    ],
    "wof:name":"Yasenok-Podlubnoye",
    "wof:placetype":"locality"
},
  "geometry": {"coordinates":[38.35724,54.18158],"type":"Point"}
}