{
  "type": "Feature",
  "properties": {
    "gn:admin1_code":"71",
    "gn:asciiname":"Kislyanka",
    "gn:country_code":"RU",
    "gn:dem":162,
    "gn:feature_class":"P",
    "gn:feature_code":"PPL",
    "gn:name":"Kislyanka",
    "gn:population":0,
    "gn:timezone":"Asia/Yekaterinburg",
    "iso:country":"RU",
    "name:rus_x_preferred":[
        "\u041a\u0438\u0441\u043b\u044f\u043d\u043a\u0430"
    ],
    "wof:name":"Kislyanka",
    "wof:placetype":"locality"
},
  "geometry": {"coordinates":[61.7966,57.3483],"type":"Point"}
}