{
  "type": "Feature",
  "properties": {
    "gn:admin1_code":"85",
    "gn:asciiname":"Vozdvizhen'ye",
    "gn:country_code":"RU",
    "gn:dem":145,
    "gn:feature_class":"P",
    "gn:feature_code":"PPL",
    "gn:name":"Vozdvizhen\u2019ye",
    "gn:population":0,
    "gn:timezone":"Europe/Moscow",
    "iso:country":"RU",
    "name:rus_x_preferred":[
        "\u0412\u043e\u0437\u0434\u0432\u0438\u0436\u0435\u043d\u044c\u0435"
    ],
    "name:und_x_variant":[
        "Vozdvizhen\u2019ye",
        "\u0412\u043e\u0437\u0434\u0432\u0438\u0436\u0435\u043d\u044c\u0435"
    ],
    "wof:name":"Vozdvizhen'ye",
    "wof:placetype":"locality"
},
  "geometry": {"coordinates":[38.0238,59.8899],"type":"Point"}
}