{
  "type": "Feature",
  "properties": {
    "gn:admin1_code":"77",
    "gn:asciiname":"Ivanishchi",
    "gn:country_code":"RU",
    "gn:dem":153,
    "gn:feature_class":"P",
    "gn:feature_code":"PPL",
    "gn:name":"Ivanishchi",
    "gn:population":0,
    "gn:timezone":"Europe/Moscow",
    "iso:country":"RU",
    "name:rus_x_preferred":[
        "\u0418\u0432\u0430\u043d\u0438\u0449\u0438"
    ],
    "name:und_x_variant":[
        "\u0418\u0432\u0430\u043d\u0438\u0449\u0438"
    ],
    "wof:name":"Ivanishchi",
    "wof:placetype":"locality"
},
  "geometry": {"coordinates":[36.2529,58.0899],"type":"Point"}
}