{
  "type": "Feature",
  "properties": {
    "gn:admin1_code":"15",
    "gn:asciiname":"Torgovyy Punkt Yakuttorga",
    "gn:cc2":"RU",
    "gn:country_code":"RU",
    "gn:dem":261,
    "gn:feature_class":"P",
    "gn:feature_code":"PPL",
    "gn:name":"Torgovyy Punkt Yakuttorga",
    "gn:population":0,
    "gn:timezone":"Asia/Anadyr",
    "iso:country":"RU",
    "name:und_x_variant":[
        "Yakuttorg",
        "Torgovyy Punkt Yakuttorg",
        "Torgovyy Punkt Yakuttorga"
    ],
    "wof:name":"Torgovyy Punkt Yakuttorga",
    "wof:placetype":"locality"
},
  "geometry": {"coordinates":[160.86667,65.95],"type":"Point"}
}