{
  "type": "Feature",
  "properties": {
    "gn:admin1_code":"25",
    "gn:asciiname":"Bolottskoye",
    "gn:country_code":"RU",
    "gn:dem":123,
    "gn:feature_class":"P",
    "gn:feature_code":"PPL",
    "gn:name":"Bolottskoye",
    "gn:population":0,
    "gn:timezone":"Europe/Moscow",
    "iso:country":"RU",
    "name:rus_x_preferred":[
        "\u0411\u043e\u043b\u043e\u0442\u0442\u0441\u043a\u043e\u0435"
    ],
    "wof:name":"Bolottskoye",
    "wof:placetype":"locality"
},
  "geometry": {"coordinates":[36.64018,55.02848],"type":"Point"}
}