{
  "type": "Feature",
  "properties": {
    "gn:admin1_code":"60",
    "gn:asciiname":"Tulai",
    "gn:country_code":"RU",
    "gn:dem":183,
    "gn:feature_class":"P",
    "gn:feature_code":"PPL",
    "gn:name":"Tulai",
    "gn:population":0,
    "gn:timezone":"Europe/Moscow",
    "iso:country":"RU",
    "name:rus_x_preferred":[
        "\u0422\u0443\u043b\u0430\u0438"
    ],
    "wof:name":"Tulai",
    "wof:placetype":"locality"
},
  "geometry": {"coordinates":[29.0275,56.5617],"type":"Point"}
}