{
  "type": "Feature",
  "properties": {
    "gn:country":"RU",
    "gn:fcode":"PPL",
    "gn:pop":0,
    "iso:country":"RU",
    "name:rus_x_preferred":[
        "\u0420\u044b\u0431\u0430\u043a\u0438"
    ],
    "name:unk_x_variant":[
        "\u0420\u044b\u0431\u0430\u043a\u0438"
    ],
    "qs:name":"Rybaki",
    "qs:name_adm0":"Russia",
    "qs:name_adm1":"Moscow Oblast",
    "qs:photos_9k":1,
    "qs:photos_9r":1,
    "qs:photos_all":11,
    "qs:photos_sr":0,
    "qs:placetype":"Town",
    "qs:pop_sr":"0",
    "wd:wordcount":142,
    "wof:name":"Rybaki",
    "wof:placetype":"locality",
    "wof:population":0
},
  "geometry": {"coordinates":[37.36667,56.05],"type":"Point"}
}