{
  "type": "Feature",
  "properties": {
    "gn:admin1_code":"73.0",
    "gn:asciiname":"Abzyabar",
    "gn:country_code":"RU",
    "gn:dem":92,
    "gn:feature_class":"P",
    "gn:feature_code":"PPL",
    "gn:name":"Abzyabar",
    "gn:population":0,
    "gn:timezone":"Europe/Moscow",
    "iso:country":"RU",
    "name:nor_x_preferred":[
        "Abziabar"
    ],
    "name:rus_x_preferred":[
        "\u0410\u0431\u0437\u044f\u0431\u0430\u0440"
    ],
    "wof:name":"Abzyabar",
    "wof:placetype":"locality"
},
  "geometry": {"coordinates":[49.72041,56.08168000000001],"type":"Point"}
}