{
  "type": "Feature",
  "properties": {
    "gn:admin1_code":"45",
    "gn:asciiname":"Kachenki",
    "gn:country_code":"RU",
    "gn:dem":155,
    "gn:feature_class":"P",
    "gn:feature_code":"PPL",
    "gn:name":"Kachenki",
    "gn:population":0,
    "gn:timezone":"Europe/Moscow",
    "iso:country":"RU",
    "name:rus_x_preferred":[
        "\u041a\u0430\u0447\u0435\u043d\u043a\u0438"
    ],
    "wof:name":"Kachenki",
    "wof:placetype":"locality"
},
  "geometry": {"coordinates":[49.0349,57.2516],"type":"Point"}
}