{
  "type": "Feature",
  "properties": {
    "gn:admin1_code":"60",
    "gn:asciiname":"Sekirnitsa",
    "gn:country_code":"RU",
    "gn:dem":230,
    "gn:feature_class":"P",
    "gn:feature_code":"PPL",
    "gn:name":"Sekirnitsa",
    "gn:population":0,
    "gn:timezone":"Europe/Moscow",
    "iso:country":"RU",
    "name:rus_x_preferred":[
        "\u0421\u0435\u043a\u0438\u0440\u043d\u0438\u0446\u0430"
    ],
    "wof:name":"Sekirnitsa",
    "wof:placetype":"locality"
},
  "geometry": {"coordinates":[29.3777,56.7283],"type":"Point"}
}