{
  "type": "Feature",
  "properties": {
    "gn:admin1_code":"33",
    "gn:asciiname":"Lopotovo",
    "gn:country_code":"RU",
    "gn:dem":113,
    "gn:feature_class":"P",
    "gn:feature_code":"PPL",
    "gn:name":"Lopotovo",
    "gn:population":0,
    "gn:timezone":"Europe/Kirov",
    "iso:country":"RU",
    "name:rus_x_preferred":[
        "\u041b\u043e\u043f\u043e\u0442\u043e\u0432\u043e"
    ],
    "wof:name":"Lopotovo",
    "wof:placetype":"locality"
},
  "geometry": {"coordinates":[48.1412,60.5074],"type":"Point"}
}