{
  "type": "Feature",
  "properties": {
    "gn:admin1_code":"4",
    "gn:asciiname":"Tayga",
    "gn:country_code":"RU",
    "gn:dem":209,
    "gn:feature_class":"P",
    "gn:feature_code":"PPL",
    "gn:name":"Tayga",
    "gn:population":0,
    "gn:timezone":"Asia/Barnaul",
    "iso:country":"RU",
    "name:ara_x_preferred":[
        "\u062a\u0627\u064a\u063a\u0627"
    ],
    "name:azb_x_preferred":[
        "\u062a\u0627\u06cc\u0642\u0627"
    ],
    "name:bel_x_preferred":[
        "\u0422\u0430\u0439\u0433\u0430"
    ],
    "name:bul_x_preferred":[
        "\u0422\u0430\u0439\u0433\u0430"
    ],
    "name:ceb_x_preferred":[
        "Tayga"
    ],
    "name:deu_x_preferred":[
        "Taiga"
    ],
    "name:epo_x_preferred":[
        "Tajga"
    ],
    "name:fas_x_preferred":[
        "\u062a\u0627\u06cc\u06af\u0627"
    ],
    "name:fra_x_preferred":[
        "Ta\u00efga"
    ],
    "name:hsb_x_preferred":[
        "Tajga"
    ],
    "name:ita_x_preferred":[
        "Tajga"
    ],
    "name:jpn_x_preferred":[
        "\u30bf\u30a4\u30ac"
    ],
    "name:kor_x_preferred":[
        "\ud0c0\uc774\uac00"
    ],
    "name:lit_x_preferred":[
        "Taiga"
    ],
    "name:nld_x_preferred":[
        "Tajga"
    ],
    "name:nno_x_preferred":[
        "Tajga"
    ],
    "name:nor_x_preferred":[
        "Tajga"
    ],
    "name:pol_x_preferred":[
        "Tajga"
    ],
    "name:por_x_preferred":[
        "Taiga"
    ],
    "name:rus_x_preferred":[
        "\u0422\u0430\u0439\u0433\u0430"
    ],
    "name:srp_x_preferred":[
        "\u0422\u0430\u0458\u0433\u0430"
    ],
    "name:tat_x_preferred":[
        "\u0422\u0430\u0439\u0433\u0430"
    ],
    "name:tgl_x_preferred":[
        "Tayga"
    ],
    "name:tur_x_preferred":[
        "Tayga"
    ],
    "name:ukr_x_preferred":[
        "\u0422\u0430\u0439\u0433\u0430"
    ],
    "name:vep_x_preferred":[
        "Taig"
    ],
    "name:war_x_preferred":[
        "Tayga"
    ],
    "wof:name":"Tayga",
    "wof:placetype":"locality"
},
  "geometry": {"coordinates":[81.31667,51.45],"type":"Point"}
}