{
  "type": "Feature",
  "properties": {
    "gn:admin1_code":"52",
    "gn:asciiname":"Karel-Ramen'ye",
    "gn:country_code":"RU",
    "gn:dem":259,
    "gn:feature_class":"P",
    "gn:feature_code":"PPL",
    "gn:name":"Karel-Ramen\u2019ye",
    "gn:population":0,
    "gn:timezone":"Europe/Moscow",
    "iso:country":"RU",
    "name:rus_x_preferred":[
        "\u041a\u0430\u0440\u0435\u043b-\u0420\u0430\u043c\u0435\u043d\u044c\u0435"
    ],
    "name:und_x_variant":[
        "Karel-Ramen\u2019ye"
    ],
    "wof:name":"Karel-Ramen'ye",
    "wof:placetype":"locality"
},
  "geometry": {"coordinates":[33.68333,59.11666999999999],"type":"Point"}
}