{
  "type": "Feature",
  "properties": {
    "gn:admin1_code":"6",
    "gn:asciiname":"Khabarovo",
    "gn:country_code":"RU",
    "gn:dem":76,
    "gn:feature_class":"P",
    "gn:feature_code":"PPL",
    "gn:name":"Khabarovo",
    "gn:population":0,
    "gn:timezone":"Europe/Moscow",
    "iso:country":"RU",
    "name:rus_x_preferred":[
        "\u0425\u0430\u0431\u0430\u0440\u043e\u0432\u043e"
    ],
    "wof:name":"Khabarovo",
    "wof:placetype":"locality"
},
  "geometry": {"coordinates":[46.51667,61.41667],"type":"Point"}
}