{
  "type": "Feature",
  "properties": {
    "gn:admin1_code":"71",
    "gn:asciiname":"Verkhnyaya Boyevka",
    "gn:cc2":"RU",
    "gn:country_code":"RU",
    "gn:dem":241,
    "gn:feature_class":"P",
    "gn:feature_code":"PPL",
    "gn:name":"Verkhnyaya Boyevka",
    "gn:population":0,
    "gn:timezone":"Asia/Yekaterinburg",
    "iso:country":"RU",
    "name:rus_x_preferred":[
        "\u0412\u0435\u0440\u0445\u043d\u044f\u044f \u0411\u043e\u0435\u0432\u043a\u0430"
    ],
    "name:und_x_variant":[
        "Boyevskoye",
        "Verkhnyaya Boyevka"
    ],
    "wof:name":"Verkhnyaya Boyevka",
    "wof:placetype":"locality"
},
  "geometry": {"coordinates":[60.97167,56.25389000000001],"type":"Point"}
}