{
  "type": "Feature",
  "properties": {
    "gn:admin1_code":"10",
    "gn:asciiname":"Novonovitskaya",
    "gn:country_code":"RU",
    "gn:dem":163,
    "gn:feature_class":"P",
    "gn:feature_code":"PPL",
    "gn:name":"Novonovitskaya",
    "gn:population":0,
    "gn:timezone":"Europe/Moscow",
    "iso:country":"RU",
    "name:rus_x_preferred":[
        "\u041d\u043e\u0432\u043e\u043d\u043e\u0432\u0438\u0446\u043a\u0430\u044f"
    ],
    "name:und_x_variant":[
        "Novaya Novitskaya",
        "Novonovitskaya"
    ],
    "wof:name":"Novonovitskaya",
    "wof:placetype":"locality"
},
  "geometry": {"coordinates":[31.9477,53.0095],"type":"Point"}
}