{
  "type": "Feature",
  "properties": {
    "gn:admin1_code":"15",
    "gn:asciiname":"Avan'",
    "gn:country_code":"RU",
    "gn:dem":111,
    "gn:feature_class":"P",
    "gn:feature_code":"PPL",
    "gn:name":"Avan\u2019",
    "gn:population":0,
    "gn:timezone":"Asia/Anadyr",
    "iso:country":"RU",
    "name:nor_x_preferred":[
        "Avan"
    ],
    "name:rus_x_preferred":[
        "\u0410\u0432\u0430\u043d\u044c"
    ],
    "name:und_x_variant":[
        "Ikhtykhed",
        "Istikhet",
        "Avan\u2019"
    ],
    "wof:name":"Avan'",
    "wof:placetype":"locality"
},
  "geometry": {"coordinates":[173.30000000000001,64.28333000000001],"type":"Point"}
}