{
  "type": "Feature",
  "properties": {
    "gn:admin1_code":"33.0",
    "gn:asciiname":"Pestery",
    "gn:country_code":"RU",
    "gn:dem":133,
    "gn:feature_class":"P",
    "gn:feature_code":"PPL",
    "gn:name":"Pestery",
    "gn:population":0,
    "gn:timezone":"Europe/Kirov",
    "iso:country":"RU",
    "name:rus_x_preferred":[
        "\u041f\u0435\u0441\u0442\u0435\u0440\u044b"
    ],
    "name:und_x_variant":[
        "Pesterovskiy",
        "Pestery",
        "\u041f\u0435\u0441\u0442\u0435\u0440\u044b"
    ],
    "wof:name":"Pestery",
    "wof:placetype":"locality"
},
  "geometry": {"coordinates":[49.91278,58.46807],"type":"Point"}
}