{
  "type": "Feature",
  "properties": {
    "gn:admin1_code":"38.0",
    "gn:asciiname":"Babichevskiye",
    "gn:country_code":"RU",
    "gn:dem":-2,
    "gn:feature_class":"P",
    "gn:feature_code":"PPL",
    "gn:name":"Babichevskiye",
    "gn:population":0,
    "gn:timezone":"Europe/Moscow",
    "iso:country":"RU",
    "name:nor_x_preferred":[
        "Babitsjevskije"
    ],
    "name:rus_x_preferred":[
        "\u0411\u0430\u0431\u0438\u0447\u0435\u0432\u0441\u043a\u0438\u0435"
    ],
    "wof:name":"Babichevskiye",
    "wof:placetype":"locality"
},
  "geometry": {"coordinates":[37.87611,45.47639],"type":"Point"}
}