{
  "type": "Feature",
  "properties": {
    "gn:admin1_code":"29",
    "gn:asciiname":"Cheresh",
    "gn:country_code":"RU",
    "gn:dem":235,
    "gn:feature_class":"P",
    "gn:feature_code":"PPL",
    "gn:name":"Cheresh",
    "gn:population":0,
    "gn:timezone":"Asia/Novokuznetsk",
    "iso:country":"RU",
    "name:rus_x_preferred":[
        "\u0427\u0435\u0440\u0435\u0448"
    ],
    "name:und_x_variant":[
        "\u0427\u0435\u0440\u0435\u0448"
    ],
    "wof:name":"Cheresh",
    "wof:placetype":"locality"
},
  "geometry": {"coordinates":[87.5433,53.805],"type":"Point"}
}