{
  "type": "Feature",
  "properties": {
    "gn:admin1_code":"53",
    "gn:asciiname":"Urgul'ka",
    "gn:country_code":"RU",
    "gn:dem":123,
    "gn:feature_class":"P",
    "gn:feature_code":"PPL",
    "gn:name":"Urgul\u2019ka",
    "gn:population":0,
    "gn:timezone":"Asia/Novosibirsk",
    "iso:country":"RU",
    "wof:name":"Urgul'ka",
    "wof:placetype":"locality"
},
  "geometry": {"coordinates":[77.83333,56.38333000000001],"type":"Point"}
}