{
  "type": "Feature",
  "properties": {
    "gn:admin1_code":"5",
    "gn:asciiname":"Yemel'yanovskiy",
    "gn:country_code":"RU",
    "gn:dem":386,
    "gn:feature_class":"P",
    "gn:feature_code":"PPL",
    "gn:name":"Yemel\u2019yanovskiy",
    "gn:population":0,
    "gn:timezone":"Asia/Yakutsk",
    "iso:country":"RU",
    "wof:name":"Yemel'yanovskiy",
    "wof:placetype":"locality"
},
  "geometry": {"coordinates":[128.88333,54.78333000000001],"type":"Point"}
}