{
  "type": "Feature",
  "properties": {
    "gn:admin1_code":"77.0",
    "gn:asciiname":"Barutino",
    "gn:country_code":"RU",
    "gn:dem":206,
    "gn:feature_class":"P",
    "gn:feature_code":"PPL",
    "gn:name":"Barutino",
    "gn:population":0,
    "gn:timezone":"Europe/Moscow",
    "iso:country":"RU",
    "name:nor_x_preferred":[
        "Barutino"
    ],
    "name:rus_x_preferred":[
        "\u0411\u0430\u0440\u0443\u0442\u0438\u043d\u043e"
    ],
    "name:und_x_variant":[
        "Barutina",
        "Barutino"
    ],
    "wof:name":"Barutino",
    "wof:placetype":"locality"
},
  "geometry": {"coordinates":[32.72456,57.24934],"type":"Point"}
}