{
  "type": "Feature",
  "properties": {
    "gn:admin1_code":"93",
    "gn:asciiname":"Kamenka",
    "gn:country_code":"RU",
    "gn:dem":591,
    "gn:feature_class":"P",
    "gn:feature_code":"PPL",
    "gn:name":"Kamenka",
    "gn:population":0,
    "gn:timezone":"Asia/Chita",
    "iso:country":"RU",
    "name:rus_x_preferred":[
        "\u041a\u0430\u043c\u0435\u043d\u043a\u0430"
    ],
    "name:und_x_variant":[
        "\u041a\u0430\u043c\u0435\u043d\u043a\u0430"
    ],
    "wof:name":"Kamenka",
    "wof:placetype":"locality"
},
  "geometry": {"coordinates":[116.66667,51.58333],"type":"Point"}
}