{
  "type": "Feature",
  "properties": {
    "gn:admin1_code":"33.0",
    "gn:asciiname":"Shmaki",
    "gn:country_code":"RU",
    "gn:dem":136,
    "gn:feature_class":"P",
    "gn:feature_code":"PPL",
    "gn:name":"Shmaki",
    "gn:population":0,
    "gn:timezone":"Europe/Kirov",
    "iso:country":"RU",
    "name:rus_x_preferred":[
        "\u0428\u043c\u0430\u043a\u0438"
    ],
    "wof:name":"Shmaki",
    "wof:placetype":"locality"
},
  "geometry": {"coordinates":[48.44611,58.34417],"type":"Point"}
}