{
  "type": "Feature",
  "properties": {
    "gn:admin1_code":"52",
    "gn:asciiname":"Ruch'i",
    "gn:country_code":"RU",
    "gn:dem":200,
    "gn:feature_class":"P",
    "gn:feature_code":"PPL",
    "gn:name":"Ruch\u2019i",
    "gn:population":0,
    "gn:timezone":"Europe/Moscow",
    "iso:country":"RU",
    "name:rus_x_preferred":[
        "\u0420\u0443\u0447\u044c\u0438"
    ],
    "name:und_x_variant":[
        "Ruch\u2019i"
    ],
    "wof:name":"Ruch'i",
    "wof:placetype":"locality"
},
  "geometry": {"coordinates":[32.8316,57.8496],"type":"Point"}
}