{
  "type": "Feature",
  "properties": {
    "gn:admin1_code":"60",
    "gn:asciiname":"Veret'ye",
    "gn:country_code":"RU",
    "gn:dem":103,
    "gn:feature_class":"P",
    "gn:feature_code":"PPL",
    "gn:name":"Veret\u2019y\u00eb",
    "gn:population":0,
    "gn:timezone":"Europe/Moscow",
    "iso:country":"RU",
    "wof:name":"Veret'ye",
    "wof:placetype":"locality"
},
  "geometry": {"coordinates":[30.36667000000001,57.03333000000001],"type":"Point"}
}