{
  "type": "Feature",
  "properties": {
    "gn:admin1_code":"77",
    "gn:asciiname":"Derzhanskaya",
    "gn:country_code":"RU",
    "gn:dem":110,
    "gn:feature_class":"P",
    "gn:feature_code":"PPL",
    "gn:name":"Derzhanskaya",
    "gn:population":0,
    "gn:timezone":"Europe/Moscow",
    "iso:country":"RU",
    "name:rus_x_preferred":[
        "\u0414\u0435\u0440\u0436\u0430\u043d\u0441\u043a\u0430\u044f"
    ],
    "wof:name":"Derzhanskaya",
    "wof:placetype":"locality"
},
  "geometry": {"coordinates":[31.21778,56.90333],"type":"Point"}
}