{
  "type": "Feature",
  "properties": {
    "gn:admin1_code":"37",
    "gn:asciiname":"Staraya Doroga",
    "gn:country_code":"RU",
    "gn:dem":145,
    "gn:feature_class":"P",
    "gn:feature_code":"PPL",
    "gn:name":"Staraya Doroga",
    "gn:population":0,
    "gn:timezone":"Europe/Moscow",
    "iso:country":"RU",
    "name:rus_x_preferred":[
        "\u0421\u0442\u0430\u0440\u0430\u044f \u0414\u043e\u0440\u043e\u0433\u0430"
    ],
    "name:und_x_variant":[
        "\u0421\u0442\u0430\u0440\u0430\u044f \u0414\u043e\u0440\u043e\u0433\u0430"
    ],
    "wof:name":"Staraya Doroga",
    "wof:placetype":"locality"
},
  "geometry": {"coordinates":[45.9635,58.9472],"type":"Point"}
}