{
  "type": "Feature",
  "properties": {
    "gn:admin1_code":"71",
    "gn:asciiname":"Semenova",
    "gn:country_code":"RU",
    "gn:dem":89,
    "gn:feature_class":"P",
    "gn:feature_code":"PPL",
    "gn:name":"Sem\u00ebnova",
    "gn:population":0,
    "gn:timezone":"Asia/Yekaterinburg",
    "iso:country":"RU",
    "name:eng_x_preferred":[
        "Sem\u00ebnova"
    ],
    "name:nor_x_preferred":[
        "Semenova"
    ],
    "name:rus_x_preferred":[
        "\u0421\u0435\u043c\u0435\u043d\u043e\u0432\u0430"
    ],
    "name:rus_x_variant":[
        "\u0421\u0435\u043c\u0451\u043d\u043e\u0432\u0430"
    ],
    "name:und_x_variant":[
        "Titovo-Sem\u00ebnovo",
        "Semenovo"
    ],
    "wof:name":"Semenova",
    "wof:placetype":"locality"
},
  "geometry": {"coordinates":[61.05736,59.37277],"type":"Point"}
}