{
  "type": "Feature",
  "properties": {
    "gn:admin1_code":"55",
    "gn:asciiname":"Goluboy Fakel",
    "gn:country_code":"RU",
    "gn:dem":257,
    "gn:feature_class":"P",
    "gn:feature_code":"PPL",
    "gn:name":"Goluboy Fakel",
    "gn:population":0,
    "gn:timezone":"Asia/Yekaterinburg",
    "iso:country":"RU",
    "name:rus_x_preferred":[
        "\u0413\u043e\u043b\u0443\u0431\u043e\u0439 \u0424\u0430\u043a\u0435\u043b"
    ],
    "wof:name":"Goluboy Fakel",
    "wof:placetype":"locality"
},
  "geometry": {"coordinates":[59.33639,50.87944],"type":"Point"}
}