{
  "type": "Feature",
  "properties": {
    "gn:admin1_code":"73",
    "gn:asciiname":"Tyuryush",
    "gn:country_code":"RU",
    "gn:dem":180,
    "gn:feature_class":"P",
    "gn:feature_code":"PPL",
    "gn:name":"Tyuryush",
    "gn:population":0,
    "gn:timezone":"Europe/Moscow",
    "iso:country":"RU",
    "name:rus_x_preferred":[
        "\u0422\u044e\u0440\u044e\u0448"
    ],
    "wof:name":"Tyuryush",
    "wof:placetype":"locality"
},
  "geometry": {"coordinates":[53.4995,55.3313],"type":"Point"}
}