{
  "type": "Feature",
  "properties": {
    "gn:admin1_code":"67",
    "gn:asciiname":"Kalininskoye",
    "gn:country_code":"RU",
    "gn:dem":74,
    "gn:feature_class":"P",
    "gn:feature_code":"PPL",
    "gn:name":"Kalininskoye",
    "gn:population":0,
    "gn:timezone":"Europe/Saratov",
    "iso:country":"RU",
    "name:eng_x_preferred":[
        "Kalininskoye"
    ],
    "name:nor_x_preferred":[
        "Kalininskoje"
    ],
    "name:rus_x_preferred":[
        "\u041a\u0430\u043b\u0438\u043d\u0438\u043d\u0441\u043a\u043e\u0435"
    ],
    "name:und_x_variant":[
        "Millersfel\u2019d",
        "Kalininskoye"
    ],
    "wof:name":"Kalininskoye",
    "wof:placetype":"locality"
},
  "geometry": {"coordinates":[47.09227,51.51442],"type":"Point"}
}