{
  "type": "Feature",
  "properties": {
    "gn:admin1_code":"12.0",
    "gn:asciiname":"Gugatoy",
    "gn:country_code":"RU",
    "gn:dem":1248,
    "gn:feature_class":"P",
    "gn:feature_code":"PPL",
    "gn:name":"Gugatoy",
    "gn:population":0,
    "gn:timezone":"Europe/Moscow",
    "iso:country":"RU",
    "name:rus_x_preferred":[
        "\u0413\u0443\u0433\u0430\u0442\u043e\u0439"
    ],
    "wof:name":"Gugatoy",
    "wof:placetype":"locality"
},
  "geometry": {"coordinates":[45.61972,42.68917],"type":"Point"}
}