{
  "type": "Feature",
  "properties": {
    "gn:admin1_code":"12.0",
    "gn:asciiname":"Bashen-Kale",
    "gn:country_code":"RU",
    "gn:dem":710,
    "gn:feature_class":"P",
    "gn:feature_code":"PPL",
    "gn:name":"Bashen-Kale",
    "gn:population":0,
    "gn:timezone":"Europe/Moscow",
    "iso:country":"RU",
    "name:che_x_preferred":[
        "Ba\u015fan-Qelli"
    ],
    "name:che_x_variant":[
        "Ba\u015fen-Kale",
        "Ba\u015fen-Kali",
        "\u0411\u0430\u0448\u0430\u043d-\u041a\u0445\u0435\u043b\u043b\u0438",
        "\u0411\u0430\u0448\u0435\u043d-\u041a\u0430\u043b\u0438"
    ],
    "name:nor_x_preferred":[
        "Basjen-Kale"
    ],
    "name:rus_x_preferred":[
        "\u0411\u0430\u0448\u0435\u043d-\u041a\u0430\u043b\u0435"
    ],
    "name:und_x_variant":[
        "Bashankaloy",
        "Bashinkale",
        "Bashen-Kale"
    ],
    "wof:name":"Bashen-Kale",
    "wof:placetype":"locality"
},
  "geometry": {"coordinates":[45.62088,42.80424],"type":"Point"}
}