{
  "type": "Feature",
  "properties": {
    "gn:admin1_code":"69",
    "gn:asciiname":"Gorodnya",
    "gn:country_code":"RU",
    "gn:dem":191,
    "gn:feature_class":"P",
    "gn:feature_code":"PPL",
    "gn:name":"Gorodnya",
    "gn:population":0,
    "gn:timezone":"Europe/Moscow",
    "iso:country":"RU",
    "name:bel_x_preferred":[
        "\u0413\u0430\u0440\u043e\u0434\u043d\u044f"
    ],
    "name:hye_x_preferred":[
        "\u0533\u0578\u0580\u0578\u0564\u0576\u0575\u0561"
    ],
    "name:rus_x_preferred":[
        "\u0413\u043e\u0440\u043e\u0434\u043d\u044f"
    ],
    "name:ukr_x_preferred":[
        "\u0413\u043e\u0440\u043e\u0434\u043d\u044f"
    ],
    "name:und_x_variant":[
        "Beleninova",
        "Gorodnya",
        "\u0413\u043e\u0440\u043e\u0434\u043d\u044f"
    ],
    "wof:name":"Gorodnya",
    "wof:placetype":"locality"
},
  "geometry": {"coordinates":[34.41376,55.91346],"type":"Point"}
}