{
  "type": "Feature",
  "properties": {
    "gn:admin1_code":"86",
    "gn:asciiname":"Gusevka Vtoraya",
    "gn:country_code":"RU",
    "gn:dem":136,
    "gn:feature_class":"P",
    "gn:feature_code":"PPL",
    "gn:name":"Gusevka Vtoraya",
    "gn:population":0,
    "gn:timezone":"Europe/Moscow",
    "iso:country":"RU",
    "name:rus_x_preferred":[
        "\u0413\u0443\u0441\u0435\u0432\u043a\u0430 \u0412\u0442\u043e\u0440\u0430\u044f"
    ],
    "wof:name":"Gusevka Vtoraya",
    "wof:placetype":"locality"
},
  "geometry": {"coordinates":[40.8478,51.3513],"type":"Point"}
}