{
  "type": "Feature",
  "properties": {
    "gn:admin1_code":"72",
    "gn:asciiname":"Maloye Pechayevo",
    "gn:cc2":"RU",
    "gn:country_code":"RU",
    "gn:dem":111,
    "gn:feature_class":"P",
    "gn:feature_code":"PPL",
    "gn:name":"Maloye Pechayevo",
    "gn:population":0,
    "gn:timezone":"Europe/Moscow",
    "iso:country":"RU",
    "name:rus_x_preferred":[
        "\u041c\u0430\u043b\u043e\u0435 \u041f\u0435\u0447\u0430\u0435\u0432\u043e"
    ],
    "name:und_x_variant":[
        "Maloye Pichayevo",
        "Maloye Pechayevo",
        "\u041c\u0430\u043b\u043e\u0435 \u041f\u0435\u0447\u0430\u0435\u0432\u043e"
    ],
    "wof:name":"Maloye Pechayevo",
    "wof:placetype":"locality"
},
  "geometry": {"coordinates":[41.78333,53.53333000000001],"type":"Point"}
}