{
  "type": "Feature",
  "properties": {
    "gn:admin1_code":"40",
    "gn:asciiname":"Dubrova",
    "gn:country_code":"RU",
    "gn:dem":150,
    "gn:feature_class":"P",
    "gn:feature_code":"PPL",
    "gn:name":"Dubrova",
    "gn:population":0,
    "gn:timezone":"Asia/Yekaterinburg",
    "iso:country":"RU",
    "name:eng_x_preferred":[
        "Dubrova"
    ],
    "name:nor_x_preferred":[
        "Dubrova"
    ],
    "name:rus_x_preferred":[
        "\u0414\u0443\u0431\u0440\u043e\u0432\u0430"
    ],
    "wof:name":"Dubrova",
    "wof:placetype":"locality"
},
  "geometry": {"coordinates":[63.219,56.381],"type":"Point"}
}