{
  "type": "Feature",
  "properties": {
    "gn:admin1_code":"41",
    "gn:asciiname":"Novoivanovka",
    "gn:country_code":"RU",
    "gn:dem":153,
    "gn:feature_class":"P",
    "gn:feature_code":"PPL",
    "gn:name":"Novoivanovka",
    "gn:population":0,
    "gn:timezone":"Europe/Moscow",
    "iso:country":"RU",
    "name:rus_x_preferred":[
        "\u041d\u043e\u0432\u043e\u0438\u0432\u0430\u043d\u043e\u0432\u043a\u0430"
    ],
    "name:und_x_variant":[
        "Novaya Ivanovka",
        "Novoivanovka",
        "\u041d\u043e\u0432\u043e\u0438\u0432\u0430\u043d\u043e\u0432\u043a\u0430"
    ],
    "wof:name":"Novoivanovka",
    "wof:placetype":"locality"
},
  "geometry": {"coordinates":[34.79248,51.26572],"type":"Point"}
}