{
  "type": "Feature",
  "properties": {
    "gn:admin1_code":"47.0",
    "gn:asciiname":"Bogatishchevo-Yepishino",
    "gn:country_code":"RU",
    "gn:dem":183,
    "gn:feature_class":"P",
    "gn:feature_code":"PPL",
    "gn:name":"Bogatishchevo-Yepishino",
    "gn:population":0,
    "gn:timezone":"Europe/Moscow",
    "iso:country":"RU",
    "name:rus_x_preferred":[
        "\u0411\u043e\u0433\u0430\u0442\u0438\u0449\u0435\u0432\u043e-\u0415\u043f\u0438\u0448\u0438\u043d\u043e"
    ],
    "name:und_x_variant":[
        "Yepishino",
        "Bogatishchevo",
        "Bogatishchevo-Yepishino",
        "\u0411\u043e\u0433\u0430\u0442\u0438\u0449\u0435\u0432\u043e-\u0415\u043f\u0438\u0448\u0438\u043d\u043e"
    ],
    "wof:name":"Bogatishchevo-Yepishino",
    "wof:placetype":"locality"
},
  "geometry": {"coordinates":[38.42143,54.78815],"type":"Point"}
}