{
  "type": "Feature",
  "properties": {
    "gn:admin1_code":"41",
    "gn:asciiname":"Kharin",
    "gn:cc2":"RU",
    "gn:country_code":"RU",
    "gn:dem":182,
    "gn:feature_class":"P",
    "gn:feature_code":"PPL",
    "gn:name":"Kharin",
    "gn:population":0,
    "gn:timezone":"Europe/Moscow",
    "iso:country":"RU",
    "name:rus_x_preferred":[
        "\u0425\u0430\u0440\u0438\u043d"
    ],
    "name:und_x_variant":[
        "Khapin\u2019",
        "Khalina",
        "Kharin"
    ],
    "wof:name":"Kharin",
    "wof:placetype":"locality"
},
  "geometry": {"coordinates":[36.34917,51.74417],"type":"Point"}
}