{
  "type": "Feature",
  "properties": {
    "gn:admin1_code":"86",
    "gn:asciiname":"Khrenishche",
    "gn:country_code":"RU",
    "gn:dem":85,
    "gn:feature_class":"P",
    "gn:feature_code":"PPL",
    "gn:name":"Khrenishche",
    "gn:population":0,
    "gn:timezone":"Europe/Moscow",
    "iso:country":"RU",
    "name:rus_x_preferred":[
        "\u0425\u0440\u0435\u043d\u0438\u0449\u0435"
    ],
    "name:und_x_variant":[
        "Pos\u00eblok Khrenishche",
        "Khrenishche"
    ],
    "wof:name":"Khrenishche",
    "wof:placetype":"locality"
},
  "geometry": {"coordinates":[39.78359,51.09796],"type":"Point"}
}