{
  "type": "Feature",
  "properties": {
    "gn:admin1_code":"86",
    "gn:asciiname":"Khvoshchevatka",
    "gn:country_code":"RU",
    "gn:dem":210,
    "gn:feature_class":"P",
    "gn:feature_code":"PPL",
    "gn:name":"Khvoshchevatka",
    "gn:population":0,
    "gn:timezone":"Europe/Moscow",
    "iso:country":"RU",
    "name:eng_x_preferred":[
        "Khvoshchevatka"
    ],
    "name:nor_x_preferred":[
        "Khvosjtsjevatka"
    ],
    "name:rus_x_preferred":[
        "\u0425\u0432\u043e\u0449\u0435\u0432\u0430\u0442\u043a\u0430"
    ],
    "name:und_x_variant":[
        "\u0425\u0432\u043e\u0449\u0435\u0432\u0430\u0442\u043a\u0430",
        "Khvoshchevatka"
    ],
    "wof:name":"Khvoshchevatka",
    "wof:placetype":"locality"
},
  "geometry": {"coordinates":[39.72167,50.64333],"type":"Point"}
}