{
  "type": "Feature",
  "properties": {
    "gn:admin1_code":"47",
    "gn:asciiname":"Starokurovo",
    "gn:country_code":"RU",
    "gn:dem":171,
    "gn:feature_class":"P",
    "gn:feature_code":"PPL",
    "gn:name":"Starokurovo",
    "gn:population":0,
    "gn:timezone":"Europe/Moscow",
    "iso:country":"RU",
    "name:rus_x_preferred":[
        "\u0421\u0442\u0430\u0440\u043e\u043a\u0443\u0440\u043e\u0432\u043e"
    ],
    "wof:name":"Starokurovo",
    "wof:placetype":"locality"
},
  "geometry": {"coordinates":[37.94249,55.0912],"type":"Point"}
}