{
  "type": "Feature",
  "properties": {
    "gn:admin1_code":"28",
    "gn:asciiname":"Velikodvorskaya",
    "gn:cc2":"RU",
    "gn:country_code":"RU",
    "gn:dem":63,
    "gn:feature_class":"P",
    "gn:feature_code":"PPL",
    "gn:name":"Velikodvorskaya",
    "gn:population":0,
    "gn:timezone":"Europe/Moscow",
    "iso:country":"RU",
    "name:und_x_variant":[
        "Velikiy Dvor",
        "Velikodvorskaya"
    ],
    "wof:name":"Velikodvorskaya",
    "wof:placetype":"locality"
},
  "geometry": {"coordinates":[36.43333,61.56667],"type":"Point"}
}