{
  "type": "Feature",
  "properties": {
    "gn:admin1_code":"42.0",
    "gn:asciiname":"Mazalovo",
    "gn:country_code":"RU",
    "gn:dem":19,
    "gn:feature_class":"P",
    "gn:feature_code":"PPL",
    "gn:name":"Mazalovo",
    "gn:population":0,
    "gn:timezone":"Europe/Moscow",
    "iso:country":"RU",
    "name:fin_x_preferred":[
        "Putronm\u00e4ki"
    ],
    "name:rus_x_preferred":[
        "\u041c\u0430\u0437\u0430\u043b\u043e\u0432\u043e"
    ],
    "wof:name":"Mazalovo",
    "wof:placetype":"locality"
},
  "geometry": {"coordinates":[30.62937,59.71019],"type":"Point"}
}