{
  "type": "Feature",
  "properties": {
    "gn:admin1_code":"49.0",
    "gn:asciiname":"Tyuva-Guba",
    "gn:country_code":"RU",
    "gn:dem":30,
    "gn:feature_class":"P",
    "gn:feature_code":"PPL",
    "gn:name":"Tyuva-Guba",
    "gn:population":0,
    "gn:timezone":"Europe/Moscow",
    "iso:country":"RU",
    "name:eng_x_preferred":[
        "Tyuva-Guba"
    ],
    "name:nor_x_preferred":[
        "Tjuva-Guba"
    ],
    "name:rus_x_preferred":[
        "\u0422\u044e\u0432\u0430-\u0413\u0443\u0431\u0430"
    ],
    "wof:name":"Tyuva-Guba",
    "wof:placetype":"locality"
},
  "geometry": {"coordinates":[33.63072,69.187],"type":"Point"}
}