{
  "type": "Feature",
  "properties": {
    "gn:admin1_code":"53",
    "gn:asciiname":"Verkhnyaya Icha",
    "gn:cc2":"RU",
    "gn:country_code":"RU",
    "gn:dem":111,
    "gn:feature_class":"P",
    "gn:feature_code":"PPL",
    "gn:name":"Verkhnyaya Icha",
    "gn:population":0,
    "gn:timezone":"Asia/Novosibirsk",
    "iso:country":"RU",
    "name:und_x_variant":[
        "Verkhne-Ichinskoye",
        "Verkhnyaya Icha"
    ],
    "wof:name":"Verkhnyaya Icha",
    "wof:placetype":"locality"
},
  "geometry": {"coordinates":[78.01666999999998,55.71666999999999],"type":"Point"}
}