{
  "type": "Feature",
  "properties": {
    "gn:admin1_code":"34",
    "gn:asciiname":"Podcher'ye",
    "gn:country_code":"RU",
    "gn:dem":74,
    "gn:feature_class":"P",
    "gn:feature_code":"PPL",
    "gn:name":"Podcher\u2019ye",
    "gn:population":0,
    "gn:timezone":"Europe/Moscow",
    "iso:country":"RU",
    "name:eng_x_preferred":[
        "Podcher'ye"
    ],
    "name:nor_x_preferred":[
        "Podtsjerje"
    ],
    "name:rus_x_preferred":[
        "\u041f\u043e\u0434\u0447\u0435\u0440\u044c\u0435"
    ],
    "name:und_x_variant":[
        "Podcherem",
        "Podcher\u2019",
        "\u041f\u043e\u0434\u0447\u0435\u0440\u044c\u0435",
        "Podcher\u2019ye"
    ],
    "wof:name":"Podcher'ye",
    "wof:placetype":"locality"
},
  "geometry": {"coordinates":[57.55631999999999,63.94406],"type":"Point"}
}