{
  "type": "Feature",
  "properties": {
    "gn:admin1_code":"45.0",
    "gn:asciiname":"Verkhniy Rogezh",
    "gn:country_code":"RU",
    "gn:dem":169,
    "gn:feature_class":"P",
    "gn:feature_code":"PPL",
    "gn:name":"Verkhniy Rogezh",
    "gn:population":0,
    "gn:timezone":"Europe/Moscow",
    "iso:country":"RU",
    "name:rus_x_preferred":[
        "\u0412\u0435\u0440\u0445\u043d\u0438\u0439 \u0420\u043e\u0433\u0435\u0436"
    ],
    "name:und_x_variant":[
        "Verkhniy Regezh",
        "Verkhniy Rogezh"
    ],
    "wof:name":"Verkhniy Rogezh",
    "wof:placetype":"locality"
},
  "geometry": {"coordinates":[49.15222,56.87389],"type":"Point"}
}