{
  "type": "Feature",
  "properties": {
    "gn:admin1_code":"73",
    "gn:asciiname":"Karas'ye Ozero",
    "gn:country_code":"RU",
    "gn:dem":135,
    "gn:feature_class":"P",
    "gn:feature_code":"PPL",
    "gn:name":"Karas\u2019ye Ozero",
    "gn:population":0,
    "gn:timezone":"Europe/Moscow",
    "iso:country":"RU",
    "name:rus_x_preferred":[
        "\u041a\u0430\u0440\u0430\u0441\u044c\u0435 \u041e\u0437\u0435\u0440\u043e"
    ],
    "name:und_x_variant":[
        "Karas\u2019ye Ozero",
        "\u041a\u0430\u0440\u0430\u0441\u044c\u0435 \u041e\u0437\u0435\u0440\u043e"
    ],
    "wof:name":"Karas'ye Ozero",
    "wof:placetype":"locality"
},
  "geometry": {"coordinates":[50.74089,55.04212],"type":"Point"}
}