{
  "type": "Feature",
  "properties": {
    "gn:admin1_code":"12.0",
    "gn:asciiname":"Khvarshini",
    "gn:country_code":"RU",
    "gn:dem":706,
    "gn:feature_class":"P",
    "gn:feature_code":"PPL",
    "gn:name":"Khvarshini",
    "gn:population":0,
    "gn:timezone":"Europe/Moscow",
    "iso:country":"RU",
    "name:rus_x_preferred":[
        "\u0425\u0432\u0430\u0440\u0448\u0438\u043d\u0438"
    ],
    "wof:name":"Khvarshini",
    "wof:placetype":"locality"
},
  "geometry": {"coordinates":[45.85278,42.95417],"type":"Point"}
}