{
  "type": "Feature",
  "properties": {
    "gn:admin1_code":"28",
    "gn:asciiname":"Kapustavara",
    "gn:country_code":"RU",
    "gn:dem":208,
    "gn:feature_class":"P",
    "gn:feature_code":"PPL",
    "gn:name":"Kapustavara",
    "gn:population":0,
    "gn:timezone":"Europe/Moscow",
    "iso:country":"RU",
    "name:rus_x_preferred":[
        "\u041a\u0430\u043f\u0443\u0441\u0442\u0430\u0432\u0430\u0440\u0430"
    ],
    "name:und_x_variant":[
        "Kapustabara",
        "Kapustavara"
    ],
    "wof:name":"Kapustavara",
    "wof:placetype":"locality"
},
  "geometry": {"coordinates":[30.94545,63.66699000000001],"type":"Point"}
}