{
  "type": "Feature",
  "properties": {
    "gn:admin1_code":"55",
    "gn:asciiname":"Maloye Kuroyedovo",
    "gn:country_code":"RU",
    "gn:dem":203,
    "gn:feature_class":"P",
    "gn:feature_code":"PPL",
    "gn:name":"Maloye Kuroyedovo",
    "gn:population":0,
    "gn:timezone":"Asia/Yekaterinburg",
    "iso:country":"RU",
    "name:eng_x_preferred":[
        "Maloye Kuroyedovo"
    ],
    "name:nor_x_preferred":[
        "Maloje Kurojedovo"
    ],
    "name:rus_x_preferred":[
        "\u041c\u0430\u043b\u043e\u0435 \u041a\u0443\u0440\u043e\u0435\u0434\u043e\u0432\u043e"
    ],
    "wof:name":"Maloye Kuroyedovo",
    "wof:placetype":"locality"
},
  "geometry": {"coordinates":[52.4414,53.487],"type":"Point"}
}