{
  "type": "Feature",
  "properties": {
    "gn:admin1_code":"32",
    "gn:asciiname":"Letta-Yaun-Pugol",
    "gn:cc2":"RU",
    "gn:country_code":"RU",
    "gn:dem":79,
    "gn:feature_class":"P",
    "gn:feature_code":"PPL",
    "gn:name":"Letta-Yaun-Pugol",
    "gn:population":0,
    "gn:timezone":"Asia/Yekaterinburg",
    "iso:country":"RU",
    "name:rus_x_preferred":[
        "\u041b\u0435\u0442\u0442\u0430-\u042f\u0443\u043d-\u041f\u0443\u0433\u043e\u043b"
    ],
    "name:und_x_variant":[
        "Letty-Yaun-Pugol",
        "Letta-Yaun-Pugol"
    ],
    "wof:name":"Letta-Yaun-Pugol",
    "wof:placetype":"locality"
},
  "geometry": {"coordinates":[74.23333000000002,62.45],"type":"Point"}
}