{
  "type": "Feature",
  "properties": {
    "gn:admin1_code":"29",
    "gn:asciiname":"Istochnyy",
    "gn:country_code":"RU",
    "gn:dem":188,
    "gn:feature_class":"P",
    "gn:feature_code":"PPL",
    "gn:name":"Istochnyy",
    "gn:population":0,
    "gn:timezone":"Asia/Novokuznetsk",
    "iso:country":"RU",
    "name:rus_x_preferred":[
        "\u0418\u0441\u0442\u043e\u0447\u043d\u044b\u0439"
    ],
    "wof:name":"Istochnyy",
    "wof:placetype":"locality"
},
  "geometry": {"coordinates":[85.56059999999999,54.6504],"type":"Point"}
}