{
  "type": "Feature",
  "properties": {
    "gn:admin1_code":"33",
    "gn:asciiname":"Metrostroy",
    "gn:country_code":"RU",
    "gn:dem":178,
    "gn:feature_class":"P",
    "gn:feature_code":"PPL",
    "gn:name":"Metrostroy",
    "gn:population":0,
    "gn:timezone":"Europe/Kirov",
    "iso:country":"RU",
    "name:eng_x_preferred":[
        "Metrostroy"
    ],
    "name:nor_x_preferred":[
        "Metrostroj"
    ],
    "name:rus_x_preferred":[
        "\u041c\u0435\u0442\u0440\u043e\u0441\u0442\u0440\u043e\u0439"
    ],
    "name:und_x_variant":[
        "\u041c\u0435\u0442\u0440\u043e\u0441\u0442\u0440\u043e\u0439",
        "Metrostroy"
    ],
    "wof:name":"Metrostroy",
    "wof:placetype":"locality"
},
  "geometry": {"coordinates":[52.33185,58.86322],"type":"Point"}
}