{
  "type": "Feature",
  "properties": {
    "gn:admin1_code":"89.0",
    "gn:asciiname":"Vtoroy Raspadok",
    "gn:country_code":"RU",
    "gn:dem":270,
    "gn:feature_class":"P",
    "gn:feature_code":"PPL",
    "gn:name":"Vtoroy Raspadok",
    "gn:population":0,
    "gn:timezone":"Asia/Vladivostok",
    "iso:country":"RU",
    "name:rus_x_preferred":[
        "\u0412\u0442\u043e\u0440\u043e\u0439 \u0420\u0430\u0441\u043f\u0430\u0434\u043e\u043a"
    ],
    "wof:name":"Vtoroy Raspadok",
    "wof:placetype":"locality"
},
  "geometry": {"coordinates":[131.03881000000001,49.00952],"type":"Point"}
}