{
  "type": "Feature",
  "properties": {
    "gn:admin1_code":"43",
    "gn:asciiname":"Parshlnovka",
    "gn:country_code":"RU",
    "gn:dem":121,
    "gn:feature_class":"P",
    "gn:feature_code":"PPL",
    "gn:name":"Parshlnovka",
    "gn:population":0,
    "gn:timezone":"Europe/Moscow",
    "iso:country":"RU",
    "name:eng_x_preferred":[
        "Parshlnovka"
    ],
    "name:nor_x_preferred":[
        "Parsjinovka"
    ],
    "name:rus_x_preferred":[
        "\u041f\u0430\u0440\u0448\u0438\u043d\u043e\u0432\u043a\u0430"
    ],
    "wof:name":"Parshlnovka",
    "wof:placetype":"locality"
},
  "geometry": {"coordinates":[40.52917,52.00333],"type":"Point"}
}