{
  "type": "Feature",
  "properties": {
    "gn:admin1_code":"60.0",
    "gn:asciiname":"Chelanovo",
    "gn:country_code":"RU",
    "gn:dem":97,
    "gn:feature_class":"P",
    "gn:feature_code":"PPL",
    "gn:name":"Chelanovo",
    "gn:population":0,
    "gn:timezone":"Europe/Moscow",
    "iso:country":"RU",
    "name:rus_x_preferred":[
        "\u0427\u0435\u043b\u0430\u043d\u043e\u0432\u043e"
    ],
    "wof:name":"Chelanovo",
    "wof:placetype":"locality"
},
  "geometry": {"coordinates":[28.00868,56.82684],"type":"Point"}
}