{
  "type": "Feature",
  "properties": {
    "gn:admin1_code":"51",
    "gn:asciiname":"Krasnogor",
    "gn:country_code":"RU",
    "gn:dem":133,
    "gn:feature_class":"P",
    "gn:feature_code":"PPL",
    "gn:name":"Krasnogor",
    "gn:population":0,
    "gn:timezone":"Europe/Moscow",
    "iso:country":"RU",
    "name:eng_x_preferred":[
        "Krasnogor"
    ],
    "name:nor_x_preferred":[
        "Krasnogor"
    ],
    "name:rus_x_preferred":[
        "\u041a\u0440\u0430\u0441\u043d\u043e\u0433\u043e\u0440"
    ],
    "wof:name":"Krasnogor",
    "wof:placetype":"locality"
},
  "geometry": {"coordinates":[46.29804,57.75653000000001],"type":"Point"}
}