{
  "type": "Feature",
  "properties": {
    "gn:admin1_code":"10",
    "gn:asciiname":"Markovshchina",
    "gn:country_code":"RU",
    "gn:dem":142,
    "gn:feature_class":"P",
    "gn:feature_code":"PPL",
    "gn:name":"Markovshchina",
    "gn:population":0,
    "gn:timezone":"Europe/Moscow",
    "iso:country":"RU",
    "name:rus_x_preferred":[
        "\u041c\u0430\u0440\u043a\u043e\u0432\u0449\u0438\u043d\u0430"
    ],
    "wof:name":"Markovshchina",
    "wof:placetype":"locality"
},
  "geometry": {"coordinates":[32.0826,52.24784],"type":"Point"}
}