{
  "type": "Feature",
  "properties": {
    "gn:admin1_code":"90",
    "gn:asciiname":"Pikhtari",
    "gn:country_code":"RU",
    "gn:dem":133,
    "gn:feature_class":"P",
    "gn:feature_code":"PPL",
    "gn:name":"Pikhtari",
    "gn:population":0,
    "gn:timezone":"Asia/Yekaterinburg",
    "iso:country":"RU",
    "name:rus_x_preferred":[
        "\u041f\u0438\u0445\u0442\u0430\u0440\u0438"
    ],
    "wof:name":"Pikhtari",
    "wof:placetype":"locality"
},
  "geometry": {"coordinates":[56.6158,57.30095],"type":"Point"}
}