{
  "type": "Feature",
  "properties": {
    "gn:admin1_code":"19",
    "gn:asciiname":"Nizhniy Alkun",
    "gn:country_code":"RU",
    "gn:dem":747,
    "gn:feature_class":"P",
    "gn:feature_code":"PPL",
    "gn:name":"Nizhniy Alkun",
    "gn:population":0,
    "gn:timezone":"Europe/Moscow",
    "iso:country":"RU",
    "name:eng_x_preferred":[
        "Nizhniy Alkun"
    ],
    "name:nor_x_preferred":[
        "Nizjnij Alkun"
    ],
    "name:rus_x_preferred":[
        "\u041d\u0438\u0436\u043d\u0438\u0439 \u0410\u043b\u043a\u0443\u043d"
    ],
    "name:und_x_variant":[
        "Lesogor\u2019ye",
        "Lesogornoye",
        "Nizhniy Alkun"
    ],
    "wof:name":"Nizhniy Alkun",
    "wof:placetype":"locality"
},
  "geometry": {"coordinates":[45.01231,42.98122],"type":"Point"}
}