{
  "type": "Feature",
  "properties": {
    "gn:admin1_code":"1.0",
    "gn:asciiname":"Buryachnyy",
    "gn:country_code":"RU",
    "gn:dem":266,
    "gn:feature_class":"P",
    "gn:feature_code":"PPL",
    "gn:name":"Buryachnyy",
    "gn:population":0,
    "gn:timezone":"Europe/Moscow",
    "iso:country":"RU",
    "name:rus_x_preferred":[
        "\u0411\u0443\u0440\u044f\u0447\u043d\u044b\u0439"
    ],
    "wof:name":"Buryachnyy",
    "wof:placetype":"locality"
},
  "geometry": {"coordinates":[40.23333,44.71667],"type":"Point"}
}