{
  "type": "Feature",
  "properties": {
    "gn:admin1_code":"86",
    "gn:asciiname":"Krasnoyarskiy",
    "gn:cc2":"RU",
    "gn:country_code":"RU",
    "gn:dem":95,
    "gn:feature_class":"P",
    "gn:feature_code":"PPL",
    "gn:name":"Krasnoyarskiy",
    "gn:population":0,
    "gn:timezone":"Europe/Moscow",
    "iso:country":"RU",
    "name:rus_x_preferred":[
        "\u041a\u0440\u0430\u0441\u043d\u043e\u044f\u0440\u0441\u043a\u0438\u0439"
    ],
    "name:und_x_variant":[
        "Krasnyy Yar",
        "Krasnoyarskiy"
    ],
    "wof:name":"Krasnoyarskiy",
    "wof:placetype":"locality"
},
  "geometry": {"coordinates":[40.37528,50.24472],"type":"Point"}
}