{
  "type": "Feature",
  "properties": {
    "gn:admin1_code":"63",
    "gn:asciiname":"N'uuchcha",
    "gn:country_code":"RU",
    "gn:dem":19,
    "gn:feature_class":"P",
    "gn:feature_code":"PPL",
    "gn:name":"N\u2019uuchcha",
    "gn:population":0,
    "gn:timezone":"Asia/Vladivostok",
    "iso:country":"RU",
    "name:rus_x_preferred":[
        "\u041d\u044c\u0443\u0443\u0447\u0447\u0430"
    ],
    "name:und_x_variant":[
        "N\u2019uuchcha",
        "\u041d\u044c\u0443\u0443\u0447\u0447\u0430"
    ],
    "wof:name":"N'uuchcha",
    "wof:placetype":"locality"
},
  "geometry": {"coordinates":[137.19999999999999,70.98333000000002],"type":"Point"}
}