{
  "type": "Feature",
  "properties": {
    "gn:admin1_code":"90.0",
    "gn:asciiname":"Yakimova",
    "gn:country_code":"RU",
    "gn:dem":147,
    "gn:feature_class":"P",
    "gn:feature_code":"PPL",
    "gn:name":"Yakimova",
    "gn:population":0,
    "gn:timezone":"Asia/Yekaterinburg",
    "iso:country":"RU",
    "name:rus_x_preferred":[
        "\u042f\u043a\u0438\u043c\u043e\u0432\u0430"
    ],
    "wof:name":"Yakimova",
    "wof:placetype":"locality"
},
  "geometry": {"coordinates":[55.1282,58.1133],"type":"Point"}
}