{
  "type": "Feature",
  "properties": {
    "gn:admin1_code":"52",
    "gn:asciiname":"Luchki",
    "gn:country_code":"RU",
    "gn:dem":53,
    "gn:feature_class":"P",
    "gn:feature_code":"PPL",
    "gn:name":"Luchki",
    "gn:population":0,
    "gn:timezone":"Europe/Moscow",
    "iso:country":"RU",
    "name:rus_x_preferred":[
        "\u041b\u0443\u0447\u043a\u0438"
    ],
    "name:und_x_variant":[
        "\u041b\u0443\u0447\u043a\u0438"
    ],
    "wof:name":"Luchki",
    "wof:placetype":"locality"
},
  "geometry": {"coordinates":[30.16736,58.40115],"type":"Point"}
}