{
  "type": "Feature",
  "properties": {
    "gn:admin1_code":"53.0",
    "gn:asciiname":"Poros",
    "gn:country_code":"RU",
    "gn:dem":200,
    "gn:feature_class":"P",
    "gn:feature_code":"PPL",
    "gn:name":"Poros",
    "gn:population":0,
    "gn:timezone":"Asia/Novosibirsk",
    "iso:country":"RU",
    "name:rus_x_preferred":[
        "\u041f\u043e\u0440\u043e\u0441"
    ],
    "name:und_x_variant":[
        "\u041f\u043e\u0440\u043e\u0441"
    ],
    "wof:name":"Poros",
    "wof:placetype":"locality"
},
  "geometry": {"coordinates":[83.723,55.3565],"type":"Point"}
}