{
  "type": "Feature",
  "properties": {
    "gn:admin1_code":"53.0",
    "gn:asciiname":"Poros",
    "gn:country_code":"RU",
    "gn:dem":200,
    "gn:feature_class":"P",
    "gn:feature_code":"PPL",
    "gn:name":"Poros",
    "gn:population":0,
    "gn:timezone":"Asia/Novosibirsk",
    "iso:country":"RU",
    "name:ara_x_preferred":[
        "\u0628\u0648\u0631\u0648\u0633"
    ],
    "name:bul_x_preferred":[
        "\u041f\u043e\u0440\u043e\u0441"
    ],
    "name:cat_x_preferred":[
        "Poros"
    ],
    "name:ceb_x_preferred":[
        "P\u00f3ros"
    ],
    "name:dan_x_preferred":[
        "Poros"
    ],
    "name:deu_x_preferred":[
        "Poros"
    ],
    "name:ell_x_preferred":[
        "\u03a0\u03cc\u03c1\u03bf\u03c2"
    ],
    "name:epo_x_preferred":[
        "Poros"
    ],
    "name:est_x_preferred":[
        "P\u00f3rose saar"
    ],
    "name:fas_x_preferred":[
        "\u067e\u0648\u0631\u0648\u0633"
    ],
    "name:fin_x_preferred":[
        "P\u00f3ros"
    ],
    "name:fra_x_preferred":[
        "Poros"
    ],
    "name:glg_x_preferred":[
        "Poros"
    ],
    "name:hrv_x_preferred":[
        "Poros"
    ],
    "name:hun_x_preferred":[
        "P\u00f3rosz"
    ],
    "name:ind_x_preferred":[
        "Poros"
    ],
    "name:ita_x_preferred":[
        "Poros"
    ],
    "name:jpn_x_preferred":[
        "\u30dd\u30ed\u30b9\u5cf6"
    ],
    "name:nld_x_preferred":[
        "Poros"
    ],
    "name:nno_x_preferred":[
        "P\u00f3ros"
    ],
    "name:nor_x_preferred":[
        "Poros"
    ],
    "name:pol_x_preferred":[
        "Poros"
    ],
    "name:por_x_preferred":[
        "Poros"
    ],
    "name:rus_x_preferred":[
        "\u041f\u043e\u0440\u043e\u0441"
    ],
    "name:spa_x_preferred":[
        "Poros"
    ],
    "name:sqi_x_preferred":[
        "Poros"
    ],
    "name:srp_x_preferred":[
        "\u041f\u043e\u0440\u043e\u0441"
    ],
    "name:swe_x_preferred":[
        "Poros"
    ],
    "name:ukr_x_preferred":[
        "\u041f\u043e\u0440\u043e\u0441"
    ],
    "name:und_x_variant":[
        "\u041f\u043e\u0440\u043e\u0441"
    ],
    "name:vie_x_preferred":[
        "Poros"
    ],
    "name:zho_x_preferred":[
        "\u6ce2\u7f85\u65af\u5cf6"
    ],
    "wof:name":"Poros",
    "wof:placetype":"locality"
},
  "geometry": {"coordinates":[83.723,55.3565],"type":"Point"}
}