{
  "type": "Feature",
  "properties": {
    "gn:admin1_code":"54",
    "gn:asciiname":"Novosergeyevka",
    "gn:country_code":"RU",
    "gn:dem":113,
    "gn:feature_class":"P",
    "gn:feature_code":"PPL",
    "gn:name":"Novosergeyevka",
    "gn:population":0,
    "gn:timezone":"Asia/Omsk",
    "iso:country":"RU",
    "name:eng_x_preferred":[
        "Novosergeyevka"
    ],
    "name:nor_x_preferred":[
        "Novosergejevka"
    ],
    "name:rus_x_preferred":[
        "\u041d\u043e\u0432\u043e\u0441\u0435\u0440\u0433\u0435\u0435\u0432\u043a\u0430"
    ],
    "name:und_x_variant":[
        "Novosergiyevskiy",
        "\u041d\u043e\u0432\u043e\u0441\u0435\u0440\u0433\u0435\u0435\u0432\u043a\u0430",
        "Novosergeyevka"
    ],
    "wof:name":"Novosergeyevka",
    "wof:placetype":"locality"
},
  "geometry": {"coordinates":[71.98835,54.45818000000001],"type":"Point"}
}