{
  "type": "Feature",
  "properties": {
    "gn:admin1_code":"42",
    "gn:asciiname":"Varzolovo",
    "gn:country_code":"RU",
    "gn:dem":58,
    "gn:feature_class":"P",
    "gn:feature_code":"PPL",
    "gn:name":"Varzolovo",
    "gn:population":32,
    "gn:timezone":"Europe/Moscow",
    "iso:country":"RU",
    "name:fin_x_preferred":[
        "Varsala"
    ],
    "name:rus_x_preferred":[
        "\u0412\u0430\u0440\u0437\u043e\u043b\u043e\u0432\u043e"
    ],
    "wof:name":"Varzolovo",
    "wof:placetype":"locality",
    "wof:population":32
},
  "geometry": {"coordinates":[30.44492,60.32576],"type":"Point"}
}