{
  "type": "Feature",
  "properties": {
    "gn:admin1_code":"84",
    "gn:asciiname":"Krasnyye Lipki",
    "gn:country_code":"RU",
    "gn:dem":127,
    "gn:feature_class":"P",
    "gn:feature_code":"PPL",
    "gn:name":"Krasnyye Lipki",
    "gn:population":0,
    "gn:timezone":"Europe/Volgograd",
    "iso:country":"RU",
    "name:rus_x_preferred":[
        "\u041a\u0440\u0430\u0441\u043d\u044b\u0435 \u041b\u0438\u043f\u043a\u0438"
    ],
    "name:und_x_variant":[
        "Krasnolipskiy",
        "Krasnyye Lipki",
        "\u041a\u0440\u0430\u0441\u043d\u044b\u0435 \u041b\u0438\u043f\u043a\u0438"
    ],
    "wof:name":"Krasnyye Lipki",
    "wof:placetype":"locality"
},
  "geometry": {"coordinates":[43.7419,49.6397],"type":"Point"}
}