{
  "type": "Feature",
  "properties": {
    "gn:admin1_code":"9.0",
    "gn:asciiname":"Golevka",
    "gn:country_code":"RU",
    "gn:dem":234,
    "gn:feature_class":"P",
    "gn:feature_code":"PPL",
    "gn:name":"Golevka",
    "gn:population":0,
    "gn:timezone":"Europe/Moscow",
    "iso:country":"RU",
    "name:rus_x_preferred":[
        "\u0413\u043e\u043b\u0435\u0432\u043a\u0430"
    ],
    "name:und_x_variant":[
        "\u0413\u043e\u043b\u0435\u0432\u043a\u0430"
    ],
    "wof:name":"Golevka",
    "wof:placetype":"locality"
},
  "geometry": {"coordinates":[37.1732,50.85013],"type":"Point"}
}