{
  "type": "Feature",
  "properties": {
    "gn:admin1_code":"90",
    "gn:asciiname":"Bakharevka",
    "gn:country_code":"RU",
    "gn:dem":150,
    "gn:feature_class":"P",
    "gn:feature_code":"PPL",
    "gn:name":"Bakharevka",
    "gn:population":0,
    "gn:timezone":"Asia/Yekaterinburg",
    "iso:country":"RU",
    "name:nor_x_preferred":[
        "Bakharevka"
    ],
    "name:rus_x_preferred":[
        "\u0411\u0430\u0445\u0430\u0440\u0435\u0432\u043a\u0430"
    ],
    "wof:name":"Bakharevka",
    "wof:placetype":"locality"
},
  "geometry": {"coordinates":[56.246,57.9428],"type":"Point"}
}