{
  "type": "Feature",
  "properties": {
    "gn:admin1_code":"41",
    "gn:asciiname":"Petrovskaya",
    "gn:cc2":"RU",
    "gn:country_code":"RU",
    "gn:dem":170,
    "gn:feature_class":"P",
    "gn:feature_code":"PPL",
    "gn:name":"Petrovskaya",
    "gn:population":0,
    "gn:timezone":"Europe/Moscow",
    "iso:country":"RU",
    "name:rus_x_preferred":[
        "\u041f\u0435\u0442\u0440\u043e\u0432\u0441\u043a\u0430\u044f"
    ],
    "name:und_x_variant":[
        "Petrovskoye",
        "Petrovskaya"
    ],
    "wof:name":"Petrovskaya",
    "wof:placetype":"locality"
},
  "geometry": {"coordinates":[36.56056,51.73667],"type":"Point"}
}