{
  "type": "Feature",
  "properties": {
    "gn:admin1_code":"05",
    "gn:asciiname":"Severnoye",
    "gn:country_code":"RU",
    "gn:dem":101,
    "gn:feature_class":"P",
    "gn:feature_code":"PPL",
    "gn:name":"Severnoye",
    "gn:population":0,
    "gn:timezone":"Asia/Yakutsk",
    "iso:country":"RU",
    "name:eng_x_preferred":[
        "Severnoye"
    ],
    "name:nor_x_preferred":[
        "Severnyj"
    ],
    "name:rus_x_preferred":[
        "\u0421\u0435\u0432\u0435\u0440\u043d\u044b\u0439"
    ],
    "name:rus_x_variant":[
        "\u0421\u0435\u0432\u0435\u0440\u043d\u043e\u0435"
    ],
    "name:und_x_variant":[
        "Severnyy",
        "Severnoye"
    ],
    "wof:name":"Severnoye",
    "wof:placetype":"locality"
},
  "geometry": {"coordinates":[129.55534,49.45012],"type":"Point"}
}