{
  "type": "Feature",
  "properties": {
    "gn:admin1_code":"25",
    "gn:asciiname":"Timashovo",
    "gn:country_code":"RU",
    "gn:dem":122,
    "gn:feature_class":"P",
    "gn:feature_code":"PPL",
    "gn:name":"Timashovo",
    "gn:population":0,
    "gn:timezone":"Europe/Moscow",
    "iso:country":"RU",
    "name:und_x_variant":[
        "Timash\u00ebvo",
        "Timashovo"
    ],
    "wof:name":"Timashovo",
    "wof:placetype":"locality"
},
  "geometry": {"coordinates":[36.86774000000001,54.91141],"type":"Point"}
}