{
  "type": "Feature",
  "properties": {
    "gn:admin1_code":"23",
    "gn:asciiname":"Romanovo",
    "gn:country_code":"RU",
    "gn:dem":46,
    "gn:feature_class":"P",
    "gn:feature_code":"PPL",
    "gn:name":"Romanovo",
    "gn:population":0,
    "gn:timezone":"Europe/Kaliningrad",
    "iso:country":"RU",
    "name:eng_x_preferred":[
        "Romanovo"
    ],
    "name:nor_x_preferred":[
        "Romanovo"
    ],
    "name:rus_x_preferred":[
        "\u0420\u043e\u043c\u0430\u043d\u043e\u0432\u043e"
    ],
    "name:und_x_variant":[
        "Pobethen",
        "Pobeten",
        "\u0420\u043e\u043c\u0430\u043d\u043e\u0432\u043e",
        "Romanovo"
    ],
    "wof:name":"Romanovo",
    "wof:placetype":"locality"
},
  "geometry": {"coordinates":[20.28059,54.8942],"type":"Point"}
}