{
  "type": "Feature",
  "properties": {
    "gn:admin1_code":"46.0",
    "gn:asciiname":"Ryabkinskiy Zavod",
    "gn:country_code":"RU",
    "gn:dem":141,
    "gn:feature_class":"P",
    "gn:feature_code":"PPL",
    "gn:name":"Ryabkinskiy Zavod",
    "gn:population":0,
    "gn:timezone":"Europe/Moscow",
    "iso:country":"RU",
    "wof:name":"Ryabkinskiy Zavod",
    "wof:placetype":"locality"
},
  "geometry": {"coordinates":[43.95237,54.32697],"type":"Point"}
}