{
  "type": "Feature",
  "properties": {
    "gn:admin1_code":"79",
    "gn:asciiname":"Ak-Erik",
    "gn:country_code":"RU",
    "gn:dem":954,
    "gn:feature_class":"P",
    "gn:feature_code":"PPL",
    "gn:name":"Ak-Erik",
    "gn:population":0,
    "gn:timezone":"Asia/Krasnoyarsk",
    "iso:country":"RU",
    "name:eng_x_preferred":[
        "Ak-Erik"
    ],
    "name:nor_x_preferred":[
        "Ak-Erik"
    ],
    "name:rus_x_preferred":[
        "\u0410\u043a-\u042d\u0440\u0438\u043a"
    ],
    "wof:name":"Ak-Erik",
    "wof:placetype":"locality"
},
  "geometry": {"coordinates":[94.61809,50.51376],"type":"Point"}
}