{
  "type": "Feature",
  "properties": {
    "gn:admin1_code":"34",
    "gn:asciiname":"Laya",
    "gn:country_code":"RU",
    "gn:dem":30,
    "gn:feature_class":"P",
    "gn:feature_code":"PPL",
    "gn:name":"Laya",
    "gn:population":0,
    "gn:timezone":"Europe/Moscow",
    "iso:country":"RU",
    "name:rus_x_preferred":[
        "\u041b\u0430\u044f"
    ],
    "name:und_x_variant":[
        "Layskiy",
        "Laya",
        "\u041b\u0430\u044f"
    ],
    "wof:name":"Laya",
    "wof:placetype":"locality"
},
  "geometry": {"coordinates":[55.16483,66.13943],"type":"Point"}
}