{
  "type": "Feature",
  "properties": {
    "gn:admin1_code":"69",
    "gn:asciiname":"Koty",
    "gn:country_code":"RU",
    "gn:dem":187,
    "gn:feature_class":"P",
    "gn:feature_code":"PPL",
    "gn:name":"Koty",
    "gn:population":0,
    "gn:timezone":"Europe/Moscow",
    "iso:country":"RU",
    "name:bel_x_preferred":[
        "\u041a\u0430\u0442\u044b"
    ],
    "name:pol_x_preferred":[
        "Koty"
    ],
    "name:rus_x_preferred":[
        "\u041a\u043e\u0442\u044b"
    ],
    "name:ukr_x_preferred":[
        "\u041a\u043e\u0442\u0438"
    ],
    "wof:name":"Koty",
    "wof:placetype":"locality"
},
  "geometry": {"coordinates":[34.66611,55.91528],"type":"Point"}
}