{
  "type": "Feature",
  "properties": {
    "gn:country":"RU",
    "gn:fcode":"PPL",
    "gn:population":3578,
    "iso:country":"RU",
    "name:eng_x_preferred":[
        "Novoalekseyevskaya"
    ],
    "name:nor_x_preferred":[
        "Novoaleksejevskaja"
    ],
    "name:rus_x_preferred":[
        "\u041d\u043e\u0432\u043e\u0430\u043b\u0435\u043a\u0441\u0435\u0435\u0432\u0441\u043a\u0430\u044f"
    ],
    "qs:name":"Novoalekseyevskaya",
    "qs:photos_9r":0,
    "qs:photos_sr":0,
    "qs:pop_sr":"4",
    "wof:name":"Novoalekseyevskaya",
    "wof:placetype":"locality",
    "wof:population":3578
},
  "geometry": {"coordinates":[40.93389,44.81889],"type":"Point"}
}