{
  "type": "Feature",
  "properties": {
    "gn:admin1_code":"83",
    "gn:asciiname":"Pichugino",
    "gn:country_code":"RU",
    "gn:dem":134,
    "gn:feature_class":"P",
    "gn:feature_code":"PPL",
    "gn:name":"Pichugino",
    "gn:population":0,
    "gn:timezone":"Europe/Moscow",
    "iso:country":"RU",
    "name:eng_x_preferred":[
        "Pichugino"
    ],
    "name:nor_x_preferred":[
        "Pitsjugino"
    ],
    "name:rus_x_preferred":[
        "\u041f\u0438\u0447\u0443\u0433\u0438\u043d\u043e"
    ],
    "name:und_x_variant":[
        "\u041f\u0438\u0447\u0443\u0433\u0438\u043d\u043e",
        "Pichugino"
    ],
    "wof:name":"Pichugino",
    "wof:placetype":"locality"
},
  "geometry": {"coordinates":[41.2472,55.3416],"type":"Point"}
}