{
  "type": "Feature",
  "properties": {
    "gn:admin1_code":"8",
    "gn:asciiname":"Kiseik",
    "gn:country_code":"RU",
    "gn:dem":348,
    "gn:feature_class":"P",
    "gn:feature_code":"PPL",
    "gn:name":"Kiseik",
    "gn:population":0,
    "gn:timezone":"Asia/Yekaterinburg",
    "iso:country":"RU",
    "name:eng_x_preferred":[
        "Kiseik"
    ],
    "name:nor_x_preferred":[
        "Kiseik"
    ],
    "name:rus_x_preferred":[
        "\u041a\u0438\u0441\u0435\u0438\u043a"
    ],
    "wof:name":"Kiseik",
    "wof:placetype":"locality"
},
  "geometry": {"coordinates":[58.8132,55.4858],"type":"Point"}
}