{
  "type": "Feature",
  "properties": {
    "gn:admin1_code":"37",
    "gn:asciiname":"Maytikha",
    "gn:country_code":"RU",
    "gn:dem":156,
    "gn:feature_class":"P",
    "gn:feature_code":"PPL",
    "gn:name":"Maytikha",
    "gn:population":0,
    "gn:timezone":"Europe/Moscow",
    "iso:country":"RU",
    "name:eng_x_preferred":[
        "Maytikha"
    ],
    "name:nor_x_preferred":[
        "Majtikha"
    ],
    "name:rus_x_preferred":[
        "\u041c\u0430\u0439\u0442\u0438\u0445\u0430"
    ],
    "wof:name":"Maytikha",
    "wof:placetype":"locality"
},
  "geometry": {"coordinates":[45.46754,58.06191999999999],"type":"Point"}
}