{
  "type": "Feature",
  "properties": {
    "gn:admin1_code":"90",
    "gn:asciiname":"Sosnovyy Mys",
    "gn:country_code":"RU",
    "gn:dem":164,
    "gn:feature_class":"P",
    "gn:feature_code":"PPL",
    "gn:name":"Sosnovyy Mys",
    "gn:population":0,
    "gn:timezone":"Asia/Yekaterinburg",
    "iso:country":"RU",
    "name:rus_x_preferred":[
        "\u0421\u043e\u0441\u043d\u043e\u0432\u044b\u0439 \u041c\u044b\u0441"
    ],
    "name:und_x_variant":[
        "Sosnovka",
        "Sosnovyy Mys"
    ],
    "wof:name":"Sosnovyy Mys",
    "wof:placetype":"locality"
},
  "geometry": {"coordinates":[54.84757,58.54442],"type":"Point"}
}