{
  "type": "Feature",
  "properties": {
    "gn:admin1_code":"67",
    "gn:asciiname":"Belozerka",
    "gn:country_code":"RU",
    "gn:dem":176,
    "gn:feature_class":"P",
    "gn:feature_code":"PPL",
    "gn:name":"Beloz\u00ebrka",
    "gn:population":0,
    "gn:timezone":"Europe/Saratov",
    "iso:country":"RU",
    "name:rus_x_preferred":[
        "\u0411\u0435\u043b\u043e\u0437\u0451\u0440\u043a\u0430"
    ],
    "name:und_x_variant":[
        "Beloz\u00ebrka",
        "\u0411\u0435\u043b\u043e\u0437\u0451\u0440\u043a\u0430",
        "Belooz\u00ebrka"
    ],
    "wof:name":"Belozerka",
    "wof:placetype":"locality"
},
  "geometry": {"coordinates":[43.5281,51.6066],"type":"Point"}
}