{
  "type": "Feature",
  "properties": {
    "gn:admin1_code":"6",
    "gn:asciiname":"Sura",
    "gn:country_code":"RU",
    "gn:dem":75,
    "gn:feature_class":"P",
    "gn:feature_code":"PPL",
    "gn:name":"Sura",
    "gn:population":0,
    "gn:timezone":"Europe/Moscow",
    "iso:country":"RU",
    "name:ben_x_preferred":[
        "\u09b8\u09c1\u09b0\u09be"
    ],
    "name:eng_x_preferred":[
        "Sura"
    ],
    "name:heb_x_preferred":[
        "\u05e1\u05d5\u05e8\u05d4"
    ],
    "name:hin_x_preferred":[
        "\u0938\u0942\u0930\u093e"
    ],
    "name:ind_x_preferred":[
        "Sura"
    ],
    "name:nor_x_preferred":[
        "Sura"
    ],
    "name:rus_x_preferred":[
        "\u0421\u0443\u0440\u0430"
    ],
    "name:swe_x_preferred":[
        "Sura"
    ],
    "name:und_x_variant":[
        "Surskiy Pogost"
    ],
    "name:urd_x_preferred":[
        "\u0633\u0648\u0631\u0627"
    ],
    "name:vie_x_preferred":[
        "S\u00f4ng Sura"
    ],
    "wof:name":"Sura",
    "wof:placetype":"locality"
},
  "geometry": {"coordinates":[45.6386,63.576],"type":"Point"}
}