{
  "type": "Feature",
  "properties": {
    "gn:admin1_code":"38",
    "gn:asciiname":"Krasnyy Dar",
    "gn:country_code":"RU",
    "gn:dem":6,
    "gn:feature_class":"P",
    "gn:feature_code":"PPL",
    "gn:name":"Krasnyy Dar",
    "gn:population":0,
    "gn:timezone":"Europe/Moscow",
    "iso:country":"RU",
    "name:rus_x_preferred":[
        "\u041a\u0440\u0430\u0441\u043d\u044b\u0439 \u0414\u0430\u0440"
    ],
    "wof:name":"Krasnyy Dar",
    "wof:placetype":"locality"
},
  "geometry": {"coordinates":[38.84641,46.6744],"type":"Point"}
}