{
  "type": "Feature",
  "properties": {
    "gn:admin1_code":"16",
    "gn:asciiname":"Turunovo",
    "gn:country_code":"RU",
    "gn:dem":94,
    "gn:feature_class":"P",
    "gn:feature_code":"PPL",
    "gn:name":"Turunovo",
    "gn:population":0,
    "gn:timezone":"Europe/Moscow",
    "iso:country":"RU",
    "name:rus_x_preferred":[
        "\u0422\u0443\u0440\u0443\u043d\u043e\u0432\u043e"
    ],
    "name:und_x_variant":[
        "Trunovo",
        "Turunovo"
    ],
    "wof:name":"Turunovo",
    "wof:placetype":"locality"
},
  "geometry": {"coordinates":[47.31693,55.52141],"type":"Point"}
}