{
  "type": "Feature",
  "properties": {
    "gn:admin1_code":"73",
    "gn:asciiname":"Mul'ma",
    "gn:country_code":"RU",
    "gn:dem":82,
    "gn:feature_class":"P",
    "gn:feature_code":"PPL",
    "gn:name":"Mul\u2019ma",
    "gn:population":0,
    "gn:timezone":"Europe/Moscow",
    "iso:country":"RU",
    "name:eng_x_preferred":[
        "Mul'ma"
    ],
    "name:nor_x_preferred":[
        "Mulma"
    ],
    "name:rus_x_preferred":[
        "\u041c\u0443\u043b\u044c\u043c\u0430"
    ],
    "name:und_x_variant":[
        "Mul\u2019ma"
    ],
    "wof:name":"Mul'ma",
    "wof:placetype":"locality"
},
  "geometry": {"coordinates":[49.58559,56.0514],"type":"Point"}
}