{
  "type": "Feature",
  "properties": {
    "gn:admin1_code":"41.0",
    "gn:asciiname":"Arsen'yevka",
    "gn:country_code":"RU",
    "gn:dem":171,
    "gn:feature_class":"P",
    "gn:feature_code":"PPL",
    "gn:name":"Arsen\u2019yevka",
    "gn:population":0,
    "gn:timezone":"Europe/Moscow",
    "iso:country":"RU",
    "name:nor_x_preferred":[
        "Arsenjevka"
    ],
    "name:rus_x_preferred":[
        "\u0410\u0440\u0441\u0435\u043d\u044c\u0435\u0432\u043a\u0430"
    ],
    "name:und_x_variant":[
        "Arsenevka",
        "Arsen\u2019yevka"
    ],
    "wof:name":"Arsen'yevka",
    "wof:placetype":"locality"
},
  "geometry": {"coordinates":[35.1922,51.9475],"type":"Point"}
}