{
  "type": "Feature",
  "properties": {
    "gn:admin1_code":"75",
    "gn:asciiname":"Myl'dzhino",
    "gn:country_code":"RU",
    "gn:dem":64,
    "gn:feature_class":"P",
    "gn:feature_code":"PPL",
    "gn:name":"Myl\u2019dzhino",
    "gn:population":0,
    "gn:timezone":"Asia/Tomsk",
    "iso:country":"RU",
    "name:eng_x_preferred":[
        "Myl'dzhino"
    ],
    "name:nor_x_preferred":[
        "Myldzjino"
    ],
    "name:rus_x_preferred":[
        "\u041c\u044b\u043b\u044c\u0434\u0436\u0438\u043d\u043e"
    ],
    "name:und_x_variant":[
        "Mil\u2019dzhiny",
        "Mil\u2019jihy",
        "Myl\u2019dzhino"
    ],
    "wof:name":"Myl'dzhino",
    "wof:placetype":"locality"
},
  "geometry": {"coordinates":[78.4674,58.99599],"type":"Point"}
}