{
  "type": "Feature",
  "properties": {
    "gn:admin1_code":"63",
    "gn:asciiname":"Sorevnovaniye",
    "gn:country_code":"RU",
    "gn:dem":407,
    "gn:feature_class":"P",
    "gn:feature_code":"PPL",
    "gn:name":"Sorevnovaniye",
    "gn:population":0,
    "gn:timezone":"Asia/Vladivostok",
    "iso:country":"RU",
    "name:eng_x_preferred":[
        "Sorevnovaniye"
    ],
    "name:nor_x_preferred":[
        "Sorevnovanije"
    ],
    "name:rus_x_preferred":[
        "\u0421\u043e\u0440\u0435\u0432\u043d\u043e\u0432\u0430\u043d\u0438\u0435"
    ],
    "wof:name":"Sorevnovaniye",
    "wof:placetype":"locality"
},
  "geometry": {"coordinates":[136.65951999999999,66.55189],"type":"Point"}
}