{
  "type": "Feature",
  "properties": {
    "gn:admin1_code":"85",
    "gn:asciiname":"Novo-Tryumovo",
    "gn:country_code":"RU",
    "gn:dem":161,
    "gn:feature_class":"P",
    "gn:feature_code":"PPL",
    "gn:name":"Novo-Tryumovo",
    "gn:population":0,
    "gn:timezone":"Europe/Moscow",
    "iso:country":"RU",
    "name:rus_x_preferred":[
        "\u041d\u043e\u0432\u043e-\u0422\u0440\u044e\u043c\u043e\u0432\u043e"
    ],
    "name:und_x_variant":[
        "\u041d\u043e\u0432\u043e-\u0422\u0440\u044e\u043c\u043e\u0432\u043e"
    ],
    "wof:name":"Novo-Tryumovo",
    "wof:placetype":"locality"
},
  "geometry": {"coordinates":[37.84439,59.47174],"type":"Point"}
}