{
  "type": "Feature",
  "properties": {
    "gn:admin1_code":"78",
    "gn:asciiname":"Noven'kiy",
    "gn:country_code":"RU",
    "gn:dem":67,
    "gn:feature_class":"P",
    "gn:feature_code":"PPL",
    "gn:name":"Noven\u2019kiy",
    "gn:population":0,
    "gn:timezone":"Asia/Yekaterinburg",
    "iso:country":"RU",
    "name:rus_x_preferred":[
        "\u041d\u043e\u0432\u0435\u043d\u044c\u043a\u0438\u0439"
    ],
    "name:und_x_variant":[
        "Novyye",
        "Noven\u2019kiy",
        "\u041d\u043e\u0432\u0435\u043d\u044c\u043a\u0438\u0439"
    ],
    "wof:name":"Noven'kiy",
    "wof:placetype":"locality"
},
  "geometry": {"coordinates":[69.18333,57.21666999999999],"type":"Point"}
}