{
  "type": "Feature",
  "properties": {
    "gn:admin1_code":"62",
    "gn:asciiname":"Korneyevka",
    "gn:country_code":"RU",
    "gn:dem":126,
    "gn:feature_class":"P",
    "gn:feature_code":"PPL",
    "gn:name":"Korneyevka",
    "gn:population":0,
    "gn:timezone":"Europe/Moscow",
    "iso:country":"RU",
    "name:eng_x_preferred":[
        "Korneyevka"
    ],
    "name:nor_x_preferred":[
        "Kornejevka"
    ],
    "name:rus_x_preferred":[
        "\u041a\u043e\u0440\u043d\u0435\u0435\u0432\u043a\u0430"
    ],
    "wof:name":"Korneyevka",
    "wof:placetype":"locality"
},
  "geometry": {"coordinates":[42.2113,54.9232],"type":"Point"}
}