{
  "type": "Feature",
  "properties": {
    "gn:admin1_code":"76",
    "gn:asciiname":"Krasnitskiy",
    "gn:country_code":"RU",
    "gn:dem":210,
    "gn:feature_class":"P",
    "gn:feature_code":"PPL",
    "gn:name":"Krasnitskiy",
    "gn:population":0,
    "gn:timezone":"Europe/Moscow",
    "iso:country":"RU",
    "name:eng_x_preferred":[
        "Krasnitskiy"
    ],
    "name:nor_x_preferred":[
        "Krasnitskij"
    ],
    "name:rus_x_preferred":[
        "\u041a\u0440\u0430\u0441\u043d\u0438\u0446\u043a\u0438\u0439"
    ],
    "name:und_x_variant":[
        "Krasnitsy",
        "\u041a\u0440\u0430\u0441\u043d\u0438\u0446\u043a\u0438\u0439",
        "Krasnitskiy"
    ],
    "wof:name":"Krasnitskiy",
    "wof:placetype":"locality"
},
  "geometry": {"coordinates":[38.30399,53.7957],"type":"Point"}
}