{
  "type": "Feature",
  "properties": {
    "gn:admin1_code":"88",
    "gn:asciiname":"Novoye",
    "gn:country_code":"RU",
    "gn:dem":183,
    "gn:feature_class":"P",
    "gn:feature_code":"PPL",
    "gn:name":"Novoye",
    "gn:population":0,
    "gn:timezone":"Europe/Moscow",
    "iso:country":"RU",
    "name:rus_x_preferred":[
        "\u041d\u043e\u0432\u043e\u0435"
    ],
    "name:und_x_variant":[
        "\u041d\u043e\u0432\u043e\u0435"
    ],
    "wof:name":"Novoye",
    "wof:placetype":"locality"
},
  "geometry": {"coordinates":[38.68333,56.73333],"type":"Point"}
}