{
  "type": "Feature",
  "properties": {
    "gn:admin1_code":"33.0",
    "gn:asciiname":"Yulichi",
    "gn:country_code":"RU",
    "gn:dem":129,
    "gn:feature_class":"P",
    "gn:feature_code":"PPL",
    "gn:name":"Yulichi",
    "gn:population":0,
    "gn:timezone":"Europe/Kirov",
    "iso:country":"RU",
    "name:rus_x_preferred":[
        "\u042e\u043b\u0438\u0447\u0438"
    ],
    "wof:name":"Yulichi",
    "wof:placetype":"locality"
},
  "geometry": {"coordinates":[48.41868,58.55724],"type":"Point"}
}