{
  "type": "Feature",
  "properties": {
    "gn:admin1_code":"52",
    "gn:asciiname":"Kiprovo",
    "gn:country_code":"RU",
    "gn:dem":31,
    "gn:feature_class":"P",
    "gn:feature_code":"PPL",
    "gn:name":"Kiprovo",
    "gn:population":0,
    "gn:timezone":"Europe/Moscow",
    "iso:country":"RU",
    "name:rus_x_preferred":[
        "\u041a\u0438\u043f\u0440\u043e\u0432\u043e"
    ],
    "wof:name":"Kiprovo",
    "wof:placetype":"locality"
},
  "geometry": {"coordinates":[31.68333,58.95],"type":"Point"}
}