{
  "type": "Feature",
  "properties": {
    "gn:admin1_code":"77",
    "gn:asciiname":"Miklyukovo",
    "gn:country_code":"RU",
    "gn:dem":134,
    "gn:feature_class":"P",
    "gn:feature_code":"PPL",
    "gn:name":"Miklyukovo",
    "gn:population":0,
    "gn:timezone":"Europe/Moscow",
    "iso:country":"RU",
    "name:rus_x_preferred":[
        "\u041c\u0438\u043a\u043b\u044e\u043a\u043e\u0432\u043e"
    ],
    "name:und_x_variant":[
        "\u041c\u0438\u043a\u043b\u044e\u043a\u043e\u0432\u043e"
    ],
    "wof:name":"Miklyukovo",
    "wof:placetype":"locality"
},
  "geometry": {"coordinates":[37.8388,57.3846],"type":"Point"}
}