{
  "type": "Feature",
  "properties": {
    "gn:admin1_code":"46",
    "gn:asciiname":"Maziluk",
    "gn:country_code":"RU",
    "gn:dem":149,
    "gn:feature_class":"P",
    "gn:feature_code":"PPL",
    "gn:name":"Maziluk",
    "gn:population":0,
    "gn:timezone":"Europe/Moscow",
    "iso:country":"RU",
    "name:rus_x_preferred":[
        "\u041c\u0430\u0437\u0438\u043b\u0443\u043a"
    ],
    "wof:name":"Maziluk",
    "wof:placetype":"locality"
},
  "geometry": {"coordinates":[43.21667,54.18333000000001],"type":"Point"}
}