{
  "type": "Feature",
  "properties": {
    "gn:admin1_code":"77",
    "gn:asciiname":"Bludki",
    "gn:country_code":"RU",
    "gn:dem":189,
    "gn:feature_class":"P",
    "gn:feature_code":"PPL",
    "gn:name":"Bludki",
    "gn:population":0,
    "gn:timezone":"Europe/Moscow",
    "iso:country":"RU",
    "name:rus_x_preferred":[
        "\u0411\u043b\u0443\u0434\u043a\u0438"
    ],
    "name:und_x_variant":[
        "\u0411\u043b\u0443\u0434\u043a\u0438"
    ],
    "wof:name":"Bludki",
    "wof:placetype":"locality"
},
  "geometry": {"coordinates":[37.1639,57.7664],"type":"Point"}
}