{
  "type": "Feature",
  "properties": {
    "gn:admin1_code":"80",
    "gn:asciiname":"Novyy Multan",
    "gn:country_code":"RU",
    "gn:dem":177,
    "gn:feature_class":"P",
    "gn:feature_code":"PPL",
    "gn:name":"Novyy Multan",
    "gn:population":0,
    "gn:timezone":"Europe/Samara",
    "iso:country":"RU",
    "name:rus_x_preferred":[
        "\u041d\u043e\u0432\u044b\u0439 \u041c\u0443\u043b\u0442\u0430\u043d"
    ],
    "wof:name":"Novyy Multan",
    "wof:placetype":"locality"
},
  "geometry": {"coordinates":[51.73631,56.40867],"type":"Point"}
}