{
  "type": "Feature",
  "properties": {
    "gn:admin1_code":"42",
    "gn:asciiname":"Usadishche",
    "gn:country_code":"RU",
    "gn:dem":45,
    "gn:feature_class":"P",
    "gn:feature_code":"PPL",
    "gn:name":"Usadishche",
    "gn:population":0,
    "gn:timezone":"Europe/Moscow",
    "iso:country":"RU",
    "name:eng_x_preferred":[
        "Usadishche"
    ],
    "name:nor_x_preferred":[
        "Usadisjtsje"
    ],
    "name:rus_x_preferred":[
        "\u0423\u0441\u0430\u0434\u0438\u0449\u0435"
    ],
    "wof:name":"Usadishche",
    "wof:placetype":"locality"
},
  "geometry": {"coordinates":[30.92694,59.43306],"type":"Point"}
}