{
  "type": "Feature",
  "properties": {
    "gn:admin1_code":"42.0",
    "gn:admin2_code":"575409",
    "gn:asciiname":"Boloto",
    "gn:country_code":"RU",
    "gn:dem":72,
    "gn:feature_class":"P",
    "gn:feature_code":"PPL",
    "gn:name":"Boloto",
    "gn:population":0,
    "gn:timezone":"Europe/Moscow",
    "iso:country":"RU",
    "name:rus_x_preferred":[
        "\u0411\u043e\u043b\u043e\u0442\u043e"
    ],
    "wof:name":"Boloto",
    "wof:placetype":"locality"
},
  "geometry": {"coordinates":[33.76326,59.36227],"type":"Point"}
}