{
  "type": "Feature",
  "properties": {
    "gn:admin1_code":"8",
    "gn:asciiname":"Ishteryakovo",
    "gn:country_code":"RU",
    "gn:dem":129,
    "gn:feature_class":"P",
    "gn:feature_code":"PPL",
    "gn:name":"Ishteryakovo",
    "gn:population":0,
    "gn:timezone":"Asia/Yekaterinburg",
    "iso:country":"RU",
    "name:eng_x_preferred":[
        "Ishteryakovo"
    ],
    "name:nor_x_preferred":[
        "Isjterjakovo"
    ],
    "name:rus_x_preferred":[
        "\u0418\u0448\u0442\u0435\u0440\u044f\u043a\u043e\u0432\u043e"
    ],
    "name:und_x_variant":[
        "Ishteryakova",
        "\u0418\u0448\u0442\u0435\u0440\u044f\u043a\u043e\u0432\u043e",
        "Ishteryakovo"
    ],
    "wof:name":"Ishteryakovo",
    "wof:placetype":"locality"
},
  "geometry": {"coordinates":[54.19534,55.37989],"type":"Point"}
}