{
  "type": "Feature",
  "properties": {
    "gn:admin1_code":"28.0",
    "gn:asciiname":"Gizhino",
    "gn:country_code":"RU",
    "gn:dem":66,
    "gn:feature_class":"P",
    "gn:feature_code":"PPL",
    "gn:name":"Gizhino",
    "gn:population":0,
    "gn:timezone":"Europe/Moscow",
    "iso:country":"RU",
    "name:fin_x_preferred":[
        "Hiitiniemi"
    ],
    "name:rus_x_preferred":[
        "\u0413\u0438\u0436\u0438\u043d\u043e"
    ],
    "name:und_x_variant":[
        "Gazhino",
        "Gizhino"
    ],
    "wof:name":"Gizhino",
    "wof:placetype":"locality"
},
  "geometry": {"coordinates":[33.79036,60.99214],"type":"Point"}
}