{
  "type": "Feature",
  "properties": {
    "gn:admin1_code":"88",
    "gn:asciiname":"Vas'ki",
    "gn:country_code":"RU",
    "gn:dem":136,
    "gn:feature_class":"P",
    "gn:feature_code":"PPL",
    "gn:name":"Vas\u2019ki",
    "gn:population":0,
    "gn:timezone":"Europe/Moscow",
    "iso:country":"RU",
    "name:rus_x_preferred":[
        "\u0412\u0430\u0441\u044c\u043a\u0438"
    ],
    "name:und_x_variant":[
        "Vas\u2019ki",
        "Naseki"
    ],
    "wof:name":"Vas'ki",
    "wof:placetype":"locality"
},
  "geometry": {"coordinates":[38.034,58.0215],"type":"Point"}
}