{
  "type": "Feature",
  "properties": {
    "gn:admin1_code":"28",
    "gn:asciiname":"Sariporog",
    "gn:country_code":"RU",
    "gn:dem":44,
    "gn:feature_class":"P",
    "gn:feature_code":"PPL",
    "gn:name":"Sariporog",
    "gn:population":0,
    "gn:timezone":"Europe/Moscow",
    "iso:country":"RU",
    "name:fin_x_preferred":[
        "Saarikoski"
    ],
    "name:rus_x_preferred":[
        "\u0421\u0430\u0440\u0438\u043f\u043e\u0440\u043e\u0433"
    ],
    "name:und_x_variant":[
        "Saari-Porog",
        "Sari-Porogi",
        "Sariporog"
    ],
    "wof:name":"Sariporog",
    "wof:placetype":"locality"
},
  "geometry": {"coordinates":[33.06184,61.08855],"type":"Point"}
}