{
  "type": "Feature",
  "properties": {
    "gn:admin1_code":"77",
    "gn:asciiname":"Novoye-Kotchishche",
    "gn:country_code":"RU",
    "gn:dem":164,
    "gn:feature_class":"P",
    "gn:feature_code":"PPL",
    "gn:name":"Novoye-Kotchishche",
    "gn:population":0,
    "gn:timezone":"Europe/Moscow",
    "iso:country":"RU",
    "name:rus_x_preferred":[
        "\u041d\u043e\u0432\u043e\u0435-\u041a\u043e\u0442\u0447\u0438\u0449\u0435"
    ],
    "name:und_x_variant":[
        "\u041d\u043e\u0432\u043e\u0435-\u041a\u043e\u0442\u0447\u0438\u0449\u0435"
    ],
    "wof:name":"Novoye-Kotchishche",
    "wof:placetype":"locality"
},
  "geometry": {"coordinates":[34.4811,57.7384],"type":"Point"}
}