{
  "type": "Feature",
  "properties": {
    "gn:admin1_code":"28",
    "gn:asciiname":"Kentozero",
    "gn:cc2":"RU",
    "gn:country_code":"RU",
    "gn:dem":131,
    "gn:feature_class":"P",
    "gn:feature_code":"PPL",
    "gn:name":"Kentozero",
    "gn:population":0,
    "gn:timezone":"Europe/Moscow",
    "iso:country":"RU",
    "name:fin_x_preferred":[
        "Kenttij\u00e4rvi"
    ],
    "name:rus_x_preferred":[
        "\u041a\u0435\u043d\u0442\u043e\u0437\u0435\u0440\u043e"
    ],
    "name:und_x_variant":[
        "Kentozero-Rikolya",
        "Kentozero",
        "\u041a\u0435\u043d\u0442\u043e\u0437\u0435\u0440\u043e"
    ],
    "wof:name":"Kentozero",
    "wof:placetype":"locality"
},
  "geometry": {"coordinates":[31.11465,64.88408000000001],"type":"Point"}
}