{
  "type": "Feature",
  "properties": {
    "gn:admin1_code":"84.0",
    "gn:asciiname":"Akatovka",
    "gn:country_code":"RU",
    "gn:dem":42,
    "gn:feature_class":"P",
    "gn:feature_code":"PPL",
    "gn:name":"Akatovka",
    "gn:population":0,
    "gn:timezone":"Europe/Volgograd",
    "iso:country":"RU",
    "name:nor_x_preferred":[
        "Akatovka"
    ],
    "name:rus_x_preferred":[
        "\u0410\u043a\u0430\u0442\u043e\u0432\u043a\u0430"
    ],
    "wof:name":"Akatovka",
    "wof:placetype":"locality"
},
  "geometry": {"coordinates":[44.66639,48.88861],"type":"Point"}
}