{
  "type": "Feature",
  "properties": {
    "gn:country":"RU",
    "gn:fcode":"PPL",
    "gn:population":8368,
    "iso:country":"RU",
    "name:ara_x_preferred":[
        "\u0645\u063a\u0644\u064a\u0646"
    ],
    "name:azb_x_preferred":[
        "\u0645\u0642\u0644\u06cc\u0646"
    ],
    "name:bel_x_preferred":[
        "\u0413\u043e\u0440\u0430\u0434 \u041c\u0433\u043b\u0456\u043d"
    ],
    "name:bel_x_variant":[
        "\u041c\u0433\u043b\u0456\u043d"
    ],
    "name:ceb_x_preferred":[
        "Mglin"
    ],
    "name:che_x_preferred":[
        "\u041c\u0433\u043b\u0438\u043d"
    ],
    "name:cym_x_preferred":[
        "Mglin"
    ],
    "name:deu_x_preferred":[
        "Mglin"
    ],
    "name:diq_x_preferred":[
        "Mglin"
    ],
    "name:eng_x_preferred":[
        "Mglin"
    ],
    "name:epo_x_preferred":[
        "Mglin"
    ],
    "name:est_x_preferred":[
        "Mglin"
    ],
    "name:fas_x_preferred":[
        "\u0645\u06af\u0644\u06cc\u0646"
    ],
    "name:fin_x_preferred":[
        "Mglin"
    ],
    "name:fra_x_preferred":[
        "Mgline"
    ],
    "name:heb_x_preferred":[
        "\u05de\u05d2\u05dc\u05d9\u05df"
    ],
    "name:hsb_x_preferred":[
        "Mglin"
    ],
    "name:ita_x_preferred":[
        "Mglin"
    ],
    "name:jpn_x_preferred":[
        "\u30e0\u30b0\u30ea\u30f3"
    ],
    "name:kor_x_preferred":[
        "\ubbc0\uae00\ub9b0"
    ],
    "name:lav_x_preferred":[
        "Mg\u013cina"
    ],
    "name:ltz_x_preferred":[
        "Mglin"
    ],
    "name:nld_x_preferred":[
        "Mglin"
    ],
    "name:nno_x_preferred":[
        "Mglin"
    ],
    "name:nob_x_preferred":[
        "Mglin"
    ],
    "name:nor_x_preferred":[
        "Mglin"
    ],
    "name:pol_x_preferred":[
        "Mglin"
    ],
    "name:rus_x_preferred":[
        "\u041c\u0433\u043b\u0438\u043d"
    ],
    "name:spa_x_preferred":[
        "Mglin"
    ],
    "name:srp_x_preferred":[
        "\u041c\u0433\u043b\u0438\u043d"
    ],
    "name:swe_x_preferred":[
        "Mglin"
    ],
    "name:tat_x_preferred":[
        "\u041c\u0433\u043b\u0438\u043d"
    ],
    "name:tgl_x_preferred":[
        "Mglin"
    ],
    "name:tur_x_preferred":[
        "Mglin"
    ],
    "name:ukr_x_preferred":[
        "\u041c\u0433\u043b\u0438\u043d"
    ],
    "name:vep_x_preferred":[
        "Mglin"
    ],
    "name:war_x_preferred":[
        "Mglin"
    ],
    "name:xal_x_preferred":[
        "\u041c\u0433\u043b\u0438\u043d \u0431\u0430\u043b\u04bb\u0441\u043d"
    ],
    "name:zho_x_preferred":[
        "\u59c6\u683c\u6797"
    ],
    "qs:name":"Mglin",
    "qs:photos_9r":0,
    "qs:photos_sr":0,
    "qs:pop_sr":"5",
    "wd:wordcount":961,
    "wof:name":"Mglin",
    "wof:placetype":"locality",
    "wof:population":8368
},
  "geometry": {"coordinates":[32.84753,53.05907],"type":"Point"}
}