{
  "type": "Feature",
  "properties": {
    "gn:admin1_code":"77",
    "gn:asciiname":"Gradobit'",
    "gn:country_code":"RU",
    "gn:dem":190,
    "gn:feature_class":"P",
    "gn:feature_code":"PPL",
    "gn:name":"Gradobit\u2019",
    "gn:population":0,
    "gn:timezone":"Europe/Moscow",
    "iso:country":"RU",
    "name:eng_x_preferred":[
        "Gradobit'"
    ],
    "name:nor_x_preferred":[
        "Gradobit"
    ],
    "name:rus_x_preferred":[
        "\u0413\u0440\u0430\u0434\u043e\u0431\u0438\u0442\u044c"
    ],
    "name:und_x_variant":[
        "\u0413\u0440\u0430\u0434\u043e\u0431\u0438\u0442\u044c",
        "Gradobit\u2019"
    ],
    "wof:name":"Gradobit'",
    "wof:placetype":"locality"
},
  "geometry": {"coordinates":[33.86333,57.71556],"type":"Point"}
}