{
  "type": "Feature",
  "properties": {
    "gn:admin1_code":"25.0",
    "gn:asciiname":"Avdeyevka",
    "gn:country_code":"RU",
    "gn:dem":192,
    "gn:feature_class":"P",
    "gn:feature_code":"PPL",
    "gn:name":"Avdeyevka",
    "gn:population":0,
    "gn:timezone":"Europe/Moscow",
    "iso:country":"RU",
    "name:eng_x_preferred":[
        "Avdeyevka"
    ],
    "name:nor_x_preferred":[
        "Avdejevka"
    ],
    "name:rus_x_preferred":[
        "\u0410\u0432\u0434\u0435\u0435\u0432\u043a\u0430"
    ],
    "name:und_x_variant":[
        "\u0410\u0432\u0434\u0435\u0435\u0432\u043a\u0430",
        "Avdeyevka"
    ],
    "wof:name":"Avdeyevka",
    "wof:placetype":"locality"
},
  "geometry": {"coordinates":[34.73807,53.43083000000001],"type":"Point"}
}