{
  "type": "Feature",
  "properties": {
    "gn:admin1_code":"88",
    "gn:asciiname":"Nesterkovo",
    "gn:country_code":"RU",
    "gn:dem":135,
    "gn:feature_class":"P",
    "gn:feature_code":"PPL",
    "gn:name":"Nesterkovo",
    "gn:population":0,
    "gn:timezone":"Europe/Moscow",
    "iso:country":"RU",
    "name:rus_x_preferred":[
        "\u041d\u0435\u0441\u0442\u0435\u0440\u043a\u043e\u0432\u043e"
    ],
    "wof:name":"Nesterkovo",
    "wof:placetype":"locality"
},
  "geometry": {"coordinates":[39.12511,57.70079000000001],"type":"Point"}
}