{
  "type": "Feature",
  "properties": {
    "gn:admin1_code":"91",
    "gn:asciiname":"Seredinka",
    "gn:country_code":"RU",
    "gn:dem":338,
    "gn:feature_class":"P",
    "gn:feature_code":"PPL",
    "gn:name":"Seredinka",
    "gn:population":0,
    "gn:timezone":"Asia/Krasnoyarsk",
    "iso:country":"RU",
    "name:eng_x_preferred":[
        "Seredinka"
    ],
    "name:nor_x_preferred":[
        "Seredinka"
    ],
    "name:rus_x_preferred":[
        "\u0421\u0435\u0440\u0435\u0434\u0438\u043d\u043a\u0430"
    ],
    "wof:name":"Seredinka",
    "wof:placetype":"locality"
},
  "geometry": {"coordinates":[95.6135,55.3757],"type":"Point"}
}